Workbook
Name billion: About!$A$38
Name IQ_CH: 110000
Name IQ_CQ: 5000
Name IQ_CY: 10000
Name IQ_DAILY: 500000
Name IQ_FH: 100000
Name IQ_FQ: 500
Name IQ_FY: 1000
Name IQ_LTM: 2000
Name IQ_MONTH: 15000
Name IQ_NTM: 6000
Name IQ_WEEK: 50000
Name IQ_YTD: 3000
Name thousand: About!$A$37

Sheet About
A1: BAADTbVT BAU Average Annual Dist Traveled by Vehicle Type | B1: New Jersey | C1: 46245 | E1: State | F1: State
B2: =LOOKUP(B1,E2:F51,F2:F51) -> NJ | E2: Alabama | F2: AL
A3: Source: | B3: All vehicle types except motorbikes and passenger ships | D3: NREL calibration factors for ships | E3: Alaska | F3: AK
B4: EIA | D4: National Renewable Energy Laboratory | E4: Arizona | F4: AZ
B5: 2024 | D5: 2017 | E5: Arkansas | F5: AR
B6: SEDS | D6: Electrification Futures Study | E6: California | F6: CA
B7: https://www.eia.gov/state/seds/ | D7: Final Demand | E7: Colorado | F7: CO
D8: https://data.nrel.gov/submissions/92 | E8: Connecticut | F8: CT
E9: Delaware | F9: DE
B10: Motorbikes | D10: Passenger Rail Scaling | E10: Florida | F10: FL
B11: National Highway Traffic Safety Administration | D11: National Transit Database Tables | E11: Georgia | F11: GA
B12: 2016 | D12: American Public Transportation Association | E12: Hawaii | F12: HI
B13: Quick Facts 2014 | D13: 2020 | E13: Idaho | F13: ID
B14: http://www-nrd.nhtsa.dot.gov/Pubs/812234.pdf | D14: https://www.apta.com/research-technical-resources/transit-statistics/ntd-data-tables/ | E14: Illinois | F14: IL
B15: Page 1, "Exposure Data" | E15: Indiana | F15: IN
E16: Iowa | F16: IA
B17: passenger ships | E17: Kansas | F17: KS
B18: U.S. Coast Guard | E18: Kentucky | F18: KY
B19: 2013 | E19: Louisiana | F19: LA
B20: National Recreational Boating Survey 2012 | E20: Maine | F20: ME
B21: http://www.uscgboating.org/library/recreational-boating-servey/2012survey%20report.pdf | E21: Maryland | F21: MD
B22: Page 63, Table 40 | E22: Massachusetts | F22: MA
E23: Michigan | F23: MI
A24: Notes: | E24: Minnesota | F24: MN
A25: In the U.S. model, passenger ships are recreational boats, and they are represented | E25: Mississippi | F25: MS
A26: in hours per year rather than distance per year. | E26: Missouri | F26: MO
E27: Montana | F27: MT
A28: This is a time-series variable to support countries or regions where average distance | E28: Nebraska | F28: NE
A29: traveled per year changes over the model run. The values are constant in the U.S. | E29: Nevada | F29: NV
A30: version of the model. | E30: New Hampshire | F30: NH
E31: New Jersey | F31: NJ
A32: Start Year | B32: 2018 | E32: New Mexico | F32: NM
A33: The start year is the year prior the first simulated year in the model. | E33: New York | F33: NY
A34: For the U.S. in EPS 3.0, the start year is 2018, as the first simulated year is 2019. | E34: North Carolina | F34: NC
A35: We use AEO 2019 to calculate start year vehicles, as AEO 2020 does not include 2018 data. | E35: North Dakota | F35: ND
E36: Ohio | F36: OH
A37: 1000 | E37: Oklahoma | F37: OK
A38: =10^9 -> 1000000000 | E38: Oregon | F38: OR
E39: Pennsylvania | F39: PA
E40: Rhode Island | F40: RI
E41: South Carolina | F41: SC
E42: South Dakota | F42: SD
E43: Tennessee | F43: TN
E44: Texas | F44: TX
E45: Utah | F45: UT
E46: Vermont | F46: VT
E47: Virginia | F47: VA
E48: Washington | F48: WA
E49: West Virginia | F49: WV
E50: Wisconsin | F50: WI
E51: Wyoming | F51: WY

Sheet all_csv_SYVbT-passenger
A1: SourceFolder | B1: Number of Vehicles | C1: battery electric vehicle | D1: natural gas vehicle | E1: gasoline vehicle | F1: diesel vehicle | G1: plugin hybrid vehicle | H1: LPG vehicle | I1: hydrogen vehicle
A2: AK | B2: LDVs | C2: 4769953 | D2: 14506 | E2: 257649823 | F2: 1553093 | G2: 1417825 | H2: 13525 | I2: 17094
A3: AK | B3: HDVs | C3: 300 | D3: 128402 | E3: 101051 | F3: 802832 | G3: 0 | H3: 47038 | I3: 174
A4: AK | B4: aircraft | C4: 0 | D4: 0 | E4: 0 | F4: 6767 | G4: 0 | H4: 0 | I4: 0
A5: AK | B5: rail | C5: 2564 | D5: 0 | E5: 0 | F5: 173 | G5: 0 | H5: 0 | I5: 0
A6: AK | B6: ships | C6: 0 | D6: 0 | E6: 10214830 | F6: 2490170 | G6: 0 | H6: 0 | I6: 0
A7: AK | B7: motorbikes | C7: 0 | D7: 0 | E7: 9261249 | F7: 0 | G7: 0 | H7: 0 | I7: 0
A8: AL | B8: LDVs | C8: 17500 | D8: 100 | E8: 5181820 | F8: 28594 | G8: 6800 | H8: 100 | I8: 0
A9: AL | B9: HDVs | C9: 1 | D9: 401 | E9: 315 | F9: 2505 | G9: 0 | H9: 147 | I9: 1
A10: AL | B10: aircraft | C10: 0 | D10: 0 | E10: 0 | F10: 24 | G10: 0 | H10: 0 | I10: 0
A11: AL | B11: rail | C11: 0 | D11: 0 | E11: 0 | F11: 0 | G11: 0 | H11: 0 | I11: 0
A12: AL | B12: ships | C12: 0 | D12: 0 | E12: 219517 | F12: 53514 | G12: 0 | H12: 0 | I12: 0
A13: AL | B13: motorbikes | C13: 0 | D13: 0 | E13: 129014 | F13: 0 | G13: 0 | H13: 0 | I13: 0
... A313: WY | B313: motorbikes | C313: 0 | D313: 0 | E313: 28613 | F313: 0 | G313: 0 | H313: 0 | I313: 0

Sheet all_csv_SYVbT-freight
A1: SourceFolder | B1: Number of Vehicles | C1: battery electric vehicle | D1: natural gas vehicle | E1: gasoline vehicle | F1: diesel vehicle | G1: plugin hybrid vehicle | H1: LPG vehicle | I1: hydrogen vehicle | J1: Unnamed: 8 | K1: Unnamed: 9
A2: AK | B2: LDVs | C2: 138292 | D2: 25267 | E2: 12833715 | F2: 10968619 | G2: 493 | H2: 2238 | I2: 0
A3: AK | B3: HDVs | C3: 2114 | D3: 57392 | E3: 38136 | F3: 5453223 | G3: 0 | H3: 3057 | I3: 0
A4: AK | B4: aircraft | C4: 0 | D4: 0 | E4: 0 | F4: 925 | G4: 0 | H4: 0 | I4: 0
A5: AK | B5: rail | C5: 0 | D5: 0 | E5: 0 | F5: 24526 | G5: 0 | H5: 0 | I5: 0
A6: AK | B6: ships | C6: 0 | D6: 0 | E6: 0 | F6: 164 | G6: 0 | H6: 0 | I6: 0
A7: AK | B7: motorbikes | C7: 0 | D7: 0 | E7: 0 | F7: 0 | G7: 0 | H7: 0 | I7: 0
A8: AL | B8: LDVs | C8: 897 | D8: 164 | E8: 83198 | F8: 71107 | G8: 3 | H8: 15 | I8: 0
A9: AL | B9: HDVs | C9: 50 | D9: 1371 | E9: 911 | F9: 130263 | G9: 0 | H9: 73 | I9: 0
A10: AL | B10: aircraft | C10: 0 | D10: 0 | E10: 0 | F10: 4 | G10: 0 | H10: 0 | I10: 0
A11: AL | B11: rail | C11: 0 | D11: 0 | E11: 0 | F11: 371 | G11: 0 | H11: 0 | I11: 0
A12: AL | B12: ships | C12: 0 | D12: 0 | E12: 0 | F12: 4 | G12: 0 | H12: 0 | I12: 0
A13: AL | B13: motorbikes | C13: 0 | D13: 0 | E13: 0 | F13: 0 | G13: 0 | H13: 0 | I13: 0
... A67: HI | B67: motorbikes | C67: 0 | D67: 0 | E67: 0 | F67: 0 | G67: 0 | H67: 0 | I67: 0
A68: HI
A69: HI
A70: HI
A71: HI
A72: HI
A73: HI
A74: HI
A75: HI
A76: HI
A77: HI
A78: HI
A79: HI
... A83: HI
A84: IA | B84: LDVs | C84: 662 | D84: 121 | E84: 61426 | F84: 52499 | G84: 2 | H84: 11 | I84: 0
A85: IA | B85: HDVs | C85: 37 | D85: 1012 | E85: 673 | F85: 96175 | G85: 0 | H85: 54 | I85: 0
A86: IA | B86: aircraft | C86: 0 | D86: 0 | E86: 0 | F86: 4 | G86: 0 | H86: 0 | I86: 0
A87: IA | B87: rail | C87: 0 | D87: 0 | E87: 0 | F87: 339 | G87: 0 | H87: 0 | I87: 0
A88: IA | B88: ships | C88: 0 | D88: 0 | E88: 0 | F88: 0 | G88: 0 | H88: 0 | I88: 0
A89: IA | B89: motorbikes | C89: 0 | D89: 0 | E89: 0 | F89: 0 | G89: 0 | H89: 0 | I89: 0
A90: ID | B90: LDVs | C90: 360 | D90: 66 | E90: 33426 | F90: 28568 | G90: 1 | H90: 6 | I90: 0
A91: ID | B91: HDVs | C91: 20 | D91: 551 | E91: 366 | F91: 52334 | G91: 0 | H91: 29 | I91: 0
A92: ID | B92: aircraft | C92: 0 | D92: 0 | E92: 0 | F92: 2 | G92: 0 | H92: 0 | I92: 0
A93: ID | B93: rail | C93: 0 | D93: 0 | E93: 0 | F93: 86 | G93: 0 | H93: 0 | I93: 0
A94: ID | B94: ships | C94: 0 | D94: 0 | E94: 0 | F94: 0 | G94: 0 | H94: 0 | I94: 0
A95: ID | B95: motorbikes | C95: 0 | D95: 0 | E95: 0 | F95: 0 | G95: 0 | H95: 0 | I95: 0
... A329: WY | B329: motorbikes | C329: 0 | D329: 0 | E329: 0 | F329: 0 | G329: 0 | H329: 0 | I329: 0

Sheet all_csv_AVLo-passengers
B1: Vehicle Loading (passengers) | C1: 2015 | D1: State
A2: 0 | B2: LDVs | C2: 1.67 | D2: AK | E2: AVLo-passengers
A3: 1 | B3: HDVs | C3: 21.196137 | D3: AK | E3: AVLo-passengers
A4: 2 | B4: aircraft | C4: 111.39416 | D4: AK | E4: AVLo-passengers
A5: 3 | B5: rail | C5: 15.34784 | D5: AK | E5: AVLo-passengers
A6: 4 | B6: ships | C6: 1 | D6: AK | E6: AVLo-passengers
A7: 5 | B7: motorbikes | C7: 1.2700757 | D7: AK | E7: AVLo-passengers

Sheet all_csv_AVLo-freight
B1: Vehicle Loading (tons) | C1: 2021 | D1: State | E1: Metric Name
A2: 0 | B2: LDVs | C2: 1 | D2: AK | E2: AVLo-freight
A3: 1 | B3: HDVs | C3: 16 | D3: AK | E3: AVLo-freight
A4: 2 | B4: aircraft | C4: 41.989116 | D4: AK | E4: AVLo-freight
A5: 3 | B5: rail | C5: 3512.3592 | D5: AK | E5: AVLo-freight
A6: 4 | B6: ships | C6: 1974.4736 | D6: AK | E6: AVLo-freight
A7: 5 | B7: motorbikes | C7: 0 | D7: AK | E7: AVLo-freight

Sheet all_csv_SYFAFE-psgr
B1: Fuel Economy (passenger*miles/BTU) | C1: battery electric vehicle | D1: natural gas vehicle | E1: gasoline vehicle | F1: diesel vehicle | G1: plugin hybrid vehicle | H1: LPG vehicle | I1: hydrogen vehicle | J1: State
A2: 0 | B2: LDVs | C2: 0.001464487 | D2: 0.000285996 | E2: 0.000308115 | F2: 0.000349551 | G2: 0.000544402 | H2: 0.000245972 | I2: 0.000954776 | J2: AK | K2: SYFAFE-psgr
A3: 1 | B3: HDVs | C3: 0.003319966 | D3: 0.002348966 | E3: 0.000851798 | F3: 0.001033139 | G3: 0.002290894 | H3: 0.001829444 | I3: 0.003099417 | J3: AK | K3: SYFAFE-psgr
A4: 2 | B4: aircraft | C4: 0.000978983 | D4: 0.000304649 | E4: 0.000304649 | F4: 0.000304649 | G4: 0 | H4: 0 | I4: 0.000913948 | J4: AK | K4: SYFAFE-psgr
A5: 3 | B5: rail | C5: 0.000674285 | D5: 5.05863e-05 | E5: 5.05863e-05 | F5: 5.05863e-05 | G5: 0 | H5: 0 | I5: 0.000151759 | J5: AK | K5: SYFAFE-psgr
A6: 4 | B6: ships | C6: 3.81517e-05 | D6: 0 | E6: 1.18724e-05 | F6: 1.18724e-05 | G6: 0 | H6: 0 | I6: 3.56172e-05 | J6: AK | K6: SYFAFE-psgr
A7: 5 | B7: motorbikes | C7: 0.005802878 | D7: 0.001822391 | E7: 0.001822391 | F7: 0.001822391 | G7: 0.004011659 | H7: 0.001412353 | I7: 0.005467174 | J7: AK | K7: SYFAFE-psgr

Sheet all_csv_SYFAFE-frgt
B1: Fuel Economy (freight ton*miles/BTU) | C1: battery electric vehicle | D1: natural gas vehicle | E1: gasoline vehicle | F1: diesel vehicle | G1: plugin hybrid vehicle | H1: LPG vehicle | I1: hydrogen vehicle | J1: State | K1: Metric Name
A2: 0 | B2: LDVs | C2: 0.0003015665 | D2: 7.0213474e-05 | E2: 9.3322264e-05 | F2: 8.9590244e-05 | G2: 0.0001534286 | H2: 0.00011549321 | I2: 8.3798902e-05 | J2: AK | K2: SYFAFE-frgt
A3: 1 | B3: HDVs | C3: 0.0016283397 | D3: 0.00077263482 | E3: 0.0006720672 | F3: 0.00075059325 | G3: 0 | H3: 0.00068755018 | I3: 0 | J3: AK | K3: SYFAFE-frgt
A4: 2 | B4: aircraft | C4: 0.00029962433 | D4: 9.3239985e-05 | E4: 9.3239985e-05 | F4: 9.3239985e-05 | G4: 0 | H4: 0 | I4: 0.00027971996 | J4: AK | K4: SYFAFE-frgt
A5: 3 | B5: rail | C5: 0.010840496 | D5: 0.00337345 | E5: 0.00337345 | F5: 0.00337345 | G5: 0 | H5: 0 | I5: 0.01012035 | J5: AK | K5: SYFAFE-frgt
A6: 4 | B6: ships | C6: 0.01561035 | D6: 0.004857779 | E6: 0.004857779 | F6: 0.004857779 | G6: 0 | H6: 0 | I6: 0.014573337 | J6: AK | K6: SYFAFE-frgt
A7: 5 | B7: motorbikes | C7: 0 | D7: 0 | E7: 0 | F7: 0 | G7: 0 | H7: 0 | I7: 0 | J7: AK | K7: SYFAFE-frgt

Sheet Codes_and_Descriptions
B2: State Energy Data System
B3: Data Series Names (MSN) and Descriptions
B6: The MSNs are five-character codes, most of which are structured as follows:
B7: First and second characters - describes an energy source (for example, NG for natural gas, MG for motor gasoline)
B8: Third and fourth characters - describes an energy sector or an energy activity (for example, RC for residential consumption, PR for production)
B9: Fifth character - describes a type of data (for example, P for data in physical unit, B for data in billion Btu)
B11: MSN | C11: Description | D11: Unit
B12: ABICB | C12: Aviation gasoline blending components consumed by the industrial sector | D12: Billion Btu
B13: ABICP | C13: Aviation gasoline blending components consumed by the industrial sector | D13: Thousand barrels
B14: ARICB | C14: Asphalt and road oil consumed by the industrial sector | D14: Billion Btu
B15: ARICD | C15: Asphalt and road oil price in the industrial sector | D15: Dollars per million Btu
B16: ARICP | C16: Asphalt and road oil consumed by the industrial sector | D16: Thousand barrels
B17: ARICV | C17: Asphalt and road oil expenditures in the industrial sector | D17: Million dollars
B18: ARTCB | C18: Asphalt and road oil total consumption | D18: Billion Btu
B19: ARTCD | C19: Asphalt and road oil average price, all sectors | D19: Dollars per million Btu
B20: ARTCP | C20: Asphalt and road oil total consumption | D20: Thousand barrels
B21: ARTCV | C21: Asphalt and road oil total expenditures | D21: Million dollars
B22: ARTXB | C22: Asphalt and road oil total end-use consumption | D22: Billion Btu
... B395: NGICP | C395: Natural gas consumed by the industrial sector | D395: Million cubic feet
B396: NGICV | C396: Natural gas expenditures in the industrial sector | D396: Million dollars | E396: =SUM(A397:A398,A407) -> 0
B397: NGISB | C397: Natural gas consumed by the industrial sector excluding refinery fuel | D397: Billion Btu
B398: NGLPB | C398: Natural gas consumed as lease and plant fuel | D398: Billion Btu | E398: energy pipelines or oil and gas
B399: NGMPB | C399: Natural gas marketed production | D399: Billion Btu
B400: NGMPK | C400: Conversion factor for natural gas marketed production | D400: Thousand Btu per cubic feet
B401: NGMPP | C401: Natural gas marketed production | D401: Million cubic feet
B402: NGPZB | C402: Natural gas for pipeline and distribution use | D402: Billion Btu
B403: NGRCB | C403: Natural gas consumed by (delivered to) the residential sector | D403: Billion Btu
B404: NGRCD | C404: Natural gas price in the residential sector | D404: Dollars per million Btu
B405: NGRCP | C405: Natural gas consumed by (delivered to) the residential sector | D405: Million cubic feet
B406: NGRCV | C406: Natural gas expenditures in the residential sector | D406: Million dollars
B407: NGRFB | C407: Natural gas consumed as refinery fuel | D407: Billion Btu | E407: refinery
B408: NGSCB | C408: Natural gas total consumption adjusted for process fuel | D408: Billion Btu
B409: NGTCB | C409: Natural gas total consumption | D409: Billion Btu
B410: NGTCD | C410: Natural gas average price, all sectors | D410: Dollars per million Btu
B411: NGTCK | C411: Factor for converting natural gas total consumption from physical units to Btu | D411: Thousand Btu per cubic foot
B412: NGTCP | C412: Natural gas total consumption | D412: Million cubic feet
B413: NGTCV | C413: Natural gas total expenditures | D413: Million dollars
B414: NGTPB | C414: Natural gas total consumption per capita | D414: Million Btu
B415: NGTPP | C415: Natural gas total consumption per capita | D415: Thousand cubic feet
B416: NGTXB | C416: Natural gas total end-use consumption | D416: Billion Btu
B417: NGTXD | C417: Natural gas average price, all end-use sectors | D417: Dollars per million Btu
B418: NGTXK | C418: Factor for converting natural gas consumed by all sectors other than electric power from physical units to Btu | D418: Thousand Btu per cubic foot
B419: NGTXP | C419: Natural gas total end-use consumption | D419: Million cubic feet
... B732: ZWHDP | C732: Heating degree days | D732: Days

Sheet SEDS_use_all_btu
A1: Data_Status | B1: State | C1: MSN | D1: 2021 | E1: 2022 | F1: 2023 | G1: 2024
A2: 2024P | B2: AK | C2: ABICB | D2: -8 | E2: -6 | F2: -6 | G2: -10
A3: 2024P | B3: AK | C3: ARICB | D3: 13425 | E3: 12981 | F3: 13173 | G3: 13322
A4: 2024P | B4: AK | C4: ARTCB | D4: 13425 | E4: 12981 | F4: 13173 | G4: 13322
A5: 2024P | B5: AK | C5: ARTXB | D5: 13425 | E5: 12981 | F5: 13173 | G5: 13322
A6: 2024P | B6: AK | C6: AVACB | D6: 1037 | E6: 1073 | F6: 1019 | G6: 1096
A7: 2024P | B7: AK | C7: AVTCB | D7: 1037 | E7: 1073 | F7: 1019 | G7: 1096
A8: 2024P | B8: AK | C8: AVTXB | D8: 1037 | E8: 1073 | F8: 1019 | G8: 1096
A9: 2024P | B9: AK | C9: B1ABB | D9: 0 | E9: 0 | F9: 0 | G9: 0
A10: 2024P | B10: AK | C10: B1ACB | D10: 0 | E10: 0 | F10: 0 | G10: 0
A11: 2024P | B11: AK | C11: B1AUB | D11: 0 | E11: 0 | F11: 0 | G11: 0
A12: 2024P | B12: AK | C12: B1RIB | D12: 0 | E12: 0 | F12: 0 | G12: 0
... A26: 2024P | B26: AK | C26: BDRUB | D26: 0 | E26: 0 | F26: 0 | G26: 0
A27: 2024P | B27: AK | C27: BDSAB
A28: 2024P | B28: AK | C28: BDSUB | D28: 0 | E28: 0 | F28: 0 | G28: 0
A29: 2024P | B29: AK | C29: BDTCB | D29: 0 | E29: 0 | F29: 0 | G29: 0
A30: 2024P | B30: AK | C30: BDTXB | D30: 0 | E30: 0 | F30: 0 | G30: 0
A31: 2024P | B31: AK | C31: BDXUB | D31: 0 | E31: 0 | F31: 0 | G31: 0
A32: 2024P | B32: AK | C32: BFLCB | D32: 0 | E32: 0 | F32: 0 | G32: 0
A33: 2024P | B33: AK | C33: BFTCB | D33: 0 | E33: 0 | F33: 0 | G33: 0
A34: 2024P | B34: AK | C34: BMCAS | D34: 62.1 | E34: 66.6 | F34: 63.5 | G34: 69.8
A35: 2024P | B35: AK | C35: BMTCB | D35: 3153 | E35: 3873 | F35: 3431 | G35: 3308
A36: 2024P | B36: AK | C36: BQICB | D36: 0 | E36: 0 | F36: 0 | G36: 0
A37: 2024P | B37: AK | C37: BQTCB | D37: 0 | E37: 0 | F37: 0 | G37: 0
A38: 2024P | B38: AK | C38: BTCAS | D38: 0.1 | E38: 0.1 | F38: 0.4 | G38: 0.4
A39: 2024P | B39: AK | C39: BTGBP | D39: 45 | E39: 92 | F39: 92 | G39: 132
... A347: 2024P | B347: AL | C347: BDRUB | D347: 0 | E347: 0 | F347: 0 | G347: 0
A348: 2024P | B348: AL | C348: BDSAB
A349: 2024P | B349: AL | C349: BDSUB | D349: 1905 | E349: 1745 | F349: 2498 | G349: 2683
A350: 2024P | B350: AL | C350: BDTCB | D350: 3316 | E350: 2976 | F350: 3970 | G350: 4133
A351: 2024P | B351: AL | C351: BDTXB | D351: 3316 | E351: 2976 | F351: 3970 | G351: 4133
A352: 2024P | B352: AL | C352: BDXUB | D352: 1905 | E352: 1745 | F352: 2498 | G352: 2683
A353: 2024P | B353: AL | C353: BFLCB | D353: 22 | E353: 22 | F353: 29 | G353: 26
A354: 2024P | B354: AL | C354: BFTCB | D354: 28786 | E354: 30648 | F354: 30582 | G354: 33095
A355: 2024P | B355: AL | C355: BMCAS | D355: 72.8 | E355: 68.3 | F355: 67.7 | G355: 72.2
A356: 2024P | B356: AL | C356: BMTCB | D356: 198543 | E356: 201913 | F356: 196969 | G356: 202371
A357: 2024P | B357: AL | C357: BQICB | D357: 0 | E357: 0 | F357: 0 | G357: 0
A358: 2024P | B358: AL | C358: BQTCB | D358: 0 | E358: 0 | F358: 0 | G358: 0
A359: 2024P | B359: AL | C359: BTCAS | D359: 1.9 | E359: 3.2 | F359: 5.8 | G359: 0
A360: 2024P | B360: AL | C360: BTGBP | D360: 1 | E360: 1 | F360: 1 | G360: 1
... A668: 2024P | B668: AR | C668: BDRUB | D668: 0 | E668: 0 | F668: 0 | G668: 0
A669: 2024P | B669: AR | C669: BDSAB
A670: 2024P | B670: AR | C670: BDSUB | D670: 1344 | E670: 1276 | F670: 1855 | G670: 1965
A671: 2024P | B671: AR | C671: BDTCB | D671: 2339 | E671: 2177 | F671: 2948 | G671: 3026
A672: 2024P | B672: AR | C672: BDTXB | D672: 2339 | E672: 2177 | F672: 2948 | G672: 3026
A673: 2024P | B673: AR | C673: BDXUB | D673: 1344 | E673: 1276 | F673: 1855 | G673: 1965
A674: 2024P | B674: AR | C674: BFLCB | D674: 83 | E674: 84 | F674: 108 | G674: 89
A675: 2024P | B675: AR | C675: BFTCB | D675: 14450 | E675: 15174 | F675: 15941 | G675: 16621
A676: 2024P | B676: AR | C676: BMCAS | D676: 54 | E676: 53.1 | F676: 47.4 | G676: 53.2
A677: 2024P | B677: AR | C677: BMTCB | D677: 72939 | E677: 79216 | F677: 75713 | G677: 78846
A678: 2024P | B678: AR | C678: BQICB | D678: 0 | E678: 0 | F678: 0 | G678: 0
A679: 2024P | B679: AR | C679: BQTCB | D679: 0 | E679: 0 | F679: 0 | G679: 0
A680: 2024P | B680: AR | C680: BTCAS | D680: 0.6 | E680: 0.4 | F680: 0.5 | G680: 0.2
A681: 2024P | B681: AR | C681: BTGBP | D681: 12 | E681: 22 | F681: 22 | G681: 28
... A989: 2024P | B989: AZ | C989: BDRUB | D989: 0 | E989: 0 | F989: 0 | G989: 0
A990: 2024P | B990: AZ | C990: BDSAB
A991: 2024P | B991: AZ | C991: BDSUB | D991: 295 | E991: 267 | F991: 288 | G991: 314
A992: 2024P | B992: AZ | C992: BDTCB | D992: 513 | E992: 455 | F992: 458 | G992: 484
A993: 2024P | B993: AZ | C993: BDTXB | D993: 513 | E993: 455 | F993: 458 | G993: 484
A994: 2024P | B994: AZ | C994: BDXUB | D994: 295 | E994: 267 | F994: 288 | G994: 314
A995: 2024P | B995: AZ | C995: BFLCB | D995: 0 | E995: 0 | F995: 0 | G995: 0
A996: 2024P | B996: AZ | C996: BFTCB | D996: 26429 | E996: 26427 | F996: 26863 | G996: 26842
A997: 2024P | B997: AZ | C997: BMCAS | D997: 86 | E997: 83.6 | F997: 79 | G997: 75.4
A998: 2024P | B998: AZ | C998: BMTCB | D998: 35287 | E998: 36855 | F998: 37076 | G998: 36521
A999: 2024P | B999: AZ | C999: BQICB | D999: 0 | E999: 0 | F999: 0 | G999: 0
A1000: 2024P | B1000: AZ | C1000: BQTCB | D1000: 0 | E1000: 0 | F1000: 0 | G1000: 0
A1001: 2024P | B1001: AZ | C1001: BTCAS | D1001: 6.6 | E1001: 6.6 | F1001: 5.5 | G1001: 12
A1002: 2024P | B1002: AZ | C1002: BTGBP | D1002: 97 | E1002: 97 | F1002: 931 | G1002: 2121
... A1310: 2024P | B1310: CA | C1310: BDRUB | D1310: 0 | E1310: 0 | F1310: 0 | G1310: 0
A1311: 2024P | B1311: CA | C1311: BDSAB
A1312: 2024P | B1312: CA | C1312: BDSUB | D1312: 21261 | E1312: 21065 | F1312: 21588 | G1312: 20160
A1313: 2024P | B1313: CA | C1313: BDTCB | D1313: 37012 | E1313: 35933 | F1313: 34309 | G1313: 31054
A1314: 2024P | B1314: CA | C1314: BDTXB | D1314: 37012 | E1314: 35933 | F1314: 34309 | G1314: 31054
A1315: 2024P | B1315: CA | C1315: BDXUB | D1315: 21261 | E1315: 21065 | F1315: 21588 | G1315: 20160
A1316: 2024P | B1316: CA | C1316: BFLCB | D1316: 5119 | E1316: 4410 | F1316: 3397 | G1316: 5145
A1317: 2024P | B1317: CA | C1317: BFTCB | D1317: 317256 | E1317: 375528 | F1317: 498024 | G1317: 578883
A1318: 2024P | B1318: CA | C1318: BMCAS | D1318: 57.1 | E1318: 56.5 | F1318: 53.5 | G1318: 52.5
A1319: 2024P | B1319: CA | C1319: BMTCB | D1319: 462829 | E1319: 499915 | F1319: 614870 | G1319: 690083
A1320: 2024P | B1320: CA | C1320: BQICB | D1320: 0 | E1320: 0 | F1320: 0 | G1320: 0
A1321: 2024P | B1321: CA | C1321: BQTCB | D1321: 0 | E1321: 0 | F1321: 0 | G1321: 0
A1322: 2024P | B1322: CA | C1322: BTCAS | D1322: 8 | E1322: 8.8 | F1322: 9.2 | G1322: 10.3
A1323: 2024P | B1323: CA | C1323: BTGBP | D1323: 2328 | E1323: 4864 | F1323: 7985 | G1323: 11717
... A1631: 2024P | B1631: CO | C1631: BDRUB | D1631: 0 | E1631: 0 | F1631: 0 | G1631: 0
A1632: 2024P | B1632: CO | C1632: BDSAB
A1633: 2024P | B1633: CO | C1633: BDSUB | D1633: 492 | E1633: 315 | F1633: 392 | G1633: 142
A1634: 2024P | B1634: CO | C1634: BDTCB | D1634: 856 | E1634: 537 | F1634: 622 | G1634: 219
A1635: 2024P | B1635: CO | C1635: BDTXB | D1635: 856 | E1635: 537 | F1635: 622 | G1635: 219
A1636: 2024P | B1636: CO | C1636: BDXUB | D1636: 492 | E1636: 315 | F1636: 392 | G1636: 142
A1637: 2024P | B1637: CO | C1637: BFLCB | D1637: 7440 | E1637: 7971 | F1637: 7619 | G1637: 7816
A1638: 2024P | B1638: CO | C1638: BFTCB | D1638: 27231 | E1638: 28142 | F1638: 26255 | G1638: 26526
A1639: 2024P | B1639: CO | C1639: BMCAS | D1639: 67.5 | E1639: 64.9 | F1639: 53.1 | G1639: 32.5
A1640: 2024P | B1640: CO | C1640: BMTCB | D1640: 36334 | E1640: 38941 | F1640: 35791 | G1640: 34951
A1641: 2024P | B1641: CO | C1641: BQICB | D1641: 0 | E1641: 0 | F1641: 0 | G1641: 0
A1642: 2024P | B1642: CO | C1642: BQTCB | D1642: 0 | E1642: 0 | F1642: 0 | G1642: 0
A1643: 2024P | B1643: CO | C1643: BTCAS | D1643: 1.3 | E1643: 1.9 | F1643: 9.8 | G1643: 12.4
A1644: 2024P | B1644: CO | C1644: BTGBP | D1644: 10 | E1644: 10 | F1644: 241 | G1644: 346
... A1952: 2024P | B1952: CT | C1952: BDRUB | D1952: 1996 | E1952: 2021 | F1952: 2136 | G1952: 2311
A1953: 2024P | B1953: CT | C1953: BDSAB
A1954: 2024P | B1954: CT | C1954: BDSUB | D1954: 2917 | E1954: 2897 | F1954: 3233 | G1954: 3472
A1955: 2024P | B1955: CT | C1955: BDTCB | D1955: 5078 | E1955: 4941 | F1955: 5138 | G1955: 5349
...

Sheet BAADTBVT-USA
A1: BAADTbVT-passengers
A2: Annual Distance (miles/vehicle) | B2: 2024 | C2: 2025 | D2: 2026 | E2: 2027 | F2: 2028 | G2: 2029 | H2: 2030 | I2: 2031 | J2: 2032 | K2: 2033 | L2: 2034 | M2: 2035 | N2: 2036 | O2: 2037 | P2: 2038 | Q2: 2039 | R2: 2040 | S2: 2041 | T2: 2042 | U2: 2043 | V2: 2044 | W2: 2045 | X2: 2046 | Y2: 2047 | Z2: 2048 | AA2: 2049 | AB2: 2050 | AC2: 2048 | AD2: 2049 | AE2: 2050
A3: LDVs | B3: 11354 | C3: 10518 | D3: 10488 | E3: 10461 | F3: 10399 | G3: 10327 | H3: 10237 | I3: 10141 | J3: 10051 | K3: 9948 | L3: 9859 | M3: 9767 | N3: 9694 | O3: 9628 | P3: 9565 | Q3: 9500 | R3: 9440 | S3: 9380 | T3: 9325 | U3: 9274 | V3: 9232 | W3: 9195 | X3: 9164 | Y3: 9133 | Z3: 9112 | AA3: 9095 | AB3: 9092 | AC3: 11804 | AD3: 11849 | AE3: 11900
A4: HDVs | B4: 16361 | C4: 16361 | D4: 16361 | E4: 16361 | F4: 16361 | G4: 16361 | H4: 16361 | I4: 16361 | J4: 16361 | K4: 16361 | L4: 16361 | M4: 16361 | N4: 16361 | O4: 16361 | P4: 16361 | Q4: 16361 | R4: 16361 | S4: 16361 | T4: 16361 | U4: 16361 | V4: 16361 | W4: 16361 | X4: 16361 | Y4: 16361 | Z4: 16361 | AA4: 16361 | AB4: 16361 | AC4: 16680 | AD4: 16680 | AE4: 16680
A5: aircraft | B5: 685003 | C5: 685003 | D5: 685003 | E5: 685003 | F5: 685003 | G5: 685003 | H5: 685003 | I5: 685003 | J5: 685003 | K5: 685003 | L5: 685003 | M5: 685003 | N5: 685003 | O5: 685003 | P5: 685003 | Q5: 685003 | R5: 685003 | S5: 685003 | T5: 685003 | U5: 685003 | V5: 685003 | W5: 685003 | X5: 685003 | Y5: 685003 | Z5: 685003 | AA5: 685003 | AB5: 685003 | AC5: 1366021 | AD5: 1370295 | AE5: 1374610
A6: rail | B6: 395569 | C6: 395569 | D6: 395569 | E6: 395569 | F6: 395569 | G6: 395569 | H6: 395569 | I6: 395569 | J6: 395569 | K6: 395569 | L6: 395569 | M6: 395569 | N6: 395569 | O6: 395569 | P6: 395569 | Q6: 395569 | R6: 395569 | S6: 395569 | T6: 395569 | U6: 395569 | V6: 395569 | W6: 395569 | X6: 395569 | Y6: 395569 | Z6: 395569 | AA6: 395569 | AB6: 395569 | AC6: 395569 | AD6: 395569 | AE6: 395569
A7: ships | B7: 194 | C7: 194 | D7: 194 | E7: 194 | F7: 194 | G7: 194 | H7: 194 | I7: 194 | J7: 194 | K7: 194 | L7: 194 | M7: 194 | N7: 194 | O7: 194 | P7: 194 | Q7: 194 | R7: 194 | S7: 194 | T7: 194 | U7: 194 | V7: 194 | W7: 194 | X7: 194 | Y7: 194 | Z7: 194 | AA7: 194 | AB7: 194 | AC7: 194 | AD7: 194 | AE7: 194
A8: motorbikes | B8: 8797 | C8: 8797 | D8: 8797 | E8: 8797 | F8: 8797 | G8: 8797 | H8: 8797 | I8: 8797 | J8: 8797 | K8: 8797 | L8: 8797 | M8: 8797 | N8: 8797 | O8: 8797 | P8: 8797 | Q8: 8797 | R8: 8797 | S8: 8797 | T8: 8797 | U8: 8797 | V8: 8797 | W8: 8797 | X8: 8797 | Y8: 8797 | Z8: 8797 | AA8: 8797 | AB8: 8797 | AC8: 2093 | AD8: 2093 | AE8: 2093
A10: BAADTbVT-freight
A11: Annual Distance (miles/vehicle) | B11: 2024 | C11: 2025 | D11: 2026 | E11: 2027 | F11: 2028 | G11: 2029 | H11: 2030 | I11: 2031 | J11: 2032 | K11: 2033 | L11: 2034 | M11: 2035 | N11: 2036 | O11: 2037 | P11: 2038 | Q11: 2039 | R11: 2040 | S11: 2041 | T11: 2042 | U11: 2043 | V11: 2044 | W11: 2045 | X11: 2046 | Y11: 2047 | Z11: 2048 | AA11: 2049 | AB11: 2050 | AC11: 2048 | AD11: 2049 | AE11: 2050
A12: LDVs | B12: 9797 | C12: 9797 | D12: 9782 | E12: 9778 | F12: 9750 | G12: 9718 | H12: 9714 | I12: 9691 | J12: 9669 | K12: 9644 | L12: 9645 | M12: 9658 | N12: 9681 | O12: 9721 | P12: 9777 | Q12: 9839 | R12: 9911 | S12: 9969 | T12: 10020 | U12: 10030 | V12: 10027 | W12: 10040 | X12: 10066 | Y12: 10101 | Z12: 10132 | AA12: 10185 | AB12: 10246 | AC12: 10690 | AD12: 10741 | AE12: 10830
A13: HDVs | B13: 35195 | C13: 35195 | D13: 35195 | E13: 35195 | F13: 35195 | G13: 35195 | H13: 35195 | I13: 35195 | J13: 35195 | K13: 35195 | L13: 35195 | M13: 35195 | N13: 35195 | O13: 35195 | P13: 35195 | Q13: 35195 | R13: 35195 | S13: 35195 | T13: 35195 | U13: 35195 | V13: 35195 | W13: 35195 | X13: 35195 | Y13: 35195 | Z13: 35195 | AA13: 35195 | AB13: 35195 | AC13: 31564 | AD13: 31573 | AE13: 31720
A14: aircraft | B14: 889421 | C14: 889421 | D14: 889421 | E14: 889421 | F14: 889421 | G14: 889421 | H14: 889421 | I14: 889421 | J14: 889421 | K14: 889421 | L14: 889421 | M14: 889421 | N14: 889421 | O14: 889421 | P14: 889421 | Q14: 889421 | R14: 889421 | S14: 889421 | T14: 889421 | U14: 889421 | V14: 889421 | W14: 889421 | X14: 889421 | Y14: 889421 | Z14: 889421 | AA14: 889421 | AB14: 889421 | AC14: 988086 | AD14: 988086 | AE14: 988086
A15: rail | B15: 17005 | C15: 17005 | D15: 17005 | E15: 17005 | F15: 17005 | G15: 17005 | H15: 17005 | I15: 17005 | J15: 17005 | K15: 17005 | L15: 17005 | M15: 17005 | N15: 17005 | O15: 17005 | P15: 17005 | Q15: 17005 | R15: 17005 | S15: 17005 | T15: 17005 | U15: 17005 | V15: 17005 | W15: 17005 | X15: 17005 | Y15: 17005 | Z15: 17005 | AA15: 17005 | AB15: 17005 | AC15: 18501 | AD15: 18501 | AE15: 18501
A16: ships | B16: 7513092 | C16: 7513092 | D16: 7513092 | E16: 7513092 | F16: 7513092 | G16: 7513092 | H16: 7513092 | I16: 7513092 | J16: 7513092 | K16: 7513092 | L16: 7513092 | M16: 7513092 | N16: 7513092 | O16: 7513092 | P16: 7513092 | Q16: 7513092 | R16: 7513092 | S16: 7513092 | T16: 7513092 | U16: 7513092 | V16: 7513092 | W16: 7513092 | X16: 7513092 | Y16: 7513092 | Z16: 7513092 | AA16: 7513092 | AB16: 7513092 | AC16: 218680 | AD16: 218680 | AE16: 218680
A17: motorbikes | B17: 0 | C17: 0 | D17: 0 | E17: 0 | F17: 0 | G17: 0 | H17: 0 | I17: 0 | J17: 0 | K17: 0 | L17: 0 | M17: 0 | N17: 0 | O17: 0 | P17: 0 | Q17: 0 | R17: 0 | S17: 0 | T17: 0 | U17: 0 | V17: 0 | W17: 0 | X17: 0 | Y17: 0 | Z17: 0 | AA17: 0 | AB17: 0 | AC17: 0 | AD17: 0 | AE17: 0

Sheet BPoEFUbVT-ships-frgt-dslveh
A1: Percentage Fuel Use (dimensionless) | B1: 2021
A2: electricity | B2: 0
A3: natural gas | B3: 0
A4: petroleum gasoline | B4: 0
A5: petroleum diesel | B5: 0.25
A6: biofuel gasoline | B6: 0
A7: biofuel diesel | B7: 0
A8: jet fuel | B8: 0
A9: heavy or residual fuel oil | B9: 0.75
A10: LPG propane or butane | B10: 0
A11: hydrogen | B11: 0

Sheet Scale to SEDS
B2: 1. Conversion Factors | C2: BTU per Gallon Liquid Fuels
C3: gasoline | D3: 120476
C4: diesel | D4: 137452
C5: billion | D5: =10^9 -> 1000000000
B7: 2. EIA Fuel Consumption | C7: EIA: Diesel and Gas Energy Consumption
C8: SEDS FUEL
C9: billion btu | E9: btu
E10: 2024
A11: JFACB | B11: AVACB | C11: Transportation | D11: JET FUEL | E11: =SUM(SUMIFS(SEDS_use_all_btu!G:G,SEDS_use_all_btu!B:B,About!$B$2,SEDS_use_all_btu!C:C,$A11),SUMIFS(SEDS_use_all_btu!G:G,SEDS_use_all_btu!B:B,About!$B$2,SEDS_use_all_btu!C:C,$B11))*$D$5 -> 107999000000000
A12: BDACB | B12: DFACB | C12: Transportation | D12: DIESEL | E12: =SUM(SUMIFS(SEDS_use_all_btu!G:G,SEDS_use_all_btu!B:B,About!$B$2,SEDS_use_all_btu!C:C,$A12),SUMIFS(SEDS_use_all_btu!G:G,SEDS_use_all_btu!B:B,About!$B$2,SEDS_use_all_btu!C:C,$B12))*$D$5 -> 110235000000000
B13: MGACB | C13: Transportation | D13: GASOLINE | E13: =SUMIFS(SEDS_use_all_btu!G:G,SEDS_use_all_btu!B:B,About!$B$2,SEDS_use_all_btu!C:C,$B13)*$D$5 -> 412731000000000
B14: RFACB | C14: Transportation | D14: RESIDUAL FUEL | E14: =SUMIFS(SEDS_use_all_btu!G:G,SEDS_use_all_btu!B:B,About!$B$2,SEDS_use_all_btu!C:C,$B14)*$D$5 -> 23811000000000
B17: 3. Estimated fuel consumption using US BAAD
C18: we estimate fuel consumption using US miles traveled and then scale to the specific state
E19: Gasoline Fuel | F19: Diesel Fuel | G19: jet fuel
C20: Transportation | E20: petroleum gasoline | F20: petroleum diesel | G20: jet fuel
D21: LDV-psgr | E21: =IFERROR(E101*E117*E132/E86,0) -> 3.4067846e+14 | F21: =IFERROR(F101*F117*F132/F86,0) -> 9.3121341e+11
D22: HDV-psgr | E22: =IFERROR(E102*E118*E133/E87,0) -> 9.6081982e+11 | F22: =IFERROR(F102*F118*F133/F87,0) -> 6.2934085e+12
D23: aircraft-psgr | G23: =IFERROR(G103*G119*G134/G88,0) -> 4.5335011e+13
D24: rail-psgr | E24: =IFERROR(E104*E120*E135/E89,0) -> 0 | F24: =IFERROR(F104*F120*F135/F89,0) -> 2.400306e+12
D25: ships-psgr | E25: =IFERROR(E105*E121*E136/E90,0) -> 2.283688e+12 | F25: =IFERROR(F105*F121*F136/F90,0) -> 5.567181e+11
D26: motorbikes | E26: =IFERROR(E106*E122*E137/E91,0) -> 8.9512649e+11 | F26: =IFERROR(F106*F122*F137/F91,0) -> 0
D27: LDV-frgt | E27: =IFERROR(E107*E123*E138/E92,0) -> 9.2802592e+12 | F27: =IFERROR(F107*F123*F138/F92,0) -> 8.2619793e+12
D28: HDV-frgt | E28: =IFERROR(E108*E124*E139/E93,0) -> 8.1107984e+11 | F28: =IFERROR(F108*F124*F139/F93,0) -> 1.0383828e+14
D29: aircraft-frgt | G29: =IFERROR(G109*G125*G140/G94,0) -> 7.209654e+12
D30: rail-frgt | E30: =IFERROR(E110*E126*E141/E95,0) -> 0 | F30: =IFERROR(F110*F126*F141/F95,0) -> 1.1472981e+13
D31: ships-frgt | E31: =IFERROR(E111*E127*E142/E96,0) -> 0 | F31: =IFERROR(F111*F127*F142/F96,0)*'BPoEFUbVT-ships-frgt-dslveh'!B5 -> 1.2315984e+11
D32: TOTAL | E32: =SUM(E21:E31) -> 3.5490944e+14 | F32: =SUM(F21:F31) -> 1.3387805e+14 | G32: =SUM(G21:G31) -> 5.2544665e+13
C34: percent of fuel consumption
E35: Gasoline Fuel | F35: Diesel Fuel | G35: jet fuel
C36: Transportation | E36: petroleum gasoline | F36: petroleum diesel | G36: jet fuel
D37: LDV-psgr | E37: =E21/E$32 -> 0.95990252 | F37: =F21/F$32 -> 0.0069556841 | G37: =G21/G$32 -> 0
D38: HDV-psgr | E38: =E22/E$32 -> 0.0027072254 | F38: =F22/F$32 -> 0.047008517 | G38: =G22/G$32 -> 0
D39: aircraft-psgr | E39: =E23/E$32 -> 0 | F39: =F23/F$32 -> 0 | G39: =G23/G$32 -> 0.86278999
D40: rail-psgr | E40: =E24/E$32 -> 0 | F40: =F24/F$32 -> 0.017929048 | G40: =G24/G$32 -> 0
D41: ships-psgr | E41: =E25/E$32 -> 0.0064345656 | F41: =F25/F$32 -> 0.0041583973 | G41: =G25/G$32 -> 0
D42: motorbikes | E42: =E26/E$32 -> 0.0025221265 | F42: =F26/F$32 -> 0 | G42: =G26/G$32 -> 0
D43: LDV-frgt | E43: =E27/E$32 -> 0.026148246 | F43: =F27/F$32 -> 0.061712727 | G43: =G27/G$32 -> 0
D44: HDV-frgt | E44: =E28/E$32 -> 0.002285315 | F44: =F28/F$32 -> 0.77561843 | G44: =G28/G$32 -> 0
D45: aircraft-frgt | E45: =E29/E$32 -> 0 | F45: =F29/F$32 -> 0 | G45: =G29/G$32 -> 0.13721001
D46: rail-frgt | E46: =E30/E$32 -> 0 | F46: =F30/F$32 -> 0.085697256 | G46: =G30/G$32 -> 0
D47: ships-frgt | E47: =E31/E$32 -> 0 | F47: =F31/F$32 -> 0.00091994052 | G47: =G31/G$32 -> 0
D48: TOTAL | E48: =SUM(E37:E47) -> 1 | F48: =SUM(F37:F47) -> 1 | G48: =SUM(G37:G47) -> 1
C50: Assigned state fuel consumption
E51: Gasoline Fuel | F51: Diesel Fuel | G51: jet fuel | H51: baad*bcd*avlo*syvbt/syfate
C52: Transportation | E52: petroleum gasoline | F52: petroleum diesel | G52: jet fuel
D53: LDV-psgr | E53: =E37*$E$13 -> 3.9618153e+14 | F53: =F37*$E$12 -> 7.6675984e+11 | G53: =G37*$E$11 -> 0
D54: HDV-psgr | E54: =E38*$E$13 -> 1.1173558e+12 | F54: =F38*$E$12 -> 5.1819839e+12 | G54: =G38*$E$11 -> 0
D55: aircraft-psgr | E55: =E39*$E$13 -> 0 | F55: =F39*$E$12 -> 0 | G55: =G39*$E$11 -> 9.3180456e+13
D56: rail-psgr | E56: =E40*$E$13 -> 0 | F56: =F40*$E$12 -> 1.9764086e+12 | G56: =G40*$E$11 -> 0
D57: ships-psgr | E57: =E41*$E$13 -> 2.6557447e+12 | F57: =F41*$E$12 -> 4.5840092e+11 | G57: =G41*$E$11 -> 0
D58: motorbikes | E58: =E42*$E$13 -> 1.0409598e+12 | F58: =F42*$E$12 -> 0 | G58: =G42*$E$11 -> 0
D59: LDV-frgt | E59: =E43*$E$13 -> 1.0792192e+13 | F59: =F43*$E$12 -> 6.8029024e+12 | G59: =G43*$E$11 -> 0
D60: HDV-frgt | E60: =E44*$E$13 -> 9.4322033e+11 | F60: =F44*$E$12 -> 8.5500298e+13 | G60: =G44*$E$11 -> 0
D61: aircraft-frgt | E61: =E45*$E$13 -> 0 | F61: =F45*$E$12 -> 0 | G61: =G45*$E$11 -> 1.4818544e+13
D62: rail-frgt | E62: =E46*$E$13 -> 0 | F62: =F46*$E$12 -> 9.446837e+12 | G62: =G46*$E$11 -> 0
D63: ships-frgt | E63: =E47*$E$13 -> 0 | F63: =F47*$E$12+E14 -> 2.391241e+13 | G63: =G47*$E$11 -> 0 | H63: <add residual fuel to freight ships
B66: 3. Readjusted BAADTVBT
E67: Gasoline Fuel | F67: Diesel Fuel | G67: jet fuel
C68: Transportation | E68: petroleum gasoline | F68: petroleum diesel | G68: jet fuel
D69: LDV-psgr | E69: =IFERROR(E53*E86/E101/E117,0) -> 13203.785 | F69: =IFERROR(F53*F86/F101/F117,0) -> 9348.868 | G69: =IFERROR(G53*G86/G101/G117,0) -> 0
D70: HDV-psgr | E70: =IFERROR(E54*E87/E102/E118,0) -> 19026.521 | F70: =IFERROR(F54*F87/F102/F118,0) -> 13471.625 | G70: =IFERROR(G54*G87/G102/G118,0) -> 0
D71: aircraft-psgr | E71: =IFERROR(E55*E88/E103/E119,0) -> 0 | F71: =IFERROR(F55*F88/F103/F119,0) -> 0 | G71: =IFERROR(G55*G88/G103/G119,0) -> 1407938.2
D72: rail-psgr | E72: =IFERROR(E56*E89/E104/E120,0) -> 0 | F72: =IFERROR(F56*F89/F104/F120,0) -> 325710.97 | G72: =IFERROR(G56*G89/G104/G120,0) -> 0
D73: ships-psgr | E73: =IFERROR(E57*E90/E105/E121,0) -> 225.60633 | F73: =IFERROR(F57*F90/F105/F121,0) -> 159.73933 | G73: =IFERROR(G57*G90/G105/G121,0) -> 0
D74: motorbikes | E74: =IFERROR(E58*E91/E106/E122,0) -> 10230.2 | F74: =IFERROR(F58*F91/F106/F122,0) -> 0 | G74: =IFERROR(G58*G91/G106/G122,0) -> 0
D75: LDV-frgt | E75: =IFERROR(E59*E92/E107/E123,0) -> 11393.119 | F75: =IFERROR(F59*F92/F107/F123,0) -> 8066.8363 | G75: =IFERROR(G59*G92/G107/G123,0) -> 0
D76: HDV-frgt | E76: =IFERROR(E60*E93/E108/E124,0) -> 40928.942 | F76: =IFERROR(F60*F93/F108/F124,0) -> 28979.515 | G76: =IFERROR(G60*G93/G108/G124,0) -> 0
D77: aircraft-frgt | E77: =IFERROR(E61*E94/E109/E125,0) -> 0 | F77: =IFERROR(F61*F94/F109/F125,0) -> 0 | G77: =IFERROR(G61*G94/G109/G125,0) -> 1828093.8
D78: rail-frgt | E78: =IFERROR(E62*E95/E110/E126,0) -> 0 | F78: =IFERROR(F62*F95/F110/F126,0) -> 14001.894 | G78: =IFERROR(G62*G95/G110/G126,0) -> 0
D79: ships-frgt | E79: =IFERROR(E63*E96/E111/E127,0) -> 0 | F79: =IFERROR(F63*F96/F111/F127,0) -> 9805246.2 | G79: =IFERROR(G63*G96/G111/G127,0) -> 0
B82: STATE DATA
C83: SYVFE
E84: gasoline vehicle | F84: diesel vehicle | G84: diesel vehicle
C85: Transportation | E85: petroleum gasoline | F85: petroleum diesel | G85: jet fuel
C86: LDVs | D86: LDV-psgr | E86: =SUMIFS('all_csv_SYFAFE-psgr'!E:E,'all_csv_SYFAFE-psgr'!$B:$B,$C86) -> 0.000308115 | F86: =SUMIFS('all_csv_SYFAFE-psgr'!F:F,'all_csv_SYFAFE-psgr'!$B:$B,$C86) -> 0.000349551
C87: HDVs | D87: HDV-psgr | E87: =SUMIFS('all_csv_SYFAFE-psgr'!E:E,'all_csv_SYFAFE-psgr'!$B:$B,$C87) -> 0.000851798 | F87: =SUMIFS('all_csv_SYFAFE-psgr'!F:F,'all_csv_SYFAFE-psgr'!$B:$B,$C87) -> 0.001033139
C88: aircraft | D88: aircraft-psgr | E88: =SUMIFS('all_csv_SYFAFE-psgr'!E:E,'all_csv_SYFAFE-psgr'!$B:$B,$C88) -> 0.000304649 | F88: =SUMIFS('all_csv_SYFAFE-psgr'!F:F,'all_csv_SYFAFE-psgr'!$B:$B,$C88) -> 0.000304649 | G88: =F88 -> 0.000304649
C89: rail | D89: rail-psgr | E89: =SUMIFS('all_csv_SYFAFE-psgr'!E:E,'all_csv_SYFAFE-psgr'!$B:$B,$C89) -> 5.05863e-05 | F89: =SUMIFS('all_csv_SYFAFE-psgr'!F:F,'all_csv_SYFAFE-psgr'!$B:$B,$C89) -> 5.05863e-05
C90: ships | D90: ships-psgr | E90: =SUMIFS('all_csv_SYFAFE-psgr'!E:E,'all_csv_SYFAFE-psgr'!$B:$B,$C90) -> 1.18724e-05 | F90: =SUMIFS('all_csv_SYFAFE-psgr'!F:F,'all_csv_SYFAFE-psgr'!$B:$B,$C90) -> 1.18724e-05
C91: motorbikes | D91: motorbikes | E91: =SUMIFS('all_csv_SYFAFE-psgr'!E:E,'all_csv_SYFAFE-psgr'!$B:$B,$C91) -> 0.001822391 | F91: =SUMIFS('all_csv_SYFAFE-psgr'!F:F,'all_csv_SYFAFE-psgr'!$B:$B,$C91) -> 0.001822391
C92: LDVs | D92: LDV-frgt | E92: =SUMIFS('all_csv_SYFAFE-frgt'!E:E,'all_csv_SYFAFE-frgt'!$B:$B,$C92) -> 9.3322264e-05 | F92: =SUMIFS('all_csv_SYFAFE-frgt'!F:F,'all_csv_SYFAFE-frgt'!$B:$B,$C92) -> 8.9590244e-05
C93: HDVs | D93: HDV-frgt | E93: =SUMIFS('all_csv_SYFAFE-frgt'!E:E,'all_csv_SYFAFE-frgt'!$B:$B,$C93) -> 0.0006720672 | F93: =SUMIFS('all_csv_SYFAFE-frgt'!F:F,'all_csv_SYFAFE-frgt'!$B:$B,$C93) -> 0.00075059325
C94: aircraft | D94: aircraft-frgt | E94: =SUMIFS('all_csv_SYFAFE-frgt'!E:E,'all_csv_SYFAFE-frgt'!$B:$B,$C94) -> 9.3239985e-05 | F94: =SUMIFS('all_csv_SYFAFE-frgt'!F:F,'all_csv_SYFAFE-frgt'!$B:$B,$C94) -> 9.3239985e-05 | G94: =F94 -> 9.3239985e-05
C95: rail | D95: rail-frgt | E95: =SUMIFS('all_csv_SYFAFE-frgt'!E:E,'all_csv_SYFAFE-frgt'!$B:$B,$C95) -> 0.00337345 | F95: =SUMIFS('all_csv_SYFAFE-frgt'!F:F,'all_csv_SYFAFE-frgt'!$B:$B,$C95) -> 0.00337345
C96: ships | D96: ships-frgt | E96: =SUMIFS('all_csv_SYFAFE-frgt'!E:E,'all_csv_SYFAFE-frgt'!$B:$B,$C96) -> 0.004857779 | F96: =SUMIFS('all_csv_SYFAFE-frgt'!F:F,'all_csv_SYFAFE-frgt'!$B:$B,$C96) -> 0.004857779
C98: SYVBT
C99: Tab is copied via script | E99: Gasoline Fuel | F99: Diesel Fuel | G99: jet fuel
C100: Transportation | E100: petroleum gasoline | F100: petroleum diesel | G100: jet fuel
C101: passenger | D101: LDVs | E101: =SUMIFS('all_csv_SYVbT-passenger'!E:E,'all_csv_SYVbT-passenger'!$B:$B,$D101,'all_csv_SYVbT-passenger'!$A:$A,About!$B$2) -> 5535950 | F101: =SUMIFS('all_csv_SYVbT-passenger'!F:F,'all_csv_SYVbT-passenger'!$B:$B,$D101,'all_csv_SYVbT-passenger'!$A:$A,About!$B$2) -> 17167
C102: passenger | D102: HDVs | E102: =SUMIFS('all_csv_SYVbT-passenger'!E:E,'all_csv_SYVbT-passenger'!$B:$B,$D102,'all_csv_SYVbT-passenger'!$A:$A,About!$B$2) -> 2360 | F102: =SUMIFS('all_csv_SYVbT-passenger'!F:F,'all_csv_SYVbT-passenger'!$B:$B,$D102,'all_csv_SYVbT-passenger'!$A:$A,About!$B$2) -> 18749
C103: passenger | D103: aircraft | E103: =SUMIFS('all_csv_SYVbT-passenger'!E:E,'all_csv_SYVbT-passenger'!$B:$B,$D103,'all_csv_SYVbT-passenger'!$A:$A,About!$B$2) -> 0 | F103: =SUMIFS('all_csv_SYVbT-passenger'!F:F,'all_csv_SYVbT-passenger'!$B:$B,$D103,'all_csv_SYVbT-passenger'!$A:$A,About!$B$2) -> 181 | G103: =F103 -> 181
C104: passenger | D104: rail | E104: =SUMIFS('all_csv_SYVbT-passenger'!E:E,'all_csv_SYVbT-passenger'!$B:$B,$D104,'all_csv_SYVbT-passenger'!$A:$A,About!$B$2) -> 0 | F104: =SUMIFS('all_csv_SYVbT-passenger'!F:F,'all_csv_SYVbT-passenger'!$B:$B,$D104,'all_csv_SYVbT-passenger'!$A:$A,About!$B$2) -> 20
C105: passenger | D105: ships | E105: =SUMIFS('all_csv_SYVbT-passenger'!E:E,'all_csv_SYVbT-passenger'!$B:$B,$D105,'all_csv_SYVbT-passenger'!$A:$A,About!$B$2) -> 139757 | F105: =SUMIFS('all_csv_SYVbT-passenger'!F:F,'all_csv_SYVbT-passenger'!$B:$B,$D105,'all_csv_SYVbT-passenger'!$A:$A,About!$B$2) -> 34070
C106: passenger | D106: motorbikes | E106: =SUMIFS('all_csv_SYVbT-passenger'!E:E,'all_csv_SYVbT-passenger'!$B:$B,$D106,'all_csv_SYVbT-passenger'!$A:$A,About!$B$2) -> 146003 | F106: =SUMIFS('all_csv_SYVbT-passenger'!F:F,'all_csv_SYVbT-passenger'!$B:$B,$D106,'all_csv_SYVbT-passenger'!$A:$A,About!$B$2) -> 0
C107: freight | D107: LDVs | E107: =SUMIFS('all_csv_SYVbT-freight'!E:E,'all_csv_SYVbT-freight'!$B:$B,$D107,'all_csv_SYVbT-freight'!$A:$A,About!$B$2) -> 88400 | F107: =SUMIFS('all_csv_SYVbT-freight'!F:F,'all_csv_SYVbT-freight'!$B:$B,$D107,'all_csv_SYVbT-freight'!$A:$A,About!$B$2) -> 75553
C108: freight | D108: HDVs | E108: =SUMIFS('all_csv_SYVbT-freight'!E:E,'all_csv_SYVbT-freight'!$B:$B,$D108,'all_csv_SYVbT-freight'!$A:$A,About!$B$2) -> 968 | F108: =SUMIFS('all_csv_SYVbT-freight'!F:F,'all_csv_SYVbT-freight'!$B:$B,$D108,'all_csv_SYVbT-freight'!$A:$A,About!$B$2) -> 138408
C109: freight | D109: aircraft | E109: =SUMIFS('all_csv_SYVbT-freight'!E:E,'all_csv_SYVbT-freight'!$B:$B,$D109,'all_csv_SYVbT-freight'!$A:$A,About!$B$2) -> 0 | F109: =SUMIFS('all_csv_SYVbT-freight'!F:F,'all_csv_SYVbT-freight'!$B:$B,$D109,'all_csv_SYVbT-freight'!$A:$A,About!$B$2) -> 18 | G109: =F109 -> 18
C110: freight | D110: rail | E110: =SUMIFS('all_csv_SYVbT-freight'!E:E,'all_csv_SYVbT-freight'!$B:$B,$D110,'all_csv_SYVbT-freight'!$A:$A,About!$B$2) -> 0 | F110: =SUMIFS('all_csv_SYVbT-freight'!F:F,'all_csv_SYVbT-freight'!$B:$B,$D110,'all_csv_SYVbT-freight'!$A:$A,About!$B$2) -> 648
C111: freight | D111: ships | E111: =SUMIFS('all_csv_SYVbT-freight'!E:E,'all_csv_SYVbT-freight'!$B:$B,$D111,'all_csv_SYVbT-freight'!$A:$A,About!$B$2) -> 0 | F111: =SUMIFS('all_csv_SYVbT-freight'!F:F,'all_csv_SYVbT-freight'!$B:$B,$D111,'all_csv_SYVbT-freight'!$A:$A,About!$B$2) -> 6
...

Sheet Annual Service Data_rail only
A1: Agency | B1: City | C1: State | D1: Legacy NTD ID | E1: NTD ID | F1: Organization Type | G1: NTD Reporter Type | H1: Primary UZA Population | I1: Agency VOMS | J1: Mode | K1: Type of Service | L1: Mode VOMS | M1: Mode VOMS Questionable | N1: Max Trains in Operation | O1: Max Trains in Operation Questionable | P1: Average Speed (mi/hr) | Q1: Average Speed (mi/hr) Questionable | R1: Average Passenger Trip Length (mi) | S1: Average Passenger Trip Length (mi) Questionable | T1: Passengers per Hour | U1: Passengers per Hour Questionable | V1: Scheduled Vehicle Revenue Miles | W1: Scheduled Vehicle Revenue Miles Questionable | X1: Vehicle Miles | Y1: Vehicle Miles Questionable | Z1: Vehicle Revenue Miles | AA1: Vehicle Revenue Miles Questionable | AB1: Deadhead Miles | AC1: Deadhead Miles Questionable | AD1: Vehicle Hours | AE1: Vehicle Hours Questionable | AF1: Vehicle Revenue Hours | AG1: Vehicle Revenue Hours Questionable | AH1: Deadhead Hours | AI1: Deadhead Hours Questionable | AJ1: Train Miles | AK1: Train Miles Questionable | AL1: Train Revenue Miles | AM1: Train Revenue Miles Questionable | AN1: Train Hours | AO1: Train Hours Questionable | AP1: Train Revenue Hours | AQ1: Train Revenue Hours Questionable | AR1: Unlinked Passenger Trips | AS1: Unlinked Passenger Trips Questionable | AT1: Passenger Miles | AU1: Passenger Miles Questionable | AV1: Directional Route Miles | AW1: Directional Route Miles Questionable | AX1: Any data questionable
A2: MTA New York City Transit | B2: Brooklyn | C2: NY | D2: 2008 | E2: 20008 | F2: Subsidiary Unit of a Transit Agency, Reporting Separately | G2: Full Reporter | H2: 18351295 | I2: 10427 | J2: HR | K2: DO | L2: 5413 | N2: 527 | P2: 18.2156 | R2: 4.2032 | T2: 62.4037 | V2: 376401985 | X2: 334949157 | Z2: 324782077 | AB2: 10167080 | AD2: 18782357 | AF2: 17829918 | AH2: 952439 | AJ2: 36770774 | AL2: 35625281 | AN2: 2060234 | AP2: 1955760 | AR2: 1112653405 | AT2: 4676670633 | AV2: 493.68 | AX2: No
A3: New Jersey Transit Corporation | B3: Newark | C3: NJ | D3: 2080 | E3: 20080 | F3: Other Publicly-Owned or Privately Chartered Corporation | G3: Full Reporter | H3: 18351295 | I3: 3646 | J3: LR | K3: PT | L3: 42 | N3: 20 | P3: 16.5765 | R3: 3.7544 | T3: 104.7091 | V3: 1809860 | X3: 1929113 | Z3: 1893039 | AB3: 36074 | AD3: 115699 | AF3: 114200 | AH3: 1499 | AJ3: 1096779 | AL3: 1076347 | AN3: 64689 | AP3: 63804 | AR3: 11957780 | AT3: 44894834 | AV3: 34.08 | AX3: No
A4: New Jersey Transit Corporation | B4: Newark | C4: NJ | D4: 2080 | E4: 20080 | F4: Other Publicly-Owned or Privately Chartered Corporation | G4: Full Reporter | H4: 18351295 | I4: 3646 | J4: LR | K4: DO | L4: 15 | N4: 15 | P4: 9.3913 | R4: 2.2517 | T4: 88.6621 | V4: 458806 | X4: 481308 | Z4: 470004 | AB4: 11304 | AD4: 55608 | AF4: 50047 | AH4: 5561 | AJ4: 481308 | AL4: 470004 | AN4: 55608 | AP4: 50047 | AR4: 4437270 | AT4: 9991369 | AV4: 12.42 | AX4: No
A5: New Jersey Transit Corporation | B5: Newark | C5: NJ | D5: 2080 | E5: 20080 | F5: Other Publicly-Owned or Privately Chartered Corporation | G5: Full Reporter | H5: 18351295 | I5: 3646 | J5: CR | K5: DO | L5: 904 | N5: 105 | P5: 32.758 | R5: 22.0101 | T5: 40.0147 | V5: 54847772 | X5: 57155030 | Z5: 54301350 | AB5: 2853680 | AD5: 1953118 | AF5: 1657653 | AH5: 295465 | AJ5: 8422625 | AL5: 7942892 | AN5: 287491 | AP5: 248272 | AR5: 66330426 | AT5: 1459936301 | AV5: 920.4 | AX5: No
A6: Los Angeles County Metropolitan Transportation Authority, dba: Metro | B6: Los Angeles | C6: CA | D6: 9154 | E6: 90154 | F6: Independent Public Agency or Authority of Transit Service | G6: Full Reporter | H6: 12150996 | I6: 3482 | J6: LR | K6: DO | L6: 203 | N6: 74 | P6: 20.558 | R6: 7.5713 | T6: 55.704 | V6: 15592469 | X6: 16090545 | Z6: 15536688 | AB6: 553857 | AD6: 792734 | AF6: 755749 | AH6: 36985 | AJ6: 6384468 | AL6: 6156417 | AN6: 309440 | AP6: 294220 | AR6: 42098255 | AT6: 318737668 | AV6: 171.92 | AX6: No
A7: Los Angeles County Metropolitan Transportation Authority, dba: Metro | B7: Los Angeles | C7: CA | D7: 9154 | E7: 90154 | F7: Independent Public Agency or Authority of Transit Service | G7: Full Reporter | H7: 12150996 | I7: 3482 | J7: HR | K7: DO | L7: 68 | N7: 13 | P7: 21.8993 | R7: 4.8392 | T7: 108.4073 | V7: 6821561 | X7: 6973555 | Z7: 6801301 | AB7: 172254 | AD7: 327668 | AF7: 310572 | AH7: 17096 | AJ7: 1383514 | AL7: 1350454 | AN7: 66480 | AP7: 63158 | AR7: 33668265 | AT7: 162927528 | AV7: 31.9 | AX7: No
A8: Washington Metropolitan Area Transit Authority | B8: Washington | C8: DC | D8: 3030 | E8: 30030 | F8: Independent Public Agency or Authority of Transit Service | G8: Full Reporter | H8: 4586770 | I8: 3304 | J8: HR | K8: DO | L8: 998 | N8: 129 | P8: 23.3386 | R8: 5.6487 | T8: 51.0164 | V8: 81860566 | X8: 82234530 | Z8: 79847615 | AB8: 2386915 | AD8: 3524685 | AF8: 3421264 | AH8: 103421 | AJ8: 11770449 | AL8: 11432619 | AN8: 505929 | AP8: 489793 | AR8: 174540714 | AT8: 985922295 | AV8: 234.2 | AX8: No
A9: Chicago Transit Authority | B9: Chicago | C9: IL | D9: 5066 | E9: 50066 | F9: Independent Public Agency or Authority of Transit Service | G9: Full Reporter | H9: 8608208 | I9: 2703 | J9: HR | K9: DO | L9: 1148 | N9: 158 | P9: 18.0276 | R9: 6.3144 | S9: W | T9: 19.7235 | V9: 82996946 | X9: 70519745 | Z9: 69510641 | AB9: 1009104 | AD9: 4177041 | AF9: 3855798 | AH9: 321243 | AJ9: 10533049 | AL9: 10388783 | AN9: 631507 | AP9: 582079 | AR9: 76049871 | AT9: 480210760 | AU9: W | AV9: 207.84 | AX9: Yes
A10: Massachusetts Bay Transportation Authority | B10: Boston | C10: MA | D10: 1003 | E10: 10003 | F10: Independent Public Agency or Authority of Transit Service | G10: Full Reporter | H10: 4181019 | I10: 2428 | J10: LR | K10: DO | L10: 154 | N10: 86 | P10: 7.3029 | R10: 2.3538 | T10: 57.7745 | V10: 5714964 | X10: 5260506 | Z10: 5241369 | AB10: 19137 | AD10: 726323 | AF10: 717709 | AH10: 8614 | AI10: Q | AJ10: 2876932 | AL10: 2870560 | AN10: 321018 | AP10: 315916 | AR10: 41465243 | AT10: 97602251 | AV10: 51 | AX10: Yes
A11: Massachusetts Bay Transportation Authority | B11: Boston | C11: MA | D11: 1003 | E11: 10003 | F11: Independent Public Agency or Authority of Transit Service | G11: Full Reporter | H11: 4181019 | I11: 2428 | J11: HR | K11: DO | L11: 338 | N11: 56 | P11: 16.7071 | R11: 3.5198 | T11: 87.0464 | V11: 23317516 | X11: 22746421 | Z11: 22203578 | AB11: 542843 | AD11: 1393950 | AF11: 1328990 | AH11: 64960 | AJ11: 3791070 | AL11: 3700596 | AN11: 253575 | AP11: 242748 | AR11: 115683733 | AT11: 407181618 | AV11: 76.3 | AX11: No
A12: Massachusetts Bay Transportation Authority | B12: Boston | C12: MA | D12: 1003 | E12: 10003 | F12: Independent Public Agency or Authority of Transit Service | G12: Full Reporter | H12: 4181019 | I12: 2428 | J12: CR | K12: PT | L12: 436 | N12: 67 | P12: 29.7292 | R12: 20.751 | T12: 33.01 | V12: 22195183 | X12: 22810502 | Z12: 22300695 | AB12: 509807 | AD12: 768699 | AF12: 750128 | AH12: 18571 | AJ12: 4189947 | AL12: 4093393 | AN12: 141215 | AP12: 137738 | AR12: 24761705 | AT12: 513830968 | AV12: 776.08 | AX12: No
A13: Southeastern Pennsylvania Transportation Authority | B13: Philadelphia | C13: PA | D13: 3019 | E13: 30019 | F13: Independent Public Agency or Authority of Transit Service | G13: Full Reporter | H13: 5441567 | I13: 2406 | J13: HR | K13: DO | L13: 286 | N13: 61 | P13: 17.0971 | R13: 4.4254 | S13: W | T13: 75.5141 | U13: W | V13: 16431036 | X13: 16168711 | Z13: 16089713 | AB13: 78998 | AD13: 945947 | AF13: 941080 | AH13: 4867 | AJ13: 3121305 | AL13: 3101700 | AN13: 182557 | AP13: 181391 | AR13: 71064786 | AS13: W | AT13: 314489396 | AU13: W | AV13: 74.9 | AX13: Yes
A14: Southeastern Pennsylvania Transportation Authority | B14: Philadelphia | C14: PA | D14: 3019 | E14: 30019 | F14: Independent Public Agency or Authority of Transit Service | G14: Full Reporter | H14: 5441567 | I14: 2406 | J14: CR | K14: DO | L14: 357 | N14: 84 | P14: 19.6909 | R14: 13.4494 | S14: W | T14: 29.7939 | U14: W | V14: 16896038 | X14: 17498310 | Z14: 16621821 | AB14: 876489 | AD14: 882766 | AF14: 844136 | AH14: 38630 | AJ14: 4453116 | AL14: 4225898 | AN14: 224140 | AP14: 214329 | AR14: 25150117 | AS14: W | AT14: 338253606 | AU14: W | AV14: 446.94 | AX14: Yes
A15: Metropolitan Transit Authority of Harris County, Texas, dba: Metro | B15: Houston | C15: TX | D15: 6008 | E15: 60008 | F15: Independent Public Agency or Authority of Transit Service | G15: Full Reporter | H15: 4944332 | I15: 2157 | J15: LR | K15: DO | L15: 56 | N15: 29 | P15: 12.1474 | R15: 2.9095 | T15: 48.3795 | V15: 3257209 | X15: 3247125 | Z15: 3236011 | AB15: 11114 | AD15: 268268 | AF15: 266396 | AH15: 1872 | AJ15: 1940638 | AL15: 1929524 | AN15: 176143 | AP15: 174271 | AR15: 12888105 | AT15: 37497523 | AV15: 43.59 | AX15: No
A16: Maryland Transit Administration | B16: Baltimore | C16: MD | D16: 3034 | E16: 30034 | F16: State Government Unit or Department of Transportation | G16: Full Reporter | H16: 2203663 | I16: 1888 | J16: LR | K16: DO | L16: 38 | N16: 18 | P16: 19.6769 | R16: 5.7128 | S16: W | T16: 35.3738 | V16: 2774375 | X16: 2676810 | Z16: 2588105 | AB16: 88705 | AD16: 138492 | AF16: 131530 | AH16: 6962 | AJ16: 1046361 | AL16: 1044905 | AN16: 58730 | AP16: 58193 | AR16: 4652718 | AT16: 26579844 | AU16: W | AV16: 57.6 | AX16: Yes
A17: Maryland Transit Administration | B17: Baltimore | C17: MD | D17: 3034 | E17: 30034 | F17: State Government Unit or Department of Transportation | G17: Full Reporter | H17: 2203663 | I17: 1888 | J17: HR | K17: DO | L17: 54 | N17: 9 | P17: 26.0926 | R17: 4.7674 | S17: W | T17: 36.698 | V17: 4289979 | X17: 4659371 | Z17: 4169492 | AB17: 489879 | AD17: 180401 | AF17: 159796 | AH17: 20605 | AJ17: 845652 | AL17: 734915 | AN17: 32887 | AP17: 28462 | AR17: 5864191 | AT17: 27957087 | AU17: W | AV17: 29.4 | AX17: Yes
A18: Maryland Transit Administration | B18: Baltimore | C18: MD | D18: 3034 | E18: 30034 | F18: State Government Unit or Department of Transportation | G18: Full Reporter | H18: 2203663 | I18: 1888 | J18: CR | K18: PT | L18: 149 | N18: 28 | P18: 38.3283 | R18: 29.5846 | S18: W | T18: 45.7479 | V18: 6001808 | X18: 5996542 | Z18: 5596811 | AB18: 399731 | AD18: 155174 | AF18: 146023 | AH18: 9151 | AJ18: 1094365 | AL18: 1036558 | AN18: 30902 | AP18: 28513 | AR18: 6680248 | AT18: 197632189 | AU18: W | AV18: 400.4 | AX18: Yes
A19: County of Miami-Dade, dba: Transportation & Public Work | B19: Miami | C19: FL | D19: 4034 | E19: 40034 | F19: City, County or Local Government Unit or Department of Transportation | G19: Full Reporter | H19: 5502379 | I19: 1452 | J19: HR | K19: DO | L19: 76 | N19: 18 | P19: 21.7622 | R19: 7.3831 | S19: W | T19: 35.9601 | V19: 7212362 | X19: 7598157 | Z19: 7178627 | AB19: 419530 | AD19: 362201 | AF19: 329867 | AH19: 32334 | AJ19: 1899556 | AL19: 1794673 | AN19: 90549 | AP19: 82465 | AR19: 11862059 | AT19: 87578321 | AU19: W | AV19: 49.84 | AX19: Yes
A20: Denver Regional Transportation District | B20: Denver | C20: CO | D20: 8006 | E20: 80006 | F20: Independent Public Agency or Authority of Transit Service | G20: Full Reporter | H20: 2374203 | I20: 1431 | J20: LR | K20: DO | L20: 156 | N20: 41 | P20: 17.2002 | R20: 6.9673 | T20: 19.8586 | V20: 9004264 | X20: 9327859 | Z20: 9063803 | AB20: 264056 | AD20: 590892 | AF20: 526960 | AH20: 63932 | AJ20: 3900081 | AL20: 3745938 | AN20: 267096 | AP20: 226007 | AR20: 10464678 | AT20: 72910951 | AV20: 119.78 | AX20: No
A21: Denver Regional Transportation District | B21: Denver | C21: CO | D21: 8006 | E21: 80006 | F21: Independent Public Agency or Authority of Transit Service | G21: Full Reporter | H21: 2374203 | I21: 1431 | J21: CR | K21: PT | L21: 44 | N21: 12 | P21: 27.5631 | R21: 11.5166 | T21: 21.7837 | V21: 6222945 | X21: 6197643 | Z21: 6048702 | AB21: 148941 | AD21: 228257 | AF21: 219449 | AH21: 8808 | AJ21: 2010537 | AL21: 1917204 | AN21: 74540 | AP21: 70293 | AR21: 4780402 | AT21: 55053882 | AV21: 72.76 | AX21: No
A22: Denver Regional Transportation District | B22: Denver | C22: CO | D22: 8006 | E22: 80006 | F22: Independent Public Agency or Authority of Transit Service | G22: Full Reporter | H22: 2374203 | I22: 1431 | J22: CR | K22: DO | L22: 8 | N22: 3 | P22: 20.4842 | R22: 8.6131 | T22: 18.0161 | V22: 203262 | X22: 223786 | Z22: 197570 | AB22: 26216 | AD22: 12511 | AF22: 9645 | AH22: 2866 | AJ22: 115030 | AL22: 98743 | AN22: 6243 | AP22: 4937 | AR22: 173765 | AT22: 1496661 | AV22: 26.32 | AX22: No
A23: Metro-North Commuter Railroad Company, dba: MTA Metro-North Railroad | B23: New York | C23: NY | D23: 2078 | E23: 20078 | F23: Subsidiary Unit of a Transit Agency, Reporting Separately | G23: Full Reporter | H23: 18351295 | I23: 1133 | J23: CR | K23: DO | L23: 1122 | N23: 135 | P23: 31.2997 | R23: 22.8524 | S23: W | T23: 18.8824 | V23: 47488237 | X23: 53139671 | Z23: 48719168 | AB23: 4420503 | AD23: 1709469 | AF23: 1556539 | AH23: 152930 | AJ23: 7201726 | AL23: 6564652 | AN23: 225218 | AP23: 203440 | AR23: 29391259 | AT23: 671661254 | AU23: W | AV23: 545.74 | AX23: Yes
A24: Dallas Area Rapid Transit | B24: Dallas | C24: TX | D24: 6056 | E24: 60056 | F24: Independent Public Agency or Authority of Transit Service | G24: Full Reporter | H24: 5121892 | I24: 1082 | J24: LR | K24: DO | L24: 117 | N24: 44 | P24: 20.5101 | R24: 8.1822 | T24: 41.7424 | V24: 9953657 | X24: 9937246 | Z24: 9866803 | AB24: 70443 | AD24: 486886 | AF24: 481071 | AH24: 5815 | AJ24: 5348975 | AL24: 5310292 | AN24: 261692 | AP24: 258495 | AR24: 20081036 | AT24: 164306746 | AV24: 182.44 | AX24: No
A25: Dallas Area Rapid Transit | B25: Dallas | C25: TX | D25: 6056 | E25: 60056 | F25: Independent Public Agency or Authority of Transit Service | G25: Full Reporter | H25: 5121892 | I25: 1082 | J25: CR | K25: PT | L25: 23 | N25: 3 | P25: 22.474 | R25: 17.3008 | T25: 20.2524 | V25: 1390207 | X25: 1437340 | Z25: 1404961 | AB25: 32379 | AD25: 63773 | AF25: 62515 | AH25: 1258 | AJ25: 506768 | AL25: 495677 | AN25: 22535 | AP25: 22090 | AR25: 1266076 | AT25: 21904126 | AV25: 72.3 | AX25: No
A26: Utah Transit Authority | B26: Salt Lake City | C26: UT | D26: 8001 | E26: 80001 | F26: Independent Public Agency or Authority of Transit Service | G26: Full Reporter | H26: 1021243 | I26: 1081 | J26: LR | K26: DO | L26: 89 | N26: 22 | P26: 17.1928 | R26: 4.7437 | T26: 23.1914 | V26: 6112222 | X26: 6204641 | Z26: 6114108 | AB26: 90533 | AD26: 367255 | AF26: 355621 | AH26: 11634 | AJ26: 2255583 | AL26: 2223959 | AN26: 136213 | AP26: 131989 | AR26: 8247364 | AT26: 39122864 | AV26: 93.91 | AX26: No
A27: Utah Transit Authority | B27: Salt Lake City | C27: UT | D27: 8001 | E27: 80001 | F27: Independent Public Agency or Authority of Transit Service | G27: Full Reporter | H27: 1021243 | I27: 1081 | J27: CR | K27: DO | L27: 50 | N27: 9 | P27: 32.4736 | R27: 25.6439 | T27: 16.2748 | V27: 4053946 | X27: 4051779 | Z27: 4039581 | AB27: 12198 | AD27: 128674 | AF27: 124396 | AH27: 4278 | AJ27: 1067699 | AL27: 1064546 | AN27: 33846 | AP27: 32741 | AR27: 2024524 | AT27: 51916777 | AV27: 174.46 | AX27: No
A28: Northeast Illinois Regional Commuter Railroad Corporation, dba: Metra | B28: Chicago | C28: IL | D28: 5118 | E28: 50118 | F28: Independent Public Agency or Authority of Transit Service | G28: Full Reporter | H28: 8608208 | I28: 1066 | J28: CR | K28: PT | L28: 527 | N28: 40 | P28: 30.9325 | R28: 21.7125 | T28: 18.9791 | V28: 16284231 | X28: 16302662 | Z28: 15388572 | AB28: 914090 | AD28: 520340 | AF28: 497488 | AH28: 22852 | AJ28: 2394714 | AL28: 2258067 | AN28: 76862 | AP28: 73504 | AR28: 9441882 | AT28: 205006670 | AV28: 399.6 | AX28: No
A29: Northeast Illinois Regional Commuter Railroad Corporation, dba: Metra | B29: Chicago | C29: IL | D29: 5118 | E29: 50118 | F29: Independent Public Agency or Authority of Transit Service | G29: Full Reporter | H29: 8608208 | I29: 1066 | J29: CR | K29: DO | L29: 539 | N29: 53 | P29: 29.0824 | R29: 21.1725 | T29: 13.8796 | V29: 16028080 | X29: 15585872 | Z29: 15273179 | AB29: 312693 | AD29: 535954 | AF29: 525169 | AH29: 10785 | AJ29: 2545102 | AL29: 2494601 | AN29: 89035 | AP29: 87312 | AR29: 7289149 | AT29: 154329520 | AV29: 575.4 | AX29: No
A30: MTA Long Island Rail Road | B30: Jamaica | C30: NY | D30: 2100 | E30: 20100 | F30: Subsidiary Unit of a Transit Agency, Reporting Separately | G30: Full Reporter | H30: 18351295 | I30: 1022 | J30: CR | K30: DO | L30: 1022 | N30: 107 | P30: 29.2123 | R30: 28.2692 | S30: W | T30: 20.566 | U30: W | V30: 61301708 | X30: 68469245 | Z30: 61766650 | AB30: 6702595 | AD30: 2305899 | AF30: 2114409 | AH30: 191490 | AJ30: 7765181 | AL30: 6968685 | AN30: 266731 | AP30: 199752 | AR30: 43484907 | AS30: W | AT30: 1229284540 | AU30: W | AV30: 638.2 | AX30: Yes
A31: City and County of San Francisco, dba: San Francisco Municipal Transportation Agency (MUNI) | B31: San Francisco | C31: CA | D31: 9015 | E31: 90015 | F31: City, County or Local Government Unit or Department of Transportation | G31: Full Reporter | H31: 3281212 | I31: 996 | J31: LR | K31: DO | L31: 149 | N31: 141 | P31: 9.497 | R31: 2.7421 | T31: 76.5848 | V31: 4944335 | X31: 4660934 | Z31: 4640244 | AB31: 20690 | AD31: 491748 | AF31: 488601 | AH31: 3147 | AJ31: 3097363 | AL31: 3084167 | AN31: 326422 | AP31: 324323 | AR31: 37419416 | AT31: 102607757 | AV31: 64.4 | AX31: No
A32: Tri-County Metropolitan Transportation District of Oregon, dba: TriMet | B32: Portland | C32: OR | D32: 8 | E32: 8 | F32: Independent Public Agency or Authority of Transit Service | G32: Full Reporter | H32: 1849898 | I32: 982 | J32: LR | K32: DO | L32: 116 | N32: 55 | P32: 14.1369 | R32: 5.2552 | T32: 48.3924 | V32: 8977599 | X32: 8981104 | Z32: 8864217 | AB32: 116887 | AD32: 636882 | AF32: 627025 | AH32: 9857 | AJ32: 4501055 | AL32: 4442373 | AN32: 319090 | AP32: 314140 | AR32: 30343267 | AT32: 159458488 | AV32: 118.91 | AX32: No
A33: Metropolitan Atlanta Rapid Transit Authority | B33: Atlanta | C33: GA | D33: 4022 | E33: 40022 | F33: Independent Public Agency or Authority of Transit Service | G33: Full Reporter | H33: 4515419 | I33: 943 | J33: HR | K33: DO | L33: 212 | N33: 39 | P33: 26.494 | R33: 7.2762 | T33: 58.7473 | V33: 20499724 | X33: 21145309 | Z33: 20430752 | AB33: 714557 | AD33: 794602 | AF33: 771146 | AH33: 23456 | AJ33: 3715370 | AL33: 3628801 | AN33: 143614 | AP33: 139086 | AR33: 45302714 | AT33: 329631085 | AV33: 96.06 | AX33: No
A34: Port Authority of Allegheny County | B34: Pittsburgh | C34: PA | D34: 3022 | E34: 30022 | F34: Independent Public Agency or Authority of Transit Service | G34: Full Reporter | H34: 1733853 | I34: 930 | J34: LR | K34: DO | L34: 58 | N34: 29 | P34: 12.9097 | R34: 4.0318 | T34: 37.5305 | V34: 2027777 | X34: 1999310 | Z34: 1916792 | AB34: 82518 | AD34: 155486 | AF34: 148477 | AH34: 7009 | AJ34: 1497766 | AL34: 1442245 | AN34: 116738 | AP34: 112071 | AR34: 5572417 | AT34: 22466673 | AV34: 49.64 | AX34: No
A35: San Diego Metropolitan Transit System | B35: San Diego | C35: CA | D35: 9026 | E35: 90026 | F35: Independent Public Agency or Authority of Transit Service | G35: Full Reporter | H35: 2956746 | I35: 906 | J35: LR | K35: DO | L35: 103 | N35: 35 | P35: 18.1208 | R35: 6.0708 | T35: 62.966 | V35: 9662505 | X35: 9410942 | Z35: 9210076 | AB35: 200866 | AD35: 527144 | AF35: 508259 | AH35: 18885 | AJ35: 3279625 | AL35: 3207856 | AN35: 183992 | AP35: 177429 | AR35: 32003027 | AT35: 194284885 | AV35: 108.4 | AX35: No
A36: Metro Transit, dba: Metro Transit | B36: Minneapolis | C36: MN | D36: 5027 | E36: 50027 | F36: Subsidiary Unit of a Transit Agency, Reporting Separately | G36: Full Reporter | H36: 2650890 | I36: 823 | J36: LR | K36: DO | L36: 76 | N36: 23 | P36: 11.9859 | R36: 3.9724 | S36: W | T36: 30.4653 | V36: 4237895 | X36: 4129925 | Z36: 4034814 | AB36: 95111 | AD36: 354913 | AF36: 336629 | AH36: 18284 | AJ36: 1500026 | AL36: 1436691 | AN36: 125192 | AP36: 118274 | AR36: 10255520 | AT36: 40738989 | AU36: W | AV36: 44.26 | AX36: Yes
A37: Metro Transit, dba: Metro Transit | B37: Minneapolis | C37: MN | D37: 5027 | E37: 50027 | F37: Subsidiary Unit of a Transit Agency, Reporting Separately | G37: Full Reporter | H37: 2650890 | I37: 823 | J37: CR | K37: PT | L37: 20 | N37: 4 | P37: 43.769 | R37: 24.7025 | S37: W | T37: 26.3444 | V37: 253487 | X37: 256360 | Z37: 253291 | AB37: 3069 | AD37: 6199 | AF37: 5787 | AH37: 412 | AJ37: 64139 | AL37: 63372 | AN37: 1552 | AP37: 1448 | AR37: 152455 | AT37: 3766017 | AU37: W | AV37: 77.9 | AX37: Yes
A38: Santa Clara Valley Transportation Authority | B38: San Jose | C38: CA | D38: 9013 | E38: 90013 | F38: Independent Public Agency or Authority of Transit Service | G38: Full Reporter | H38: 1664496 | I38: 635 | J38: LR | K38: DO | L38: 61 | N38: 29 | P38: 14.6876 | R38: 5.3386 | T38: 31.9576 | V38: 3049391 | X38: 3045104 | Z38: 2886997 | AB38: 158107 | AD38: 208938 | AF38: 196560 | AH38: 12378 | AJ38: 1824324 | AL38: 1733696 | AN38: 131172 | AP38: 123509 | AR38: 6281578 | AT38: 33535077 | AV38: 80.96 | AX38: No
A39: San Francisco Bay Area Rapid Transit District | B39: Oakland | C39: CA | D39: 9003 | E39: 90003 | F39: Independent Public Agency or Authority of Transit Service | G39: Full Reporter | H39: 3281212 | I39: 616 | J39: HR | K39: DO | L39: 599 | N39: 56 | P39: 34.8299 | Q39: W | R39: 13.963 | T39: 44.2609 | U39: W | V39: 69597595 | X39: 72050709 | Z39: 69799195 | AB39: 2251514 | AD39: 2377255 | AF39: 2004002 | AG39: W | AH39: 373253 | AJ39: 8255518 | AL39: 7973519 | AN39: 277276 | AP39: 229211 | AR39: 88698878 | AT39: 1238506222 | AV39: 239.42 | AX39: Yes
A40: Bi-State Development Agency of the Missouri-Illinois Metropolitan District, dba: St. Louis Metro | B40: Saint Louis | C40: MO | D40: 7006 | E40: 70006 | F40: Independent Public Agency or Authority of Transit Service | G40: Full Reporter | H40: 2150706 | I40: 493 | J40: LR | K40: DO | L40: 50 | N40: 25 | P40: 23.1905 | R40: 6.749 | T40: 41.7394 | V40: 5954691 | X40: 5905439 | Z40: 5839491 | AB40: 65948 | AD40: 256119 | AF40: 251805 | AH40: 4314 | AJ40: 2952712 | AL40: 2919745 | AN40: 128060 | AP40: 125902 | AR40: 10510179 | AT40: 70933375 | AV40: 91.06 | AX40: No
A41: The Greater Cleveland Regional Transit Authority | B41: Cleveland | C41: OH | D41: 5015 | E41: 50015 | F41: Independent Public Agency or Authority of Transit Service | G41: Full Reporter | H41: 1780673 | I41: 418 | J41: LR | K41: DO | L41: 6 | N41: 6 | P41: 14.0802 | R41: 3.5057 | S41: W | T41: 14.4611 | V41: 559327 | X41: 577077 | Z41: 573726 | AB41: 3351 | AD41: 41389 | AF41: 40747 | AH41: 642 | AJ41: 562513 | AL41: 559161 | AN41: 40336 | AP41: 39693 | AR41: 589245 | AT41: 2065735 | AU41: W | AV41: 30.38 | AX41: Yes
A42: The Greater Cleveland Regional Transit Authority | B42: Cleveland | C42: OH | D42: 5015 | E42: 50015 | F42: Independent Public Agency or Authority of Transit Service | G42: Full Reporter | H42: 1780673 | I42: 418 | J42: HR | K42: DO | L42: 16 | N42: 8 | P42: 19.0147 | R42: 6.9599 | S42: W | T42: 20.6055 | V42: 2472057 | X42: 2440418 | Z42: 2434523 | AB42: 5895 | AD42: 129302 | AF42: 128034 | AH42: 1268 | AJ42: 1238321 | AL42: 1235375 | AN42: 65610 | AP42: 64976 | AR42: 2638201 | AT42: 18361515 | AU42: W | AV42: 38.08 | AX42: Yes
A43: Transportation District Commission of Hampton Roads, dba: Hampton Roads Transit | B43: Hampton | C43: VA | D43: 3083 | E43: 30083 | F43: Independent Public Agency or Authority of Transit Service | G43: Full Reporter | H43: 1439666 | I43: 417 | J43: LR | K43: DO | L43: 6 | N43: 6 | P43: 13.2671 | R43: 3.2272 | T43: 40.309 | V43: 344336 | X43: 344847 | Z43: 343618 | AB43: 1229 | AD43: 26101 | AF43: 25900 | AH43: 201 | AJ43: 344847 | AL43: 343618 | AN43: 26101 | AP43: 25900 | AR43: 1044002 | AT43: 3369249 | AV43: 14.8 | AX43: No
A44: City of Charlotte North Carolina, dba: Charlotte Area Transit System | B44: Charlotte | C44: NC | D44: 4008 | E44: 40008 | F44: City, County or Local Government Unit or Department of Transportation | G44: Full Reporter | H44: 1249442 | I44: 409 | J44: LR | K44: DO | L44: 36 | N44: 16 | P44: 16.1408 | R44: 5.183 | T44: 55.5262 | V44: 2178959 | X44: 2267166 | Z44: 2110955 | AB44: 156211 | AD44: 138754 | AF44: 130784 | AH44: 7970 | AJ44: 1141671 | AL44: 1059265 | AN44: 69828 | AP44: 65622 | AR44: 7261944 | AT44: 37638865 | AV44: 37.3 | AX44: No
A45: Central Puget Sound Regional Transit Authority, dba: Sound Transit | B45: Seattle | C45: WA | D45: 40 | E45: 40 | F45: Independent Public Agency or Authority of Transit Service | G45: Full Reporter | H45: 3059393 | I45: 381 | J45: LR | K45: DO | L45: 48 | N45: 17 | P45: 18.259 | R45: 6.303 | T45: 35.3672 | V45: 3994837 | X45: 4168064 | Z45: 4078592 | AB45: 89472 | AD45: 233843 | AF45: 223374 | AH45: 10469 | AJ45: 1165448 | AL45: 1140397 | AN45: 65104 | AP45: 61879 | AR45: 7900122 | AT45: 49794569 | AV45: 40.4 | AX45: No
A46: Central Puget Sound Regional Transit Authority, dba: Sound Transit | B46: Seattle | C46: WA | D46: 40 | E46: 40 | F46: Independent Public Agency or Authority of Transit Service | G46: Full Reporter | H46: 3059393 | I46: 381 | J46: CR | K46: PT | L46: 70 | N46: 23 | P46: 30.1167 | R46: 25.1925 | T46: 24.971 | V46: 1617729 | X46: 1562310 | Z46: 1526737 | AB46: 35573 | AD46: 54020 | AF46: 50694 | AH46: 3326 | AJ46: 250453 | AL46: 244746 | AN46: 8818 | AP46: 8281 | AR46: 1265882 | AT46: 31890678 | AV46: 163.84 | AX46: No
A47: Niagara Frontier Transportation Authority | B47: Buffalo | C47: NY | D47: 2004 | E47: 20004 | F47: Independent Public Agency or Authority of Transit Service | G47: Full Reporter | H47: 935906 | I47: 359 | J47: LR | K47: DO | L47: 23 | N47: 7 | P47: 11.1447 | R47: 2.6665 | T47: 48.6101 | V47: 962940 | X47: 984827 | Z47: 968353 | AB47: 16474 | AD47: 91599 | AF47: 86889 | AH47: 4710 | AJ47: 347313 | AL47: 341503 | AN47: 32115 | AP47: 30462 | AR47: 4223681 | AT47: 11262397 | AV47: 12.4 | AX47: No
A48: Sacramento Regional Transit District, dba: Sacramento RT | B48: Sacramento | C48: CA | D48: 9019 | E48: 90019 | F48: Independent Public Agency or Authority of Transit Service | G48: Full Reporter | H48: 1723634 | I48: 331 | J48: LR | K48: DO | L48: 69 | N48: 18 | P48: 17.4438 | R48: 5.9108 | T48: 43.4332 | V48: 3637080 | X48: 3765256 | Z48: 3610107 | AB48: 155149 | AD48: 213385 | AF48: 206957 | AH48: 6428 | AJ48: 1757466 | AL48: 1710343 | AN48: 101083 | AP48: 98064 | AR48: 8988806 | AT48: 53131252 | AV48: 84.92 | AX48: No
A49: Fort Worth Transportation Authority, dba: Trinity Metro | B49: Fort Worth | C49: TX | D49: 6007 | E49: 60007 | F49: Independent Public Agency or Authority of Transit Service | G49: Full Reporter | H49: 5121892 | I49: 312 | J49: CR | K49: PT | L49: 20 | N49: 5 | P49: 19.5091 | R49: 15.8208 | S49: Q | T49: 2.8579 | U49: Q | V49: 2417541 | X49: 2349671 | Z49: 2320998 | AB49: 28673 | AD49: 120510 | AF49: 118970 | AH49: 1540 | AJ49: 587418 | AL49: 580250 | AM49: Q | AN49: 30128 | AP49: 29743 | AQ49: Q | AR49: 340008 | AS49: Q | AT49: 5379214 | AU49: Q | AV49: 52.34 | AX49: Yes
A50: Port Authority Trans-Hudson Corporation | B50: New York | C50: NJ | D50: 2098 | E50: 20098 | F50: Independent Public Agency or Authority of Transit Service | G50: Full Reporter | H50: 18351295 | I50: 310 | J50: HR | K50: DO | L50: 304 | N50: 33 | P50: 13.6246 | R50: 5.0684 | T50: 31.7035 | V50: 12823047 | X50: 13103345 | Z50: 12744198 | AB50: 359147 | AD50: 954091 | AF50: 935379 | AH50: 18712 | AJ50: 1753804 | AL50: 1705415 | AN50: 129406 | AP50: 126903 | AR50: 29654770 | AT50: 150302485 | AV50: 28.6 | AX50: No
A51: North County Transit District | B51: Oceanside | C51: CA | D51: 9030 | E51: 90030 | F51: Independent Public Agency or Authority of Transit Service | G51: Full Reporter | H51: 2956746 | I51: 205 | J51: CR | K51: PT | L51: 24 | N51: 4 | P51: 31.6775 | R51: 26.4412 | T51: 25.2045 | V51: 1181583 | X51: 1254334 | Z51: 1186577 | AB51: 67757 | AD51: 42212 | AF51: 37458 | AH51: 4754 | AJ51: 243076 | AL51: 230008 | AN51: 7881 | AP51: 7305 | AR51: 944109 | AT51: 24963395 | AV51: 82.2 | AX51: No
A52: Southern California Regional Rail Authority, dba: Metrolink | B52: Los Angeles | C52: CA | D52: 9151 | E52: 90151 | F52: Independent Public Agency or Authority of Transit Service | G52: Full Reporter | H52: 12150996 | I52: 195 | J52: CR | K52: PT | L52: 195 | N52: 40 | P52: 36.3401 | R52: 34.3582 | S52: W | T52: 26.0574 | U52: W | V52: 13061501 | X52: 13618637 | Z52: 13049429 | AB52: 569208 | AD52: 387165 | AF52: 359092 | AH52: 28073 | AJ52: 2786037 | AL52: 2674879 | AN52: 80963 | AP52: 73871 | AR52: 9357013 | AS52: W | AT52: 321490316 | AU52: W | AV52: 826.8 | AX52: Yes
A53: Peninsula Corridor Joint Powers Board, dba: Caltrain | B53: San Carlos | C53: CA | D53: 9134 | E53: 90134 | F53: Independent Public Agency or Authority of Transit Service | G53: Full Reporter | H53: 3281212 | I53: 141 | J53: CR | K53: PT | L53: 111 | N53: 20 | P53: 32.3387 | R53: 22.0776 | T53: 68.2619 | V53: 6469218 | X53: 6644705 | Z53: 6486852 | AB53: 157853 | AD53: 216487 | AF53: 200591 | AH53: 15896 | AJ53: 1179829 | AL53: 1151035 | AN53: 38509 | AP53: 35662 | AR53: 13692716 | AT53: 302302869 | AV53: 153.68 | AX53: No
A54: Virginia Railway Express | B54: Alexandria | C54: VA | D54: 3073 | E54: 30073 | F54: Independent Public Agency or Authority of Transit Service | G54: Full Reporter | H54: 4586770 | I54: 99 | J54: CR | K54: PT | L54: 99 | N54: 32 | P54: 30.8269 | R54: 30.3917 | T54: 46.2879 | V54: 2148620 | X54: 2234620 | Z54: 2146074 | AB54: 88546 | AD54: 76838 | AF54: 69617 | AH54: 7221 | AJ54: 333795 | AL54: 320541 | AN54: 11411 | AP54: 10330 | AR54: 3222428 | AT54: 97935058 | AV54: 173.62 | AX54: No
A55: Port Authority Transit Corporation | B55: Lindenwold | C55: NJ | D55: 2075 | E55: 20075 | F55: Independent Public Agency or Authority of Transit Service | G55: Full Reporter | H55: 5441567 | I55: 78 | J55: HR | K55: DO | L55: 78 | N55: 11 | P55: 31.0718 | R55: 8.5806 | T55: 27.4235 | V55: 5618718 | X55: 4662890 | Z55: 4474868 | AB55: 188022 | AD55: 154306 | AF55: 144017 | AH55: 10289 | AJ55: 899973 | AL55: 836001 | AN55: 31034 | AP55: 28828 | AR55: 3949450 | AT55: 33888694 | AV55: 31.5 | AX55: No
A56: Northern Indiana Commuter Transportation District | B56: Chesterton | C56: IN | D56: 5104 | E56: 50104 | F56: Independent Public Agency or Authority of Transit Service | G56: Full Reporter | H56: 8608208 | I56: 70 | J56: CR | K56: DO | L56: 70 | N56: 17 | P56: 34.7689 | R56: 33 | T56: 8.8186 | V56: 4013838 | X56: 3988838 | Z56: 3923145 | AB56: 65693 | AD56: 114811 | AF56: 112835 | AH56: 1976 | AJ56: 739801 | AL56: 724288 | AN56: 21331 | AP56: 20981 | AR56: 995049 | AT56: 32836617 | AV56: 179.8 | AX56: No
A57: South Florida Regional Transportation Authority, dba: TRI-Rail | B57: Pompano Beach | C57: FL | D57: 4077 | E57: 40077 | F57: Independent Public Agency or Authority of Transit Service | G57: Full Reporter | H57: 5502379 | I57: 65 | J57: CR | K57: PT | L57: 43 | N57: 10 | P57: 27.9588 | R57: 27.1649 | T57: 31.1711 | V57: 3327000 | X57: 3379135 | Z57: 3159070 | AB57: 220065 | AD57: 125765 | AF57: 112990 | AH57: 12775 | AJ57: 1016844 | AL57: 958905 | AN57: 37346 | AP57: 33681 | AR57: 3522017 | AT57: 95675095 | AV57: 142.24 | AX57: No
A58: Rio Metro Regional Transit District | B58: Albuquerque | C58: NM | D58: 6111 | E58: 60111 | F58: Independent Public Agency or Authority of Transit Service | G58: Full Reporter | H58: 741318 | I58: 58 | J58: CR | K58: PT | L58: 25 | N58: 7 | P58: 37.3762 | R58: 46.6062 | T58: 20.3422 | V58: 949106 | X58: 965030 | Z58: 948235 | AB58: 16795 | AD58: 26411 | AF58: 25370 | AH58: 1041 | AJ58: 350454 | AL58: 318879 | AN58: 8899 | AP58: 8580 | AR58: 516082 | AT58: 24052625 | AV58: 193.1 | AX58: No
A59: Alternativa de Transporte Integrado -ATI | B59: San Juan | C59: PR | D59: 4094 | E59: 40094 | F59: State Government Unit or Department of Transportation | G59: Full Reporter | H59: 2148346 | I59: 54 | J59: HR | K59: PT | L59: 32 | N59: 8 | P59: 18.2421 | R59: 4.7439 | T59: 48.9513 | V59: 1280494 | X59: 1388955 | Z59: 1315913 | AB59: 73042 | AD59: 75239 | AF59: 72136 | AH59: 3103 | AJ59: 434149 | AL59: 411208 | AN59: 23224 | AP59: 22380 | AR59: 3531150 | AT59: 16751299 | AV59: 20.62 | AX59: No
A60: Regional Transportation Authority | B60: Madison | C60: TN | D60: 4159 | E60: 40159 | F60: Independent Public Agency or Authority of Transit Service | G60: Full Reporter | H60: 969587 | I60: 46 | J60: CR | K60: PT | L60: 8 | N60: 2 | P60: 27.2001 | R60: 15.8946 | T60: 31.5783 | V60: 185032 | X60: 208873 | Z60: 184417 | AB60: 24456 | AD60: 9329 | AF60: 6780 | AH60: 2549 | AJ60: 80763 | AL60: 75873 | AN60: 3127 | AP60: 2616 | AR60: 214101 | AT60: 3403059 | AV60: 62.8 | AX60: No
A61: Staten Island Rapid Transit Operating Authority, dba: MTA Staten Island Railway | B61: Staten Island | C61: NY | D61: 2099 | E61: 20099 | F61: Subsidiary Unit of a Transit Agency, Reporting Separately | G61: Full Reporter | H61: 18351295 | I61: 44 | J61: HR | K61: DO | L61: 44 | N61: 11 | P61: 14.9787 | R61: 6.2369 | T61: 20.2651 | V61: 2119585 | X61: 2255067 | Z61: 2005981 | AB61: 249086 | AD61: 144198 | AF61: 133922 | AH61: 10276 | AJ61: 563767 | AL61: 501496 | AN61: 36049 | AP61: 33480 | AR61: 2713941 | AT61: 16926538 | AV61: 28.6 | AX61: No
A62: Connecticut Department of Transportation | B62: Newington | C62: CT | D62: 1102 | E62: 10102 | F62: State Government Unit or Department of Transportation | G62: Full Reporter | H62: 924859 | I62: 43 | J62: CR | K62: PT | L62: 28 | N62: 5 | P62: 41.5304 | R62: 26.9747 | T62: 14.137 | V62: 1532134 | X62: 1717047 | Z62: 1403229 | AB62: 313818 | AD62: 40817 | AF62: 33788 | AH62: 7029 | AJ62: 501997 | AL62: 418641 | AN62: 11906 | AP62: 9943 | AR62: 477660 | AT62: 12884750 | AV62: 101.2 | AX62: No
A63: Valley Metro Rail, Inc. | B63: Phoenix | C63: AZ | D63: 9209 | E63: 90209 | F63: Other Publicly-Owned or Privately Chartered Corporation | G63: Full Reporter | H63: 3629114 | I63: 38 | J63: LR | K63: PT | L63: 38 | N63: 17 | P63: 15.7327 | R63: 7.0599 | T63: 59.3261 | V63: 3379368 | X63: 3435184 | Z63: 3401452 | AB63: 33732 | AD63: 220467 | AF63: 216203 | AH63: 4264 | AJ63: 1639416 | AL63: 1623906 | AN63: 105253 | AP63: 103186 | AR63: 12826471 | AT63: 90553779 | AV63: 54.48 | AX63: No
A64: Altamont Corridor Express | B64: Stockton | C64: CA | D64: 9182 | E64: 90182 | F64: Independent Public Agency or Authority of Transit Service | G64: Full Reporter | H64: 370583 | I64: 35 | J64: CR | K64: PT | L64: 35 | N64: 7 | P64: 39.3647 | R64: 43.7104 | T64: 41.437 | V64: 1050950 | X64: 1050950 | Z64: 1008877 | AB64: 42073 | AD64: 31545 | AF64: 25629 | AH64: 5916 | AJ64: 168072 | AL64: 158131 | AN64: 4801 | AP64: 4126 | AR64: 1061990 | AT64: 46419957 | AV64: 172 | AX64: No
... A67: Pennsylvania Department of Transportation | B67: Harrisburg | C67: PA | D67: 3057 | E67: 30057 | F67: State Government Unit or Department of Transportation | G67: Full Reporter | H67: 5441567 | I67: 20 | J67: CR | K67: PT | L67: 20 | N67: 2 | P67: 56.7263 | R67: 86.2939 | T67: 20.1547 | V67: 2195188 | X67: 1628329 | Z67: 1628329 | AB67: 0 | AD67: 28705 | AF67: 28705 | AH67: 0 | AJ67: 325666 | AL67: 325666 | AN67: 5741 | AP67: 5741 | AR67: 578541 | AT67: 49924566 | AV67: 144.4 | AX67: No
A68: Sonoma-Marin Area Rail Transit District | B68: Petaluma | C68: CA | E68: 90299 | F68: Independent Public Agency or Authority of Transit Service | G68: Full Reporter | H68: 308231 | I68: 12 | J68: CR | K68: DO | L68: 12 | N68: 4 | P68: 28.3315 | R68: 23.8338 | T68: 19.56 | V68: 857003 | X68: 833350 | Z68: 821415 | AB68: 11935 | AD68: 30370 | AF68: 28993 | AH68: 1377 | AJ68: 389580 | AL68: 384000 | AN68: 14198 | AP68: 13554 | AR68: 567103 | AT68: 13516234 | AV68: 90.1 | AX68: No
N71: =SUM(N2:N68) -> 2748

Sheet Fuel and Energy_rail only
A1: Agency | B1: City | C1: State | D1: Legacy NTD ID | E1: NTD ID | F1: Organization Type | G1: Primary UZA Population | H1: Agency VOMS | I1: Mode | J1: TOS | K1: Mode VOMS | L1: Fuel/Energy Used: | M1: Diesel (gal) | N1: Diesel (gal) Questionable | O1: Gasoline (gal) | P1: Gasoline (gal) Questionable | Q1: Liquefied Petroleum Gas (gal equivalent) | R1: Liquefied Petroleum Gas (gal equivalent) Questionable | S1: Compressed Natural Gas (gal equivalent) | T1: Compressed Natural Gas (gal equivalent) Questionable | U1: Bio-Diesel (gal) | V1: Bio-Diesel (gal) Questionable | W1: Other Fuel (gal/gal equivalent) | X1: Other Fuel (gal/gal equivalent) Questionable | Y1: Electric Propulsion (kwh) | Z1: Electric Propulsion (kwh) Questionable | AA1: Electric Battery (kwh) | AB1: Electric Battery (kwh) Questionable | AC1: Miles Traveled by Vehicles Fueled by: | AD1: Diesel | AE1: Diesel Questionable | AF1: Gasoline | AG1: Gasoline Questionable | AH1: Liquefied Petroleum Gas | AI1: Liquefied Petroleum Gas Questionable | AJ1: Compressed Natural Gas | AK1: Compressed Natural Gas Questionable | AL1: Other Fuel | AM1: Other Fuel Questionable | AN1: Electric Propulsion | AO1: Electric Propulsion Questionable | AP1: Electric Battery | AQ1: Electric Battery Questionable | AR1: Miles per Gallon/KwH: | AS1: Diesel (mpg) | AT1: Diesel (mpg) Questionable | AU1: Gasoline (mpg) | AV1: Gasoline (mpg) Questionable | AW1: Liquefied Petroleum Gas (mpg) | AX1: Liquefied Petroleum Gas (mpg) Questionable | AY1: Compressed Natural Gas (mpg) | AZ1: Compressed Natural Gas (mpg) Questionable | BA1: Other Fuel (mpg) | BB1: Other Fuel (mpg) Questionable | BC1: Electric Propulsion (mi/kwh) | BD1: Electric Propulsion (mi/kwh) Questionable | BE1: Electric Battery (mi/kwh) | BF1: Electric Battery (mi/kwh) Questionable | BG1: Any data questionable?
A2: MTA New York City Transit | B2: Brooklyn | C2: NY | D2: 2008 | E2: 20008 | F2: Subsidiary Unit of a Transit Agency, Reporting Separately | G2: 18351295 | H2: 10427 | I2: HR | J2: DO | K2: 5413 | M2: 0 | O2: 0 | Q2: 0 | S2: 0 | U2: 0 | W2: 0 | Y2: 1596235000 | AA2: 0 | AD2: 0 | AF2: 0 | AH2: 0 | AJ2: 0 | AL2: 0 | AN2: 335497633 | AP2: 0 | BC2: 0.2102 | BG2: No
A3: New Jersey Transit Corporation | B3: Newark | C3: NJ | D3: 2080 | E3: 20080 | F3: Other Publicly-Owned or Privately Chartered Corporation | G3: 18351295 | H3: 3646 | I3: CR | J3: DO | K3: 904 | M3: 13166567 | O3: 0 | Q3: 0 | S3: 0 | U3: 0 | W3: 0 | Y3: 359673989 | AA3: 0 | AD3: 2485889 | AF3: 0 | AH3: 0 | AJ3: 0 | AL3: 1663636 | AN3: 8381067 | AP3: 0 | AS3: 0.1888 | BC3: 0.0233 | BG3: No
A4: New Jersey Transit Corporation | B4: Newark | C4: NJ | D4: 2080 | E4: 20080 | F4: Other Publicly-Owned or Privately Chartered Corporation | G4: 18351295 | H4: 3646 | I4: LR | J4: PT | K4: 42 | M4: 0 | O4: 0 | Q4: 0 | S4: 0 | U4: 0 | W4: 0 | Y4: 27163871 | AA4: 0 | AD4: 0 | AF4: 0 | AH4: 0 | AJ4: 0 | AL4: 0 | AN4: 2073346 | AP4: 0 | BC4: 0.0763 | BG4: No
A5: New Jersey Transit Corporation | B5: Newark | C5: NJ | D5: 2080 | E5: 20080 | F5: Other Publicly-Owned or Privately Chartered Corporation | G5: 18351295 | H5: 3646 | I5: LR | J5: DO | K5: 15 | M5: 0 | O5: 0 | Q5: 0 | S5: 0 | U5: 0 | W5: 0 | Y5: 6694675 | AA5: 0 | AD5: 0 | AF5: 0 | AH5: 0 | AJ5: 0 | AL5: 0 | AN5: 492775 | AP5: 0 | BC5: 0.0736 | BG5: No
A6: Los Angeles County Metropolitan Transportation Authority, dba: Metro | B6: Los Angeles | C6: CA | D6: 9154 | E6: 90154 | F6: Independent Public Agency or Authority of Transit Service | G6: 12150996 | H6: 3482 | I6: HR | J6: DO | K6: 68 | M6: 0 | O6: 0 | Q6: 0 | S6: 0 | U6: 0 | W6: 0 | Y6: 82163176 | AA6: 0 | AD6: 0 | AF6: 0 | AH6: 0 | AJ6: 0 | AL6: 0 | AN6: 6909214 | AP6: 0 | BC6: 0.0841 | BG6: No
A7: Los Angeles County Metropolitan Transportation Authority, dba: Metro | B7: Los Angeles | C7: CA | D7: 9154 | E7: 90154 | F7: Independent Public Agency or Authority of Transit Service | G7: 12150996 | H7: 3482 | I7: LR | J7: DO | K7: 203 | M7: 0 | O7: 0 | Q7: 0 | S7: 0 | U7: 0 | W7: 0 | Y7: 144995154 | AA7: 0 | AD7: 0 | AF7: 0 | AH7: 0 | AJ7: 0 | AL7: 0 | AN7: 16469107 | AP7: 0 | BC7: 0.1136 | BG7: No
A8: Washington Metropolitan Area Transit Authority | B8: Washington | C8: DC | D8: 3030 | E8: 30030 | F8: Independent Public Agency or Authority of Transit Service | G8: 4586770 | H8: 3304 | I8: HR | J8: DO | K8: 998 | M8: 0 | O8: 0 | Q8: 0 | S8: 0 | U8: 0 | W8: 0 | Y8: 576455528 | AA8: 0 | AD8: 0 | AF8: 0 | AH8: 0 | AJ8: 0 | AL8: 0 | AN8: 64920984 | AP8: 0 | BC8: 0.1126 | BG8: No
A9: Chicago Transit Authority | B9: Chicago | C9: IL | D9: 5066 | E9: 50066 | F9: Independent Public Agency or Authority of Transit Service | G9: 8608208 | H9: 2703 | I9: HR | J9: DO | K9: 1148 | M9: 0 | O9: 0 | Q9: 0 | S9: 0 | U9: 0 | W9: 0 | Y9: 366545522 | AA9: 0 | AD9: 0 | AF9: 0 | AH9: 0 | AJ9: 0 | AL9: 0 | AN9: 63157258 | AP9: 0 | BC9: 0.1723 | BG9: No
A10: Massachusetts Bay Transportation Authority | B10: Boston | C10: MA | D10: 1003 | E10: 10003 | F10: Independent Public Agency or Authority of Transit Service | G10: 4181019 | H10: 2428 | I10: CR | J10: PT | K10: 436 | M10: 13360985 | O10: 0 | Q10: 0 | S10: 0 | U10: 0 | W10: 0 | Y10: 0 | AA10: 0 | AD10: 4339139 | AF10: 0 | AH10: 0 | AJ10: 0 | AL10: 0 | AN10: 0 | AP10: 0 | AS10: 0.3248 | BG10: No
A11: Massachusetts Bay Transportation Authority | B11: Boston | C11: MA | D11: 1003 | E11: 10003 | F11: Independent Public Agency or Authority of Transit Service | G11: 4181019 | H11: 2428 | I11: HR | J11: DO | K11: 338 | M11: 0 | O11: 0 | Q11: 0 | S11: 0 | U11: 0 | W11: 0 | Y11: 178406868 | AA11: 0 | AD11: 0 | AF11: 0 | AH11: 0 | AJ11: 0 | AL11: 0 | AN11: 22078161 | AP11: 0 | BC11: 0.1238 | BG11: No
A12: Massachusetts Bay Transportation Authority | B12: Boston | C12: MA | D12: 1003 | E12: 10003 | F12: Independent Public Agency or Authority of Transit Service | G12: 4181019 | H12: 2428 | I12: LR | J12: DO | K12: 154 | M12: 0 | O12: 0 | Q12: 0 | S12: 0 | U12: 0 | W12: 0 | Y12: 46803331 | AA12: 0 | AD12: 0 | AF12: 0 | AH12: 0 | AJ12: 0 | AL12: 0 | AN12: 5523588 | AP12: 0 | BC12: 0.118 | BG12: No
A13: Southeastern Pennsylvania Transportation Authority | B13: Philadelphia | C13: PA | D13: 3019 | E13: 30019 | F13: Independent Public Agency or Authority of Transit Service | G13: 5441567 | H13: 2406 | I13: CR | J13: DO | K13: 357 | M13: 0 | O13: 0 | Q13: 0 | S13: 0 | U13: 0 | W13: 0 | Y13: 190958248 | AA13: 0 | AD13: 0 | AF13: 0 | AH13: 0 | AJ13: 0 | AL13: 0 | AN13: 15598066 | AP13: 0 | BC13: 0.0817 | BG13: No
A14: Southeastern Pennsylvania Transportation Authority | B14: Philadelphia | C14: PA | D14: 3019 | E14: 30019 | F14: Independent Public Agency or Authority of Transit Service | G14: 5441567 | H14: 2406 | I14: HR | J14: DO | K14: 286 | M14: 0 | O14: 0 | Q14: 0 | S14: 0 | U14: 0 | W14: 0 | Y14: 125067726 | AA14: 0 | AD14: 0 | AF14: 0 | AH14: 0 | AJ14: 0 | AL14: 0 | AN14: 14000061 | AP14: 0 | BC14: 0.1119 | BG14: No
A15: Metropolitan Transit Authority of Harris County, Texas, dba: Metro | B15: Houston | C15: TX | D15: 6008 | E15: 60008 | F15: Independent Public Agency or Authority of Transit Service | G15: 4944332 | H15: 2157 | I15: LR | J15: DO | K15: 56 | M15: 0 | O15: 0 | Q15: 0 | S15: 0 | U15: 0 | W15: 0 | Y15: 20764234 | AA15: 0 | AD15: 0 | AF15: 0 | AH15: 0 | AJ15: 0 | AL15: 0 | AN15: 3420524 | AP15: 0 | BC15: 0.1647 | BG15: No
A16: Maryland Transit Administration | B16: Baltimore | C16: MD | D16: 3034 | E16: 30034 | F16: State Government Unit or Department of Transportation | G16: 2203663 | H16: 1888 | I16: HR | J16: DO | K16: 54 | M16: 0 | O16: 0 | Q16: 0 | S16: 0 | U16: 0 | W16: 0 | Y16: 44465246 | AA16: 0 | AD16: 0 | AF16: 0 | AH16: 0 | AJ16: 0 | AL16: 0 | AN16: 0 | AP16: 0 | BC16: 0 | BG16: No
A17: Maryland Transit Administration | B17: Baltimore | C17: MD | D17: 3034 | E17: 30034 | F17: State Government Unit or Department of Transportation | G17: 2203663 | H17: 1888 | I17: LR | J17: DO | K17: 38 | M17: 0 | O17: 0 | Q17: 0 | S17: 0 | U17: 0 | W17: 0 | Y17: 25044315 | AA17: 0 | AD17: 0 | AF17: 0 | AH17: 0 | AJ17: 0 | AL17: 0 | AN17: 2679810 | AP17: 0 | BC17: 0.107 | BG17: No
A18: Maryland Transit Administration | B18: Baltimore | C18: MD | D18: 3034 | E18: 30034 | F18: State Government Unit or Department of Transportation | G18: 2203663 | H18: 1888 | I18: CR | J18: PT | K18: 149 | M18: 3709703 | O18: 0 | Q18: 0 | S18: 0 | U18: 0 | W18: 0 | Y18: 21715405 | AA18: 0 | AD18: 764117 | AF18: 0 | AH18: 0 | AJ18: 0 | AL18: 0 | AN18: 163832 | AP18: 0 | AS18: 0.206 | BC18: 0.0075 | BG18: No
A19: County of Miami-Dade, dba: Transportation & Public Work | B19: Miami | C19: FL | D19: 4034 | E19: 40034 | F19: City, County or Local Government Unit or Department of Transportation | G19: 5502379 | H19: 1452 | I19: HR | J19: DO | K19: 76 | M19: 0 | O19: 0 | Q19: 0 | S19: 0 | U19: 0 | W19: 0 | Y19: 66954261 | AA19: 0 | AD19: 0 | AF19: 0 | AH19: 0 | AJ19: 0 | AL19: 0 | AN19: 559892 | AP19: 0 | BC19: 0.0084 | BG19: No
A20: Denver Regional Transportation District | B20: Denver | C20: CO | D20: 8006 | E20: 80006 | F20: Independent Public Agency or Authority of Transit Service | G20: 2374203 | H20: 1431 | I20: CR | J20: DO | K20: 8 | M20: 0 | O20: 0 | Q20: 0 | S20: 0 | U20: 0 | W20: 0 | Y20: 688983 | AA20: 0 | AD20: 0 | AF20: 0 | AH20: 0 | AJ20: 0 | AL20: 0 | AN20: 0 | AP20: 0 | BC20: 0 | BG20: No
A21: Denver Regional Transportation District | B21: Denver | C21: CO | D21: 8006 | E21: 80006 | F21: Independent Public Agency or Authority of Transit Service | G21: 2374203 | H21: 1431 | I21: CR | J21: PT | K21: 44 | M21: 0 | O21: 0 | Q21: 0 | S21: 0 | U21: 0 | W21: 0 | Y21: 40149051 | AA21: 0 | AD21: 0 | AF21: 0 | AH21: 0 | AJ21: 0 | AL21: 0 | AN21: 6311542 | AP21: 0 | BC21: 0.1572 | BG21: No
A22: Denver Regional Transportation District | B22: Denver | C22: CO | D22: 8006 | E22: 80006 | F22: Independent Public Agency or Authority of Transit Service | G22: 2374203 | H22: 1431 | I22: LR | J22: DO | K22: 156 | M22: 0 | O22: 0 | Q22: 0 | S22: 0 | U22: 0 | W22: 0 | Y22: 60630772 | AA22: 0 | AD22: 0 | AF22: 0 | AH22: 0 | AJ22: 0 | AL22: 0 | AN22: 9327859 | AP22: 0 | BC22: 0.1538 | BG22: No
A23: Metro-North Commuter Railroad Company, dba: MTA Metro-North Railroad | B23: New York | C23: NY | D23: 2078 | E23: 20078 | F23: Subsidiary Unit of a Transit Agency, Reporting Separately | G23: 18351295 | H23: 1133 | I23: CR | J23: DO | K23: 1122 | M23: 5697351 | O23: 0 | Q23: 0 | S23: 0 | U23: 0 | W23: 0 | Y23: 367362724 | AA23: 0 | AD23: 0 | AF23: 0 | AH23: 0 | AJ23: 0 | AL23: 2002432 | AN23: 40070882 | AP23: 0 | AS23: 0 | BC23: 0.1091 | BG23: No
A24: Dallas Area Rapid Transit | B24: Dallas | C24: TX | D24: 6056 | E24: 60056 | F24: Independent Public Agency or Authority of Transit Service | G24: 5121892 | H24: 1082 | I24: CR | J24: PT | K24: 23 | M24: 1375987 | O24: 0 | Q24: 0 | S24: 0 | U24: 0 | W24: 0 | Y24: 0 | AA24: 0 | AD24: 460806 | AF24: 0 | AH24: 0 | AJ24: 0 | AL24: 0 | AN24: 0 | AP24: 0 | AS24: 0.3349 | BG24: No
A25: Dallas Area Rapid Transit | B25: Dallas | C25: TX | D25: 6056 | E25: 60056 | F25: Independent Public Agency or Authority of Transit Service | G25: 5121892 | H25: 1082 | I25: LR | J25: DO | K25: 117 | M25: 0 | O25: 0 | Q25: 0 | S25: 0 | U25: 0 | W25: 0 | Y25: 116183770 | AA25: 0 | AD25: 0 | AF25: 0 | AH25: 0 | AJ25: 0 | AL25: 0 | AN25: 9894309 | AP25: 0 | BC25: 0.0852 | BG25: No
A26: Utah Transit Authority | B26: Salt Lake City | C26: UT | D26: 8001 | E26: 80001 | F26: Independent Public Agency or Authority of Transit Service | G26: 1021243 | H26: 1081 | I26: LR | J26: DO | K26: 89 | M26: 0 | O26: 0 | Q26: 0 | S26: 0 | U26: 0 | W26: 0 | Y26: 39602347 | AA26: 0 | AD26: 0 | AF26: 0 | AH26: 0 | AJ26: 0 | AL26: 0 | AN26: 6307169 | AP26: 0 | BC26: 0.1593 | BG26: No
A27: Utah Transit Authority | B27: Salt Lake City | C27: UT | D27: 8001 | E27: 80001 | F27: Independent Public Agency or Authority of Transit Service | G27: 1021243 | H27: 1081 | I27: CR | J27: DO | K27: 50 | M27: 1921417 | O27: 0 | Q27: 0 | S27: 0 | U27: 0 | W27: 0 | Y27: 0 | AA27: 0 | AD27: 850933 | AF27: 0 | AH27: 0 | AJ27: 0 | AL27: 0 | AN27: 0 | AP27: 0 | AS27: 0.4429 | BG27: No
A28: Northeast Illinois Regional Commuter Railroad Corporation, dba: Metra | B28: Chicago | C28: IL | D28: 5118 | E28: 50118 | F28: Independent Public Agency or Authority of Transit Service | G28: 8608208 | H28: 1066 | I28: CR | J28: DO | K28: 539 | M28: 18100043 | O28: 0 | Q28: 0 | S28: 0 | U28: 0 | W28: 0 | Y28: 56262281 | AA28: 0 | AD28: 5202961 | AF28: 0 | AH28: 0 | AJ28: 0 | AL28: 0 | AN28: 3759786 | AP28: 0 | AS28: 0.2875 | BC28: 0.0668 | BG28: No
A29: Northeast Illinois Regional Commuter Railroad Corporation, dba: Metra | B29: Chicago | C29: IL | D29: 5118 | E29: 50118 | F29: Independent Public Agency or Authority of Transit Service | G29: 8608208 | H29: 1066 | I29: CR | J29: PT | K29: 527 | M29: 18100043 | O29: 0 | Q29: 0 | S29: 0 | U29: 0 | W29: 0 | Y29: 0 | AA29: 0 | AD29: 0 | AF29: 0 | AH29: 0 | AJ29: 0 | AL29: 0 | AN29: 0 | AP29: 0 | AS29: 0 | BG29: No
A30: MTA Long Island Rail Road | B30: Jamaica | C30: NY | D30: 2100 | E30: 20100 | F30: Subsidiary Unit of a Transit Agency, Reporting Separately | G30: 18351295 | H30: 1022 | I30: CR | J30: DO | K30: 1022 | M30: 7034074 | O30: 0 | Q30: 0 | S30: 0 | U30: 0 | W30: 0 | Y30: 471350200 | AA30: 0 | AD30: 757533 | AF30: 0 | AH30: 0 | AJ30: 0 | AL30: 757533 | AN30: 54919600 | AP30: 0 | AS30: 0.1077 | BC30: 0.1165 | BG30: No
A31: City and County of San Francisco, dba: San Francisco Municipal Transportation Agency (MUNI) | B31: San Francisco | C31: CA | D31: 9015 | E31: 90015 | F31: City, County or Local Government Unit or Department of Transportation | G31: 3281212 | H31: 996 | I31: LR | J31: DO | K31: 149 | M31: 0 | O31: 0 | Q31: 0 | S31: 0 | U31: 0 | W31: 0 | Y31: 51453351 | AA31: 0 | AD31: 0 | AF31: 0 | AH31: 0 | AJ31: 0 | AL31: 0 | AN31: 5286597 | AP31: 0 | BC31: 0.1027 | BG31: No
A32: Tri-County Metropolitan Transportation District of Oregon, dba: TriMet | B32: Portland | C32: OR | D32: 8 | E32: 8 | F32: Independent Public Agency or Authority of Transit Service | G32: 1849898 | H32: 982 | I32: LR | J32: DO | K32: 116 | M32: 0 | O32: 0 | Q32: 0 | S32: 0 | U32: 0 | W32: 0 | Y32: 54389715 | AA32: 0 | AD32: 0 | AF32: 0 | AH32: 0 | AJ32: 0 | AL32: 0 | AN32: 9045741 | AP32: 0 | BC32: 0.1663 | BG32: No
A33: Metropolitan Atlanta Rapid Transit Authority | B33: Atlanta | C33: GA | D33: 4022 | E33: 40022 | F33: Independent Public Agency or Authority of Transit Service | G33: 4515419 | H33: 943 | I33: HR | J33: DO | K33: 212 | M33: 0 | O33: 0 | Q33: 0 | S33: 0 | U33: 0 | W33: 0 | Y33: 83566447 | AA33: 0 | AD33: 0 | AF33: 0 | AH33: 0 | AJ33: 0 | AL33: 0 | AN33: 19692749 | AP33: 0 | BC33: 0.2357 | BG33: No
A34: Port Authority of Allegheny County | B34: Pittsburgh | C34: PA | D34: 3022 | E34: 30022 | F34: Independent Public Agency or Authority of Transit Service | G34: 1733853 | H34: 930 | I34: LR | J34: DO | K34: 58 | M34: 0 | O34: 0 | Q34: 0 | S34: 0 | U34: 0 | W34: 0 | Y34: 30547053 | AA34: 0 | AD34: 0 | AF34: 0 | AH34: 0 | AJ34: 0 | AL34: 0 | AN34: 2154526 | AP34: 0 | BC34: 0.0705 | BG34: No
A35: San Diego Metropolitan Transit System | B35: San Diego | C35: CA | D35: 9026 | E35: 90026 | F35: Independent Public Agency or Authority of Transit Service | G35: 2956746 | H35: 906 | I35: LR | J35: DO | K35: 103 | M35: 0 | O35: 0 | Q35: 0 | S35: 0 | U35: 0 | W35: 0 | Y35: 52502166 | AA35: 0 | AD35: 0 | AF35: 0 | AH35: 0 | AJ35: 0 | AL35: 0 | AN35: 9579691 | AP35: 0 | BC35: 0.1825 | BG35: No
A36: Metro Transit, dba: Metro Transit | B36: Minneapolis | C36: MN | D36: 5027 | E36: 50027 | F36: Subsidiary Unit of a Transit Agency, Reporting Separately | G36: 2650890 | H36: 823 | I36: LR | J36: DO | K36: 76 | M36: 0 | O36: 0 | Q36: 0 | S36: 0 | U36: 0 | W36: 0 | Y36: 31871652 | AA36: 0 | AD36: 0 | AF36: 0 | AH36: 0 | AJ36: 0 | AL36: 0 | AN36: 4153269 | AP36: 0 | BC36: 0.1303 | BG36: No
A37: Metro Transit, dba: Metro Transit | B37: Minneapolis | C37: MN | D37: 5027 | E37: 50027 | F37: Subsidiary Unit of a Transit Agency, Reporting Separately | G37: 2650890 | H37: 823 | I37: CR | J37: PT | K37: 20 | M37: 213780 | O37: 0 | Q37: 0 | S37: 0 | U37: 0 | W37: 0 | Y37: 0 | AA37: 0 | AD37: 63438 | AF37: 0 | AH37: 0 | AJ37: 0 | AL37: 0 | AN37: 0 | AP37: 0 | AS37: 0.2967 | BG37: No
A38: Santa Clara Valley Transportation Authority | B38: San Jose | C38: CA | D38: 9013 | E38: 90013 | F38: Independent Public Agency or Authority of Transit Service | G38: 1664496 | H38: 635 | I38: LR | J38: DO | K38: 61 | M38: 0 | O38: 0 | Q38: 0 | S38: 0 | U38: 0 | W38: 0 | Y38: 22062611 | AA38: 0 | AD38: 0 | AF38: 0 | AH38: 0 | AJ38: 0 | AL38: 0 | AN38: 3093884 | AP38: 0 | BC38: 0.1402 | BG38: No
A39: San Francisco Bay Area Rapid Transit District | B39: Oakland | C39: CA | D39: 9003 | E39: 90003 | F39: Independent Public Agency or Authority of Transit Service | G39: 3281212 | H39: 616 | I39: HR | J39: DO | K39: 599 | M39: 0 | O39: 0 | Q39: 0 | S39: 0 | U39: 0 | W39: 0 | Y39: 298200780 | AA39: 0 | AD39: 0 | AF39: 0 | AH39: 0 | AJ39: 0 | AL39: 0 | AN39: 61097126 | AP39: 0 | BC39: 0.2049 | BG39: No
A40: Bi-State Development Agency of the Missouri-Illinois Metropolitan District, dba: St. Louis Metro | B40: Saint Louis | C40: MO | D40: 7006 | E40: 70006 | F40: Independent Public Agency or Authority of Transit Service | G40: 2150706 | H40: 493 | I40: LR | J40: DO | K40: 50 | M40: 0 | O40: 0 | Q40: 0 | S40: 0 | U40: 0 | W40: 0 | Y40: 36496148 | AA40: 0 | AD40: 0 | AF40: 0 | AH40: 0 | AJ40: 0 | AL40: 0 | AN40: 5934378 | AP40: 0 | BC40: 0.1626 | BG40: No
A41: The Greater Cleveland Regional Transit Authority | B41: Cleveland | C41: OH | D41: 5015 | E41: 50015 | F41: Independent Public Agency or Authority of Transit Service | G41: 1780673 | H41: 418 | I41: LR | J41: DO | K41: 6 | M41: 0 | O41: 0 | Q41: 0 | S41: 0 | U41: 0 | W41: 0 | Y41: 11321758 | AA41: 0 | AD41: 0 | AF41: 0 | AH41: 0 | AJ41: 0 | AL41: 0 | AN41: 625941 | AP41: 0 | BC41: 0.0553 | BG41: No
A42: The Greater Cleveland Regional Transit Authority | B42: Cleveland | C42: OH | D42: 5015 | E42: 50015 | F42: Independent Public Agency or Authority of Transit Service | G42: 1780673 | H42: 418 | I42: HR | J42: DO | K42: 16 | M42: 0 | O42: 0 | Q42: 0 | S42: 0 | U42: 0 | W42: 0 | Y42: 20768378 | AA42: 0 | AD42: 0 | AF42: 0 | AH42: 0 | AJ42: 0 | AL42: 0 | AN42: 2295631 | AP42: 0 | BC42: 0.1105 | BG42: No
A43: Transportation District Commission of Hampton Roads, dba: Hampton Roads Transit | B43: Hampton | C43: VA | D43: 3083 | E43: 30083 | F43: Independent Public Agency or Authority of Transit Service | G43: 1439666 | H43: 417 | I43: LR | J43: DO | K43: 6 | M43: 0 | O43: 0 | Q43: 0 | S43: 0 | U43: 0 | W43: 0 | Y43: 3318000 | AA43: 0 | AD43: 0 | AF43: 0 | AH43: 0 | AJ43: 0 | AL43: 0 | AN43: 345837 | AP43: 0 | BC43: 0.1042 | BG43: No
A44: City of Charlotte North Carolina, dba: Charlotte Area Transit System | B44: Charlotte | C44: NC | D44: 4008 | E44: 40008 | F44: City, County or Local Government Unit or Department of Transportation | G44: 1249442 | H44: 409 | I44: LR | J44: DO | K44: 36 | M44: 0 | O44: 0 | Q44: 0 | S44: 0 | U44: 0 | W44: 0 | Y44: 16786660 | AA44: 0 | AD44: 0 | AF44: 0 | AH44: 0 | AJ44: 0 | AL44: 0 | AN44: 2267804 | AP44: 0 | BC44: 0.1351 | BG44: No
A45: Central Puget Sound Regional Transit Authority, dba: Sound Transit | B45: Seattle | C45: WA | D45: 40 | E45: 40 | F45: Independent Public Agency or Authority of Transit Service | G45: 3059393 | H45: 381 | I45: CR | J45: PT | K45: 70 | M45: 625305 | O45: 0 | Q45: 0 | S45: 0 | U45: 0 | W45: 0 | Y45: 0 | AA45: 0 | AD45: 335545 | AF45: 0 | AH45: 0 | AJ45: 0 | AL45: 0 | AN45: 0 | AP45: 0 | AS45: 0.5366 | BG45: No
A46: Central Puget Sound Regional Transit Authority, dba: Sound Transit | B46: Seattle | C46: WA | D46: 40 | E46: 40 | F46: Independent Public Agency or Authority of Transit Service | G46: 3059393 | H46: 381 | I46: LR | J46: DO | K46: 48 | M46: 0 | O46: 0 | Q46: 0 | S46: 0 | U46: 0 | W46: 0 | Y46: 20355203 | AA46: 0 | AD46: 0 | AF46: 0 | AH46: 0 | AJ46: 0 | AL46: 0 | AN46: 4232555 | AP46: 0 | BC46: 0.2079 | BG46: No
A47: Niagara Frontier Transportation Authority | B47: Buffalo | C47: NY | D47: 2004 | E47: 20004 | F47: Independent Public Agency or Authority of Transit Service | G47: 935906 | H47: 359 | I47: LR | J47: DO | K47: 23 | M47: 0 | O47: 0 | Q47: 0 | S47: 0 | U47: 0 | W47: 0 | Y47: 7920559 | AA47: 0 | AD47: 0 | AF47: 0 | AH47: 0 | AJ47: 0 | AL47: 0 | AN47: 990450 | AP47: 0 | BC47: 0.125 | BG47: No
A48: Sacramento Regional Transit District, dba: Sacramento RT | B48: Sacramento | C48: CA | D48: 9019 | E48: 90019 | F48: Independent Public Agency or Authority of Transit Service | G48: 1723634 | H48: 331 | I48: LR | J48: DO | K48: 69 | M48: 0 | O48: 0 | Q48: 0 | S48: 0 | U48: 0 | W48: 0 | Y48: 30089655 | AA48: 0 | AD48: 0 | AF48: 0 | AH48: 0 | AJ48: 0 | AL48: 0 | AN48: 3768892 | AP48: 0 | BC48: 0.1253 | BG48: No
A49: Fort Worth Transportation Authority, dba: Trinity Metro | B49: Fort Worth | C49: TX | D49: 6007 | E49: 60007 | F49: Independent Public Agency or Authority of Transit Service | G49: 5121892 | H49: 312 | I49: CR | J49: PT | K49: 20 | M49: 442412 | O49: 0 | Q49: 0 | S49: 0 | U49: 0 | W49: 0 | Y49: 0 | AA49: 0 | AD49: 2349673 | AF49: 0 | AH49: 0 | AJ49: 0 | AL49: 0 | AN49: 0 | AP49: 0 | AS49: 5.3111 | BG49: No
A50: Port Authority Trans-Hudson Corporation | B50: New York | C50: NJ | D50: 2098 | E50: 20098 | F50: Independent Public Agency or Authority of Transit Service | G50: 18351295 | H50: 310 | I50: HR | J50: DO | K50: 304 | M50: 0 | O50: 0 | Q50: 0 | S50: 0 | U50: 0 | W50: 0 | Y50: 93567629 | AA50: 0 | AD50: 0 | AF50: 0 | AH50: 0 | AJ50: 0 | AL50: 0 | AN50: 13256385 | AP50: 0 | BC50: 0.1417 | BG50: No
A51: North County Transit District | B51: Oceanside | C51: CA | D51: 9030 | E51: 90030 | F51: Independent Public Agency or Authority of Transit Service | G51: 2956746 | H51: 205 | I51: CR | J51: PT | K51: 24 | M51: 766773 | O51: 0 | Q51: 0 | S51: 0 | U51: 0 | W51: 0 | Y51: 0 | AA51: 0 | AD51: 253519 | AF51: 0 | AH51: 0 | AJ51: 0 | AL51: 0 | AN51: 0 | AP51: 0 | AS51: 0.3306 | BG51: No
A52: Southern California Regional Rail Authority, dba: Metrolink | B52: Los Angeles | C52: CA | D52: 9151 | E52: 90151 | F52: Independent Public Agency or Authority of Transit Service | G52: 12150996 | H52: 195 | I52: CR | J52: PT | K52: 195 | M52: 8293151 | O52: 0 | Q52: 0 | S52: 0 | U52: 0 | W52: 0 | Y52: 0 | AA52: 0 | AD52: 2539026 | AF52: 0 | AH52: 0 | AJ52: 0 | AL52: 0 | AN52: 0 | AP52: 0 | AS52: 0.3062 | BG52: No
A53: Peninsula Corridor Joint Powers Board, dba: Caltrain | B53: San Carlos | C53: CA | D53: 9134 | E53: 90134 | F53: Independent Public Agency or Authority of Transit Service | G53: 3281212 | H53: 141 | I53: CR | J53: PT | K53: 111 | M53: 3805923 | O53: 0 | Q53: 0 | S53: 0 | U53: 0 | W53: 0 | Y53: 0 | AA53: 0 | AD53: 1179829 | AF53: 0 | AH53: 0 | AJ53: 0 | AL53: 0 | AN53: 0 | AP53: 0 | AS53: 0.31 | BG53: No
A54: Virginia Railway Express | B54: Alexandria | C54: VA | D54: 3073 | E54: 30073 | F54: Independent Public Agency or Authority of Transit Service | G54: 4586770 | H54: 99 | I54: CR | J54: PT | K54: 99 | M54: 1430638 | O54: 0 | Q54: 0 | S54: 0 | U54: 0 | W54: 0 | Y54: 0 | AA54: 0 | AD54: 333956 | AF54: 0 | AH54: 0 | AJ54: 0 | AL54: 0 | AN54: 0 | AP54: 0 | AS54: 0.2334 | BG54: No
A55: Port Authority Transit Corporation | B55: Lindenwold | C55: NJ | D55: 2075 | E55: 20075 | F55: Independent Public Agency or Authority of Transit Service | G55: 5441567 | H55: 78 | I55: HR | J55: DO | K55: 78 | M55: 0 | O55: 0 | Q55: 0 | S55: 0 | U55: 0 | W55: 0 | Y55: 32179173 | AA55: 0 | AD55: 0 | AF55: 0 | AH55: 0 | AJ55: 0 | AL55: 0 | AN55: 4661254 | AP55: 0 | BC55: 0.1449 | BG55: No
A56: Northern Indiana Commuter Transportation District | B56: Chesterton | C56: IN | D56: 5104 | E56: 50104 | F56: Independent Public Agency or Authority of Transit Service | G56: 8608208 | H56: 70 | I56: CR | J56: DO | K56: 70 | M56: 0 | O56: 0 | Q56: 0 | S56: 0 | U56: 0 | W56: 0 | Y56: 18158000 | AA56: 0 | AD56: 0 | AF56: 0 | AH56: 0 | AJ56: 0 | AL56: 0 | AN56: 3510093 | AP56: 0 | BC56: 0.1933 | BG56: No
A57: South Florida Regional Transportation Authority, dba: TRI-Rail | B57: Pompano Beach | C57: FL | D57: 4077 | E57: 40077 | F57: Independent Public Agency or Authority of Transit Service | G57: 5502379 | H57: 65 | I57: CR | J57: PT | K57: 43 | M57: 2838234 | O57: 0 | Q57: 0 | S57: 0 | U57: 0 | W57: 0 | Y57: 0 | AA57: 0 | AD57: 1018267 | AF57: 0 | AH57: 0 | AJ57: 0 | AL57: 0 | AN57: 0 | AP57: 0 | AS57: 0.3588 | BG57: No
A58: Rio Metro Regional Transit District | B58: Albuquerque | C58: NM | D58: 6111 | E58: 60111 | F58: Independent Public Agency or Authority of Transit Service | G58: 741318 | H58: 58 | I58: CR | J58: PT | K58: 25 | M58: 0 | O58: 0 | Q58: 0 | S58: 0 | U58: 792273 | W58: 0 | Y58: 0 | AA58: 0 | AD58: 350453 | AF58: 0 | AH58: 0 | AJ58: 0 | AL58: 0 | AN58: 0 | AP58: 0 | BG58: No
A59: Alternativa de Transporte Integrado -ATI | B59: San Juan | C59: PR | D59: 4094 | E59: 40094 | F59: State Government Unit or Department of Transportation | G59: 2148346 | H59: 54 | I59: HR | J59: PT | K59: 32 | M59: 0 | O59: 0 | Q59: 0 | S59: 0 | U59: 0 | W59: 0 | Y59: 4009792 | AA59: 0 | AD59: 0 | AF59: 0 | AH59: 0 | AJ59: 0 | AL59: 0 | AN59: 1432878 | AP59: 0 | BC59: 0.3573 | BG59: No
A60: Regional Transportation Authority | B60: Madison | C60: TN | D60: 4159 | E60: 40159 | F60: Independent Public Agency or Authority of Transit Service | G60: 969587 | H60: 46 | I60: CR | J60: PT | K60: 8 | M60: 195054 | O60: 0 | Q60: 0 | S60: 0 | U60: 0 | W60: 0 | Y60: 0 | AA60: 0 | AD60: 71832 | AF60: 0 | AH60: 0 | AJ60: 0 | AL60: 0 | AN60: 0 | AP60: 0 | AS60: 0.3683 | BG60: No
A61: Staten Island Rapid Transit Operating Authority, dba: MTA Staten Island Railway | B61: Staten Island | C61: NY | D61: 2099 | E61: 20099 | F61: Subsidiary Unit of a Transit Agency, Reporting Separately | G61: 18351295 | H61: 44 | I61: HR | J61: DO | K61: 44 | M61: 0 | O61: 0 | Q61: 0 | S61: 0 | U61: 0 | W61: 0 | Y61: 27982542 | AA61: 0 | AD61: 0 | AF61: 0 | AH61: 0 | AJ61: 0 | AL61: 0 | AN61: 2267541 | AP61: 0 | BC61: 0.081 | BG61: No
A62: Connecticut Department of Transportation | B62: Newington | C62: CT | D62: 1102 | E62: 10102 | F62: State Government Unit or Department of Transportation | G62: 924859 | H62: 43 | I62: CR | J62: PT | K62: 28 | M62: 1678569 | O62: 0 | Q62: 0 | S62: 0 | U62: 0 | W62: 0 | Y62: 0 | AA62: 0 | AD62: 724004 | AF62: 0 | AH62: 0 | AJ62: 0 | AL62: 0 | AN62: 0 | AP62: 0 | AS62: 0.4313 | BG62: No
A63: Valley Metro Rail, Inc. | B63: Phoenix | C63: AZ | D63: 9209 | E63: 90209 | F63: Other Publicly-Owned or Privately Chartered Corporation | G63: 3629114 | H63: 38 | I63: LR | J63: PT | K63: 38 | M63: 0 | O63: 0 | Q63: 0 | S63: 0 | U63: 0 | W63: 0 | Y63: 23474521 | AA63: 0 | AD63: 0 | AF63: 0 | AH63: 0 | AJ63: 0 | AL63: 0 | AN63: 3452467 | AP63: 0 | BC63: 0.1471 | BG63: No
A64: Altamont Corridor Express | B64: Stockton | C64: CA | D64: 9182 | E64: 90182 | F64: Independent Public Agency or Authority of Transit Service | G64: 370583 | H64: 35 | I64: CR | J64: PT | K64: 35 | M64: 514210 | O64: 0 | Q64: 0 | S64: 0 | U64: 0 | W64: 0 | Y64: 0 | AA64: 0 | AD64: 130583 | AF64: 0 | AH64: 0 | AJ64: 0 | AL64: 0 | AN64: 0 | AP64: 0 | AS64: 0.2539 | BG64: No
A65: Central Florida Commuter Rail, dba: SunRail | B65: Tallahassee | C65: FL | D65: 4232 | E65: 40232 | F65: State Government Unit or Department of Transportation | G65: 1510516 | H65: 25 | I65: CR | J65: PT | K65: 25 | M65: 810032 | O65: 0 | Q65: 0 | S65: 0 | U65: 0 | W65: 0 | Y65: 0 | AA65: 0 | AD65: 486222 | AF65: 0 | AH65: 0 | AJ65: 0 | AL65: 0 | AN65: 0 | AP65: 0 | AS65: 0.6003 | BG65: No
A66: Northern New England Passenger Rail Authority | B66: Portland | C66: ME | D66: 1115 | E66: 10115 | F66: Independent Public Agency or Authority of Transit Service | G66: 203914 | H66: 21 | I66: CR | J66: PT | K66: 21 | M66: 628302 | O66: 0 | Q66: 0 | S66: 0 | U66: 0 | W66: 0 | Y66: 0 | AA66: 0 | AD66: 0 | AF66: 0 | AH66: 0 | AJ66: 0 | AL66: 0 | AN66: 0 | AP66: 0 | AS66: 0 | BG66: No
A67: Pennsylvania Department of Transportation | B67: Harrisburg | C67: PA | D67: 3057 | E67: 30057 | F67: State Government Unit or Department of Transportation | G67: 5441567 | H67: 20 | I67: CR | J67: PT | K67: 20 | M67: 0 | O67: 0 | Q67: 0 | S67: 0 | U67: 0 | W67: 0 | Y67: 27325354 | AA67: 0 | AD67: 0 | AF67: 0 | AH67: 0 | AJ67: 0 | AL67: 0 | AN67: 0 | AP67: 0 | BC67: 0 | BG67: No
A68: Sonoma-Marin Area Rail Transit District | B68: Petaluma | C68: CA | E68: 90299 | F68: Independent Public Agency or Authority of Transit Service | G68: 308231 | H68: 12 | I68: CR | J68: DO | K68: 12 | M68: 286520 | O68: 0 | Q68: 0 | S68: 0 | U68: 0 | W68: 0 | Y68: 0 | AA68: 0 | AD68: 931897 | AF68: 0 | AH68: 0 | AJ68: 0 | AL68: 0 | AN68: 0 | AP68: 0 | AS68: 3.2525 | BG68: No
M70: =SUM(M1:M68) -> 104995073 | N70: =SUM(N1:N68) -> 0 | O70: =SUM(O1:O68) -> 0 | P70: =SUM(P1:P68) -> 0 | Q70: =SUM(Q1:Q68) -> 0 | R70: =SUM(R1:R68) -> 0 | S70: =SUM(S1:S68) -> 0 | T70: =SUM(T1:T68) -> 0 | ... AB70: =SUM(AB1:AB68) -> 0

Sheet psgr rail calcs
B2: btu/gallon diesel | C2: 138700
B3: btu/kwh | C3: 3412.14
B4: Mode | C4: Rail types | D4: HR | E4: CR | F4: LR
E6: Number of Vehicles and Miles | P6: Vehicle Fuel Use
H7: Miles Traveled by Vehicles Fueled by:
B8: State | C8: State | D8: subregion | E8: Max Trains in Operation | F8: Vehicle Miles | G8: Passenger Miles | H8: Diesel | I8: Electric Propulsion | J8: % of miles diesel | K8: % of miles electric | L8: calc AVLO | M8: calc BAADTVBT | N8: SYVBT-diesel | O8: SYVBT-electric | P8: Diesel (gal) | Q8: Bio-Diesel (gal) | R8: Electric Propulsion (kwh) | S8: diesel (btus) | T8: electric (btu) | U8: calc SYFAFE-diesel | V8: calc SYFAFE-electric
B9: Alabama | C9: AL | D9: subregion1 | E9: =SUMIFS('Annual Service Data_rail only'!N:N,'Annual Service Data_rail only'!C:C,C9) -> 0 | F9: =SUMIFS('Annual Service Data_rail only'!X:X,'Annual Service Data_rail only'!C:C,C9) -> 0 | G9: =SUMIFS('Annual Service Data_rail only'!AT:AT,'Annual Service Data_rail only'!C:C,C9) -> 0 | H9: =SUMIFS('Fuel and Energy_rail only'!AD:AD,'Fuel and Energy_rail only'!C:C,C9) -> 0 | I9: =SUMIFS('Fuel and Energy_rail only'!AN:AN,'Fuel and Energy_rail only'!C:C,C9) -> 0 | J9: =IFERROR(H9/SUM($H9:$I9),0) -> 0 | K9: =IFERROR(I9/SUM($H9:$I9),0) -> 0 | L9: =IFERROR(G9/F9,0) -> 0 | M9: =IFERROR(F9/E9,0) -> 0 | N9: =E9*J9 -> 0 | O9: =K9*E9 -> 0 | P9: =SUMIFS('Fuel and Energy_rail only'!M:M,'Fuel and Energy_rail only'!C:C,C9) -> 0 | Q9: =SUMIFS('Fuel and Energy_rail only'!U:U,'Fuel and Energy_rail only'!C:C,C9) -> 0 | R9: =SUMIFS('Fuel and Energy_rail only'!Y:Y,'Fuel and Energy_rail only'!C:C,C9) -> 0 | S9: =SUM(P9:Q9)*$C$2 -> 0 | T9: =R9*$C$3 -> 0 | U9: =IFERROR(($L9*$M9*N9)/S9,0) -> 0 | V9: =IFERROR(($L9*$M9*O9)/T9,0) -> 0
B10: Alaska | C10: AK | D10: subregion2 | E10: =SUMIFS('Annual Service Data_rail only'!N:N,'Annual Service Data_rail only'!C:C,C10) -> 0 | F10: =SUMIFS('Annual Service Data_rail only'!X:X,'Annual Service Data_rail only'!C:C,C10) -> 0 | G10: =SUMIFS('Annual Service Data_rail only'!AT:AT,'Annual Service Data_rail only'!C:C,C10) -> 0 | H10: =SUMIFS('Fuel and Energy_rail only'!AD:AD,'Fuel and Energy_rail only'!C:C,C10) -> 0 | I10: =SUMIFS('Fuel and Energy_rail only'!AN:AN,'Fuel and Energy_rail only'!C:C,C10) -> 0 | J10: =IFERROR(H10/SUM($H10:$I10),0) -> 0 | K10: =IFERROR(I10/SUM($H10:$I10),0) -> 0 | L10: =IFERROR(G10/F10,0) -> 0 | M10: =IFERROR(F10/E10,0) -> 0 | N10: =E10*J10 -> 0 | O10: =K10*E10 -> 0 | P10: =SUMIFS('Fuel and Energy_rail only'!M:M,'Fuel and Energy_rail only'!C:C,C10) -> 0 | Q10: =SUMIFS('Fuel and Energy_rail only'!U:U,'Fuel and Energy_rail only'!C:C,C10) -> 0 | R10: =SUMIFS('Fuel and Energy_rail only'!Y:Y,'Fuel and Energy_rail only'!C:C,C10) -> 0 | S10: =SUM(P10:Q10)*$C$2 -> 0 | T10: =R10*$C$3 -> 0 | U10: =IFERROR(($L10*$M10*N10)/S10,0) -> 0 | V10: =IFERROR(($L10*$M10*O10)/T10,0) -> 0
B11: Arizona | C11: AZ | D11: subregion3 | E11: =SUMIFS('Annual Service Data_rail only'!N:N,'Annual Service Data_rail only'!C:C,C11) -> 17 | F11: =SUMIFS('Annual Service Data_rail only'!X:X,'Annual Service Data_rail only'!C:C,C11) -> 3435184 | G11: =SUMIFS('Annual Service Data_rail only'!AT:AT,'Annual Service Data_rail only'!C:C,C11) -> 90553779 | H11: =SUMIFS('Fuel and Energy_rail only'!AD:AD,'Fuel and Energy_rail only'!C:C,C11) -> 0 | I11: =SUMIFS('Fuel and Energy_rail only'!AN:AN,'Fuel and Energy_rail only'!C:C,C11) -> 3452467 | J11: =IFERROR(H11/SUM($H11:$I11),0) -> 0 | K11: =IFERROR(I11/SUM($H11:$I11),0) -> 1 | L11: =IFERROR(G11/F11,0) -> 26.360678 | M11: =IFERROR(F11/E11,0) -> 202069.65 | N11: =E11*J11 -> 0 | O11: =K11*E11 -> 17 | P11: =SUMIFS('Fuel and Energy_rail only'!M:M,'Fuel and Energy_rail only'!C:C,C11) -> 0 | Q11: =SUMIFS('Fuel and Energy_rail only'!U:U,'Fuel and Energy_rail only'!C:C,C11) -> 0 | R11: =SUMIFS('Fuel and Energy_rail only'!Y:Y,'Fuel and Energy_rail only'!C:C,C11) -> 23474521 | S11: =SUM(P11:Q11)*$C$2 -> 0 | T11: =R11*$C$3 -> 8.0098352e+10 | U11: =IFERROR(($L11*$M11*N11)/S11,0) -> 0 | V11: =IFERROR(($L11*$M11*O11)/T11,0) -> 0.0011305324
B12: Arkansas | C12: AR | D12: subregion4 | E12: =SUMIFS('Annual Service Data_rail only'!N:N,'Annual Service Data_rail only'!C:C,C12) -> 0 | F12: =SUMIFS('Annual Service Data_rail only'!X:X,'Annual Service Data_rail only'!C:C,C12) -> 0 | G12: =SUMIFS('Annual Service Data_rail only'!AT:AT,'Annual Service Data_rail only'!C:C,C12) -> 0 | H12: =SUMIFS('Fuel and Energy_rail only'!AD:AD,'Fuel and Energy_rail only'!C:C,C12) -> 0 | I12: =SUMIFS('Fuel and Energy_rail only'!AN:AN,'Fuel and Energy_rail only'!C:C,C12) -> 0 | J12: =IFERROR(H12/SUM($H12:$I12),0) -> 0 | K12: =IFERROR(I12/SUM($H12:$I12),0) -> 0 | L12: =IFERROR(G12/F12,0) -> 0 | M12: =IFERROR(F12/E12,0) -> 0 | N12: =E12*J12 -> 0 | O12: =K12*E12 -> 0 | P12: =SUMIFS('Fuel and Energy_rail only'!M:M,'Fuel and Energy_rail only'!C:C,C12) -> 0 | Q12: =SUMIFS('Fuel and Energy_rail only'!U:U,'Fuel and Energy_rail only'!C:C,C12) -> 0 | R12: =SUMIFS('Fuel and Energy_rail only'!Y:Y,'Fuel and Energy_rail only'!C:C,C12) -> 0 | S12: =SUM(P12:Q12)*$C$2 -> 0 | T12: =R12*$C$3 -> 0 | U12: =IFERROR(($L12*$M12*N12)/S12,0) -> 0 | V12: =IFERROR(($L12*$M12*O12)/T12,0) -> 0
B13: California | C13: CA | D13: subregion5 | E13: =SUMIFS('Annual Service Data_rail only'!N:N,'Annual Service Data_rail only'!C:C,C13) -> 441 | F13: =SUMIFS('Annual Service Data_rail only'!X:X,'Annual Service Data_rail only'!C:C,C13) -> 139399021 | G13: =SUMIFS('Annual Service Data_rail only'!AT:AT,'Annual Service Data_rail only'!C:C,C13) -> 2812423160 | H13: =SUMIFS('Fuel and Energy_rail only'!AD:AD,'Fuel and Energy_rail only'!C:C,C13) -> 5034854 | I13: =SUMIFS('Fuel and Energy_rail only'!AN:AN,'Fuel and Energy_rail only'!C:C,C13) -> 106204511 | J13: =IFERROR(H13/SUM($H13:$I13),0) -> 0.045261441 | K13: =IFERROR(I13/SUM($H13:$I13),0) -> 0.95473856 | L13: =IFERROR(G13/F13,0) -> 20.175344 | M13: =IFERROR(F13/E13,0) -> 316097.55 | N13: =E13*J13 -> 19.960296 | O13: =K13*E13 -> 421.0397 | P13: =SUMIFS('Fuel and Energy_rail only'!M:M,'Fuel and Energy_rail only'!C:C,C13) -> 13666577 | Q13: =SUMIFS('Fuel and Energy_rail only'!U:U,'Fuel and Energy_rail only'!C:C,C13) -> 0 | R13: =SUMIFS('Fuel and Energy_rail only'!Y:Y,'Fuel and Energy_rail only'!C:C,C13) -> 681466893 | S13: =SUM(P13:Q13)*$C$2 -> 1895554229900 | T13: =R13*$C$3 -> 2.3252604e+12 | U13: =IFERROR(($L13*$M13*N13)/S13,0) -> 6.7154146e-05 | V13: =IFERROR(($L13*$M13*O13)/T13,0) -> 0.0011547648
B14: Colorado | C14: CO | D14: subregion6 | E14: =SUMIFS('Annual Service Data_rail only'!N:N,'Annual Service Data_rail only'!C:C,C14) -> 56 | F14: =SUMIFS('Annual Service Data_rail only'!X:X,'Annual Service Data_rail only'!C:C,C14) -> 15749288 | G14: =SUMIFS('Annual Service Data_rail only'!AT:AT,'Annual Service Data_rail only'!C:C,C14) -> 129461494 | H14: =SUMIFS('Fuel and Energy_rail only'!AD:AD,'Fuel and Energy_rail only'!C:C,C14) -> 0 | I14: =SUMIFS('Fuel and Energy_rail only'!AN:AN,'Fuel and Energy_rail only'!C:C,C14) -> 15639401 | J14: =IFERROR(H14/SUM($H14:$I14),0) -> 0 | K14: =IFERROR(I14/SUM($H14:$I14),0) -> 1 | L14: =IFERROR(G14/F14,0) -> 8.220149 | M14: =IFERROR(F14/E14,0) -> 281237.29 | N14: =E14*J14 -> 0 | O14: =K14*E14 -> 56 | P14: =SUMIFS('Fuel and Energy_rail only'!M:M,'Fuel and Energy_rail only'!C:C,C14) -> 0 | Q14: =SUMIFS('Fuel and Energy_rail only'!U:U,'Fuel and Energy_rail only'!C:C,C14) -> 0 | R14: =SUMIFS('Fuel and Energy_rail only'!Y:Y,'Fuel and Energy_rail only'!C:C,C14) -> 101468806 | S14: =SUM(P14:Q14)*$C$2 -> 0 | T14: =R14*$C$3 -> 3.4622577e+11 | U14: =IFERROR(($L14*$M14*N14)/S14,0) -> 0 | V14: =IFERROR(($L14*$M14*O14)/T14,0) -> 0.00037392218
B15: Connecticut | C15: CT | D15: subregion7 | E15: =SUMIFS('Annual Service Data_rail only'!N:N,'Annual Service Data_rail only'!C:C,C15) -> 5 | F15: =SUMIFS('Annual Service Data_rail only'!X:X,'Annual Service Data_rail only'!C:C,C15) -> 1717047 | G15: =SUMIFS('Annual Service Data_rail only'!AT:AT,'Annual Service Data_rail only'!C:C,C15) -> 12884750 | H15: =SUMIFS('Fuel and Energy_rail only'!AD:AD,'Fuel and Energy_rail only'!C:C,C15) -> 724004 | I15: =SUMIFS('Fuel and Energy_rail only'!AN:AN,'Fuel and Energy_rail only'!C:C,C15) -> 0 | J15: =IFERROR(H15/SUM($H15:$I15),0) -> 1 | K15: =IFERROR(I15/SUM($H15:$I15),0) -> 0 | L15: =IFERROR(G15/F15,0) -> 7.5040171 | M15: =IFERROR(F15/E15,0) -> 343409.4 | N15: =E15*J15 -> 5 | O15: =K15*E15 -> 0 | P15: =SUMIFS('Fuel and Energy_rail only'!M:M,'Fuel and Energy_rail only'!C:C,C15) -> 1678569 | Q15: =SUMIFS('Fuel and Energy_rail only'!U:U,'Fuel and Energy_rail only'!C:C,C15) -> 0 | R15: =SUMIFS('Fuel and Energy_rail only'!Y:Y,'Fuel and Energy_rail only'!C:C,C15) -> 0 | S15: =SUM(P15:Q15)*$C$2 -> 232817520300 | T15: =R15*$C$3 -> 0 | U15: =IFERROR(($L15*$M15*N15)/S15,0) -> 5.5342699e-05 | V15: =IFERROR(($L15*$M15*O15)/T15,0) -> 0
B16: Delaware | C16: DE | D16: subregion8 | E16: =SUMIFS('Annual Service Data_rail only'!N:N,'Annual Service Data_rail only'!C:C,C16) -> 0 | F16: =SUMIFS('Annual Service Data_rail only'!X:X,'Annual Service Data_rail only'!C:C,C16) -> 0 | G16: =SUMIFS('Annual Service Data_rail only'!AT:AT,'Annual Service Data_rail only'!C:C,C16) -> 0 | H16: =SUMIFS('Fuel and Energy_rail only'!AD:AD,'Fuel and Energy_rail only'!C:C,C16) -> 0 | I16: =SUMIFS('Fuel and Energy_rail only'!AN:AN,'Fuel and Energy_rail only'!C:C,C16) -> 0 | J16: =IFERROR(H16/SUM($H16:$I16),0) -> 0 | K16: =IFERROR(I16/SUM($H16:$I16),0) -> 0 | L16: =IFERROR(G16/F16,0) -> 0 | M16: =IFERROR(F16/E16,0) -> 0 | N16: =E16*J16 -> 0 | O16: =K16*E16 -> 0 | P16: =SUMIFS('Fuel and Energy_rail only'!M:M,'Fuel and Energy_rail only'!C:C,C16) -> 0 | Q16: =SUMIFS('Fuel and Energy_rail only'!U:U,'Fuel and Energy_rail only'!C:C,C16) -> 0 | R16: =SUMIFS('Fuel and Energy_rail only'!Y:Y,'Fuel and Energy_rail only'!C:C,C16) -> 0 | S16: =SUM(P16:Q16)*$C$2 -> 0 | T16: =R16*$C$3 -> 0 | U16: =IFERROR(($L16*$M16*N16)/S16,0) -> 0 | V16: =IFERROR(($L16*$M16*O16)/T16,0) -> 0
B17: DC | C17: DC | D17: NA | E17: =SUMIFS('Annual Service Data_rail only'!N:N,'Annual Service Data_rail only'!C:C,C17) -> 129 | F17: =SUMIFS('Annual Service Data_rail only'!X:X,'Annual Service Data_rail only'!C:C,C17) -> 82234530 | G17: =SUMIFS('Annual Service Data_rail only'!AT:AT,'Annual Service Data_rail only'!C:C,C17) -> 985922295 | H17: =SUMIFS('Fuel and Energy_rail only'!AD:AD,'Fuel and Energy_rail only'!C:C,C17) -> 0 | I17: =SUMIFS('Fuel and Energy_rail only'!AN:AN,'Fuel and Energy_rail only'!C:C,C17) -> 64920984 | J17: =IFERROR(H17/SUM($H17:$I17),0) -> 0 | K17: =IFERROR(I17/SUM($H17:$I17),0) -> 1 | L17: =IFERROR(G17/F17,0) -> 11.989152 | M17: =IFERROR(F17/E17,0) -> 637476.98 | N17: =E17*J17 -> 0 | O17: =K17*E17 -> 129 | P17: =SUMIFS('Fuel and Energy_rail only'!M:M,'Fuel and Energy_rail only'!C:C,C17) -> 0 | Q17: =SUMIFS('Fuel and Energy_rail only'!U:U,'Fuel and Energy_rail only'!C:C,C17) -> 0 | R17: =SUMIFS('Fuel and Energy_rail only'!Y:Y,'Fuel and Energy_rail only'!C:C,C17) -> 576455528 | S17: =SUM(P17:Q17)*$C$2 -> 0 | T17: =R17*$C$3 -> 1.966947e+12 | U17: =IFERROR(($L17*$M17*N17)/S17,0) -> 0 | V17: =IFERROR(($L17*$M17*O17)/T17,0) -> 0.00050124498
B18: Florida | C18: FL | D18: subregion9 | E18: =SUMIFS('Annual Service Data_rail only'!N:N,'Annual Service Data_rail only'!C:C,C18) -> 35 | F18: =SUMIFS('Annual Service Data_rail only'!X:X,'Annual Service Data_rail only'!C:C,C18) -> 11964512 | G18: =SUMIFS('Annual Service Data_rail only'!AT:AT,'Annual Service Data_rail only'!C:C,C18) -> 203966246 | H18: =SUMIFS('Fuel and Energy_rail only'!AD:AD,'Fuel and Energy_rail only'!C:C,C18) -> 1504489 | I18: =SUMIFS('Fuel and Energy_rail only'!AN:AN,'Fuel and Energy_rail only'!C:C,C18) -> 559892 | J18: =IFERROR(H18/SUM($H18:$I18),0) -> 0.72878456 | K18: =IFERROR(I18/SUM($H18:$I18),0) -> 0.27121544 | L18: =IFERROR(G18/F18,0) -> 17.047603 | M18: =IFERROR(F18/E18,0) -> 341843.2 | N18: =E18*J18 -> 25.50746 | O18: =K18*E18 -> 9.4925404 | P18: =SUMIFS('Fuel and Energy_rail only'!M:M,'Fuel and Energy_rail only'!C:C,C18) -> 3648266 | Q18: =SUMIFS('Fuel and Energy_rail only'!U:U,'Fuel and Energy_rail only'!C:C,C18) -> 0 | R18: =SUMIFS('Fuel and Energy_rail only'!Y:Y,'Fuel and Energy_rail only'!C:C,C18) -> 66954261 | S18: =SUM(P18:Q18)*$C$2 -> 506014494200 | T18: =R18*$C$3 -> 2.2845731e+11 | U18: =IFERROR(($L18*$M18*N18)/S18,0) -> 0.00029376125 | V18: =IFERROR(($L18*$M18*O18)/T18,0) -> 0.00024214062
B19: Georgia | C19: GA | D19: subregion10 | E19: =SUMIFS('Annual Service Data_rail only'!N:N,'Annual Service Data_rail only'!C:C,C19) -> 39 | F19: =SUMIFS('Annual Service Data_rail only'!X:X,'Annual Service Data_rail only'!C:C,C19) -> 21145309 | G19: =SUMIFS('Annual Service Data_rail only'!AT:AT,'Annual Service Data_rail only'!C:C,C19) -> 329631085 | H19: =SUMIFS('Fuel and Energy_rail only'!AD:AD,'Fuel and Energy_rail only'!C:C,C19) -> 0 | I19: =SUMIFS('Fuel and Energy_rail only'!AN:AN,'Fuel and Energy_rail only'!C:C,C19) -> 19692749 | J19: =IFERROR(H19/SUM($H19:$I19),0) -> 0 | K19: =IFERROR(I19/SUM($H19:$I19),0) -> 1 | L19: =IFERROR(G19/F19,0) -> 15.588852 | M19: =IFERROR(F19/E19,0) -> 542187.41 | N19: =E19*J19 -> 0 | O19: =K19*E19 -> 39 | P19: =SUMIFS('Fuel and Energy_rail only'!M:M,'Fuel and Energy_rail only'!C:C,C19) -> 0 | Q19: =SUMIFS('Fuel and Energy_rail only'!U:U,'Fuel and Energy_rail only'!C:C,C19) -> 0 | R19: =SUMIFS('Fuel and Energy_rail only'!Y:Y,'Fuel and Energy_rail only'!C:C,C19) -> 83566447 | S19: =SUM(P19:Q19)*$C$2 -> 0 | T19: =R19*$C$3 -> 2.8514042e+11 | U19: =IFERROR(($L19*$M19*N19)/S19,0) -> 0 | V19: =IFERROR(($L19*$M19*O19)/T19,0) -> 0.0011560307
B20: Hawaii | C20: HI | D20: subregion11 | E20: =SUMIFS('Annual Service Data_rail only'!N:N,'Annual Service Data_rail only'!C:C,C20) -> 0 | F20: =SUMIFS('Annual Service Data_rail only'!X:X,'Annual Service Data_rail only'!C:C,C20) -> 0 | G20: =SUMIFS('Annual Service Data_rail only'!AT:AT,'Annual Service Data_rail only'!C:C,C20) -> 0 | H20: =SUMIFS('Fuel and Energy_rail only'!AD:AD,'Fuel and Energy_rail only'!C:C,C20) -> 0 | I20: =SUMIFS('Fuel and Energy_rail only'!AN:AN,'Fuel and Energy_rail only'!C:C,C20) -> 0 | J20: =IFERROR(H20/SUM($H20:$I20),0) -> 0 | K20: =IFERROR(I20/SUM($H20:$I20),0) -> 0 | L20: =IFERROR(G20/F20,0) -> 0 | M20: =IFERROR(F20/E20,0) -> 0 | N20: =E20*J20 -> 0 | O20: =K20*E20 -> 0 | P20: =SUMIFS('Fuel and Energy_rail only'!M:M,'Fuel and Energy_rail only'!C:C,C20) -> 0 | Q20: =SUMIFS('Fuel and Energy_rail only'!U:U,'Fuel and Energy_rail only'!C:C,C20) -> 0 | R20: =SUMIFS('Fuel and Energy_rail only'!Y:Y,'Fuel and Energy_rail only'!C:C,C20) -> 0 | S20: =SUM(P20:Q20)*$C$2 -> 0 | T20: =R20*$C$3 -> 0 | U20: =IFERROR(($L20*$M20*N20)/S20,0) -> 0 | V20: =IFERROR(($L20*$M20*O20)/T20,0) -> 0
... B59: Wyoming | C59: WY | D59: subregion50 | E59: =SUMIFS('Annual Service Data_rail only'!N:N,'Annual Service Data_rail only'!C:C,C59) -> 0 | F59: =SUMIFS('Annual Service Data_rail only'!X:X,'Annual Service Data_rail only'!C:C,C59) -> 0 | G59: =SUMIFS('Annual Service Data_rail only'!AT:AT,'Annual Service Data_rail only'!C:C,C59) -> 0 | H59: =SUMIFS('Fuel and Energy_rail only'!AD:AD,'Fuel and Energy_rail only'!C:C,C59) -> 0 | I59: =SUMIFS('Fuel and Energy_rail only'!AN:AN,'Fuel and Energy_rail only'!C:C,C59) -> 0 | J59: =IFERROR(H59/SUM($H59:$I59),0) -> 0 | K59: =IFERROR(I59/SUM($H59:$I59),0) -> 0 | L59: =IFERROR(G59/F59,0) -> 0 | M59: =IFERROR(F59/E59,0) -> 0 | N59: =E59*J59 -> 0 | O59: =K59*E59 -> 0 | P59: =SUMIFS('Fuel and Energy_rail only'!M:M,'Fuel and Energy_rail only'!C:C,C59) -> 0 | Q59: =SUMIFS('Fuel and Energy_rail only'!U:U,'Fuel and Energy_rail only'!C:C,C59) -> 0 | R59: =SUMIFS('Fuel and Energy_rail only'!Y:Y,'Fuel and Energy_rail only'!C:C,C59) -> 0 | S59: =SUM(P59:Q59)*$C$2 -> 0 | T59: =R59*$C$3 -> 0 | U59: =IFERROR(($L59*$M59*N59)/S59,0) -> 0 | V59: =IFERROR(($L59*$M59*O59)/T59,0) -> 0
E61: =E8 -> Max Trains in Operation | F61: =F8 -> Vehicle Miles | G61: =G8 -> Passenger Miles | L61: =L8 -> calc AVLO | M61: =M8 -> calc BAADTVBT | N61: =N8 -> SYVBT-diesel | O61: =O8 -> SYVBT-electric | S61: =S8 -> diesel (btus) | T61: =T8 -> electric (btu) | U61: =U8 -> calc SYFAFE-diesel | V61: =V8 -> calc SYFAFE-electric
D62: totals | E62: =SUM(E9:E59) -> 2740 | F62: =SUM(F9:F59) -> 1083860350 | G62: =SUM(G9:G59) -> 16634915700 | L62: =IFERROR(G62/F62,0) -> 15.34784 | M62: =IFERROR(F62/E62,0) -> 395569.47 | N62: =SUM(N9:N59) -> 173.39396 | O62: =SUM(O9:O59) -> 2563.606 | S62: =SUM(S9:S59) -> 14672704890200 | T62: =SUM(T9:T59) -> 2.0563856e+13 | U62: =IFERROR(($L62*$M62*N62)/S62,0) -> 7.1745362e-05 | V62: =IFERROR(($L62*$M62*O62)/T62,0) -> 0.00075686214
D64: CHECK | E64: =E62/SUM(N62:O62) -> 1.0010961 | G64: =L62*M62*SUM(N62:O62)/G62 -> 0.99890511 | S64: =($L62*$M62*N62/U62)/S62 -> 1 | T64: =($L62*$M62*O62/V62)/T62 -> 1

Sheet SYAADTbVT-passengers
A1: Annual Distance (miles/vehicle) | B1: 2024
A2: LDVs | B2: ='BAADTbVT-passengers'!D2 -> 13203.785
A3: HDVs | B3: ='BAADTbVT-passengers'!D3 -> 13471.625
A4: aircraft | B4: ='BAADTbVT-passengers'!D4 -> 1407938.2
A5: rail | B5: =SUMIFS('psgr rail calcs'!M:M,'psgr rail calcs'!C:C,About!B2) -> 420280.9
A6: ships | B6: ='BAADTbVT-passengers'!D6 -> 225.60633
A7: motorbikes | B7: ='BAADTbVT-passengers'!D7 -> 10230.2

Sheet SYAADTbVT-freight
A1: Annual Distance (miles/vehicle) | B1: 2024
A2: LDVs | B2: ='BAADTbVT-freight'!D2 -> 11393.119
A3: HDVs | B3: ='BAADTbVT-freight'!D3 -> 28979.515
A4: aircraft | B4: ='BAADTbVT-freight'!D4 -> 1828093.8
A5: rail | B5: ='BAADTbVT-freight'!D5 -> 14001.894
A6: ships | B6: ='BAADTbVT-freight'!D6 -> 9805246.2
A7: motorbikes | B7: ='BAADTbVT-freight'!D7 -> 0

Sheet BAADTbVT-passengers
A1: Annual Distance (miles/vehicle) | B1: 2024 | C1: 2025 | D1: 2026 | E1: 2027 | F1: 2028 | G1: 2029 | H1: 2030 | I1: 2031 | J1: 2032 | K1: 2033 | L1: 2034 | M1: 2035 | N1: 2036 | O1: 2037 | P1: 2038 | Q1: 2039 | R1: 2040 | S1: 2041 | T1: 2042 | U1: 2043 | V1: 2044 | W1: 2045 | X1: 2046 | Y1: 2047 | Z1: 2048 | AA1: 2049 | AB1: 2050
A2: LDVs | B2: ='Scale to SEDS'!E69 -> 13203.785 | C2: =$B2 -> 13203.785 | D2: =$B2 -> 13203.785 | E2: =$B2 -> 13203.785 | F2: =$B2 -> 13203.785 | G2: =$B2 -> 13203.785 | H2: =$B2 -> 13203.785 | I2: =$B2 -> 13203.785 | J2: =$B2 -> 13203.785 | ... AB2: =$B2 -> 13203.785
A3: HDVs | B3: ='Scale to SEDS'!F70 -> 13471.625 | C3: =$B3 -> 13471.625 | D3: =$B3 -> 13471.625 | E3: =$B3 -> 13471.625 | F3: =$B3 -> 13471.625 | G3: =$B3 -> 13471.625 | H3: =$B3 -> 13471.625 | I3: =$B3 -> 13471.625 | J3: =$B3 -> 13471.625 | ... AB3: =$B3 -> 13471.625
A4: aircraft | B4: ='Scale to SEDS'!G71 -> 1407938.2 | C4: =$B$4 -> 1407938.2 | D4: =$B$4 -> 1407938.2 | E4: =$B$4 -> 1407938.2 | F4: =$B$4 -> 1407938.2 | G4: =$B$4 -> 1407938.2 | H4: =$B$4 -> 1407938.2 | I4: =$B$4 -> 1407938.2 | J4: =$B$4 -> 1407938.2 | ... AB4: =$B$4 -> 1407938.2
A5: rail | B5: ='SYAADTbVT-passengers'!B5 -> 420280.9 | C5: =$B5 -> 420280.9 | D5: =$B5 -> 420280.9 | E5: =$B5 -> 420280.9 | F5: =$B5 -> 420280.9 | G5: =$B5 -> 420280.9 | H5: =$B5 -> 420280.9 | I5: =$B5 -> 420280.9 | J5: =$B5 -> 420280.9 | ... AB5: =$B5 -> 420280.9
A6: ships | B6: ='Scale to SEDS'!E73 -> 225.60633 | C6: =$B6 -> 225.60633 | D6: =$B6 -> 225.60633 | E6: =$B6 -> 225.60633 | F6: =$B6 -> 225.60633 | G6: =$B6 -> 225.60633 | H6: =$B6 -> 225.60633 | I6: =$B6 -> 225.60633 | J6: =$B6 -> 225.60633 | ... AB6: =$B6 -> 225.60633
A7: motorbikes | B7: ='Scale to SEDS'!E74 -> 10230.2 | C7: =$B7 -> 10230.2 | D7: =$B7 -> 10230.2 | E7: =$B7 -> 10230.2 | F7: =$B7 -> 10230.2 | G7: =$B7 -> 10230.2 | H7: =$B7 -> 10230.2 | I7: =$B7 -> 10230.2 | J7: =$B7 -> 10230.2 | ... AB7: =$B7 -> 10230.2

Sheet BAADTbVT-freight
A1: Annual Distance (miles/vehicle) | B1: 2024 | C1: 2025 | D1: 2026 | E1: 2027 | F1: 2028 | G1: 2029 | H1: 2030 | I1: 2031 | J1: 2032 | K1: 2033 | L1: 2034 | M1: 2035 | N1: 2036 | O1: 2037 | P1: 2038 | Q1: 2039 | R1: 2040 | S1: 2041 | T1: 2042 | U1: 2043 | V1: 2044 | W1: 2045 | X1: 2046 | Y1: 2047 | Z1: 2048 | AA1: 2049 | AB1: 2050
A2: LDVs | B2: ='Scale to SEDS'!E75 -> 11393.119 | C2: =B2 -> 11393.119 | D2: =C2 -> 11393.119 | E2: =D2 -> 11393.119 | F2: =E2 -> 11393.119 | G2: =F2 -> 11393.119 | H2: =G2 -> 11393.119 | I2: =H2 -> 11393.119 | J2: =I2 -> 11393.119 | ... AB2: =AA2 -> 11393.119
A3: HDVs | B3: ='Scale to SEDS'!F76 -> 28979.515 | C3: =B3 -> 28979.515 | D3: =C3 -> 28979.515 | E3: =D3 -> 28979.515 | F3: =E3 -> 28979.515 | G3: =F3 -> 28979.515 | H3: =G3 -> 28979.515 | I3: =H3 -> 28979.515 | J3: =I3 -> 28979.515 | ... AB3: =AA3 -> 28979.515
A4: aircraft | B4: ='Scale to SEDS'!G77 -> 1828093.8 | C4: =B4 -> 1828093.8 | D4: =C4 -> 1828093.8 | E4: =D4 -> 1828093.8 | F4: =E4 -> 1828093.8 | G4: =F4 -> 1828093.8 | H4: =G4 -> 1828093.8 | I4: =H4 -> 1828093.8 | J4: =I4 -> 1828093.8 | ... AB4: =AA4 -> 1828093.8
A5: rail | B5: ='Scale to SEDS'!F78 -> 14001.894 | C5: =B5 -> 14001.894 | D5: =C5 -> 14001.894 | E5: =D5 -> 14001.894 | F5: =E5 -> 14001.894 | G5: =F5 -> 14001.894 | H5: =G5 -> 14001.894 | I5: =H5 -> 14001.894 | J5: =I5 -> 14001.894 | ... AB5: =AA5 -> 14001.894
A6: ships | B6: ='Scale to SEDS'!F79 -> 9805246.2 | C6: =B6 -> 9805246.2 | D6: =C6 -> 9805246.2 | E6: =D6 -> 9805246.2 | F6: =E6 -> 9805246.2 | G6: =F6 -> 9805246.2 | H6: =G6 -> 9805246.2 | I6: =H6 -> 9805246.2 | J6: =I6 -> 9805246.2 | ... AB6: =AA6 -> 9805246.2
A7: motorbikes | B7: 0 | C7: =B7 -> 0 | D7: =C7 -> 0 | E7: =D7 -> 0 | F7: =E7 -> 0 | G7: =F7 -> 0 | H7: =G7 -> 0 | I7: =H7 -> 0 | J7: =I7 -> 0 | ... AB7: =AA7 -> 0
