Workbook

Sheet About
A1: Web App Data | B1: New Jersey | C1: 45747 | G1: abrv | H1: state
B2: =_xlfn.XLOOKUP(B1,H:H,G:G,0,0,1) -> NJ | C2: =_xlfn.XLOOKUP(B2,G:G, H:H, 0,0,1) -> New Jersey | G2: AK | H2: Alaska
A3: This spreadsheet contains data that is used to populate the web application interface | G3: AL | H3: Alabama
A4: for the Energy Policy Simulator. The data in other tabs in this spreadsheet are used | G4: AR | H4: Arkansas
A5: to establish the policy levers, lever bounds, descriptive text for pop-over | G5: AZ | H5: Arizona
A6: panels, output graphs, and reference scenarios available in the web app. | G6: CA | H6: California
G7: CO | H7: Colorado
A8: A live version of the web application interface powered by a copy of this model | G8: CT | H8: Connecticut
A9: can be found at: | G9: DC | H9: DC
A10: https://www.energypolicy.solutions | G10: DE | H10: Delaware
G11: FL | H11: Florida
A12: You are unlikely to need to use or change the contents of this spreadsheet, unless | G12: GA | H12: Georgia
A13: you are adapting the Energy Policy Simulator to a new country and desire | G13: HI | H13: Hawaii
A14: a web application interface customized for your country-specific model version. | G14: IA | H14: Iowa
G15: ID | H15: Idaho
A16: Checks for Policy ID Number Validity | G16: IL | H16: Illinois
A17: Max policy ID number in use | B17: =MAX(PolicyLevers!H:H) -> 2769 | G17: IN | H17: Indiana
A18: Lowest duplicate ID number | B18: {=IF(MIN(IF(COUNTIF(PolicyLevers!$H$2:$H$2025,PolicyLevers!$H$2:$H$2025)>1,PolicyLevers!$H$2:$H$2025, ""))=0,"No duplicate ID numbers",MIN(IF(COUNTIF(PolicyLevers!$H$2:$H$2025,PolicyLevers!$H$2:$H$2025)>1,PolicyLevers!$H$2:$H$2025, "")))} -> No duplicate ID numbers | G18: KS | H18: Kansas
A19: Row of first policy missing a valid ID number | B19: {=IF(MIN(IF((NOT(ISNUMBER(PolicyLevers!$H$2:$H$2025)))*(ISTEXT(PolicyLevers!$I$2:$I$2025)),ROW(PolicyLevers!$H$2:$H$2025)))=0,"No missing ID numbers",MIN(IF((NOT(ISNUMBER(PolicyLevers!$H$2:$H$2025)))*(ISTEXT(PolicyLevers!$I$2:$I$2025)),ROW(PolicyLevers!$H$2:$H$2025))))} -> No missing ID numbers | G19: KY | H19: Kentucky
G20: LA | H20: Louisiana
A21: Customizing Policy Levers | G21: MA | H21: Massachusetts
A22: Define most policy properties on the "Policy Characteristics" tab. | G22: MD | H22: Maryland
A23: Specify the subscripted elements of each policy and which are enabled/disabled on the "PolicyLevers" tab. | G23: ME | H23: Maine
A24: On the PolicyLevers tab, only manually edit the cells under the green column headers. Simply extend the | G24: MI | H24: Michigan
A25: existing formulas up or down to fill cells under the red headers on that tab. | G25: MN | H25: Minnesota
G26: MO | H26: Missouri
A27: Notes on Meaning of Blank Cells on the Policy Characteristics Tab | G27: MS | H27: Mississippi
A28: Leave the "Policy Schedule Subscript" cell blank to deny the ability to edit the implementation | G28: MT | H28: Montana
A29: schedule for a lever. This should generally only be done for levers that do not use an | G29: NC | H29: North Carolina
A30: implementation schedule: the toggle to Non-BAU Mandated Capacity Construction | G30: ND | H30: North Dakota
A31: (which has its own schedule built into its input data) and the Nuclear Lifetime Extension | G31: NE | H31: Nebraska
A32: (which simply delays retirements that would occur in the BAU Retirements input data). | G32: NH | H32: New Hampshire
G33: NJ | H33: New Jersey
A34: Leave the "Policy Group" cell blank to exclude a lever from wedge diagrams and abatement cost curves. | G34: NM | H34: New Mexico
A35: This should always be done for "Control Settings" (which affect both the BAU and policy cases), | G35: NV | H35: Nevada
A36: and should generally never be done for actual policy levers. | G36: NY | H36: New York
G37: OH | H37: Ohio
A38: Leave the "URL for "How the model handles this policy" links" cell blank to exclude this link from | G38: OK | H38: Oklahoma
A39: the policy's pop-over pane. You should generally do this whenever there is no on-topic place | G39: OR | H39: Oregon
A40: in the documentation to which to send a user. | G40: PA | H40: Pennsylvania
G41: RI | H41: Rhode Island
A42: Leave the "URL for "How to design this policy well" links" cell blank to exclude this link from | G42: SC | H42: South Carolina
A43: the policy's pop-over pane. You should generally do this whenever no documentation page | G43: SD | H43: South Dakota
A44: for that policy exists. | G44: TN | H44: Tennessee
G45: TX | H45: Texas
A46: Notes on Unit Formatting on Policy Characteristics Tab | G46: UT | H46: Utah
A47: If you want a policy lever to be formatted as a percentage in the web interface, the percent | G47: VA | H47: Virginia
A48: symbol (%) must appear somewhere in the "Units" field for that policy. | G48: VT | H48: Vermont
G49: WA | H49: Washington
A50: For percentages, the web interface will choose the number of decimal places to show for | G50: WI | H50: Wisconsin
A51: policy settings based on the "Slider Step Size." Up to 2 decimal places (e.g. showing values as | G51: WV | H51: West Virginia
A52: small as 0.01%) are supported. If the slider step size is 1% or larger, you must use an integer | G52: WY | H52: Wyoming
A53: step size (e.g. 1.5% is not a valid step size, but 1%, 2%, 0.5% and 0.05% are all valid).

Sheet Policy Characteristics
A1: This tab contains information about each policy that does not vary by subscripted element of that policy.
A2: It matches policies to the listing in the "PolicyLevers" tab using the "Vensim Variable Name" column.
A3: Sector | B3: Short Name | C3: Vensim Variable Name | D3: Policy Group | E3: Policy Schedule Subscript | F3: Min Slider Value | G3: Max Slider Value | H3: Slider Step Size | I3: Units | J3: Text for Pop-Over Panel Description | K3: URL for "How the model handles this policy" links | L3: URL for "How to design this policy well" links | M3: Source for Guidance Text (if any) | N3: Source for Max Slider Value (if any)
A4: Transportation | B4: Conventional Pollutant Standards | C4: Percentage Reduction of Separately Regulated Pollutants | D4: Conventional Pollutant Standard | E4: trans reduce regulated pollutants | F4: 0 | G4: 1 | H4: 0.02 | I4: % reduction in emissions | J4: **Description:** This policy represents strengthening standards for the selected pollutant(s) emitted by the selected vehicle type(s). Conventional pollutants' most important, harmful impacts are on human health rather than on climate change. The following descriptions detail the different vehicle types: // **Passenger cars and SUVs:** most light-duty road vehicles // **Light and Medium Commercial Trucks:** commercial trucks carrying freight, not passengers // **Buses:** including school, transit, and intercity buses // **Heavy Duty Trucks:** all other heavy road vehicles (mostly freight trucks) // **Commercial passenger flights:** this is not general aviation // **Commercial freight flights:** this includes all other commercial flights, and is not general aviation // **Passenger rail:** intercity, transit, and commuter rail // **Freight rail:** all other rail // **Recreational boats:** not commercial passenger ferries // **Cargo ships:** commercial ships carrying freight // **Passenger motorbikes:** registered motorcycles // **Guidance for setting values:** In the United States, since 1997, the 24-hour national ambient air quality standard (NAAQS) for PM2.5, the most harmful type of particulate for human health, declined from 65 µg/m^3 to 35 µg/m^3, a reduction of 46%. | K4: transportation-sector-main.html#conv-pol-stds | L4: conventional-pollutant-standards.html
A5: Transportation | B5: Electric Vehicle Charger Deployment | C5: Percentage Increase in EV Chargers | D5: EV Charger Deployment | E5: trans EV charger deployment | F5: -2 | G5: 3 | H5: 0.1 | I5: % change | J5: **Description:** This policy increases the deployment of EV charging stations, including DC Fast and Level 2 charging stations. A negative value decreases chargers relative to the Current Policies scenario. // **Guidance for setting values:** This policy increases vehicle deployment by lowering the perceived charging availability penalty for EVs, insofar as it increases the ratio of EV chargers to gasoline pumps. In the United States, we find the charging availability penalty already reaches zero by roughly 2030. Beyond that point, this policy lever will have no additional effect on EV deployment. | L5: ev-charger-deployment.html | M5: Number of EV chargers: https://evadoption.com/ev-charging-stations-statistics/ Number of gas stations: U.S. Census, Statistics of U.S. Businesses, https://www.census.gov/data/tables/2016/econ/susb/2016-susb-annual.html Pumps per station: https://247wallst.com/economy/2014/05/22/why-are-there-115000-or-150000-gas-stations-in-america/
A6: Transportation | B6: Electric Vehicle Range | C6: Reduce EV Range Anxiety | D6: EV Range & Charging Time | E6: trans reduce EV range anxiety | F6: 0 | G6: 1 | H6: 0.02 | I6: % reduction in concern | J6: **Description:** This policy specifies a percentage reduction in vehicle buyers' aversion to electric vehicles due to concerns over the vehicles' range (how far the EV can travel on a charge). A 100% setting implies consumers are no more concerned about EV range and charging time than they are about range and fueling time of gasoline vehicles. It does not imply that range is infinite. This policy only affects passenger cars and SUVs (most light-duty road vehicles). // **Guidance for setting values:** U.S. model year 2017 all-electric (not hybrid) vehicles had ranges from 58 to 335 miles (median 114 miles). | L6: reduce-range-anxiety-charging-time.html | M6: Ranges: https://www.energy.gov/eere/vehicles/articles/fotw-1010-january-1-2018-all-electric-light-vehicle-ranges-can-exceed-those Charging Times: https://www.chargepoint.com/files/Quick_Guide_to_Fast_Charging.pdf
A7: Transportation | B7: Passenger Vehicle Subsidy | C7: Additional Passenger Vehicle Subsidy | D7: Vehicle Subsidy | E7: trans psgr subsidy | F7: -45000 | G7: 50000 | H7: 100 | I7: $ / vehicle | J7: =_xlfn.XLOOKUP($C7,'State Policy Descriptions'!$C:$C,'State Policy Descriptions'!$L:$L,0,1,1) -> **Description:** This policy specifies the dollar amount offered as a subsidy to the purchaser of a new passenger vehicle. This is in addition to subsidies that exist in the BAU case. A negative value implies a tax or removal of subsidies. // **Guidance for setting values:** The U.S. currently offers a federal tax credit for up to $7,500 for qualifying clean passenger light-duty vehicles as part of the Inflation Reduction Act. This tax credit is included in the BAU scenario as an estimated average credit for new vehicles, accounting for the fact many vehicles will not be eligible starting in 2025 due to requirements for critical minerals sourcing. The BAU also includes the state-level credit on top of the federal tax credits. As of late 2020, there is an additional state subsidy of $5000. | K7: transportation-sector-main.html#ev-subsidy | L7: ev-subsidy.html | M7: https://www.fueleconomy.gov/feg/taxevb.shtml plus Chevrolet and Tesla websites
A8: Transportation | B8: Freight Vehicle Subsidy | C8: Additional Freight Vehicle Subsidy | D8: Vehicle Subsidy | E8: trans frgt subsidy | F8: -45000 | G8: 50000 | H8: 100 | I8: $ / vehicle | J8: =_xlfn.XLOOKUP($C8,'State Policy Descriptions'!$C:$C,'State Policy Descriptions'!$L:$L,0,1,1) -> **Description:** This policy specifies the dollar amount offered as a subsidy to the purchaser of a new freight vehicle. This is in addition to subsidies that exist in the BAU case. A negative value implies a tax or removal of subsidies. // **Guidance for setting values:** The U.S. currently offers a federal tax credit for up to $40,500 for qualifying clean commercial vehicles, which is incorporated in the BAU. This state has no additional state subsidies. | K8: transportation-sector-main.html#ev-subsidy | L8: ev-subsidy.html
A9: Transportation | B9: Feebate | C9: LDVs Feebate Rate | D9: Feebate | E9: trans LDVs feebate | F9: 0 | G9: 1 | H9: 0.02 | I9: % of global best practice rate | J9: **Description:** This policy implements a fee on sales of inefficient cars and SUVs (light-duty road vehicles; LDVs) that is rebated to buyers of efficient LDVs. The feebate policy is revenue-neutral, as the pivot point (the efficiency level that incurs neither a rebate nor a fee) is set such that the total of all fees equals the total of all rebates. // **Guidance for setting values:** The feebate is set as a fraction of the global best practice feebate rate. The global best practice feebate rate is $2000 per (hundredth gal/mile), which equates to a $2000 fee on an LDV that gets 20 mpg if the pivot point is 25 mpg. (To see this: 20 mpg is 0.04 gpm. 25 mpg is 0.05 gpm. The difference is -.01 gpm. So in order to levy a $2000 fee on the 20 mpg car when the pivot point is 25 mpg, we need a rate of $2000/.01 gpm.) | K9: transportation-sector-main.html#feebate | L9: feebate.html | M9: Greene et al., 2005, "Feebates, rebates and gas-guzzler taxes: a study of incentives for increased fuel economy", Energy Policy, 33(6), 757-775, http://cta.ornl.gov/cta/Publications/Reports/FeebateEnergyPolicy_FINAL.pdf. | N9: John German and Dan Meszler, 2010, "Best Practices for Feebate Program Design and Implementation", ICCT, http://www.theicct.org/sites/default/files/publications/ICCT_feebates_may2010.pdf, Table 2
A10: Transportation | B10: Fuel Economy Standard | C10: Percentage Additional Improvement of Fuel Economy Std | D10: Vehicle Fuel Economy Standards | E10: trans fuel economy standards | F10: -0.25 | G10: =ROUND(MaxBoundCalculations!B88,1) -> 1 | H10: 0.01 | I10: % change in miles/gal | J10: **Description:** This policy specifies a percentage improvement in fuel economy (distance traveled on the same quantity of fuel with the same cargo or passenger loading) due to fuel economy standards for newly sold vehicles of the selected type(s) with fossil fuel-burning engines. A negative value implies a rollback of fuel economy standards relative to those in the BAU scenario. The following descriptions detail the different vehicle types: // **Passenger cars and SUVs:** most light-duty road vehicles // **Light and Medium Commercial Trucks:** commercial trucks carrying freight, not passengers // **Buses:** including school, transit, and intercity buses // **Heavy Duty Trucks:** all other heavy road vehicles (mostly freight trucks) // **Commercial passenger flights:** this is not general aviation // **Commercial freight flights:** this includes all other commercial flights, and is not general aviation // **Passenger rail:** intercity, transit, and commuter rail // **Freight rail:** all other rail // **Recreational boats:** not commercial passenger ferries // **Cargo ships:** commercial ships carrying freight // **Passenger motorbikes:** registered motorcycles // **Guidance for setting values:** // **Passenger cars and SUVs:** U.S. combined fuel economy standards for cars and light trucks were 34.6 mpg in 2020 and are scheduled to rise to 38.3 mpg through 2026, then remain constant. This improvement is reflected in the BAU case. The National Research Council's estimated future average fuel economy is roughly 74 mpg for a midrange scenario and 94 mpg for an optimistic scenario. // **Light and Medium Commercial Trucks:** U.S. fuel economy standards for heavy-duty vehicles vary by vehicle characteristics, but proposed standards for vocational vehicles (the category that includes buses) would reduce GHG emissions by 24% for 2027 model year vehicles relative to the 2018 model year, then remain constant. Extrapolating this trend to 2050 would be an 85% improvement relative to 2018, compared to a 40% improvement relative to 2018 in the BAU case. This could be represented by a policy lever setting of 45%. // **Heavy Duty Trucks:** U.S. fuel economy standards for heavy-duty vehicles vary by vehicle characteristics, but proposed standards for combination tractor-trailers (which are responsible for roughly 60% of HDV emissions) would reduce GHG emissions by 25% for 2027 model year trucks relative to the 2018 model year, then remain constant. Extrapolating this trend to 2050 would be an 96% improvement relative to 2018, compared to a 40% improvement relative to 2018 in the BAU case. This could be represented by a policy lever setting of 56%. // **Commercial passenger flights:** The U.S. currently does not have fuel economy standards for aircraft. In the absence of standards, new passenger aircraft fuel economy is projected to improve roughly 17% from 2018-2050 in the BAU case. // **Commercial freight flights:** The U.S. currently does not have fuel economy standards for aircraft. In the absence of standards, new freight aircraft fuel economy is projected to improve roughly 50% from 2018-2050 in the BAU case. // **Passenger rail:** The U.S. currently does not have fuel economy standards for trains. In the absence of standards, new passenger train fuel economy is not projected to change significantly from 2018-2050 in the BAU case. // **Freight rail:** The U.S. currently does not have fuel economy standards for trains. In the absence of standards, new freight train fuel economy is projected to improve roughly 23% from 2018-2050 in the BAU case. // **Recreational boats:** The U.S. currently does not have fuel economy standards for recreational boats. In the absence of standards, new passenger boat fuel economy is not projected to change significantly from 2018-2050 in the BAU case. // **Cargo ships:** The U.S. currently does not have fuel economy standards for ships. In the absence of standards, new freight ship fuel economy is projected to improve roughly 21% from 2018-2050 in the BAU case. however, the ICCT suggests in-use CO2 intensity of freight ships could fall by roughly 50% by 2040, corresponding to a 100% improvement in fuel economy. // **Passenger motorbikes:** The U.S. currently does not have fuel economy standards for motorbikes. In the absence of standards, new motorbike fuel economy is not projected to change significantly from 2018-2050 in the BAU case. | K10: transportation-sector-main.html#fuel-econ-std | L10: fuel-economy-standard.html | M10: U. S. EPA, 2012, "Fact Sheet: EPA and NHTSA Set Standards to Reduce Greenhouse Gases and Improve Fuel Economy for Model Years 2017-2025 Cars and Light Trucks", https://nepis.epa.gov/Exe/ZyNET.exe/P100EZ7C.txt?ZyActionD=ZyDocument&Client=EPA&Index=2011%20Thru%202015&Docs=&Query=&Time=&EndTime=&SearchMethod=1&TocRestrict=n&Toc=&TocEntry=&QField=&QFieldYear=&QFieldMonth=&QFieldDay=&UseQField=&IntQFieldOp=0&ExtQFieldOp=0&XmlQuery=&File=D%3A%5CZYFILES%5CINDEX%20DATA%5C11THRU15%5CTXT%5C00000005%5CP100EZ7C.txt&User=ANONYMOUS&Password=anonymous&SortMethod=h%7C-&MaximumDocuments=1&FuzzyDegree=0&ImageQuality=r75g8/r75g8/x150y150g16/i425&Display=hpfr&DefSeekPage=x&SearchBack=ZyActionL&Back=ZyActionS&BackDesc=Results%20page&MaximumPages=1&ZyEntry=4, Table 1, Row 4. U.S. EPA, 2015, "EPA and NHTSA Propose Standards to Reduce Greenhouse Gas Emissions and Improve Fuel Efficiency of Medium- and Heavy-Duty Vehicles for Model Year 2018 and Beyond", https://nepis.epa.gov/Exe/ZyNET.exe/P100P7NL.txt?ZyActionD=ZyDocument&Client=EPA&Index=2016%20Thru%202020&Docs=&Query=&Time=&EndTime=&SearchMethod=1&TocRestrict=n&Toc=&TocEntry=&QField=&QFieldYear=&QFieldMonth=&QFieldDay=&UseQField=&IntQFieldOp=0&ExtQFieldOp=0&XmlQuery=&File=D%3A%5CZYFILES%5CINDEX%20DATA%5C16THRU20%5CTXT%5C00000002%5CP100P7NL.txt&User=ANONYMOUS&Password=anonymous&SortMethod=h%7C-&MaximumDocuments=1&FuzzyDegree=0&ImageQuality=r75g8/r75g8/x150y150g16/i425&Display=hpfr&DefSeekPage=x&SearchBack=ZyActionL&Back=ZyActionS&BackDesc=Results%20page&MaximumPages=1&ZyEntry=3, Page 3. https://theicct.org/sites/default/files/publications/ICCT_ShipEfficiency_20130723.pdf Others calculated from model input data. | N10: National Research Council, 2013, "Transitions to Alternative Vehicles and Fuels", https://www.nap.edu/catalog/18264/transitions-to-alternative-vehicles-and-fuels, Table 2.9, Fuel economy test mpg. U.S. DoE, 2013, "Potential for Energy Efficiency Improvement Beyond the Light-Duty-Vehicle Sector," http://www.nrel.gov/docs/fy13osti/55637.pdf, Table 2.2 and Section 3.4.5, Paragraph 1 David McCollum, Gregory Gould, and Davide Greene, 2009, "Greenhouse Gas Emissions from Aviation and Marine Transportation: Mitigation Potential and Policies", Pew Center on Global Climate Change, http://www.c2es.org/docUploads/aviation-and-marine-report-2009.pdf, Table 4 https://theicct.org/sites/default/files/publications/ICCT_ShipEfficiency_20130723.pdf
A11: Transportation | B11: Low Carbon Fuel Standard | C11: Additional LCFS Percentage | D11: Low Carbon Fuel Standard | E11: trans LCFS | F11: 0 | G11: 1 | H11: 0.01 | I11: % reduction in carbon emissions | J11: **Description:** This policy specifies the percentage reduction in carbon emissions from the transportation sector that must be achieved via fuel switching. By default, this policy applies to all non-aviation vehicle types. If the lever Non-BAU LCFS-Qualifying Vehicles is enabled, this policy only applies to aviation and represents the use of sustainable aviation fuels. The value set in this lever is in addition to BAU requirements. // **Guidance for setting values:** The U.S. National Renewable Fuel Standard equates to a BAU LCFS of 2.2% - 4.6% (varying by year). California adopted an LCFS that required a 10% reduction in carbon intensity of the transportation fuel pool by 2020. | K11: transportation-sector-main.html#lcfs | L11: low-carbon-fuel-standard.html | M11: https://www.arb.ca.gov/fuels/lcfs/background/basics.htm
A12: Transportation | B12: Non-BAU LCFS-Qualifying Vehicles | C12: Boolean Use Non BAU LCFS Vehicle Types | D12: Low Carbon Fuel Standard | E12: trans LCFS vehicles | F12: 0 | G12: 1 | H12: 1 | I12: on/off | J12: **Description:** This lever changes which vehicles qualify under the low carbon fuel standard. With the lever off, LCFS-qualifying vehicles include all vehicle types except aircraft. With the lever on, only aircraft qualify. | K12: transportation-sector-main.html#lcfs | L12: low-carbon-fuel-standard.html | M12: https://www.arb.ca.gov/fuels/lcfs/background/basics.htm
A13: Transportation | B13: Mode Shifting | C13: Percent of Travel Demand Shifted to Other Modes or Eliminated | D13: Mode Shifting | E13: trans mode shifting | F13: 0 | G13: =-ROUND(MaxBoundCalculations!$B$206,2) -> 0.33 | H13: 0.01 | I13: % of trips shifted | J13: **Description:** This policy represents a set of measures to reduce demand for passenger or freight transportation in the selected vehicle type(s). **Passenger car and SUV** trips may be shifted to other travel modes, such as buses, rail, walking, biking, or eliminated through technology such as videoconferencing. Example measures include improved public transit systems, more walking and bike paths, zoning for higher density along transit corridors, zoning for mixed-use developments, roadway and congestion pricing, and increased parking fees. **Commercial passenger and freight flight** trips may be shifted to inter-city rail or eliminated using technology such as videoconferencing. **Heavy Heavy Duty Truck** trips can be reduced through improved logistics that avoids backhauls and transporting empty shipping containers. The following descriptions detail the different vehicle types: // **Passenger cars and SUVs:** most light-duty road vehicles // **Heavy Duty Trucks:** all other heavy road vehicles (mostly freight trucks) // **Commercial passenger flights:** this is not general aviation // **Guidance for setting values:** // **Passenger cars and SUVs:** The International Energy Agency's BLUE Shifts scenario (from the 2009 report "Transport, Energy, and CO2: Moving Toward Sustainability") includes a 26% reduction in usage of cars and SUVs in OECD countries by 2050 relative to a BAU case. // **Commercial passenger flights:** The International Energy Agency's BLUE Shifts scenario (from the 2009 report "Transport, Energy, and CO2: Moving Toward Sustainability") includes a 30% reduction in usage of aircraft in OECD countries by 2050 relative to a BAU case. // **Heavy Duty Trucks:** The U.S. Federal Highway Administration reports that approximately 25% of mileage for trucks larger than pickups/minivans/other light vans are for empty backhauls and empty shipping containers. | K13: transportation-sector-main.html#tdm | L13: transportation-demand-management.html | M13: International Energy Agency, 2009, "Transport, Energy and CO2: Moving toward Sustainability", http://www.iea.org/publications/freepublications/publication/transport2009.pdf "Freight Facts and Figures", 2013, https://ops.fhwa.dot.gov/freight/freight_analysis/nat_freight_stats/docs/13factsfigures/pdfs/fff2013_highres.pdf
A14: Transportation | B14: Zero-Emission Vehicle Sales Standard | C14: Additional Minimum Required ZEV Sales Percentage for Model Region | D14: ZEV Sales Standard | E14: trans ZEV minimum | F14: -1 | G14: 1 | H14: 0.01 | I14: % of new vehicles sold | J14: =_xlfn.XLOOKUP($C14,'State Policy Descriptions'!$C:$C,'State Policy Descriptions'!$L:$L,0,1,1) -> **Description:** This policy requires the specified percentage of newly sold vehicles of the selected type(s) to consist of zero-emission vehicles. If that percentage would already be achieved through BAU sales plus the effects of other policies, such as an EV subsidy, this policy has no effect. Manufactures may meet a sales standard through techniques such as more heavily marketing electric vehicles, lowering the price of electric vehicles, or raising the price of non-electric vehicles. A negative setting for this lever implies a decrease in ZEV sales requirements relative to the BAU scenario. The following descriptions detail the different vehicle types: // **Passenger cars and SUVs:** most light-duty road vehicles //**Light and Medium Commercial Trucks:** commercial trucks carrying freight, not passengers // **Buses:** including school, transit, and intercity buses // **Heavy Duty Trucks:** all other heavy road vehicles (mostly freight trucks) // **Passenger motorbikes:** registered motorcycles // **Guidance for setting values:**//**Passenger cars and SUVs: ** Under the Clean Air Act, California was awarded a waiver enabling the state to set vehicle emissions standards that are more stringent than federal standards. The waiver has resulted in the Advanced Clean Cars (ACC) and Advanced Clean Cars II (ACC II) regulations. Other states can also choose to adopt the regulations. ACC requires requires automakers to sell ~7-10% EV sales by 2025. ACC II stipulates a 35 percent sales requirement in 2026, ramping up to a 100 percent sales target in 2035. The state has adopted ACC and partially adopted ACC II. // **Light and Medium Commercial and Heavy Duty Trucks:** Today, the share of electric freight trucks is very low, but electrification is particularly promising for certain types of trucks, such as those used to make deliveries within cities, those involved in port operations, garbage trucks, and others with frequent starts and stops. // **Buses:** Electric bus manufacturer Proterra believes all new transit bus sales could be electric as early as 2030, but transit buses make up roughly 15% of the bus fleet. // **Passenger motorbikes:** Though electric motorcycles and scooters are popular in Europe and Asia, where motorbikes are commonly used for urban transportation and commuting, electric motorbikes are not yet a significant presence in the U.S., where motorbikes are mostly used for recreation. | K14: transportation-sector-main.html#ev-mandate | L14: ev-mandate.html | M14: https://autoalliance.org/energy-environment/state-electric-vehicle-mandate/ https://www.cnbc.com/2019/08/26/colorado-joins-california-in-requiring-automakers-to-sell-more-evs.html https://www.consumerreports.org/hybrids-evs/california-says-new-cars-sold-in-the-state-must-be-zero-emissions-by-2035/ https://www.greentechmedia.com/articles/read/electric-buses-are-going-to-dominate statistics from FoVObE variable https://www.prnewswire.com/news-releases/electric-boats-and-ships-2017-2027-300561222.html
A15: Transportation | B15: Non-BAU ZEV-Qualifying Vehicles | C15: Boolean Use Non BAU ZEV Qualifying Vehicle Definitions | D15: ZEV Sales Standard | E15: trans non BAU ZEV vehicle definitions | F15: 0 | G15: 1 | H15: 1 | I15: on/off | J15: **Description:** This lever changes which vehicles qualify under the ZEV standard. With the lever off, ZEV-qualifying vehicles include battery electric vehicles, plugin hybrid vehicles, and hydrogen-fueled vehicles. With the lever on, only battery electric vehicles and hydrogen-fueled vehicles qualify.
A16: Transportation | B16: Subsidy for Vehicle Battery Production | C16: Additional Subsidy for Vehicle Battery Production | D16: Vehicle Battery Production Subsidy | E16: trans battery subsidy | F16: -50 | G16: 50 | H16: 1 | I16: $/kWh | J16: **Description:** This policy specifies the dollar per kilowatt-hour subsidy for production of vehicle batteries. This is in addition to subsidies that exist in the BAU scenario. The subsidy will only be applied to the fraction of vehicle batteries produced domestically. A negative value implies a tax or removal of subsidies. // **Guidance for setting values:** The Inflation Reduction Act includes a $35/kWh tax credit for battery cells and a $10/kWh tax credit for assembly for onroad vehicles, which are included in the BAU.
A17: Transportation | B17: Non-BAU Zero-Emission Vehicle Sales Standard by Subregion | C17: Boolean Use Non BAU Minimum Required ZEV Sales Percentage by Subregion | D17: ZEV Sales Standard | E17: trans non BAU ZEV minimum | F17: 0 | G17: 1 | H17: 1 | I17: on/off | J17: **Description:** Turning this policy lever on will edit the BAU assumptions for state-level minimum ZEV requirements. This is done by using different input data files for the model. In the United States model and in the various U.S. state models, turning this policy lever on reverses state-level Advanced Clean Cars and Advanced Clean Trucks requirements starting in 2025. This only has an effect if the state has adopted ACC or ACT.
A18: Buildings and Appliances | B18: Building Component Electrification | C18: Fraction of New Bldg Components Shifted to Other Fuels | D18: Building Component Electrification | E18: bldgs new component fuel shifting | F18: 0 | G18: 1 | H18: 0.01 | I18: % of newly sold non-electric building components | J18: =_xlfn.XLOOKUP($C18,'State Policy Descriptions'!$C:$C,'State Policy Descriptions'!$L:$L,0,1,1) -> **Description:** This policy replaces the specified fraction of newly sold non-electric building components of the selected type(s) in buildings of the selected type(s) with electricity-using components. // **Guidance for setting values:** //**Urban Residential Heating:** In the BAU case, in New Jersey, the share of electricity among fuels used for heating in urban, residential buildings will rise from 7% to 11% through 2050.//**Urban Residential Appliances:** In the BAU case, in New Jersey, the share of electricity among fuels used for appliances in urban, residential buildings will fall from 31% to 30% through 2050.//**Urban Residential Other Components:** In the United States, the share of electricity among fuels used by other components in urban, residential buildings is 100%.//**Rural Residential Heating:** In the BAU case, in New Jersey, the share of electricity among fuels used for heating in rural, residential buildings will rise from 7% to 11% through 2050.//**Rural Residential Appliances:** In the BAU case, in New Jersey, the share of electricity among fuels used for appliances in rural, residential buildings will fall from 30% to 30% through 2050.//**Rural Residential Other Components:** In the United States, the share of electricity among fuels used by other components in rural, residential buildings is 100%.//**Commercial Heating:** In the BAU case, in New Jersey, the share of electricity among fuels used for heating in commercial buildings will fall from 3% to 3% through 2050.//**Comercial Appliances:** In the BAU case, in New Jersey, the share of electricity among fuels used for appliances in commercial buildings will fall from 30% to 28% through 2050.//**Comercial Other Components:** In the BAU case, in New Jersey, the share of electricity among fuels used for other components in commercial buildings will rise from 66% to 76% through 2050. | K18: buildings-sector-main.html#component-elec | L18: building-component-electrification.html | M18: EIA AEO
A19: Buildings and Appliances | B19: Building Energy Efficiency Standards | C19: Reduction in E Use Allowed by Component Eff Std | D19: Building Energy Efficiency Standards | E19: bldgs efficiency standards | F19: 0 | G19: 0.75 | H19: 0.01 | I19: % reduction in energy use | J19: =_xlfn.XLOOKUP($C19,'State Policy Descriptions'!$C:$C,'State Policy Descriptions'!$L:$L,0,1,1) -> **Description:** This policy tightens energy efficiency standards for the selected component(s) in the selected building type(s). The policy only applies to newly sold components each year (whether for new buildings or replacement of old components of existing buildings). // **Guidance for setting values:** In "Assessment of Electricity Savings in the U.S. Achievable through New Appliance/Equipment Efficiency Standards and Building Efficiency Codes, 2010-2025" (2011), the Edison Foundation considered a 30% reduction in whole-building energy use (moderate case) and 40-45% (aggressive case) relative to BAU from 2010 to 2025. | K19: buildings-sector-main.html#eff-stds | L19: building-energy-efficiency-standards.html | M19: Edison Foundation, 2011, "Assessment of Electricity Savings in the U.S. Achievable through New Appliance/Equipment Efficiency Standards and Building Efficiency Codes (2010 - 2025)", http://www.edisonfoundation.net/iei/Documents/IEE_CodesandStandardsAssessment_2010-2025_UPDATE.pdf, Page B-2, Table B-1. | N19: Itron, 2007, "ASSESSMENT OF LONG-TERM ELECTRIC ENERGY EFFICIENCY POTENTIAL IN CALIFORNIA’S RESIDENTIAL SECTOR," http://www.energy.ca.gov/2007publications/CEC-500-2007-002/CEC-500-2007-002.PDF, p.33, Table 5-1
A20: Buildings and Appliances | B20: Contractor Training | C20: Boolean Improved Contractor Edu and Training | D20: Contractor Training | E20: bldgs contractor training | F20: 0 | G20: 1 | H20: 1 | I20: on/off | J20: **Description:** This policy represents a program to train contractors in energy-efficient products and installation practices. This covers activities such as air sealing, building framing, and choice and application of insulation. This policy affects newly sold building envelope components, which reduce the energy use of heating, cooling, and ventilation systems in buildings by 3.7% (based on a 2006 study from the Energy Center of Wisconsin). | K20: buildings-sector-main.html#contractor-ed | L20: contractor-training.html
A21: Buildings and Appliances | B21: Distributed Solar Carve-Out | C21: Min Fraction of Total Elec Demand to be Met by Distributed Solar PV | D21: Distributed Solar Promotion | E21: bldgs min fraction distributed solar | F21: 0 | G21: =ROUND(MaxBoundCalculations!B172,2) -> 0.24 | H21: 0.005 | I21: minimum % elec from solar | J21: **Description:** This policy requires at least the specified percentage of total retail electricity demand to be generated by residential and commercial buildings' distributed solar systems (typically rooftop PV). // **Guidance for setting values:** It is typical for state policy to include 0 to 5% carve-outs. For example, Colorado has established a 3% carve-out for 2020 (though it includes non-solar on-site sources). | K21: buildings-sector-main.html#solar-carve-out | L21: solar-carve-out.html | M21: MASSACHUSETTS: http://www.mass.gov/eea/energy-utilities-clean-tech/renewable-energy/solar/rps-solar-carve-out/current-status-of-the-rps-solar-carve-out-program.html COLORADO: http://www.seia.org/research-resources/rps-solar-carve-out-colorado | N21: RMI, 2011, "Reinventing Fire Electricity Sector Methodology," http://www.rmi.org/cms/Download.aspx?id=10765&file=Reinventing+Fire+Electricity+Sector+Methodology.pdf&title=Reinventing+Fire+Electricity+Sector+Methodology, Page 11, 2050 Generation by Case
A22: Buildings and Appliances | B22: Distributed Solar Subsidy | C22: Additional Perc Subsidy for Distributed Solar PV Capacity | D22: Distributed Solar Promotion | E22: bldgs distributed solar subsidy | F22: 0 | G22: 0.5 | H22: 0.01 | I22: % of PV system cost | J22: **Description:** This policy causes the government to reimburse building owners for an additional percentage of the cost of new distributed solar PV capacity that is installed on or around buildings. This is in addition to the subsidy that is included in BAU. // **Guidance for setting values:** The Inflation Reduction Act includes a 30% tax credit for residential solar through 2032, phased down to 0% by 2035. This is incorporated in the BAU scenario. | K22: buildings-sector-main.html#distributed-solar-subsidy | L22: distributed-solar-subsidy.html | M22: Department of Energy. Business Energy Investment Tax Credit (ITC). http://energy.gov/savings/business-energy-investment-tax-credit-itc
A23: Buildings and Appliances | B23: Distributed Solar Capacity Requirement | C23: Min Required Rooftop Solar Capacity | D23: Distributed Solar Promotion | E23: bldgs min req rooftop solar | F23: 0 | G23: 600000 | H23: 5000 | I23: MW | J23: **Description:** This policy requires at least the specified capacity of distributed solar be built by the model. // **Guidance for setting values:** We estimate the maximum rooftop solar potential in the U.S. at 385 GW for commercial buildings, 595 GW for urban residential buildings, and 135 GW for rural residential buildings. We recommend users not set the value above this potential.
A24: Buildings and Appliances | B24: Non BAU Distributed Solar Capacity | C24: Boolean Use Non BAU Distributed Solar Capacity | D24: Distributed Solar Promotion | E24: non BAU dist solar | F24: 0 | G24: 1 | H24: 1 | I24: on/off | J24: **Description:** Turning this policy lever on will edit the BAU assumptions for deployment of distributed solar. This is done by using different input data files for the model. In the United States model and in the various U.S. state models, turning this policy lever on will remove the incremental distributed solar deployments expected from the Inflation Reduction Act. //
A25: Buildings and Appliances | B25: Improved Labeling | C25: Boolean Improved Device Labeling | D25: Improved Labeling | E25: bldgs device labeling | F25: 0 | G25: 1 | H25: 1 | I25: on/off | J25: **Description:** This policy represents a program requiring newly sold heating systems, cooling and ventilation systems, and appliances to feature prominent, well-designed labels highlighting their energy efficiencies. The policy reduces energy consumption of newly sold building components of these types by 10%. | K25: buildings-sector-main.html#device-labeling | L25: improved-labeling.html | M25: none
A26: Buildings and Appliances | B26: Retrofit Existing Buildings | C26: Share of Preexisting Buildings Subject to Retrofitting | D26: Increased Retrofitting | E26: bldgs retrofitting | F26: 0 | G26: 1 | H26: 0.01 | I26: % of existing buildings | J26: **Description:** Each year, the specified percentage of the selected building type(s) that existed at the start of the model run will be retrofit with more efficient heating, cooling, and envelope components. // **Guidance for setting values:** By 2050, roughly 88% of the preexisting residential buildings and 83% of the preexisting commercial buildings will still survive without major renovations, so values of 88% and 83% in 2050 will retrofit all such surviving buildings by that year. Policy settings higher than this will retrofit all eligible buildings sooner than 2050. | K26: buildings-sector-main.html#retrofitting | L26: increased-retrofitting.html | M26: Calculated from model data; see the relevant variable(s) in the InputData folder for source information.
A27: Buildings and Appliances | B27: Rebate for Efficient Products | C27: Boolean Rebate Program for Efficient Components | D27: Rebate for Efficient Products | E27: bldgs rebate | F27: 0 | G27: 1 | H27: 1 | I27: on/off | J27: **Description:** This policy represents a modest rebate paid to customers who purchase energy-efficient building equipment of the selected type(s). Typical rebate amounts represented by this policy are $50-100 for a clothes washer and $25-50 for a dishwasher or refrigerator. | K27: buildings-sector-main.html#rebate | L27: rebate-for-efficient-products.html
A28: Electricity Supply | B28: Ban New Power Plants | C28: Boolean Ban New Power Plants | D28: Ban New Power Plants | E28: elec ban new power plants | F28: 0 | G28: 1 | H28: 1 | I28: on/off | J28: =_xlfn.XLOOKUP($C28,'State Policy Descriptions'!$C:$C,'State Policy Descriptions'!$L:$L,0,1,1) -> **Description:** This policy prevents new capacity of the selected type(s) from being built or deployed. // **Guidance for setting values:** No new coal is planned in New Jersey. | K28: electricity-sector-main.html#ban | L28: ban-new-capacity.html
A29: Electricity Supply | B29: Ban New Power Plant Retrofits | C29: Boolean Ban New Power Plant Retrofits | D29: Ban New Power Plant Retrofits | E29: elec ban new power plant retrofits | F29: 0 | G29: 1 | H29: 1 | I29: on/off | J29: **Description:** This policy prevents new capacity of the selected CCS plant type(s) from being built to replace existing non-CCS plants.
A30: Electricity Supply | B30: Clean Electricity Standard | C30: Renewable Portfolio Std Percentage | D30: Clean Electricity Standard | E30: elec renewable portfolio standards | F30: 0 | G30: 1 | H30: 0.01 | I30: % of electricity generation | J30: =_xlfn.XLOOKUP($C30,'State Policy Descriptions'!$C:$C,'State Policy Descriptions'!$L:$L,0,1,1) -> **Description:** This policy specifies an increase in the fraction of electricity generation that must come from qualifying carbon-free sources (wind, solar, biomass, nuclear, hydro, geothermal, ccs, and hydrogen) in 2050. This policy has no effect until the user-set value exceeds the existing fraction of carbon-free electricity and any carbon-free electricity standards which have been enacted at the state level. To use this policy, turn the associated 'Non BAU RPS Qualifying Resources' policy to ON and the 'Lift the Clean Electricity Standard Alternative Compliance Payment' policy to ON. // **Guidance for setting values:** Multiple states have set 100% clean energy or renewable energy laws or goals, not including New Jersey. When setting a high CES with this lever, users should also turn on supporting power sector policies (i.e., Grid-Scale Electricity Storage, Increase Transmission, and Demand Response) to avoid curtailment of renewables. At very high CES values, the associated policy costs are highly uncertain and should be complemented with other modeling. The business-as-usual CES value assumes the portion of an existing RPS standard met by imports remains constant. | K30: electricity-sector-main.html#ces | L30: clean-energy-standard.html | M30: White House, 2015, "Fact Sheet: President Obama to Announce Historic Carbon Pollution Standards for Power Plants", https://www.whitehouse.gov/the-press-office/2015/08/03/fact-sheet-president-obama-announce-historic-carbon-pollution-standards.
A31: Electricity Supply | B31: Clean Electricity Standard Foresight | C31: BESHFoFRV Boolean Electricity Suppliers Have Foresight of Future RPS Values | F31: 0 | G31: 1 | H31: 1 | I31: on/off | J31: **Description:** This setting indicates whether electricity suppliers have foresight of future-year CES values (both BAU case values and any values set by the user in the CES policy lever). With foresight, electricity suppliers will build some CES-qualifying resources in earlier years than would be strictly necessary to meet the CES requirement in those years if it allows them to approach a higher, future-year CES target more gradually, lessening the need to build power plants abruptly if the CES rises more steeply in the future.
A32: Electricity Supply | B32: Lift the Clean Electricity Standard Alternative Compliance Payment | C32: Boolean Use Non BAU RPS Alternative Compliance Payment | D32: Clean Electricity Standard | E32: elec non BAU RACP | F32: 0 | G32: 1 | H32: 1 | I32: on/off | J32: =_xlfn.XLOOKUP($C32,'State Policy Descriptions'!$C:$C,'State Policy Descriptions'!$L:$L,0,1,1) -> **Description:** The BAU scenario includes a CES alternative compliance payment of roughly 50 $/MWh. If the CES credit price hits this $/MWh amount in a given year, the model will not deploy any additional CES qualifying resources in an attempt to meet the CES. Enabling this policy lifts this cap, meaning there is no price constraint on new resources.
A33: Electricity Supply | B33: Change Electricity Exports | C33: Percent Change in Electricity Exports | D33: Electricity Imports and Exports | E33: elec change exports | F33: -0.5 | G33: 1 | H33: 0.1 | I33: % change in exports | J33: =_xlfn.XLOOKUP($C33,'State Policy Descriptions'!$C:$C,'State Policy Descriptions'!$L:$L,0,1,1) -> **Description:** This policy increases or decreases the amount of electricity exported from the United States to Canada and Mexico. It does not cause the construction or removal of transmission lines linking these countries. // **Guidance for setting values:** Multiple states have set 100% clean energy or renewable energy laws or goals, not including New Jersey. When setting a high CES with this lever, users should also turn on supporting power sector policies (i.e., Grid-Scale Electricity Storage, Increase Transmission, and Demand Response) to avoid curtailment of renewables. At very high CES values, the associated policy costs are highly uncertain and should be complemented with other modeling. The business-as-usual CES value assumes the portion of an existing RPS standard met by imports remains constant. | K33: electricity-sector-main.html#elec-exports | L33: electricity-imports-exports.html | M33: Energy Information Administation. 2016. Electric Power Annual. Table 2.13.
A34: Electricity Supply | B34: Change Electricity Imports | C34: Percent Change in Electricity Imports | D34: Electricity Imports and Exports | E34: elec change imports | F34: -0.5 | G34: 1 | H34: 0.02 | I34: % change in imports | J34: =_xlfn.XLOOKUP($C34,'State Policy Descriptions'!$C:$C,'State Policy Descriptions'!$L:$L,0,1,1) -> **Description:** This policy increases or decreases the amount of electricity imported to the United States from Canada and Mexico. It does not cause the construction or removal of transmission lines linking these countries. // **Guidance for setting values:** From 2008 to 2021, electricity imports grew by -32%. | K34: electricity-sector-main.html#elec-imports | L34: electricity-imports-exports.html | M34: Energy Information Administation. 2016. Electric Power Annual. Table 2.13.
A35: Electricity Supply | B35: Non BAU Guaranteed Dispatch | C35: Boolean Use Non BAU Guaranteed Dispatch Settings | D35: Non BAU Guaranteed Dispatch | E35: elec non BAU guaranteed dispatch | F35: 0 | G35: 1 | H35: 1 | I35: on/off
A36: Electricity Supply | B36: Decrease Cost of Capital | C36: Percentage Decrease in Cost of Capital for Power Plants | D36: Decrease Electricity Sector Cost of Capital | E36: elec power plant cost of capital | F36: 0 | G36: 1 | H36: 1 | I36: % decrease | J36: **Description:** This policy decreases the cost of capital for new power plant investments, making the specified plant type more attractive to deploy. // **Guidance for setting values:** The BAU cost of capital for all plant types is calculated as 7.4%, based on data from Lazard. | M36: https://www.lazard.com/media/451905/lazards-levelized-cost-of-energy-version-150-vf.pdf
A37: Electricity Supply | B37: Demand Response | C37: Fraction of Additional Demand Response Potential Achieved | D37: Demand Response | E37: elec demand response | F37: 0 | G37: 1 | H37: 0.01 | I37: % of potential achieved | J37: =_xlfn.XLOOKUP($C37,'State Policy Descriptions'!$C:$C,'State Policy Descriptions'!$L:$L,0,1,1) -> **Description:** This policy represents regulations that cause more demand response (DR) capacity to be added to the electric grid. Demand response provides flexibility that allows for the integration of more wind and solar PV, if the electricity system is flexibility-constrained. Demand response can be load-shedding (demand is reduced in the worst hours without adding demand in other hours) or load-shifting (demand is reduced in the worst hours and added in other hours). The type of demand response modeled here is load-shedding, which is by far the most common type of demand response that exists today. // **Guidance for setting values:**For New Jersey, a 100% setting provides for an additional 4751 MW of demand response capacity in 2050 (on top of a BAU quantity of 2272 MW). | K37: electricity-sector-main.html#dr | L37: demand-response.html | M37: Calculated from model data; see the relevant variable(s) in the InputData folder for source information.
A38: Electricity Supply | B38: Early Retirement of Power Plants | C38: Annual Additional Capacity Retired due to Early Retirement Policy | D38: Early Retirement of Power Plants | E38: elec early retirement | F38: 0 | G38: 5000 | H38: 50 | I38: MW/year | J38: =_xlfn.XLOOKUP($C38,'State Policy Descriptions'!$C:$C,'State Policy Descriptions'!$L:$L,0,1,1) -> **Description:** This policy causes the specified quantity of otherwise non-retiring capacity of the selected type(s) to be retired each year. // **Guidance for setting values:** // **Hard coal:** The EIA projects that New Jersey will retire 0 MW of coal by 2050. New Jersey currently has 463 MW of coal capacity.//**Natural gas non-peaker:** The EIA projects that NJ will retire 0 MW of natural gas by 2050. NJ currently has 8570 MW of natural gas non-peaker capacity.//**Nuclear:** The EIA projects that NJ will retire 0 MW of nuclear by 2050. NJ currently has 3467 MW of nuclear capacity.//**Natural gas peaker:** The EIA projects that NJ will retire 0 MW of natural gas by 2050. NJ currently has 2770 MW of natural gas peaker capacity.//**Lignite:** The EIA projects that NJ will retire 0 MW of lignite by 2050. NJ currently has 0 MW of lignite capacity. | K38: electricity-sector-main.html#early-ret | L38: early-retirement-of-power-plants.html | M38: Energy Information Administration, 2014, "Annual Energy Outlook 2014", http://www.eia.gov/oiaf/aeo/tablebrowser/#release=AEO2014&subject=6-AEO2014&table=9-AEO2014&region=0-0&cases=hccstom-d012314a,ref2014-d102413a, Table Browser. Select Electric Power Sector, Electricity Generating Capacity (and check Reference and Accelerated coal retirements scenarios). | N38: The Brattle Group, 2012, "Potential Coal Plant Retirements: 2012 Update," http://greatlakeslegalfoundation.org/wwcms/wp-content/uploads/documents/regulatory/TrainWreck/12Oct15_BrattleStudy.pdf, Page 8, Table 4
A39: Electricity Supply | B39: Non BAU Capacity Retirement Schedule | C39: Boolean Use Non BAU Capacity Retirement Schedule | D39: Non BAU Capacity Retirement Schedule | F39: 0 | G39: 1 | H39: 1 | I39: on/off | J39: **Description:** The EPS calculates economc capacity additions and retirements in each time step. In addition, it incorporates any announced retirements through input data files. This policy uses an alternate input data file specifying planned retirement schedules for existing capacity of the selected type(s). // **Guidance for setting values:** The Current Policies scenario includes all expected coal retirements resulting from EPA's Clean Air Act Section 111 regulations for power plants, as well as from other regulations and legislation like the Inflation Reduction Act. Turning this lever on removes the effect of those federal policies, resulting in fewer coal retirements.
A40: Electricity Supply | B40: Non BAU Mandated Capacity Construction | C40: Boolean Use Non BAU Mandated Capacity Construction Schedule | D40: Non BAU Mandated Capacity Construction | F40: 0 | G40: 1 | H40: 1 | I40: on/off | J40: **Description:** The BAU scenario includes all planned capacity additions (provided by the U.S. Energy Information Administration). This policy uses an alternative set of planned capacity additions. // **Guidance for setting values:** // **Offshore Wind:** When used in the context of the US NDC scenario, this policy results in roughly 30 GW of offshore wind by 2030 and 220 of offshore wind by 2050 nationwide.
A41: Electricity Supply | B41: Non BAU Mandated Capacity CCUS Retrofits | C41: Boolean Use Non BAU Mandated Capacity Retrofit Schedule | D41: Non BAU Mandated Capacity CCUS Retrofits | F41: 0 | G41: 1 | H41: 1 | I41: on/off | J41: **Description:** The business-as-usual case includes all planned CCUS retrofits (as modeled by the EPA for its latest Clean Air Act Section 111 regulations for power plants). Turning this policy lever on assumes those retrofits do not happen.
A42: Electricity Supply | B42: Non BAU RPS Qualifying Resources | C42: Boolean Use Non BAU RPS Qualifying Resource Definitions | D42: Non BAU RPS Qualifying Resources | E42: elec non BAU RPS qualifying resources | F42: 0 | G42: 1 | H42: 1 | I42: on/off | J42: **Description:** This policy expands the definitions for qualifying carbon-free sources to include: nuclear, hydro, wind, solar, biomass, geothermal, municipal solid waste, carbon capture and storage, and hydrogen.// | L42: =J4=K38
A43: Electricity Supply | B43: Change in Expected Power Plant Capacity Factor | C43: Percentage Reduction in Plant Downtime | D43: Reduce Plant Downtime | E43: elec reduce plant downtime | F43: -0.3 | G43: 0.6 | H43: 0.01 | I43: % reduction in downtime | J43: **Description:** This policy specifies the change in capacity factor (time spent generating power) for new natural gas combined cycle plants. This policy changes these plants' expected capacity factors, but it does not force them to be dispatched if it would be uneconomical to do so. A negative value implies a decrease in capacity factor relative to the Current Policies scenario. // **Guidance for setting values:** // **Natural Gas Combined Cycle:** As part of EPA's Clean Air Act Section 111 regulations for new power plants, natural gas combined cycle plants that operate more than 40 percent of the time must capture 90 percent of on-site emissions by 2032. This would effectively block new natural gas plants without CCS (which are tracked as a separate power plant type in the model). Therefore, we adjust the expected capacity factor for new combined cycle plants so that they would run at a maximum capacity factor of 40 percent starting in 2032. | K43: electricity-sector-main.html#red-downtime | L43: reduce-downtime.html | M43: E&E Publishing. The Clean Power Plan - A Summary. http://www.eenews.net/interactive/clean_power_plan/fact_sheets/rule National Renewable Energy Laboratory. United States (48 Contiguous States) Potential Wind Capacity Cumulative Area vs. Gross Capacity Factor. http://apps2.eere.energy.gov/wind/windexchange/pdfs/wind_maps/us_contiguous_wind_potential_chart.pdf See the discussion of multi-junction solar cells on Wikipedia at https://en.wikipedia.org/wiki/Multi-junction_solar_cell. Also NREL has a useful chart at http://www.nrel.gov/ncpv/images/efficiency_chart.jpg.
A44: Electricity Supply | B44: Reduce Soft Costs | C44: Percent Reduction in Soft Costs of Capacity Construction | D44: Reduce Soft Costs | E44: elec reduce soft costs | F44: 0 | G44: 0.9 | H44: 0.01 | I44: % reduction in soft costs | J44: **Description:** This policy specifies a reduction in soft costs (costs for things other than capital equipment) for new plants of the selected type(s), such as the costs of permitting, financing, project management, assembly, etc. // **Guidance for setting values:** Costs of permitting and financing can be reduced by streamlining permitting processes, but some soft costs (such as labor) may be difficult to reduce via policy. A value of 50% would be an aggressive soft cost reduction. | K44: endogenous-learning.html#red-soft-costs | L44: reduce-soft-costs.html
A45: Electricity Supply | B45: Reduce Transmission & Distribution Losses | C45: Percentage TnD Losses Avoided | D45: Reduce T&D Losses | E45: elec avoid TND loss | F45: 0 | G45: 0.4 | H45: 0.01 | I45: % of losses avoided | J45: **Description:** This policy specifies the reduction in transmission and distribution losses that will be achieved by 2050. // **Guidance for setting values:** The U.S. has transmission and distribution losses of about 6%. Germany, Japan, Finland, and the Netherlands have T&D losses of around 4%. Therefore, a 33% policy setting would cause the U.S. to match these countries' current level of T&D losses by 2050. | K45: electricity-sector-main.html#red-tnd-losses | L45: reduce-tnd-losses.html | M45: The World Bank. Electric power transmission and distribution losses (% of output). http://data.worldbank.org/indicator/EG.ELC.LOSS.ZS
A46: Electricity Supply | B46: Subsidy for Capacity Construction | C46: Perc Subsidy for Elec Capacity Construction | D46: Subsidy for Capacity Construction | E46: elec capacity construction subsidy | F46: 0 | G46: 0.95 | H46: 0.01 | I46: % of construction cost | J46: **Description:** This policy is a subsidy paid by the government to electricity suppliers per unit of new capacity constructed. This only applies to utilities, not distributed systems (such as rooftop solar). // **Guidance for setting values:** The U.S. provides clean electricity tax credits as part of the Inflation Reduction Act (IRA). Tax credits are claimed as either the Investment Tax Credit (per unit capacity) or Production Tax Credit (per unit electricity generation), depending on the plant type. The BAU assumes IRA tax credits will begin phasing out after the year 2036, when electricity sector emissions reach the target of 25% below 2022 levels. // **Nuclear:** The U.S. Federal Government has guaranteed billions of dollars of loans for the construction new nuclear plants and has funded billions of dollars of nuclear technology R&D. The construction of two new reactors at the Vogtle power plant, the only recently built nuclear energy project under construction in the U.S., received $12 billion in loan guarantees as of March 2019. (Loan guarantees are not equivalent to subsidies dollar-for-dollar, but they lower the cost of construction by enabling the plant to access cheaper financing.) // **Solar Thermal:** We assume IRA tax credits of 41.6%, based on assumptions on which share of new plants qualify for various bonus credits. // **Biomass:** The U.S. Federal Government has collectively guaranteed billions of dollars of loans for the construction new biomass plants. (Loan guarantees are not equivalent to subsidies dollar-for-dollar, but they lower the cost of construction by enabling the plant to access cheaper financing.) // **Geothermal:** We assume IRA tax credits of 41.6%, based on assumptions on which share of new plants qualify for various bonus credits. // **Offshore Wind:** We assume IRA tax credits of 41.6%, based on assumptions on which share of new plants qualify for various bonus credits. | K46: electricity-sector-main.html#subsidies | M46: https://www.energy.gov/articles/secretary-perry-announces-financial-close-additional-loan-guarantees-during-trip-vogtle https://www.energysage.com/solar/cost-benefit/solar-investment-tax-credit/ http://biomassmagazine.com/articles/8185/usda-loan-guarantees-support-3-biomass-power-plants
A47: Electricity Supply | B47: Subsidy for Electricity Production | C47: Subsidy for Elec Production by Fuel | D47: Subsidy for Electricity Production | E47: elec generation subsidy | F47: 0 | G47: 60 | H47: 1 | I47: =UnitControlCenter!$B$51 -> $/MWh | J47: **Description:** This policy is a subsidy paid by the government to suppliers of electricity per unit of electricity generated from the selected plant type(s).This is in addition to subsidies that exist in the BAU scenario. // **Guidance for setting values:** The U.S. provides clean electricity tax credits as part of the Inflation Reduction Act (IRA). The BAU assumes IRA tax credits will begin phasing out after the year 2039, when electricity sector emissions reach the target of 25% below 2022 levels. Tax credits are claimed as either the Investment Tax Credit (per unit capacity) or Production Tax Credit (per unit electricity generation), depending on the plant type. // Also note that the Energy Policy Simulator chooses which new power plants to build based on lifetime plant costs, and the PTC is only available for the first 10 years of a project. // **Nuclear:** We assume roughly $10/MWh worth of incentives for nuclear in our BAU as part of the IRA and the Infrastructure Investment and Jobs Act. // **Onshore Wind:** We assume IRA tax credits of roughly $20.50 per MWh, based on assumptions on which share of new plants qualify for various bonus credits. // **Solar PV:** We assume IRA tax credits of roughly $24.50, based on assumptions on which share of new plants qualify for various bonus credits. | K47: electricity-sector-main.html#subsidies | L47: subsidy-for-electricity-production.html | M47: PRODUCTION TAX CREDIT: Database of State Incentives for Renewables & Efficiency, 2013, "Renewable Energy Production Tax Credit (PTC)", http://dsireusa.org/incentives/incentive.cfm?Incentive_Code=US13F. STATE-LEVEL INCENTIVES: Energy Information Administration, 2013, "Feed-In Tariffs and similar programs", http://www.eia.gov/electricity/policies/provider_programs.cfm.
A48: Electricity Supply | B48: Use EVs for Grid Balancing | C48: Share of EVs Used for Grid Balancing | D48: EVs for Grid Balancing | E48: elec use EVs for grid balancing | F48: 0 | G48: 1 | H48: 0.01 | I48: % of EVs used | J48: **Description:** This policy increases the share of EVs that are used to assist in grid balancing on an average day. This means the EV is connected to the grid during the hours when demand-shifting would be helpful (hours of net peak load) and can pause its charging or, ideally, can partially discharge its battery during these hours to help provide electricity to the grid. // **Guidance for setting values:** Today, EVs generally are not used to help with grid balancing, and EVs and chargers may not have the capability to send electricity in the reverse direction to supply the grid (and have suitable safety cut-off systems to prevent energizing the grid when utilities intentionally shut it down to do repairs and maintenance). Automatically changing the hours when an EV charges (but not discharging to support the grid) is technologically easier but provides less support to the grid.
A49: Electricity Supply | B49: Subsidy for Grid Battery Production | C49: Additional Subsidy for Grid Battery Production | D49: Grid Battery Subsidy | E49: elec battery production subsidy | F49: -100 | G49: 100 | H49: 5 | I49: $/kWh | J49: **Description:** This policy provides a subsidy in units of dollar per kilowatt-hour of battery capacity produced by manufacturers. This is in addition to subsidies that exist in the BAU scenario. A negative value implies a tax or removal of subsidies. // **Guidance for setting values:** The BAU scenario has a $45/kWh production credit provided to manufacturers reflecting the Inflation Reduction Act's 45X tax credit.
A50: Electricity Supply | B50: Subsidy for Grid Battery Output | C50: Additional Subsidy per Unit Electricity Supplied to the Grid by Grid Batteries | D50: Grid Battery Subsidy | E50: elec battery subsidy per output | F50: -100 | G50: 100 | H50: 5 | I50: $ / MWh | J50: **Description:** This policy provides a subsidy in units of dollar per megawatt-hour electricity supplied to the grid, additional to any BAU subsidies. A negative value implies a tax or removal of subsidies. // **Guidance for setting values:** The BAU case has grid batteries claiming the Subsidy for Grid Battery Capacity, not a subsidy per unit output.
A51: Electricity Supply | B51: Subsidy for Grid Battery Capacity | C51: Additional Percent Subsidy per Unit Grid Battery Capacity Deployed | D51: Grid Battery Subsidy | E51: elec battery construction subsidy | F51: -1 | G51: 1 | H51: 0.01 | I51: % of capital costs | J51: **Description:** This policy subsidizes a percentage of grid battery capacity costs, additional to any BAU capacity construction subsidies. A negative value implies a tax or removal of subsidies. // **Guidance for setting values:** The BAU scenario assumes IRA tax credits of 41.6%, based on assumptions on which share of new projects qualify for various bonus credits.
A52: Electricity Supply | B52: Electricity CCS Subsidy | C52: Additional Subsidy for Elec CCS | D52: Electricity CCS Subsidy | E52: elec CCS subsidy | F52: -100 | G52: 100 | H52: 5 | I52: $ / metric ton CO2e | J52: **Description:** This policy provides a dollar per metric ton CO2e subsidy, additional to any BAU subsidies. A negative value implies a tax or removal of subsidies. // **Guidance for setting values:** The 45Q tax credits provide $85 per metric ton CO2e stored, which is included in the BAU case.
A53: Industry | B53: Buy In-Region Products | C53: Fraction of Imported Industrial Outputs Shifted to In Region Suppliers | D53: Buy In-Region Products | E53: indst buy in region outputs | F53: 0 | G53: 0.5 | H53: 0.01 | I53: % of imports shifted | J53: **Description:** This policy increases the extent to which the selected industry's products are supplied by producers within the modeled region. // **Guidance for setting values:** The lever specifies the percentage of imported products (in the BAU case) that are shifted to domestic suppliers (in the policy case). For example, suppose buyers within the modeled region purchase 60% of their road vehicles from domestic automakers and 40% from automakers outside the modeled region. If this policy lever is applied to the "Road Vehicles" industry with a 50% setting, buyers will obtain 80% of their road vehicles from domestic automakers and 20% from automakers outside the modeled region. // **Implementation Note:** This policy reduces imports. In reality, other regions might retaliate by restricting their own purchases of goods produced by the modeled region. However, the EPS only considers policies within the modeled region, so the Buy In-Region Products policy does not affect export levels (i.e., other countries/regions are assumed not to retaliate).
A54: Industry | B54: Carbon Capture and Sequestration | C54: Industry Sector Fraction of Potential Additional CCS Achieved | D54: Industry CCS | E54: indst CCS | F54: 0 | G54: 1 | H54: 0.01 | I54: % of CO2 captured | J54: **Description:** This policy specifies the fraction of CO2 emissions from industry that is captured and stored, above the amount predicted in the BAUlscenario. // **Guidance for setting values:** Very few CCS-equipped industrial facilities exist today, so in a scenario where industry does not transition to clean energy, a value over 20% is likely very optimistic. However, in scenarios in which industry mostly or entirely transitions to clean energy (i.e. due to other policies, such as industrial fuel switching and industrial energy efficiency), CCS settings as high as 100% (to capture the small amount of residual CO2 emissions, such as process CO2 from the cement industry) may be very feasible. | K54: ccs.html#ccs | L54: carbon-capture-and-sequestration.html
A55: Industry | B55: Non BAU Industry CCS Subsidy | C55: Boolean Use Non BAU Industry CCS Subsidies | D55: Industry CCS | E55: indst non BAU CCS | F55: 0 | G55: 1 | H55: 1 | I55: on/off | J55: **Description:** This policy allows users to model the emissions and cash flow impacts of a non-BAU industry CCS subsidy. For the United States, this lever is set up to test the impacts of removing all CCS subsidies flowing to industry from the BAU scenario. // **Guidance for setting values:** The United States currently offers 45Q tax credits through 2032 for CCS. Enabling this lever will remove those credits and the amount of CO2 sequestration they are estimated to incentivize. | K55: ccs.html#ccs | L55: carbon-capture-and-sequestration.html
A56: Industry | B56: Cement Clinker Substitution | C56: Fraction of Cement Measures Achieved | D56: Cement Clinker Substitution | E56: indst cement measures | F56: 0 | G56: 1 | H56: 0.01 | I56: % of potential achieved | J56: **Description:** This policy reduces CO2 emissions from the cement industry by substituting other inputs, such as fly ash, for a portion of the clinker in cement. // **Guidance for setting values:** If this policy is fully implemented, the share of clinker in cement is reduced to 60%. | K56: industry-ag-main.html#clinker | L56: cement-clinker-substitution.html | M56: International Energy Agency and Cement Sustainability Initiative. 2018. Technology Roadmap: Low-Carbon Transition in the Cement Industry. p41. http://www.iea.org/publications/freepublications/publication/TechnologyRoadmapLowCarbonTransitionintheCementIndustry.pdf
A57: Industry | B57: Cogeneration and Waste Heat Recovery | C57: Fraction of Potential Cogeneration and Waste Heat Recovery Adopted | D57: Cogeneration and Waste Heat Recovery | E57: indst CHP | F57: 0 | G57: 1 | H57: 0.01 | I57: % of potential achieved | J57: **Description:** This policy reduces fuel consumption in the industry sector by increasing the use of cogeneration (also known as combined heat and power) and recovery of waste heat (to perform useful work). // **Guidance for setting values:** If this policy is fully implemented, fuel use is reduced by 7.9% for all industries in 2050. | K57: industry-ag-main.html#cogen | L57: cogeneration-and-waste-heat-recovery.html | M57: Calculated from model data; see the relevant variable(s) in the InputData folder for source information.
A58: Industry | B58: Early Retirement of Industrial Facilities | C58: Fraction of Energy Savings from Early Facility Retirement Achieved | D58: Early Retirement of Industrial Facilities | E58: indst early retirement | F58: 0 | G58: 1 | H58: 0.01 | I58: % of potential achieved | J58: **Description:** This policy reduces fuel consumption in the industry sector by retiring older, inefficient industrial facilities sooner than they otherwise would retire. This policy does not affect demand for industrial products, so it is assumed that any facilities retired under this policy are replaced by new facilities or increased output from existing facilities in the same year. // **Guidance for setting values:** If this policy is fully implemented, fuel use is reduced for most industries between 2% and 9% in 2050. | K58: industry-ag-main.html#early-ret | L58: early-retirement-of-industrial-facilities.html | M58: Calculated from model data; see the relevant variable(s) in the InputData folder for source information.
A59: Industry | B59: Industry Energy Efficiency Standards | C59: Percentage Improvement in Eqpt Efficiency Standards above BAU | D59: Industry Energy Efficiency Standards | E59: indst efficiency standards | F59: 0 | G59: 0.3 | H59: 0.01 | I59: % reduction in energy use | J59: **Description:** This policy reduces fuel consumption by the selected industry by increasing the efficiency of industrial equipment through stronger standards. The policy setting refers to overall energy use reduction, not the reduction in energy use of newly sold equipment. // **Guidance for setting values:** In 2016, the U.S. Department of Energy developed an industrial energy efficiency potential analysis that suggests the US could double its annual rate of improvement rate through 2030. Extended through 2050, this equates to a maximum potential improvement of 17% by 2050 relative to BAU. | K59: industry-ag-main.html#eff-stds | L59: industry-energy-efficiency-standards.html | M59: U.S. DOE, 2016, Industrial Energy Efficiency Potential Analysis, https://energy.gov/sites/prod/files/2017/04/f34/energy-savings-by-state-industrial-methodology.pdf | N59: U.S. DOE, 2016, Industrial Energy Efficiency Potential Analysis, https://energy.gov/sites/prod/files/2017/04/f34/energy-savings-by-state-industrial-methodology.pdf
A60: Industry | B60: Improved System Design | C60: Fraction of Installation and System Integration Issues Remedied | D60: Improved System Design | E60: indst system integration | F60: 0 | G60: 1 | H60: 0.01 | I60: % of potential achieved | J60: **Description:** This policy reduces fuel consumption in the industry sector by improving the way components are put together and the way material or energy flows between them. // **Guidance for setting values:** If this policy is fully implemented, fuel use is reduced by 3.6% for all industries in 2050. | K60: industry-ag-main.html#system-integ | L60: improved-system-design.html | M60: Calculated from model data; see the relevant variable(s) in the InputData folder for source information.
A61: Industry | B61: Electrification | C61: Fraction of Eligible Industrial Energy Use Shifted to Electricity | D61: Electrification | E61: indst shift to electricity | F61: 0 | G61: 1 | H61: 0.01 | I61: % of fuel shifted | J61: **Description:** This policy reduces greenhouse gas emissions from the selected industry by switching the fuels used by facilities to electricity. Only fuel consumed for energy, not fuel used as a chemical feedstock, is affected by this policy. Biomass and purchased heat (steam) are also unaffected. // **Guidance for setting values:** Over 90% of manufacturers' thermal fuels (excluding feedstocks) are used to generate process heat, including to fuel boilers. Generally, boilers/steam and low-temperature non-boiler heat are easier to electrify than higher-temperature heat. For U.S. manufacturing industries, 21% of heat demand is at low tempratures (below 165°C), 40% is at medium temperatures (165-400°C), and the remainder is at high temperatures (above 400°C). | K61: industry-ag-main.html#fuel-switching | L61: industry-elec-and-hydrogen.html
A62: Industry | B62: F-Gas Substitution | C62: Fraction of F Gas Substitution Achieved | D62: F-gas Measures | E62: indst f gas substitution | F62: 0 | G62: 1 | H62: 0.01 | I62: % of potential achieved | J62: **Description:** This policy reduces emissions of high-GWP, fluorinated gases (F-gases) from the industry sector by substituting less-harmful chemicals. // **Guidance for setting values:** The production and consumption of f-gases are limited in the U.S. by the American Innovation and Manufacturing (AIM) Act, which is incorporated in the BAU. Therefore, the U.S. model reflects limited additional abatement potential. If this policy is fully implemented, F-gas emissions in 2050 are reduced by 27%. | K62: industry-ag-main.html#avoid-f-gases | L62: avoid-f-gases.html | M62: Calculated from model data; see the relevant variable(s) in the InputData folder for source information.
A63: Industry | B63: F-Gas Destruction | C63: Fraction of F Gas Destruction Achieved | D63: F-gas Measures | E63: indst f gas destruction | F63: 0 | G63: 1 | H63: 0.01 | I63: % of potential achieved | J63: **Description:** This policy reduces emissions of high-GWP, fluorinated gases (F-gases) from the industry sector by destroying F-gases created as byproducts during the creation of desired products. // **Guidance for setting values:** The production and consumption of f-gases are limited in the U.S. by the American Innovation and Manufacturing (AIM) Act, which is incorporated in the BAU. Therefore, the U.S. model reflects limited additional abatement potential. If this policy is fully implemented, F-gas emissions in 2050 are reduced by 1%. | K63: industry-ag-main.html#avoid-f-gases | L63: avoid-f-gases.html
A64: Industry | B64: F-Gas Recovery | C64: Fraction of F Gas Recovery Achieved | D64: F-gas Measures | E64: indst f gas recovery | F64: 0 | G64: 1 | H64: 0.01 | I64: % of potential achieved | J64: **Description:** This policy reduces emissions of high-GWP, fluorinated gases (F-gases) by recovering F-gases from equipment at the end of its service life and destroying or recycling those F-gases. // **Guidance for setting values:** The production and consumption of f-gases are limited in the U.S. by the American Innovation and Manufacturing (AIM) Act, which is incorporated in the BAU. Therefore, the U.S. model reflects limited additional abatement potential. If this policy is fully implemented, F-gas emissions in 2050 are reduced by 2%. | K64: industry-ag-main.html#avoid-f-gases | L64: avoid-f-gases.html
A65: Industry | B65: F-Gas Eqpt. Maintenance & Retrofits | C65: Fraction of F Gas Inspct Maint Retrofit Achieved | D65: F-gas Measures | E65: indst f gas inspct maint retrofit | F65: 0 | G65: 1 | H65: 0.01 | I65: % of potential achieved | J65: **Description:** This policy reduces emissions of high-GWP, fluorinated gases (F-gases) from the industry sector by reducing leakage and losses through improved inspections, maintenance, and retrofitting of equipment. // **Guidance for setting values:** The production and consumption of f-gases are limited in the U.S. by the American Innovation and Manufacturing (AIM) Act, which is incorporated in the BAU. Therefore, the U.S. model reflects limited additional abatement potential. If this policy is fully implemented, F-gas emissions in 2050 are reduced by less than 1%. | K65: industry-ag-main.html#avoid-f-gases | L65: avoid-f-gases.html
A66: Industry | B66: Feedstock Shifting | C66: Fraction of Feedstock Shifted | D66: Feedstock Shifting | E66: indst feedstock shifting | F66: 0 | G66: 1 | H66: 0.01 | I66: % of potential achieved | J66: **Description:** This policy shifts the use of fossil-fuel feedstocks to hydrogen. The production method for this new hydrogen demand can be shifted wiht the Fraction of Hydrogen Production Pathways Shifted lever. // **Guidance for setting values (Chemicals):** Approximately 52 percent of natural gas consumed as a chemical feedstock globally goes to producing ammonia and methanol. These pathways can be replaced with green electrolytic hydrogen to eliminate process emissions associated with production. // **Guidance for setting values (Iron & Steel):** Coal is the most significant feedstock used in the steel industry, largely for reducing iron ore in blast furnaces. A transition from the traditional steelmaking route (blast furnace-basic oxygen furnace) to alternatives (like hydrogen-based direct reduced iron with electric arc furnaces) can be represented by pairing this lever with electrification of industrial heat.
A67: Industry | B67: Hydrogen Combustion | C67: Fraction of Eligible Industrial Energy Use Shifted to Hydrogen | D67: Hydrogen Combustion | E67: indst shift to hydrogen | F67: 0 | G67: 1 | H67: 0.01 | I67: % of fuel shifted | J67: **Description:** This policy reduces greenhouse gas emissions from the selected industry by switching the fuels used by facilities to hydrogen combustion. Only fuel consumed for energy, not fuel used as a chemical feedstock, is affected by this policy. Biomass and purchased heat (steam) are also unaffected. // **Guidance for setting values:** Over 90% of manufacturers' thermal fuels (excluding feedstocks) are used to generate process heat, including to fuel boilers. Generally, hydrogen combustion is reserved for high-temperature heat, since it is often simpler and more efficient to directly electrify heat at lower temperatures. For U.S. manufacturing industries, 21% of heat demand is at low tempratures (below 165°C), 40% is at medium temperatures (165-400°C), and the remainder is at high temperatures (above 400°C). | K67: industry-ag-main.html#fuel-switching | L67: industry-elec-and-hydrogen.html
A68: Industry | B68: Material Efficiency, Longevity, & Re-Use | C68: Percent Reduction in Nonenergy Nonagriculture Industry Product Demand | D68: Material Efficiency, Longevity, & Re-Use | E68: indst reduce nonenergy product demand | F68: 0 | G68: 1 | H68: 0.01 | I68: % demand reduction | J68: **Description:** // **Cement and Iron & Steel:** This policy reduces demand for the selected materials through techniques such as material-efficient building codes (using modern designs that require less material per unit floor area), requirements for greater building and infrastructure longevity, greater re-use and re-purposing of buildings (rather than tearing down and building new), etc. // **Guidance for setting values:** In "Sustainable Materials Without the Hot Air: Making Buildings, Vehicles and Products Efficiently and with Less New Material," Allwood and Cullen estimate that concrete use could be reduced by up to 40% using optimized molds, and concrete building longevity could be more than doubled to 200 years. Together, these measures might reduce concrete demand by up to 70%, if demand for building floorspace reaches steady state. They estimate that steel use could be reduced by 30% by optimizing designs and controlling the loads they experience during installation and use. If the lifetime of steel products could be doubled, the resulting material reduction could be up to 65%, if sales reach steady state. // **Water and Waste:** This policy reduces demand for water treatment and waste management services through techniques such as water conservation, reduction in disposable packaging, requirements for greater product longevity, greater repair and re-use of products, and increased recycling and composting. // **Guidance for setting values:** The majority of energy use and emissions from the water and waste sector are a result of water treatment, not solid waste management. The USDA reports that agriculture accounts for 80% of U.S. water consumption, and the U.S. EPA reports that "as much as 50 percent of the water we use outdoors is lost due to wind, evaporation, and runoff caused by inefficient irrigation methods and systems." Non-agriculture uses, including lawn irrigation and in-home use, may be able to achieve similar savings through improved practices and fixtures. | L68: material-efficiency-longevity-reuse.html | M68: Allwood and Cullen, "Sustainable Materials Without the Hot Air: Making Buildings, Vehicles and Products Efficiently and with Less New Material" Allwood and Cullen, "Sustainable Materials With Both Eyes Open" - page 185, http://www.withbotheyesopen.com/read.php?c=12 USDA Irrigation & Water Use: https://www.ers.usda.gov/topics/farm-practices-management/irrigation-water-use.aspx and EPA WaterSense Statistics and Facts: https://www.epa.gov/watersense/statistics-and-facts
A69: Industry | B69: Methane Capture | C69: Fraction of Methane Capture Opportunities Achieved | D69: Methane Capture and Destruction | E69: indst methane capture | F69: 0 | G69: 1 | H69: 0.01 | I69: % of potential achieved | J69: **Description:** This policy reduces methane emissions from the selected industry by increasing the capture of methane that is currently being released into the atmosphere (for example, stopping leaks from wellheads, pipes, coal mines, landfills, etc.). // **Guidance for setting values:** The U.S. has standards for new and existing equipment covering the oil and gas production and energy pipelines and gas processing industries in the EPS, which are reflected in the BAU. The rules for existing equipment are together expected to reduce emissions by 119 MMT CO2e by the year 2039. | K69: industry-ag-main.html#methane-capture | L69: methane-capture.html
A70: Industry | B70: Methane Destruction | C70: Fraction of Methane Destruction Opportunities Achieved | D70: Methane Capture and Destruction | E70: indst methane destruction | F70: 0 | G70: 1 | H70: 0.01 | I70: % of potential achieved | J70: **Description:** This policy reduces methane emissions from the selected industry by increasing the burning of methane that is currently being released into the atmosphere (i.e. flaring instead of venting/leaking). **Guidance for setting values:** The U.S. has standards for new and existing equipment covering the oil and gas production and energy pipelines and gas processing industries in the EPS, which are reflected in the BAU. The rules for existing equipment are together expected to reduce emissions by 119 MMT CO2e by the year 2039. | K70: industry-ag-main.html#methane-destr | L70: methane-destruction.html
A71: Industry | B71: N2O Abatement | C71: Fraction of N2O Abatement Achieved | D71: N2O Abatement | E71: indst N2O abatement | F71: 0 | G71: 1 | H71: 0.01 | I71: % of potential achieved | J71: **Description:** This policy reduces nitrous oxide (N2O) process emissions from the chemicals industry (primarily from the production of nitric acid and adipic acid) by destroying the N2O rather than venting it to the atmosphere. //
A72: Industry | B72: Non BAU Increase in Process Emissions | C72: Boolean Use Non BAU Process Emissions Additions | D72: Process Emissions Increases | E72: non BAU indst process emissions | F72: 0 | G72: 1 | H72: 1 | I72: on/off | J72: **Description:** This policy lever tests increases in industrial process emissions relative to the BAU scenario according to schedules set via model input data. The following descriptions explain what scenarios this lever is set up to test: // **Guidance for setting values:** //**Methane capture and destruction:** The EPA has set standards for oil and gas methane emissions for new and existing equipment, which are projected to save 130 MMT CO2e annually by 2029. This lever repeals those standards. // **Cropland, rice, and livestock measures:** The Inflation Reduction Act includes billions in financial support for clean agricultural practices. This lever removes that financial support and the projected emissions reductions from those programs.
A73: Industry | B73: Reduce Fossil Fuel Exports | C73: Percent Reduction in Fossil Fuel Exports | D73: Percent Reduction in Fossil Fuel Exports | E73: indst reduce fossil fuel exports | F73: 0 | G73: 1 | H73: 0.01 | I73: % reduction in exports | J73: =_xlfn.XLOOKUP($C73,'State Policy Descriptions'!$C:$C,'State Policy Descriptions'!$L:$L,0,1,1) -> **Description:** This policy reduces production of the selected fuel type(s) for export. This lever may represent a reduction in fuel demand by actors outside the modeled region (i.e., not caused by domestic policy) or a conscious policy within the modeled region to transition its economy away from dependence on fossil fuel exports. // **Guidance for setting values:** // **Hard coal**: The model assumes the state has no hard coal production. //**Crude oil:**: The model assumes the state has no crude oil production. //**Heavy fuel oil:** The model assumes that exports represent 259.46% of the state's production.//**Jet fuel or kerosene:** The model assumes that exports represent 103.49% of the state's production.//**LPG propane or butane:** The model assumes that exports represent 101.15% of the state's production.//**Natural gas:** The model assumes the state has no natural gas production. //**Petroleum diesel:** The model assumes that exports represent 107.9% of the state's production.//**Petroleum gasoline:** The model assumes the state has no petroleum gasoline production. | L73: reduce-fuel-exports.html | M73: Calculated from model data; see the relevant variable(s) in the InputData folder for source information.
A74: Agriculture, Land Use, and Forestry | B74: Afforestation and Reforestation | C74: Fraction of Afforestation and Reforestation Achieved | D74: Afforestation and Reforestation | E74: land afforestation and reforestation | F74: 0 | G74: 1 | H74: 0.01 | I74: % of potential achieved | J74: =_xlfn.XLOOKUP($C74,'State Policy Descriptions'!$C:$C,'State Policy Descriptions'!$L:$L,0,1,1) -> **Description:** This policy increases the sequestration of CO2 by planting forests. Planted forests are assumed to be managed with best practices and are not used for timber harvesting. // **Guidance for setting values:** If this policy is fully implemented, the afforestation/reforestation rate reaches 7 thousand acres per year in 2050. | K74: lulucf.html#aff-ref | L74: afforestation-and-reforestation.html | M74: Calculated from model data; see the relevant variable(s) in the InputData folder for source information. | N74: Ross W. Gorte, 2009, "U.S. Tree Planting for Carbon Sequestration," Congressional Research Service, https://www.fas.org/sgp/crs/misc/R40562.pdf, p.3, paragraph 1
A75: Agriculture, Land Use, and Forestry | B75: Avoid Deforestation | C75: Fraction of Avoided Deforestation Achieved | D75: Avoid Deforestation | E75: land avoid deforestation | F75: 0 | G75: 1 | H75: 0.01 | I75: % of potential achieved | J75: **Description:** This policy prevents clear cutting of forests that would otherwise be cleared. Preserved forests are assumed to be managed with best practices. // **Guidance for setting values:** If this policy is fully implemented, the avoided deforestation rate reaches 0.2 million acres per year in 2050 (roughly equal to 0.01% of the land area of the lower 48 states). | K75: lulucf.html#avoid-def | L75: avoid-deforestation.html
A76: Agriculture, Land Use, and Forestry | B76: Grassland Restoration and Avoided Conversion | C76: Fraction of Forest Restoration Achieved | D76: Grassland Restoration and Avoided Conversion | E76: land forest restoration | F76: 0 | G76: 1 | H76: 0.01 | I76: % of potential achieved | J76: **Description:** This policy increases CO2 sequestration by avoiding the conversion of grasslands and restoring grassland areas. // **Guidance for setting values:** A 100% setting of this lever avoids 1.7 million acres of grassland conversion, and restores roughly 5 million acres of grassland. | L76: forest-restoration.html | M76: See file PLANAbPiaSY
A77: Agriculture, Land Use, and Forestry | B77: Forest Set-Asides | C77: Fraction of Forest Set Asides Achieved | D77: Forest Set-Asides | E77: land forest set asides | F77: 0 | G77: 1 | H77: 0.01 | I77: % of potential achieved | J77: **Description:** This policy avoids the release of CO2 from forests by reducing timber harvesting. // **Guidance for setting values:** A 100% setting of this lever reduces timber harvesting by 2% of the BAU amount per year, reaching a roughly 70% reduction in timber harvesting by 2050. | K77: lulucf.html#set-asides | L77: forest-set-asides.html | M77: Calculated from model data; see the relevant variable(s) in the InputData folder for source information.
A78: Agriculture, Land Use, and Forestry | B78: Cropland and Rice Measures | C78: Fraction of Cropland and Rice Measures Achieved | D78: Cropland and Rice Measures | E78: indst cropland and rice measures | F78: 0 | G78: 1 | H78: 0.01 | I78: % of potential achieved | J78: **Description:** This policy reduces CH4 and N2O emissions from agriculture through cropland management practices, such as improved crop rotations, reduced soil tillage, and improvements in fertilizer composition and application. Measures particular to rice cultivation include improved flooding practices that avoid anaerobic, methane-forming conditions. // **Guidance for setting values:** The BAU reflects increased uptake of cropland and rice measures due to incentives provided in the Inflation Reduction Act. This lever represents additional potential on top of BAU emissions reductions. To be conservative, we do not assume permanent emissions reductions after IRA funds expire, so therefore phase out the IRA impact over the course of four years after funds expire in 2032. The total potential for this policy lever is sourced from EPA's 2024 Forestry and Agriculture Sector Mitigation Analysis, which evaluates various carbon price scenarios across both the forestry and agriculture sectors and considers land use competition. At a level of $100 per ton, the cropland and rice measures potential is roughly 10 MMT CO2e in 2050. | K78: industry-ag-main.html#cropland | L78: cropland-management.html | M78: Calculated from model data; see the relevant variable(s) in the InputData folder for source information.
A79: Agriculture, Land Use, and Forestry | B79: Improved Soil Measures | C79: Fraction of CO2 Storage Through Tillage Practices | D79: Improved Soil Measures | E79: indst tillage | F79: 0 | G79: 1 | H79: 0.01 | I79: % of potential achieved | J79: **Description:** This policy stores CO2 in agricultural soils through improved tillage practices, retiring organic and marginal soils, and establishing windbreaks/shelterbelts. // **Guidance for setting values:** If this policy is fully implemented, approximately 70 MMT CO2 is stored in soils.
A80: Agriculture, Land Use, and Forestry | B80: Improved Forest Management | C80: Fraction of Improved Forest Management Achieved | D80: Improved Forest Management | E80: land forest management | F80: 0 | G80: 1 | H80: 0.01 | I80: % of potential achieved | J80: **Description:** This policy increases CO2 sequestration by forests through improved forest management practices. // **Guidance for setting values:** The potential for this policy lever is sourced from EPA's 2024 Forestry and Agriculture Sector Mitigation Analysis, which evaluates various carbon price scenarios across both the forestry and agriculture sectors and considers land use competition. At a level of $100 per ton, the forest management potential is roughly 80 MMT CO2e in 2050. | K80: lulucf.html#forest-mgmt | L80: improved-forest-management.html | M80: Calculated from model data; see the relevant variable(s) in the InputData folder for source information.
A81: Agriculture, Land Use, and Forestry | B81: Livestock Measures | C81: Fraction of Livestock Measures Achieved | D81: Livestock Measures | E81: indst livestock measures | F81: 0 | G81: 1 | H81: 0.01 | I81: % of potential achieved | J81: **Description:** This policy reduces greenhouse gas emissions from agriculture through livestock-related measures, such as feed supplements or drugs to prevent enteric methane formation. // **Guidance for setting values:** The BAU reflects increased uptake of livestock measures due to incentives provided in the Inflation Reduction Act. This lever represents additional potential on top of BAU emissions reductions. To be conservative, we do not assume permanent emissions reductions after IRA funds expire, so therefore phase out the IRA impact over the course of four years after funds expire in 2032. The potential for this policy lever is sourced from EPA's 2024 Forestry and Agriculture Sector Mitigation Analysis, which evaluates various carbon price scenarios across both the forestry and agriculture sectors and considers land use competition. At a level of $100 per ton, the livestock measures potential is roughly 55 MMT CO2e in 2050. | K81: industry-ag-main.html#livestock | L81: livestock-measures.html | M81: Calculated from model data; see the relevant variable(s) in the InputData folder for source information.
A82: Agriculture, Land Use, and Forestry | B82: Wetland Restoration | C82: Fraction of Peatland Restoration Achieved | D82: Wetland Restoration | E82: land peatland restoration | F82: 0 | G82: 1 | H82: 0.01 | I82: % of potential achieved | J82: **Description:** This policy increases CO2 sequestration by restoring wetlands and riparian forest buffers. // **Guidance for setting values:** If this policy is fully implemented, 2.5 million acres of wetlands will be restored and the 6 percent of US stream miles associated with agricultural use will be restored. | L82: peatland-restoration.html | M82: https://www.usda.gov/sites/default/files/documents/White_Paper_WEB71816.pdf
A83: Agriculture, Land Use, and Forestry | B83: Shift to Non-Animal Products | C83: Percent Animal Products Shifted to Nonanimal Products | D83: Shift to Non-Animal Products | E83: indst shift to nonanimal products | F83: 0 | G83: 1 | H83: 0.01 | I83: % reduction in animal products | J83: **Description:** This policy causes animal products to be substituted for non-animal products, which might be achieved by changes in consumer preferences or by changes in costs of agricultural products (such as by redirecting subsidies currently paid to farmers who raise animals or feed crops to farmers growing fruits, vegetables, and other plant-based foods for human consumption). Moderate settings of this policy lever do not imply a vegan diet: for instance, a 50% setting could represent each individual consuming half as many animal products, rather than half of the population consuming no animal products. // **Guidance for setting values:** According to OECD statistics, the U.S. has the highest per-capita meat consumption in the world, at 99 kg/person/year. If the U.S. were to achieve a rate similar to that in Europe (70 kg/person/yr), Japan (36 kg/person/yr), or India (3 kg/person/yr), this would be a reduction of 29% (Europe), 64% (Japan), or 97% (India) respectively. | L83: shift-to-non-animal-products.html | M83: https://en.wikipedia.org/wiki/List_of_countries_by_meat_consumption_per_capita (article revision 00:12, 22 Feb 2019)
A84: District Heat and Hydrogen | B84: Use CHP for District Heat | C84: Fraction of Non CHP Heat Production Converted to CHP | D84: District Heat CHP | E84: heat convert heat to CHP | F84: 0 | G84: 1 | H84: 0.01 | I84: % non-CHP heat converted | J84: **Description:** This policy causes a percentage of the district heat that would be generated by dedicated heat plants to instead be generated via CHP plants. In this model, this causes them to consume no additional fuel, since it is assumed CHP plants would be run anyway in order to produce electricity. // **Guidance for setting values:** In the BAU Scenario, the fraction of heat derived from CHP plants is constant at roughly 50%. Therefore, a policy setting of 50% would increase the CHP fraction to 75% in 2050. | K84: district-heating.html#chp | L84: convert-non-chp-heat-production.html | M84: Calculated from model data; see the relevant variable(s) in the InputData folder for source information.
A85: District Heat and Hydrogen | B85: Produce District Heat with Electricity | C85: Fraction of District Heat Fuel Use Shifted to Other Fuels | D85: District Heat Fuel Switching | E85: heat fuel type shifting | F85: 0 | G85: 1 | H85: 0.01 | I85: % of fuel use | J85: **Description:** This policy causes a percentage of the demand for district heat to be met with electricity instead of the fuels used in the BAU case. // **Guidance for setting values:** In the United States, 64% of district heat is made by burning natural gas, 17% from coal, 16% from biomass, and 3% from petroleum. Large scale electric heat pump technologies for district heating are still emerging, and it is not yet clear which will be the most economical pathway for decarbonizing this sector. | K85: district-heating.html#convert-coal | L85: district-heat-fuel-switching.html | M85: Calculated from model data; see the relevant variable(s) in the InputData folder for source information.
A86: District Heat and Hydrogen | B86: Shift Hydrogen Production Pathways | C86: Fraction of Hydrogen Production Pathways Shifted | D86: Shift Hydrogen Production Pathways | E86: hydgn shift production pathways | F86: 0 | G86: 1 | H86: 0.01 | I86: % of hydrogen production | J86: **Description:** By default, this policy causes a percentage of merchant hydrogen (i.e. hydrogen produced for sale, not hydrogen produced and consumed on-site within a facility) to be produced via electrolysis rather than via other production pathways. If the Non BAU Hydrogen Production Pathways lever is enabled, this lever works in the opposite direction by shifting hydrogen production to steam methane reforming. // **Guidance for setting values:** As of 2025, in the United States, roughly 95% of hydrogen is produced via steam reforming of natural gas and 5% is produced via electrolysis. These shares are projected to shift towards electrolysis in the BAU scenario due to hydrogen tax credits provided by the Inflation Reduction Act. | L86: switch-hydrogen-production-pathway.html
A87: District Heat and Hydrogen | B87: Non BAU Hydrogen Production Shifting | C87: Boolean Use Non BAU Hydrogen Shifting | D87: Hydrogen Steam Methane Reforming | E87: hydgn non BAU shift | F87: 0 | G87: 1 | H87: 1 | I87: on/off | J87: **Description:** This lever changes the direction of the “Shift Hydrogen Production Pathways” lever. By default, the “Shift Hydrogen Production Pathways” lever causes a percentage of merchant hydrogen (i.e. hydrogen produced for sale, not hydrogen produced and consumed on-site within a facility) to be produced via electrolysis rather than via other production pathways. If the “Non-BAU Hydrogen Production Pathways lever is enabled, it causes hydrogen production pathway shifting to work in the opposite direction, shifting hydrogen production to steam methane reforming. // **Guidance for setting values:** As of 2025, in the United States, roughly 95% of hydrogen is produced via steam reforming of natural gas and 5% is produced via electrolysis. These shares are projected to shift towards electrolysis in the BAU scenario due to hydrogen tax credits provided by the Inflation Reduction Act. Enabling this lever can be used to model repealing the Inflation Reduction Act tax credits. | L87: switch-hydrogen-production-pathway.html
A88: Cross-Sector | B88: Carbon Price | C88: Additional Carbon Tax Rate | D88: Carbon Price | E88: cross carbon tax | F88: 0 | G88: 300 | H88: 5 | I88: =UnitControlCenter!$B$50 -> $/metric ton CO2e | J88: **Description:** This policy applies a price on fuels used in the selected sector(s) based on their greenhouse gas emissions. It also increases the base cost of capital equipment (e.g., vehicles, power plants, building components) according to their embedded carbon content. When applied to the Industry Sector, the tax **is** levied on greenhouse gas emissions from non-energy industrial and agricultural processes by default, but these emissions sources can be exempted from the tax by enabling the policy lever "Exempt Process Emissions from C Tax." Note that by default, a carbon price will not include a border adjustment, but a border adjustment can be enabled using the policy lever "Toggle Carbon Tax Border Adjustment." // **Guidance for setting values:** The U.S. government's revised Social Cost of Carbon estimates for the year 2050 range from $200 to $520 per ton (in inflation-adjusted 2020 dollars), depending on one's choice of discount rate. | K88: fuels.html#carbon-tax | L88: carbon-tax.html | M88: U.S. EPA, 2015, "The Social Cost of Carbon", https://www.epa.gov/climatechange/social-cost-carbon, Row "2050". (For source for adjustment to 2018 dollars, see cpi.xlsx in InputData.) | N88: U.S. EPA, 2016, "Social Cost of CO2, 2015-2020," https://www.epa.gov/climatechange/social-cost-carbon
A89: Cross-Sector | B89: End Existing Subsidies | C89: Percent Reduction in BAU Subsidies | D89: End Existing Subsidies | E89: cross reduce BAU subsidies | F89: 0 | G89: 1 | H89: 0.01 | I89: % reduction in BAU subsidies | J89: **Description:** This policy reduces the subsidies paid for the production of the selected energy source(s) (relative to the BAU case). Note that some subsidies affect the cost of fuel (such as coal and natural gas), while some subsidies are for electricity production or capacity construction (federal Production Tax Credits and Investment Tax Credits). // **Guidance for setting values:** A value of 100% eliminates federal tax credits from the Inflation Reduction Act for wind, solar, geothermal, hydrogen, and nuclear. | K89: fuels.html#end-subsidies | L89: end-existing-subsidies.html | M89: Calculated from model data; see the relevant variable(s) in the InputData folder for source information.
A90: Cross-Sector | B90: Exempt Non-CO2 Emissions from C Tax | C90: Toggle Whether Carbon Tax Affects Non CO2 Emissions | E90: cross toggle whether carbon tax affects non CO2 emissions | F90: 0 | G90: 1 | H90: 1 | I90: on/off | J90: **Description:** By default, the carbon tax applies to CO2 and non-CO2 emissions. This policy exempts non-CO2 emissions, meaning the carbon tax will only apply to CO2 emissions. | K90: fuels.html#carbon-tax | L90: carbon-tax.html
A91: Cross-Sector | B91: Exempt Process Emissions from C Tax | C91: BEPEfCT Boolean Exempt Process Emissions from Carbon Tax | E91: cross toggle whether carbon tax affects process emissions | F91: 0 | G91: 1 | H91: 1 | I91: on/off | J91: **Description:** Turning this policy lever on prevents the carbon tax from being levied on process emissions from the selected industry categories. (Process emissions are non-energy greenhouse gas emissions from industrial and agricultural operations, for example emissions released due to chemical reactions during cement production). By default, we exempt agriculture and water and waste process emissions, as these categories are generally not covered by carbon tax proposals. | K91: fuels.html#carbon-tax | L91: carbon-tax.html
A92: Cross-Sector | B92: Toggle Carbon Tax Border Adjustment | C92: BDCTBA Boolean Disable Carbon Tax Border Adjustment | F92: 0 | G92: 1 | H92: 1 | I92: on/off | J92: **Description:** By default, carbon taxes apply to only domestically produced goods. Turning this policy lever on enables carbon tax border adjustments, meaning the carbon tax will apply to both domestically produced and imported goods. | K92: fuels.html#carbon-tax | L92: carbon-tax.html
A93: Cross-Sector | B93: Fixed Energy Prices | C93: Toggle Whether Policies Affect Energy Prices | D93: Fixed Energy Prices | E93: cross toggle whether policies affect energy prices | F93: 0 | G93: 1 | H93: 1 | I93: on/off
A94: Cross-Sector | B94: Fuel Price Deregulation | C94: Fuel Price Deregulation | D94: Fuel Price Deregulation | E94: cross fuel price deregulation | F94: 0 | G94: 1 | H94: 0.01 | I94: % of price deregulated | J94: **Description:** This policy causes the price of the selected fuel(s) for domestic buyers to approach international market prices. // **Guidance for setting values:** A value of 100% causes domestic fuel prices to equal international market prices, increasing the domestic price by roughly X% in 2050. | K94: fuels.html#fuel-price-deregulation
A95: Cross-Sector | B95: Fuel Taxes or Subsidies | C95: Additional Fuel Tax or Subsidy Rate by Fuel | D95: Fuel Taxes or Subsidies | E95: cross fuel tax | F95: -0.9 | G95: 0.9 | H95: 0.01 | I95: % of BAU price | J95: **Description:** This policy changes the tax rate for the selected fuel type(s). It is expressed as a percentage of the BAU Scenario price, which includes sales and excise taxes. To increase the tax rate, set a positive value. To reduce the BAU tax rate (or to apply a subsidy), set a negative value. // **Guidance for setting values:** In 2012, the national average sales tax rate was 6.8% and the national average tax rate on gasoline was 14%. | K95: fuels.html#fuel-taxes | L95: fuel-taxes.html | M95: AVG SALES TAX: The Sales Tax Clearinghouse, FAQ, https://thestc.com/FAQ.stm, Question "What is the average sales tax nationally?" AVG GASOLINE TAX: Energy Information Administration, 2014, Annual Energy Outlook 2014, http://www.eia.gov/forecasts/aeo/supplement/suptab_130.xlsx, Supplement Table 130.
A96: Cross-Sector | B96: Non BAU Carbon Tax Vehicle Qualification | C96: Boolean Use Non BAU Carbon Tax Vehicle Type Qualification | F96: 0 | G96: 1 | H96: 1 | I96: on/off | J96: **Description:** This lever determines which vehicle types are captured under the scope of a carbon tax. In some regions, only certain vehicle types are covered by a carbon tax or cap.
A97: Cross-Sector | B97: Non BAU Carbon Tax Industry Qualification | C97: Boolean Use Non BAU Carbon Tax Industry Category Qualification | F97: 0 | G97: 1 | H97: 1 | I97: on/off | J97: **Description:** This lever determines which industry categories are captured under the scope of a carbon tax. In some regions, only certain industries are covered by a carbon tax or cap.
A98: Cross-Sector | B98: Non BAU CBAM Industry Qualification | C98: Boolean Use Non BAU Carbon Tax Border Adjustment Industry Qualification | F98: 0 | G98: 1 | H98: 1 | I98: on/off | J98: **Description:** This lever determines which industry categories are captured under the scope of a carbon border adjustment mechanism. In some regions, only certain industries are covered by a border mechanism.
A99: Research and Development | B99: Capital Cost Reduction | C99: RnD Building Capital Cost Perc Reduction | D99: R&D Capital Cost Reductions | E99: RnD building capital cost reduction | F99: 0 | G99: 0.4 | H99: 0.01 | I99: % reduction in cost | J99: **Description:** This policy causes the capital cost of the selected type(s) of equipment to decline by the set percentage over the course of the model run. The R&D progress caused by this policy is additional to any R&D necessary to comply with other policies, such as tighter fuel economy standards. No costs associated with conducting this additional R&D (such as investments in laboratories or engineers' salaries) are included in the model. // **Guidance for setting values:** This policy should generally be set to zero unless you are exploring a scenario with unusual and unexpected technological advancement. If setting a non-zero value, more mature technologies, such as coal, should have lower values than younger technologies, such as solar. A setting of 30% implies an average of roughly 1% annual improvement, which is very substantial. | K99: architectural-design.html#rnd | L99: research-and-development.html
A100: =A$99 -> Research and Development | B100: =B$99 -> Capital Cost Reduction | C100: RnD CCS Capital Cost Perc Reduction | D100: =D$99 -> R&D Capital Cost Reductions | E100: RnD CCS capital cost reduction | F100: =F$99 -> 0 | G100: =G$99 -> 0.4 | H100: =H$99 -> 0.01 | I100: =I$99 -> % reduction in cost | J100: =J$99 -> **Description:** This policy causes the capital cost of the selected type(s) of equipment to decline by the set percentage over the course of the model run. The R&D progress caused by this policy is additional to any R&D necessary to comply with other policies, such as tighter fuel economy standards. No costs associated with conducting this additional R&D (such as investments in laboratories or engineers' salaries) are included in the model. // **Guidance for setting values:** This policy should generally be set to zero unless you are exploring a scenario with unusual and unexpected technological advancement. If setting a non-zero value, more mature technologies, such as coal, should have lower values than younger technologies, such as solar. A setting of 30% implies an average of roughly 1% annual improvement, which is very substantial. | K100: =K$99 -> architectural-design.html#rnd | L100: =L$99 -> research-and-development.html
...

Sheet State Policy Descriptions
A1: Sector | B1: Short Name | C1: Vensim Variable Name | D1: Policy Group | E1: Policy Schedule Subscript | F1: Min Slider Value | G1: Max Slider Value | H1: Slider Step Size | I1: Units | J1: Text for Pop-Over Panel Description (National model) | K1: Text for Pop-Over Panel Description (State concat) | L1: Text for Pop-Over Panel Description | M1: Text for Pop-Over Panel Description (state concat 2) | N1: Text for Pop-Over Panel Description (state concat 3) | O1: Text for Pop-Over Panel Description (state concat 4) | P1: Text for Pop-Over Panel Description (state concat 5) | Q1: Text for Pop-Over Panel Description (state concat 6) | R1: Text for Pop-Over Panel Description (state concat 7) | S1: Text for Pop-Over Panel Description (state concat 8) | T1: Text for Pop-Over Panel Description (state concat 9)
A2: Buildings and Appliances | B2: Building Component Electrification | C2: Fraction of New Bldg Components Shifted to Other Fuels | D2: Building Component Electrification | E2: bldgs new component fuel shifting | F2: 0 | G2: 1 | H2: 0.01 | I2: % of newly sold non-electric building components | J2: **Description:** This policy replaces the specified fraction of newly sold non-electric building components of the selected type(s) in buildings of the selected type(s) with electricity-using components. // **Guidance for setting values:** // | K2: =_xlfn.CONCAT("**Urban Residential Heating:** In the BAU case, in ",About!$C$2,", the share of electricity among fuels used for heating in urban, residential buildings will ",IF('Supporting Data'!$BW$3<'Supporting Data'!$BX$3,"rise","fall")," from ",'Supporting Data'!$BW$3,"% to ",'Supporting Data'!$BX$3,"% through 2050.") -> **Urban Residential Heating:** In the BAU case, in New Jersey, the share of electricity among fuels used for heating in urban, residential buildings will rise from 7% to 11% through 2050. | L2: =J2&K2&M2&N2&O2&P2&Q2&R2&S2&T2 -> **Description:** This policy replaces the specified fraction of newly sold non-electric building components of the selected type(s) in buildings of the selected type(s) with electricity-using components. // **Guidance for setting values:** //**Urban Residential Heating:** In the BAU case, in New Jersey, the share of electricity among fuels used for heating in urban, residential buildings will rise from 7% to 11% through 2050.//**Urban Residential Appliances:** In the BAU case, in New Jersey, the share of electricity among fuels used for appliances in urban, residential buildings will fall from 31% to 30% through 2050.//**Urban Residential Other Components:** In the United States, the share of electricity among fuels used by other components in urban, residential buildings is 100%.//**Rural Residential Heating:** In the BAU case, in New Jersey, the share of electricity among fuels used for heating in rural, residential buildings will rise from 7% to 11% through 2050.//**Rural Residential Appliances:** In the BAU case, in New Jersey, the share of electricity among fuels used for appliances in rural, residential buildings will fall from 30% to 30% through 2050.//**Rural Residential Other Components:** In the United States, the share of electricity among fuels used by other components in rural, residential buildings is 100%.//**Commercial Heating:** In the BAU case, in New Jersey, the share of electricity among fuels used for heating in commercial buildings will fall from 3% to 3% through 2050.//**Comercial Appliances:** In the BAU case, in New Jersey, the share of electricity among fuels used for appliances in commercial buildings will fall from 30% to 28% through 2050.//**Comercial Other Components:** In the BAU case, in New Jersey, the share of electricity among fuels used for other components in commercial buildings will rise from 66% to 76% through 2050. | M2: =_xlfn.CONCAT("//**Urban Residential Appliances:** In the BAU case, in ",About!$C$2,", the share of electricity among fuels used for appliances in urban, residential buildings will ",IF('Supporting Data'!$BY$3<'Supporting Data'!$BZ$3,"rise","fall")," from ",'Supporting Data'!$BY$3,"% to ",'Supporting Data'!$BZ$3,"% through 2050.") -> //**Urban Residential Appliances:** In the BAU case, in New Jersey, the share of electricity among fuels used for appliances in urban, residential buildings will fall from 31% to 30% through 2050. | N2: =_xlfn.CONCAT("//**Urban Residential Other Components:** In the United States, the share of electricity among fuels used by other components in urban, residential buildings is 100%.") -> //**Urban Residential Other Components:** In the United States, the share of electricity among fuels used by other components in urban, residential buildings is 100%. | O2: =_xlfn.CONCAT("//**Rural Residential Heating:** In the BAU case, in ",About!$C$2,", the share of electricity among fuels used for heating in rural, residential buildings will ",IF('Supporting Data'!$CC$3<'Supporting Data'!$CD$3,"rise","fall")," from ",'Supporting Data'!$CC$3,"% to ",'Supporting Data'!$CD$3,"% through 2050.") -> //**Rural Residential Heating:** In the BAU case, in New Jersey, the share of electricity among fuels used for heating in rural, residential buildings will rise from 7% to 11% through 2050. | P2: =_xlfn.CONCAT("//**Rural Residential Appliances:** In the BAU case, in ",About!$C$2,", the share of electricity among fuels used for appliances in rural, residential buildings will ",IF('Supporting Data'!$CE$3<'Supporting Data'!$CF$3,"rise","fall")," from ",'Supporting Data'!$CE$3,"% to ",'Supporting Data'!$CF$3,"% through 2050.") -> //**Rural Residential Appliances:** In the BAU case, in New Jersey, the share of electricity among fuels used for appliances in rural, residential buildings will fall from 30% to 30% through 2050. | Q2: =_xlfn.CONCAT("//**Rural Residential Other Components:** In the United States, the share of electricity among fuels used by other components in rural, residential buildings is 100%.") -> //**Rural Residential Other Components:** In the United States, the share of electricity among fuels used by other components in rural, residential buildings is 100%. | R2: =_xlfn.CONCAT("//**Commercial Heating:** In the BAU case, in ",About!$C$2,", the share of electricity among fuels used for heating in commercial buildings will ",IF('Supporting Data'!$BQ3<'Supporting Data'!$BR$3,"rise","fall")," from ",'Supporting Data'!$BQ$3,"% to ",'Supporting Data'!$BR$3,"% through 2050.") -> //**Commercial Heating:** In the BAU case, in New Jersey, the share of electricity among fuels used for heating in commercial buildings will fall from 3% to 3% through 2050. | S2: =_xlfn.CONCAT("//**Comercial Appliances:** In the BAU case, in ",About!$C$2,", the share of electricity among fuels used for appliances in commercial buildings will ",IF('Supporting Data'!$BS$3<'Supporting Data'!$BT$3,"rise","fall")," from ",'Supporting Data'!$BS$3,"% to ",'Supporting Data'!$BT$3,"% through 2050.") -> //**Comercial Appliances:** In the BAU case, in New Jersey, the share of electricity among fuels used for appliances in commercial buildings will fall from 30% to 28% through 2050. | T2: =_xlfn.CONCAT("//**Comercial Other Components:** In the BAU case, in ",About!$C$2,", the share of electricity among fuels used for other components in commercial buildings will ",IF('Supporting Data'!$BU3<'Supporting Data'!$BV$3,"rise","fall")," from ",'Supporting Data'!$BU$3,"% to ",'Supporting Data'!$BV$3,"% through 2050.") -> //**Comercial Other Components:** In the BAU case, in New Jersey, the share of electricity among fuels used for other components in commercial buildings will rise from 66% to 76% through 2050.
A3: Electricity Supply | B3: Clean Electricity Standard | C3: Renewable Portfolio Std Percentage | D3: Clean Electricity Standard | E3: elec renewable portfolio standards | F3: 0 | G3: 1 | H3: 0.01 | I3: % of electricity generation | J3: **Description:** This policy specifies an increase in the fraction of electricity generation that must come from qualifying carbon-free sources (wind, solar, biomass, nuclear, hydro, geothermal, ccs, and hydrogen) in 2050. This policy has no effect until the user-set value exceeds the existing fraction of carbon-free electricity and any carbon-free electricity standards which have been enacted at the state level. To use this policy, turn the associated 'Non BAU RPS Qualifying Resources' policy to ON and the 'Lift the Clean Electricity Standard Alternative Compliance Payment' policy to ON. // **Guidance for setting values:** | K3: =_xlfn.CONCAT(" Multiple states have set 100% clean energy or renewable energy laws or goals, ",IF('Supporting Data'!AM3=1,"including "," not including "),About!$C$2,".",IF('Supporting Data'!AM3=1,_xlfn.CONCAT(". After weighing for coop and municipality requirements, the BAU assumes a total ","CES of ",'Supporting Data'!$AK$3,"% in 2030 that rises to ",'Supporting Data'!$AL$3,"% by 2050. ")," "),"When setting a high CES with this lever, users should also turn on supporting power sector policies (i.e., Grid-Scale Electricity Storage, Increase Transmission, and Demand Response) ","to avoid curtailment of renewables. ","At very high CES values, the associated policy costs are highly uncertain and should be complemented with other modeling. The business-as-usual CES value assumes the portion of an existing RPS standard met by imports remains constant.") -> Multiple states have set 100% clean energy or renewable energy laws or goals, not including New Jersey. When setting a high CES with this lever, users should also turn on supporting power sector policies (i.e., Grid-Scale Electricity Storage, Increase Transmission, and Demand Response) to avoid curtailment of renewables. At very high CES values, the associated policy costs are highly uncertain and should be complemented with other modeling. The business-as-usual CES value assumes the portion of an existing RPS standard met by imports remains constant. | L3: =J3&K3 -> **Description:** This policy specifies an increase in the fraction of electricity generation that must come from qualifying carbon-free sources (wind, solar, biomass, nuclear, hydro, geothermal, ccs, and hydrogen) in 2050. This policy has no effect until the user-set value exceeds the existing fraction of carbon-free electricity and any carbon-free electricity standards which have been enacted at the state level. To use this policy, turn the associated 'Non BAU RPS Qualifying Resources' policy to ON and the 'Lift the Clean Electricity Standard Alternative Compliance Payment' policy to ON. // **Guidance for setting values:** Multiple states have set 100% clean energy or renewable energy laws or goals, not including New Jersey. When setting a high CES with this lever, users should also turn on supporting power sector policies (i.e., Grid-Scale Electricity Storage, Increase Transmission, and Demand Response) to avoid curtailment of renewables. At very high CES values, the associated policy costs are highly uncertain and should be complemented with other modeling. The business-as-usual CES value assumes the portion of an existing RPS standard met by imports remains constant.
A4: Electricity Supply | B4: Change Electricity Exports | C4: Percent Change in Electricity Exports | D4: Electricity Imports and Exports | E4: elec change exports | F4: -0.5 | G4: 1 | H4: 0.02 | I4: % change in exports | J4: **Description:** This policy increases or decreases the amount of electricity exported from the United States to Canada and Mexico. It does not cause the construction or removal of transmission lines linking these countries. // **Guidance for setting values:** | K4: =_xlfn.CONCAT(" Multiple states have set 100% clean energy or renewable energy laws or goals, ",IF('Supporting Data'!AM4=1,"including "," not including "),About!$C$2,".",IF('Supporting Data'!AM4=1,_xlfn.CONCAT(". After weighing for coop and municipality requirements, the BAU assumes a total ","CES of ",'Supporting Data'!$AK$3,"% in 2030 that rises to ",'Supporting Data'!$AL$3,"% by 2050. ")," "),"When setting a high CES with this lever, users should also turn on supporting power sector policies (i.e., Grid-Scale Electricity Storage, Increase Transmission, and Demand Response) ","to avoid curtailment of renewables. ","At very high CES values, the associated policy costs are highly uncertain and should be complemented with other modeling. The business-as-usual CES value assumes the portion of an existing RPS standard met by imports remains constant.") -> Multiple states have set 100% clean energy or renewable energy laws or goals, not including New Jersey. When setting a high CES with this lever, users should also turn on supporting power sector policies (i.e., Grid-Scale Electricity Storage, Increase Transmission, and Demand Response) to avoid curtailment of renewables. At very high CES values, the associated policy costs are highly uncertain and should be complemented with other modeling. The business-as-usual CES value assumes the portion of an existing RPS standard met by imports remains constant. | L4: =J4&K4 -> **Description:** This policy increases or decreases the amount of electricity exported from the United States to Canada and Mexico. It does not cause the construction or removal of transmission lines linking these countries. // **Guidance for setting values:** Multiple states have set 100% clean energy or renewable energy laws or goals, not including New Jersey. When setting a high CES with this lever, users should also turn on supporting power sector policies (i.e., Grid-Scale Electricity Storage, Increase Transmission, and Demand Response) to avoid curtailment of renewables. At very high CES values, the associated policy costs are highly uncertain and should be complemented with other modeling. The business-as-usual CES value assumes the portion of an existing RPS standard met by imports remains constant.
A5: Electricity Supply | B5: Change Electricity Imports | C5: Percent Change in Electricity Imports | D5: Electricity Imports and Exports | E5: elec change imports | F5: -0.5 | G5: 1 | H5: 0.02 | I5: % change in imports | J5: **Description:** This policy increases or decreases the amount of electricity imported to the United States from Canada and Mexico. It does not cause the construction or removal of transmission lines linking these countries. // **Guidance for setting values:** | K5: =_xlfn.CONCAT("From 2008 to 2021, electricity imports grew by ",'Supporting Data'!F3,"%.") -> From 2008 to 2021, electricity imports grew by -32%. | L5: =J5&K5 -> **Description:** This policy increases or decreases the amount of electricity imported to the United States from Canada and Mexico. It does not cause the construction or removal of transmission lines linking these countries. // **Guidance for setting values:** From 2008 to 2021, electricity imports grew by -32%.
A6: Electricity Supply | B6: Demand Response | C6: Fraction of Additional Demand Response Potential Achieved | D6: Demand Response | E6: elec demand response | F6: 0 | G6: 1 | H6: 0.01 | I6: % of potential achieved | J6: **Description:** This policy represents regulations that cause more demand response (DR) capacity to be added to the electric grid. Demand response provides flexibility that allows for the integration of more wind and solar PV, if the electricity system is flexibility-constrained. Demand response can be load-shedding (demand is reduced in the worst hours without adding demand in other hours) or load-shifting (demand is reduced in the worst hours and added in other hours). The type of demand response modeled here is load-shedding, which is by far the most common type of demand response that exists today. // **Guidance for setting values:** | K6: =_xlfn.CONCAT("For ", About!$C$2, ", a 100% setting provides for an additional ",'Supporting Data'!J3," MW of demand response capacity in 2050 (on top of a BAU quantity of ", 'Supporting Data'!L3, " MW).") -> For New Jersey, a 100% setting provides for an additional 4751 MW of demand response capacity in 2050 (on top of a BAU quantity of 2272 MW). | L6: =J6&K6 -> **Description:** This policy represents regulations that cause more demand response (DR) capacity to be added to the electric grid. Demand response provides flexibility that allows for the integration of more wind and solar PV, if the electricity system is flexibility-constrained. Demand response can be load-shedding (demand is reduced in the worst hours without adding demand in other hours) or load-shifting (demand is reduced in the worst hours and added in other hours). The type of demand response modeled here is load-shedding, which is by far the most common type of demand response that exists today. // **Guidance for setting values:**For New Jersey, a 100% setting provides for an additional 4751 MW of demand response capacity in 2050 (on top of a BAU quantity of 2272 MW).
A7: Electricity Supply | B7: Subsidy for Capacity Construction | C7: Perc Subsidy for Elec Capacity Construction | D7: Subsidy for Capacity Construction | E7: elec capacity construction subsidy | F7: 0 | G7: 0.95 | H7: 0.01 | I7: % of construction cost | J7: **Description:** This policy is a subsidy paid by the government to electricity suppliers per unit of new capacity constructed. This only applies to utilities, not distributed systems (such as rooftop solar). // **Guidance for setting values:** // | K7: **Nuclear:** The U.S. Federal Government has guaranteed billions of dollars of loans for the construction new nuclear plants and has funded billions of dollars of nuclear technology R&D. The construction of two new reactors at the Vogtle power plant, the only advanced nuclear energy project under construction in the U.S., has received $12 billion in loan guarantees as of March 2019. (Loan guarantees are not equivalent to subsidies dollar-for-dollar, but they lower the cost of construction by enabling the plant to access cheaper financing.) | L7: =J7&K7&M7&O7&P7&Q7 -> **Description:** This policy is a subsidy paid by the government to electricity suppliers per unit of new capacity constructed. This only applies to utilities, not distributed systems (such as rooftop solar). // **Guidance for setting values:** // **Nuclear:** The U.S. Federal Government has guaranteed billions of dollars of loans for the construction new nuclear plants and has funded billions of dollars of nuclear technology R&D. The construction of two new reactors at the Vogtle power plant, the only advanced nuclear energy project under construction in the U.S., has received $12 billion in loan guarantees as of March 2019. (Loan guarantees are not equivalent to subsidies dollar-for-dollar, but they lower the cost of construction by enabling the plant to access cheaper financing.) //**Onshore Wind:** New Jersey does not have a capacity construction subsidy. However, the Investment Tax Credit, a similar program for solar power, covers 30% of system costs through 2019, with declining amounts thereafter.//**Solar PV: **New Jersey does not have a capacity construction subsidy. However, the Investment Tax Credit, a similar program for solar power, covers 30% of system costs through 2019, with declining amounts thereafter.// **Biomass:** The U.S. Federal Government has collectively guaranteed billions of dollars of loans for the construction new biomass plants. (Loan guarantees are not equivalent to subsidies dollar-for-dollar, but they lower the cost of construction by enabling the plant to access cheaper financing.)//**Offshore Wind: **New Jersey does not have a capacity construction subsidy. However, the Investment Tax Credit, a similar program for solar power, covers 30% of system costs through 2019, with declining amounts thereafter. | M7: =_xlfn.CONCAT("//**Onshore Wind:** ",About!$C$2," does not have a capacity construction subsidy. ")&N7 -> //**Onshore Wind:** New Jersey does not have a capacity construction subsidy. However, the Investment Tax Credit, a similar program for solar power, covers 30% of system costs through 2019, with declining amounts thereafter. | N7: However, the Investment Tax Credit, a similar program for solar power, covers 30% of system costs through 2019, with declining amounts thereafter. | O7: =_xlfn.CONCAT("//**Solar PV: **",About!$C$2," does not have a capacity construction subsidy. ")&N7 -> //**Solar PV: **New Jersey does not have a capacity construction subsidy. However, the Investment Tax Credit, a similar program for solar power, covers 30% of system costs through 2019, with declining amounts thereafter. | P7: // **Biomass:** The U.S. Federal Government has collectively guaranteed billions of dollars of loans for the construction new biomass plants. (Loan guarantees are not equivalent to subsidies dollar-for-dollar, but they lower the cost of construction by enabling the plant to access cheaper financing.) | Q7: =_xlfn.CONCAT("//**Offshore Wind: **",About!$C$2," does not have a capacity construction subsidy. ")&N7 -> //**Offshore Wind: **New Jersey does not have a capacity construction subsidy. However, the Investment Tax Credit, a similar program for solar power, covers 30% of system costs through 2019, with declining amounts thereafter.
A8: Agriculture, Land Use, and Forestry | B8: Afforestation and Reforestation | C8: Fraction of Afforestation and Reforestation Achieved | D8: Afforestation and Reforestation | E8: land afforestation and reforestation | F8: 0 | G8: 1 | H8: 0.01 | I8: % of potential achieved | J8: **Description:** This policy increases the sequestration of CO2 by planting forests. Planted forests are assumed to be managed with best practices and are not used for timber harvesting. // **Guidance for setting values:** | K8: =_xlfn.CONCAT(" If this policy is fully implemented, the afforestation/reforestation rate reaches ",'Supporting Data'!C3," thousand acres per year in 2050.") -> If this policy is fully implemented, the afforestation/reforestation rate reaches 7 thousand acres per year in 2050. | L8: =J8&K8 -> **Description:** This policy increases the sequestration of CO2 by planting forests. Planted forests are assumed to be managed with best practices and are not used for timber harvesting. // **Guidance for setting values:** If this policy is fully implemented, the afforestation/reforestation rate reaches 7 thousand acres per year in 2050.
A9: Electricity Supply | B9: Ban New Power Plants | C9: Boolean Ban New Power Plants | D9: Ban New Power Plants | E9: elec ban new power plants | F9: 0 | G9: 1 | H9: 1 | I9: on/off | J9: **Description:** This policy prevents new capacity of the selected type(s) from being built or deployed. // **Guidance for setting values:** | K9: =_xlfn.CONCAT(" No new coal is planned in ", 'Supporting Data'!A3, ".") -> No new coal is planned in New Jersey. | L9: =J9&K9 -> **Description:** This policy prevents new capacity of the selected type(s) from being built or deployed. // **Guidance for setting values:** No new coal is planned in New Jersey.
A10: Transportation | B10: Passenger Vehicle Subsidy | C10: Additional Passenger Vehicle Subsidy | D10: Vehicle Subsidy | E10: trans psgr subsidy | F10: 0 | G10: 50000 | H10: 100 | I10: $ / vehicle | J10: **Description:** This policy specifies the dollar amount offered as a subsidy to the purchaser of a new passenger vehicle. This is in addition to subsidies that exist in the BAU case. A negative value implies a tax or removal of subsidies. // **Guidance for setting values:** The U.S. currently offers a federal tax credit for up to $7,500 for qualifying clean passenger light-duty vehicles as part of the Inflation Reduction Act. This tax credit is included in the BAU scenario as an estimated average credit for new vehicles, accounting for the fact many vehicles will not be eligible starting in 2025 due to requirements for critical minerals sourcing. The BAU also includes the state-level credit on top of the federal tax credits. | K10: =_xlfn.CONCAT(IF('Supporting Data'!$AN$3=0," This state has no additional state subsidies. ",_xlfn.CONCAT(" As of late 2020, there is an additional state subsidy of $",'Supporting Data'!$AN$3,"."))) -> As of late 2020, there is an additional state subsidy of $5000. | L10: =J10&K10 -> **Description:** This policy specifies the dollar amount offered as a subsidy to the purchaser of a new passenger vehicle. This is in addition to subsidies that exist in the BAU case. A negative value implies a tax or removal of subsidies. // **Guidance for setting values:** The U.S. currently offers a federal tax credit for up to $7,500 for qualifying clean passenger light-duty vehicles as part of the Inflation Reduction Act. This tax credit is included in the BAU scenario as an estimated average credit for new vehicles, accounting for the fact many vehicles will not be eligible starting in 2025 due to requirements for critical minerals sourcing. The BAU also includes the state-level credit on top of the federal tax credits. As of late 2020, there is an additional state subsidy of $5000.
A11: Transportation | B11: Freight Vehicle Subsidy | C11: Additional Freight Vehicle Subsidy | D11: Vehicle Subsidy | E11: trans frgt subsidy | F11: 0 | G11: 50000 | H11: 100 | I11: $ / vehicle | J11: **Description:** This policy specifies the dollar amount offered as a subsidy to the purchaser of a new freight vehicle. This is in addition to subsidies that exist in the BAU case. A negative value implies a tax or removal of subsidies. // **Guidance for setting values:** The U.S. currently offers a federal tax credit for up to $40,500 for qualifying clean commercial vehicles, which is incorporated in the BAU. | K11: =_xlfn.CONCAT(IF('Supporting Data'!$AO$3=0," This state has no additional state subsidies. ",_xlfn.CONCAT(" As of late 2020, there is an additional state subsidy of $",'Supporting Data'!$AO$3,"."))) -> This state has no additional state subsidies. | L11: =J11&K11 -> **Description:** This policy specifies the dollar amount offered as a subsidy to the purchaser of a new freight vehicle. This is in addition to subsidies that exist in the BAU case. A negative value implies a tax or removal of subsidies. // **Guidance for setting values:** The U.S. currently offers a federal tax credit for up to $40,500 for qualifying clean commercial vehicles, which is incorporated in the BAU. This state has no additional state subsidies.
A12: Electricity Supply | B12: Early Retirement of Power Plants | C12: Annual Additional Capacity Retired due to Early Retirement Policy | D12: Early Retirement of Power Plants | E12: elec early retirement | F12: 0 | G12: 25000 | H12: 500 | I12: MW/year | J12: **Description:** This policy causes the specified quantity of otherwise non-retiring capacity of the selected type(s) to be retired each year. // **Guidance for setting values:** // | K12: =_xlfn.CONCAT("**Hard coal:** The EIA projects that ", About!$C$2, " will retire ", 'Supporting Data'!M3, " MW of coal by 2050. ", About!$C$2, " currently has ",'Supporting Data'!T3, " MW of coal capacity." ) -> **Hard coal:** The EIA projects that New Jersey will retire 0 MW of coal by 2050. New Jersey currently has 463 MW of coal capacity. | L12: =J12&K12&M12&N12&O12&P12 -> **Description:** This policy causes the specified quantity of otherwise non-retiring capacity of the selected type(s) to be retired each year. // **Guidance for setting values:** // **Hard coal:** The EIA projects that New Jersey will retire 0 MW of coal by 2050. New Jersey currently has 463 MW of coal capacity.//**Natural gas non-peaker:** The EIA projects that NJ will retire 0 MW of natural gas by 2050. NJ currently has 8570 MW of natural gas non-peaker capacity.//**Nuclear:** The EIA projects that NJ will retire 0 MW of nuclear by 2050. NJ currently has 3467 MW of nuclear capacity.//**Natural gas peaker:** The EIA projects that NJ will retire 0 MW of natural gas by 2050. NJ currently has 2770 MW of natural gas peaker capacity.//**Lignite:** The EIA projects that NJ will retire 0 MW of lignite by 2050. NJ currently has 0 MW of lignite capacity. | M12: =_xlfn.CONCAT("//**Natural gas non-peaker:** The EIA projects that ", About!B2, " will retire ", 'Supporting Data'!N3, " MW of natural gas by 2050. ", About!B2, " currently has ",'Supporting Data'!U3, " MW of natural gas non-peaker capacity." ) -> //**Natural gas non-peaker:** The EIA projects that NJ will retire 0 MW of natural gas by 2050. NJ currently has 8570 MW of natural gas non-peaker capacity. | N12: =_xlfn.CONCAT("//**Nuclear:** The EIA projects that ", About!B2, " will retire ", 'Supporting Data'!$O$3, " MW of nuclear by 2050. ", About!B2, " currently has ",'Supporting Data'!$V$3, " MW of nuclear capacity." ) -> //**Nuclear:** The EIA projects that NJ will retire 0 MW of nuclear by 2050. NJ currently has 3467 MW of nuclear capacity. | O12: =_xlfn.CONCAT("//**Natural gas peaker:** The EIA projects that ", About!B2, " will retire ",'Supporting Data'!$R$3, " MW of natural gas by 2050. ", About!B2, " currently has ",'Supporting Data'!$AD$3, " MW of natural gas peaker capacity." ) -> //**Natural gas peaker:** The EIA projects that NJ will retire 0 MW of natural gas by 2050. NJ currently has 2770 MW of natural gas peaker capacity. | P12: =_xlfn.CONCAT("//**Lignite:** The EIA projects that ", About!B2, " will retire ", 'Supporting Data'!$S$3, " MW of lignite by 2050. ", About!B2, " currently has ",'Supporting Data'!$AE$3, " MW of lignite capacity." ) -> //**Lignite:** The EIA projects that NJ will retire 0 MW of lignite by 2050. NJ currently has 0 MW of lignite capacity.
A13: Industry | B13: Reduce Fossil Fuel Exports | C13: Percent Reduction in Fossil Fuel Exports | D13: Percent Reduction in Fossil Fuel Exports | E13: indst reduce fossil fuel exports | F13: 0 | G13: 1 | H13: 0.01 | I13: % reduction in exports | J13: **Description:** This policy reduces production of the selected fuel type(s) for export. This lever may represent a reduction in fuel demand by actors outside the modeled region (i.e., not caused by domestic policy) or a conscious policy within the modeled region to transition its economy away from dependence on fossil fuel exports. // **Guidance for setting values:** // | K13: =_xlfn.CONCAT(IF('Supporting Data'!$BB$3=0,"**Hard coal**: The model assumes the state has no hard coal production. ",_xlfn.CONCAT("**Hard coal:** The model assumes that exports represent ",'Supporting Data'!$BJ$3,"% of the state's production."))) -> **Hard coal**: The model assumes the state has no hard coal production. | L13: =J13&K13&M13&N13&O13&P13&Q13&R13&S13 -> **Description:** This policy reduces production of the selected fuel type(s) for export. This lever may represent a reduction in fuel demand by actors outside the modeled region (i.e., not caused by domestic policy) or a conscious policy within the modeled region to transition its economy away from dependence on fossil fuel exports. // **Guidance for setting values:** // **Hard coal**: The model assumes the state has no hard coal production. //**Crude oil:**: The model assumes the state has no crude oil production. //**Heavy fuel oil:** The model assumes that exports represent 259.46% of the state's production.//**Jet fuel or kerosene:** The model assumes that exports represent 103.49% of the state's production.//**LPG propane or butane:** The model assumes that exports represent 101.15% of the state's production.//**Natural gas:** The model assumes the state has no natural gas production. //**Petroleum diesel:** The model assumes that exports represent 107.9% of the state's production.//**Petroleum gasoline:** The model assumes the state has no petroleum gasoline production. | M13: =_xlfn.CONCAT(IF('Supporting Data'!$BA$3=0,"//**Crude oil:**: The model assumes the state has no crude oil production. ",_xlfn.CONCAT("//**Crude oil:** The model assumes that exports represent ",'Supporting Data'!BI3,"% of the state's production."))) -> //**Crude oil:**: The model assumes the state has no crude oil production. | N13: =_xlfn.CONCAT(IF('Supporting Data'!$BC$3=0,"//**Heavy fuel oil:**: The model assumes the state has no heavy fuel oil production. ",_xlfn.CONCAT("//**Heavy fuel oil:** The model assumes that exports represent ",'Supporting Data'!$BK$3,"% of the state's production."))) -> //**Heavy fuel oil:** The model assumes that exports represent 259.46% of the state's production. | O13: =_xlfn.CONCAT(IF('Supporting Data'!$BD$3=0,"//**Jet fuel or kerosene:** The model assumes the state has no jet fuel or kerosene production. ",_xlfn.CONCAT("//**Jet fuel or kerosene:** The model assumes that exports represent ",'Supporting Data'!$BL$3,"% of the state's production."))) -> //**Jet fuel or kerosene:** The model assumes that exports represent 103.49% of the state's production. | P13: =_xlfn.CONCAT(IF('Supporting Data'!$BE$3=0,"//**LPG propane or butane:** The model assumes the state has no LPG propane or butane production. ",_xlfn.CONCAT("//**LPG propane or butane:** The model assumes that exports represent ",'Supporting Data'!$BM$3,"% of the state's production."))) -> //**LPG propane or butane:** The model assumes that exports represent 101.15% of the state's production. | Q13: =_xlfn.CONCAT(IF('Supporting Data'!$BF$3=0,"//**Natural gas:** The model assumes the state has no natural gas production. ",_xlfn.CONCAT("//**Natural gas:** The model assumes that exports represent ",'Supporting Data'!BN3,"% of the state's production."))) -> //**Natural gas:** The model assumes the state has no natural gas production. | R13: =_xlfn.CONCAT(IF('Supporting Data'!$BH$3=0,"//**Petroleum diesel:** The model assumes the state has no petroleum diesel production. ",_xlfn.CONCAT("//**Petroleum diesel:** The model assumes that exports represent ",'Supporting Data'!BO3,"% of the state's production."))) -> //**Petroleum diesel:** The model assumes that exports represent 107.9% of the state's production. | S13: =_xlfn.CONCAT(IF('Supporting Data'!$BB$3=0,"//**Petroleum gasoline:** The model assumes the state has no petroleum gasoline production. ",_xlfn.CONCAT("//**Petroleum gasoline:** The model assumes that exports represent ",'Supporting Data'!BP3,"% of the state's production."))) -> //**Petroleum gasoline:** The model assumes the state has no petroleum gasoline production.
A14: Buildings and Appliances | B14: Building Energy Efficiency Standards | C14: Reduction in E Use Allowed by Component Eff Std | D14: Building Energy Efficiency Standards | E14: bldgs efficiency standards | F14: 0 | G14: 0.75 | H14: 0.01 | I14: % reduction in energy use | J14: **Description:** This policy tightens energy efficiency standards for the selected component(s) in the selected building type(s). The policy only applies to newly sold components each year (whether for new buildings or replacement of old components of existing buildings). // **Guidance for setting values:** In "Assessment of Electricity Savings in the U.S. Achievable through New Appliance/Equipment Efficiency Standards and Building Efficiency Codes, 2010-2025" (2011), the Edison Foundation considered a 30% reduction in whole-building energy use (moderate case) and 40-45% (aggressive case) relative to BAU from 2010 to 2025. | K14: **Description:** This policy tightens energy efficiency standards for the selected component(s) in the selected building type(s). The policy only applies to newly sold components each year (whether for new buildings or replacement of old components of existing buildings). // **Guidance for setting values:** In 'Assessment of Electricity Savings in the U.S. Achievable through New Appliance / Equipment Efficiency Standards and Building Efficiency Codes, 2010-2025' (2011), the Edison Foundation considered a 30% reduction in whole-building energy use (moderate case) and 40-45% (aggressive case) relative to BAU from 2010 to 2025. New Mexico adopted 2018 IECC codes in 2020-- according to US DOE, this will save buildings 30 percent in site energy use and 32 percent in energy costs. These savings are not included in the BAU. | L14: {=_xlfn.IFS(About!$B$2="NM", 'State Policy Descriptions'!$K$14,About!$B$2="WI",'State Policy Descriptions'!$M$14,TRUE,J14)} -> **Description:** This policy tightens energy efficiency standards for the selected component(s) in the selected building type(s). The policy only applies to newly sold components each year (whether for new buildings or replacement of old components of existing buildings). // **Guidance for setting values:** In "Assessment of Electricity Savings in the U.S. Achievable through New Appliance/Equipment Efficiency Standards and Building Efficiency Codes, 2010-2025" (2011), the Edison Foundation considered a 30% reduction in whole-building energy use (moderate case) and 40-45% (aggressive case) relative to BAU from 2010 to 2025. | M14: **Description:** This policy tightens energy efficiency standards for the selected component(s) in the selected building type(s). The policy only applies to newly sold components each year (whether for new buildings or replacement of old components of existing buildings). // **Guidance for setting values:** In 'Assessment of Electricity Savings in the U.S. Achievable through New Appliance / Equipment Efficiency Standards and Building Efficiency Codes, 2010-2025' (2011), the Edison Foundation considered a 30% reduction in whole-building energy use (moderate case) and 40-45% (aggressive case) relative to BAU from 2010 to 2025. Wisconsin adopted 2015 IECC codes in 2018-- according to US DOE, this will save buildings 11 percent in site energy use and 11 percent in energy costs compared to 2012 IECC codes.
K15: NM^ | M15: WI^
A16: Transportation | B16: Zero-Emission Vehicle Sales Standard | C16: Additional Minimum Required ZEV Sales Percentage for Model Region | D16: ZEV Sales Standard | E16: trans ZEV minimum | F16: 0 | G16: 1 | H16: 0.01 | I16: % of new vehicles sold | J16: **Description:** This policy requires the specified percentage of newly sold vehicles of the selected type(s) to consist of zero-emission vehicles. If that percentage would already be achieved through BAU sales plus the effects of other policies, such as an EV subsidy, this policy has no effect. Manufactures may meet a sales standard through techniques such as more heavily marketing electric vehicles, lowering the price of electric vehicles, or raising the price of non-electric vehicles. A negative setting for this lever implies a decrease in ZEV sales requirements relative to the BAU scenario. The following descriptions detail the different vehicle types: // **Passenger cars and SUVs:** most light-duty road vehicles //**Light and Medium Commercial Trucks:** commercial trucks carrying freight, not passengers // **Buses:** including school, transit, and intercity buses // **Heavy Duty Trucks:** all other heavy road vehicles (mostly freight trucks) // **Passenger motorbikes:** registered motorcycles // **Guidance for setting values:** | K16: {=_xlfn.IFS('Supporting Data'!$CI$3+'Supporting Data'!$CJ$3=2, "The state has adopted ACC and ACC II.",'Supporting Data'!$CI$3+'Supporting Data'!$CJ$3>1, "The state has adopted ACC and partially adopted ACC II.", 'Supporting Data'!$CI$3=1, "The state has adopted ACC but not ACC II.", 'Supporting Data'!CJ3=1, "The state has adopted ACC II.", 'Supporting Data'!$CI$3+'Supporting Data'!$CJ$3<1, "The state has not adopted ACC or ACC II.")} -> The state has adopted ACC and partially adopted ACC II. | L16: =J16&M16&K16&N16 -> **Description:** This policy requires the specified percentage of newly sold vehicles of the selected type(s) to consist of zero-emission vehicles. If that percentage would already be achieved through BAU sales plus the effects of other policies, such as an EV subsidy, this policy has no effect. Manufactures may meet a sales standard through techniques such as more heavily marketing electric vehicles, lowering the price of electric vehicles, or raising the price of non-electric vehicles. A negative setting for this lever implies a decrease in ZEV sales requirements relative to the BAU scenario. The following descriptions detail the different vehicle types: // **Passenger cars and SUVs:** most light-duty road vehicles //**Light and Medium Commercial Trucks:** commercial trucks carrying freight, not passengers // **Buses:** including school, transit, and intercity buses // **Heavy Duty Trucks:** all other heavy road vehicles (mostly freight trucks) // **Passenger motorbikes:** registered motorcycles // **Guidance for setting values:**//**Passenger cars and SUVs: ** Under the Clean Air Act, California was awarded a waiver enabling the state to set vehicle emissions standards that are more stringent than federal standards. The waiver has resulted in the Advanced Clean Cars (ACC) and Advanced Clean Cars II (ACC II) regulations. Other states can also choose to adopt the regulations. ACC requires requires automakers to sell ~7-10% EV sales by 2025. ACC II stipulates a 35 percent sales requirement in 2026, ramping up to a 100 percent sales target in 2035. The state has adopted ACC and partially adopted ACC II. // **Light and Medium Commercial and Heavy Duty Trucks:** Today, the share of electric freight trucks is very low, but electrification is particularly promising for certain types of trucks, such as those used to make deliveries within cities, those involved in port operations, garbage trucks, and others with frequent starts and stops. // **Buses:** Electric bus manufacturer Proterra believes all new transit bus sales could be electric as early as 2030, but transit buses make up roughly 15% of the bus fleet. // **Passenger motorbikes:** Though electric motorcycles and scooters are popular in Europe and Asia, where motorbikes are commonly used for urban transportation and commuting, electric motorbikes are not yet a significant presence in the U.S., where motorbikes are mostly used for recreation. | M16: //**Passenger cars and SUVs: ** Under the Clean Air Act, California was awarded a waiver enabling the state to set vehicle emissions standards that are more stringent than federal standards. The waiver has resulted in the Advanced Clean Cars (ACC) and Advanced Clean Cars II (ACC II) regulations. Other states can also choose to adopt the regulations. ACC requires requires automakers to sell ~7-10% EV sales by 2025. ACC II stipulates a 35 percent sales requirement in 2026, ramping up to a 100 percent sales target in 2035. | N16: // **Light and Medium Commercial and Heavy Duty Trucks:** Today, the share of electric freight trucks is very low, but electrification is particularly promising for certain types of trucks, such as those used to make deliveries within cities, those involved in port operations, garbage trucks, and others with frequent starts and stops. // **Buses:** Electric bus manufacturer Proterra believes all new transit bus sales could be electric as early as 2030, but transit buses make up roughly 15% of the bus fleet. // **Passenger motorbikes:** Though electric motorcycles and scooters are popular in Europe and Asia, where motorbikes are commonly used for urban transportation and commuting, electric motorbikes are not yet a significant presence in the U.S., where motorbikes are mostly used for recreation.
A17: Electricity Supply | B17: Clean Electricity Standard Alternative Compliance Payment | C17: Boolean Use Non BAU RPS Alternative Compliance Payment | F17: 0 | G17: 1000 | H17: 20 | I17: 2023 dollars / megawatt-hour (MWh) | J17: **Description:** The BAU scenario includes a CES alternative compliance payment of roughly 180 $/MWh, meaning the model will not deploy any additional CES qualifying resources above this price in an attempt to meet the CES. Enabling this policy lifts this cap, meaning there is no price constraint on new resources. | K17: If the CES credit price hits this $/MWh amount in a given year, the model will not deploy any additional CES qualifying resources in an attempt to meet the CES. Enabling this policy lifts this cap, meaning there is no price constraint on new resources. | L17: =M17&K17 -> **Description:** The BAU scenario includes a CES alternative compliance payment of roughly 50 $/MWh. If the CES credit price hits this $/MWh amount in a given year, the model will not deploy any additional CES qualifying resources in an attempt to meet the CES. Enabling this policy lifts this cap, meaning there is no price constraint on new resources. | M17: =_xlfn.CONCAT(IF('Supporting Data'!$CL$3="FALSE","**Description:** This setting caps the CES credit price. ",_xlfn.CONCAT("**Description:** The BAU scenario includes a CES alternative compliance payment of roughly ",'Supporting Data'!$CM$3," $/MWh."))) -> **Description:** The BAU scenario includes a CES alternative compliance payment of roughly 50 $/MWh.

Sheet Supporting Data
B1: PLANAbPiaSY | E1: EIAE- BIE | H1: EIAE- BEE | J1: DRC-PADRC | K1: DRC-BDRC | M1: BCRbq - 2024-2050 | T1: SYC | AJ1: BRPSDbS | AN1: BESP | AQ1: Charger plugs/ 100k | AS1: BFPIaE-exports | BA1: BFPIaE-production | BI1: Exports Percentage | BQ1: BCEU | CI1: Does this state follow: | CL1: RACP
B2: afforestation and reforestation | C2: land per year | D2: imports 2008 | E2: imports 2021 | F2: delta imports (%) | G2: exports 2008 | H2: exports 2021 | I2: delta exports (%) | J2: Potential Additional DR Capacity (MW) 2050 | K2: 2021 Demand Response (MW) | L2: 2050 Demand Response (MW) | M2: hard coal retiring | N2: natural gas nonpeaker retiring | O2: nuclear retiring | P2: biomass retiring | Q2: petroleum retiring | R2: natural gas peaker retiring | S2: lignite retiring | T2: hard coal SYC | U2: natural gas nonpeaker SYC | V2: nuclear SYC | W2: hydro SYC | X2: onshore wind SYC | Y2: solar PV SYC | Z2: solar thermal SYC | AA2: biomass SYC | AB2: geothermal SYC | AC2: petroleum SYC | AD2: natural gas peaker SYC | AE2: lignite SYC | AF2: offshore wind SYC | AG2: crude oil SYC | AH2: heavy or residual fuel oil SYC | AI2: municipal solid waste SYC | AJ2: 2021 | AK2: 2030 | AL2: 2050 | AM2: 100% plan? | AN2: LDV (2024) | AO2: HDV (2024) | AP2: Chargers (Plugs total) | AQ2: State Population | AR2: Plug/100k | AS2: crude oil | AT2: hard coal | AU2: heavy fuel oil | AV2: jet fuel or kerosene | AW2: LPG propane or butane | AX2: natural gas | AY2: petroleum diesel | AZ2: petroleum gasoline | BA2: crude oil | BB2: hard coal | BC2: heavy fuel oil | BD2: jet fuel or kerosene | BE2: LPG propane or butane | BF2: natural gas | BG2: petroleum diesel | BH2: petroleum gasoline | BI2: crude oil | BJ2: hard coal | BK2: heavy fuel oil | BL2: jet fuel or kerosene | BM2: LPG propane or butane | BN2: natural gas | BO2: petroleum diesel | BP2: petroleum gasoline | BQ2: 2021 commercial heating | BR2: 2050 commercial heating | BS2: 2021 commercial appliances | BT2: 2050 commercial appliances | BU2: 2021 commercial oth | BV2: 2050 commercial oth | BW2: 2021 urban heating | BX2: 2050 urban heating | BY2: 2021 urban appliances | BZ2: 2050 uban appliances | CA2: 2021 urban oth | CB2: 2050 urban oth | CC2: 2021 rural heating | CD2: 2050 rural heating | CE2: 2021 rural appliances | CF2: 2050 rural appliances | CG2: 2021 rural oth | CH2: 2050 rural oth | CI2: ACC I | CJ2: ACC II | CK2: ACT | CL2: Has RPS? | CM2: ACP $/MWh
A3: =About!$C$2 -> New Jersey | B3: =ROUND(SUMIFS(B$4:B$54, $A$4:$A$54, $A$3),0) -> 6819 | C3: =ROUND(SUMIFS(C$4:C$54, $A$4:$A$54, $A$3),0) -> 7 | D3: =SUMIFS(D$4:D$54, $A$4:$A$54, $A$3) -> 24337437 | E3: =SUMIFS(E$4:E$54, $A$4:$A$54, $A$3) -> 16636178 | F3: =ROUND(SUMIFS(F$4:F$54,$A$4:$A$54,$A$3)*100,0) -> -32 | G3: =SUMIFS(G$4:G$54, $A$4:$A$54, $A$3) -> 0 | H3: =SUMIFS(H$4:H$54, $A$4:$A$54, $A$3) -> 0 | I3: =ROUND(SUMIFS(I$4:I$54,$A$4:$A$54,$A$3)*100,0) -> 0 | J3: =ROUND(SUMIFS(J$4:J$54, $A$4:$A$54, $A$3),0) -> 4751 | K3: =ROUND(SUMIFS(K$4:K$54, $A$4:$A$54, $A$3),0) -> 1729 | L3: =ROUND(SUMIFS(L$4:L$54, $A$4:$A$54, $A$3),0) -> 2272 | M3: =ROUND(SUMIFS(M$4:M$54, $A$4:$A$54, $A$3),0) -> 0 | N3: =ROUND(SUMIFS(N$4:N$54, $A$4:$A$54, $A$3),0) -> 0 | O3: =ROUND(SUMIFS(O$4:O$54, $A$4:$A$54, $A$3),0) -> 0 | P3: =ROUND(SUMIFS(P$4:P$54, $A$4:$A$54, $A$3),0) -> 0 | Q3: =ROUND(SUMIFS(Q$4:Q$54, $A$4:$A$54, $A$3),0) -> 0 | ... AI3: =ROUND(SUMIFS(AI$4:AI$54, $A$4:$A$54, $A$3),0) -> 105 | AJ3: =ROUND(SUMIFS(AJ$4:AJ$54,$A$4:$A$54,$A$3)*100,0) -> 67 | AK3: =ROUND(SUMIFS(AK$4:AK$54,$A$4:$A$54,$A$3)*100,0) -> 96 | AL3: =ROUND(SUMIFS(AL$4:AL$54,$A$4:$A$54,$A$3)*100,0) -> 96 | AM3: =SUMIFS(AM$4:AM$54, $A$4:$A$54, $A$3) -> 0 | AN3: =SUMIFS(AN$4:AN$54, $A$4:$A$54, $A$3) -> 5000 | AO3: =SUMIFS(AO$4:AO$54, $A$4:$A$54, $A$3) -> 0 | AP3: =SUMIFS(AP$4:AP$54, $A$4:$A$54, $A$3) -> 1610 | AQ3: =SUMIFS(AQ$4:AQ$54, $A$4:$A$54, $A$3) -> 9320865 | AR3: =ROUND(SUMIFS(AR$4:AR$54,$A$4:$A$54,$A$3),2) -> 17.27 | AS3: =SUMIFS(AS$4:AS$54, $A$4:$A$54, $A$3) -> 0 | AT3: =SUMIFS(AT$4:AT$54, $A$4:$A$54, $A$3) -> 0 | AU3: =SUMIFS(AU$4:AU$54, $A$4:$A$54, $A$3) -> 7.1683443e+13 | AV3: =SUMIFS(AV$4:AV$54, $A$4:$A$54, $A$3) -> 7.7101005e+13 | AW3: =SUMIFS(AW$4:AW$54, $A$4:$A$54, $A$3) -> 430149287744727 | AX3: =SUMIFS(AX$4:AX$54, $A$4:$A$54, $A$3) -> 0 | AY3: =SUMIFS(AY$4:AY$54, $A$4:$A$54, $A$3) -> 229699958223607 | AZ3: =SUMIFS(AZ$4:AZ$54, $A$4:$A$54, $A$3) -> 1.9379543e+15 | ... BH3: =SUMIFS(BH$4:BH$54, $A$4:$A$54, $A$3) -> 2.1737898e+15 | BI3: =ROUND(SUMIFS(BI$4:BI$54,$A$4:$A$54,$A$3),2) -> 0 | BJ3: =ROUND(SUMIFS(BJ$4:BJ$54,$A$4:$A$54,$A$3),2) -> 0 | BK3: =ROUND(SUMIFS(BK$4:BK$54,$A$4:$A$54,$A$3),2) -> 259.46 | BL3: =ROUND(SUMIFS(BL$4:BL$54,$A$4:$A$54,$A$3),2) -> 103.49 | BM3: =ROUND(SUMIFS(BM$4:BM$54,$A$4:$A$54,$A$3),2) -> 101.15 | BN3: =ROUND(SUMIFS(BN$4:BN$54,$A$4:$A$54,$A$3),2) -> 0 | BO3: =ROUND(SUMIFS(BO$4:BO$54,$A$4:$A$54,$A$3),2) -> 107.9 | BP3: =ROUND(SUMIFS(BP$4:BP$54,$A$4:$A$54,$A$3),2) -> 89.15 | BQ3: =ROUND(SUMIFS(BQ$4:BQ$54,$A$4:$A$54,$A$3)*100,0) -> 3 | BR3: =ROUND(SUMIFS(BR$4:BR$54,$A$4:$A$54,$A$3)*100,0) -> 3 | BS3: =ROUND(SUMIFS(BS$4:BS$54,$A$4:$A$54,$A$3)*100,0) -> 30 | BT3: =ROUND(SUMIFS(BT$4:BT$54,$A$4:$A$54,$A$3)*100,0) -> 28 | BU3: =ROUND(SUMIFS(BU$4:BU$54,$A$4:$A$54,$A$3)*100,0) -> 66 | BV3: =ROUND(SUMIFS(BV$4:BV$54,$A$4:$A$54,$A$3)*100,0) -> 76 | BW3: =ROUND(SUMIFS(BW$4:BW$54,$A$4:$A$54,$A$3)*100,0) -> 7 | BX3: =ROUND(SUMIFS(BX$4:BX$54,$A$4:$A$54,$A$3)*100,0) -> 11 | ... CH3: =ROUND(SUMIFS(CH$4:CH$54,$A$4:$A$54,$A$3)*100,0) -> 100 | CI3: =SUMIFS(CI$4:CI$54, $A$4:$A$54, $A$3) -> 1 | CJ3: =SUMIFS(CJ$4:CJ$54, $A$4:$A$54, $A$3) -> 0.82 | CK3: =SUMIFS(CK$4:CK$54, $A$4:$A$54, $A$3) -> 1 | CL3: =_xlfn.XLOOKUP($A$3,A4:A54,CL4:CL54,0,0,1) -> TRUE | CM3: =SUMIFS(CM$4:CM$54, $A$4:$A$54, $A$3) -> 50
A4: Alaska | B4: 0 | C4: =B4/1000 -> 0 | D4: 0 | E4: 0 | F4: =IFERROR(($E4/$D4) - 1, 0) -> 0 | G4: 0 | H4: 0 | I4: =IFERROR(($H4/$G4)-1,0) -> 0 | J4: 420.62492 | K4: 153.06936 | L4: 201.18644 | M4: 0 | N4: 0 | O4: 0 | P4: 0 | Q4: 0 | R4: 0 | S4: 0 | T4: 47.8 | U4: 477.2 | V4: 0 | W4: 425.4 | X4: 61 | Y4: 0 | Z4: 0 | AA4: 0 | AB4: 0 | AC4: 694.7 | AD4: 785.2 | AE4: 75 | AF4: 0 | AG4: 0 | AH4: 0 | AI4: 0 | AJ4: 0.256056 | AK4: 0.256056 | AL4: 0.256056 | AM4: 0 | AN4: 0 | AO4: 0 | AP4: 81 | AQ4: 733536 | AR4: =$AP4/($AQ4/100000) -> 11.042403 | AS4: 0 | AT4: 0 | AU4: 1.6662029e+13 | AV4: 6.5669313e+13 | AW4: 0 | AX4: 0 | AY4: 0 | AZ4: 123581068315118 | BA4: 985029102555240 | BB4: 1.9171597e+13 | BC4: 1.5471734e+13 | BD4: 5.6020449e+13 | BE4: 1.2633681e+13 | BF4: 324781704984725 | BG4: 73371716298245 | BH4: 173350029425847 | BI4: =IFERROR($AS4/$BA4,0)*100 -> 0 | BJ4: =IFERROR($AT4/$BB4,0)*100 -> 0 | BK4: =IFERROR($AU4/$BC4,0)*100 -> 107.69335 | BL4: =IFERROR($AV4/$BD4,0)*100 -> 117.22382 | BM4: =IFERROR($AW4/$BE4,0)*100 -> 0 | BN4: =IFERROR($AX4/$BF4,0)*100 -> 0 | BO4: =IFERROR($AY4/$BG4,0)*100 -> 0 | BP4: =IFERROR($AZ4/$BH4,0)*100 -> 71.289903 | BQ4: 0.068524148 | BR4: 0.062100654 | BS4: 0.28467689 | BT4: 0.2556004 | BU4: 0.27366733 | BV4: 0.3746911 | BW4: 0.059503823 | BX4: 0.10054067 | BY4: 0.27923583 | BZ4: 0.26232587 | CA4: 1 | CB4: 1 | CC4: 0.059503823 | CD4: 0.10054067 | CE4: 0.27923583 | CF4: 0.26232587 | CG4: 1 | CH4: 1 | CI4: 0 | CJ4: 0 | CK4: 0 | CL4: =IF(CM4=0,"FALSE","TRUE") -> FALSE | CM4: 0
A5: Alabama | B5: 121652.04 | C5: =B5/1000 -> 121.65204 | D5: 0 | E5: 0 | F5: =IFERROR(($E5/$D5) - 1, 0) -> 0 | G5: 44550279 | H5: 47230739 | I5: =IFERROR(($H5/$G5)-1,0) -> 0.060167075 | J5: 5932.9172 | K5: 2159.0443 | L5: 2837.736 | M5: 0 | N5: 1550 | O5: 0 | P5: 0 | Q5: 0 | R5: 50 | S5: 0 | T5: 5284.3 | U5: 9663.5 | V5: 5525.4 | W5: 3291.8 | X5: 0 | Y5: 194.1 | Z5: 0 | AA5: 6.4 | AB5: 0 | AC5: 42.6 | AD5: 4334.3 | AE5: 0 | AF5: 0 | AG5: 0 | AH5: 0 | AI5: 0 | AJ5: 0.403251 | AK5: 0.403251 | AL5: 0.403251 | AM5: 0 | AN5: 0 | AO5: 0 | AP5: 480 | AQ5: 5143033 | AR5: =$AP5/($AQ5/100000) -> 9.3330142 | AS5: 27155635000000 | AT5: 5059944575163 | AU5: 0 | AV5: 0 | AW5: 7.6619247e+13 | AX5: 0 | AY5: 0 | AZ5: 0 | BA5: 2.8777062e+13 | BB5: 290930930237375 | BC5: 5.4880739e+12 | BD5: 2.9520178e+13 | BE5: 88177522699640 | BF5: 139449382056794 | BG5: 9.4233095e+13 | BH5: 6.5296837e+13 | BI5: =IFERROR($AS5/$BA5,0)*100 -> 94.365559 | BJ5: =IFERROR($AT5/$BB5,0)*100 -> 1.7392254 | BK5: =IFERROR($AU5/$BC5,0)*100 -> 0 | BL5: =IFERROR($AV5/$BD5,0)*100 -> 0 | BM5: =IFERROR($AW5/$BE5,0)*100 -> 86.892038 | BN5: =IFERROR($AX5/$BF5,0)*100 -> 0 | BO5: =IFERROR($AY5/$BG5,0)*100 -> 0 | BP5: =IFERROR($AZ5/$BH5,0)*100 -> 0 | BQ5: 0.085789392 | BR5: 0.11229567 | BS5: 0.59595278 | BT5: 0.577546 | BU5: 0.66876054 | BV5: 0.77454567 | BW5: 0.30680288 | BX5: 0.41148013 | BY5: 0.68501845 | BZ5: 0.67974706 | CA5: 1 | CB5: 1 | CC5: 0.30679662 | CD5: 0.41087333 | CE5: 0.6850121 | CF5: 0.67919527 | CG5: 1 | CH5: 1 | CI5: 0 | CJ5: 0 | CK5: 0 | CL5: =IF(CM5=0,"FALSE","TRUE") -> FALSE | CM5: 0
A6: Arkansas | B6: 68319.005 | C6: =B6/1000 -> 68.319005 | D6: 0 | E6: 0 | F6: =IFERROR(($E6/$D6) - 1, 0) -> 0 | G6: 3387482 | H6: 8613908 | I6: =IFERROR(($H6/$G6)-1,0) -> 1.5428646 | J6: 5016.7881 | K6: 1825.6563 | L6: 2399.5481 | M6: 2150 | N6: 500 | O6: 0 | P6: 0 | Q6: 0 | R6: 0 | S6: 0 | T6: 5163.4 | U6: 4609.8 | V6: 1817.8 | W6: 1265.8 | X6: 0 | Y6: 102.2 | Z6: 0 | AA6: 16.8 | AB6: 0 | AC6: 9 | AD6: 1493.6 | AE6: 0 | AF6: 0 | AG6: 0 | AH6: 0 | AI6: 0 | AJ6: 0.287796 | AK6: 0.287796 | AL6: 0.287796 | AM6: 0 | AN6: 0 | AO6: 0 | AP6: 412 | AQ6: 3089060 | AR6: =$AP6/($AQ6/100000) -> 13.337391 | AS6: 27155635000000 | AT6: 0 | AU6: 0 | AV6: 0 | AW6: 4.4661854e+13 | AX6: 162908552000000 | AY6: 0 | AZ6: 0 | BA6: 2.8777062e+13 | BB6: 0 | BC6: 3.3803618e+12 | BD6: 1.8182861e+13 | BE6: 5.4312667e+13 | BF6: 576325283662511 | BG6: 58042577405376 | BH6: 4.0219381e+13 | BI6: =IFERROR($AS6/$BA6,0)*100 -> 94.365559 | BJ6: =IFERROR($AT6/$BB6,0)*100 -> 0 | BK6: =IFERROR($AU6/$BC6,0)*100 -> 0 | BL6: =IFERROR($AV6/$BD6,0)*100 -> 0 | BM6: =IFERROR($AW6/$BE6,0)*100 -> 82.23101 | BN6: =IFERROR($AX6/$BF6,0)*100 -> 28.266772 | BO6: =IFERROR($AY6/$BG6,0)*100 -> 0 | BP6: =IFERROR($AZ6/$BH6,0)*100 -> 0 | BQ6: 0.034657058 | BR6: 0.043905819 | BS6: 0.263749 | BT6: 0.25100049 | BU6: 0.48970894 | BV6: 0.62415125 | BW6: 0.23737194 | BX6: 0.35822978 | BY6: 0.4972464 | BZ6: 0.51031828 | CA6: 1 | CB6: 1 | CC6: 0.23736317 | CD6: 0.35754467 | CE6: 0.4972343 | CF6: 0.50954398 | CG6: 1 | CH6: 1 | CI6: 0 | CJ6: 0 | CK6: 0 | CL6: =IF(CM6=0,"FALSE","TRUE") -> FALSE | CM6: 0
A7: Arizona | B7: 106989.8 | C7: =B7/1000 -> 106.9898 | D7: 87916 | E7: 0 | F7: =IFERROR(($E7/$D7) - 1, 0) -> -1 | G7: 36968920 | H7: 22825079 | I7: =IFERROR(($H7/$G7)-1,0) -> -0.38258735 | J7: 4244.4475 | K7: 1544.5943 | L7: 2030.1348 | M7: 1900 | N7: 0 | O7: 0 | P7: 0 | Q7: 0 | R7: 0 | S7: 0 | T7: 3329 | U7: 9886.1 | V7: 3937 | W7: 2720.9 | X7: 267.3 | Y7: 1860.5 | Z7: 295.6 | AA7: 30.7 | AB7: 0 | AC7: 89 | AD7: 4079.6 | AE7: 0 | AF7: 0 | AG7: 0 | AH7: 0 | AI7: 0 | AJ7: 0.456235 | AK7: 0.496235 | AL7: 0.496235 | AM7: 0 | AN7: 0 | AO7: 0 | AP7: 1952 | AQ7: 7497004 | AR7: =$AP7/($AQ7/100000) -> 26.037068 | AS7: 0 | AT7: 0 | AU7: 0 | AV7: 0 | AW7: 0 | AX7: 0 | AY7: 0 | AZ7: 0 | BA7: 0 | BB7: 7.9148221e+13 | BC7: 0 | BD7: 0 | BE7: 0 | BF7: 7.252858e+10 | BG7: 0 | BH7: 0 | BI7: =IFERROR($AS7/$BA7,0)*100 -> 0 | BJ7: =IFERROR($AT7/$BB7,0)*100 -> 0 | BK7: =IFERROR($AU7/$BC7,0)*100 -> 0 | BL7: =IFERROR($AV7/$BD7,0)*100 -> 0 | BM7: =IFERROR($AW7/$BE7,0)*100 -> 0 | BN7: =IFERROR($AX7/$BF7,0)*100 -> 0 | BO7: =IFERROR($AY7/$BG7,0)*100 -> 0 | BP7: =IFERROR($AZ7/$BH7,0)*100 -> 0 | BQ7: 0.055702457 | BR7: 0.069434031 | BS7: 0.50713131 | BT7: 0.48224196 | BU7: 0.67434715 | BV7: 0.77055495 | BW7: 0.29309353 | BX7: 0.40447901 | BY7: 0.56551534 | BZ7: 0.56526797 | CA7: 1 | CB7: 1 | CC7: 0.29255561 | CD7: 0.40330034 | CE7: 0.56487696 | CF7: 0.56396139 | CG7: 1 | CH7: 1 | CI7: 0 | CJ7: 0 | CK7: 0 | CL7: =IF(CM7=0,"FALSE","TRUE") -> FALSE | CM7: 0
A8: California | B8: 226073.17 | C8: =B8/1000 -> 226.07317 | D8: 94891488 | E8: 80377638 | F8: =IFERROR(($E8/$D8) - 1, 0) -> -0.15295208 | G8: 674638 | H8: 1233980 | I8: =IFERROR(($H8/$G8)-1,0) -> 0.82909946 | J8: 18070.645 | K8: 6576.0776 | L8: 8643.2557 | M8: 0 | N8: 3950 | O8: 2000 | P8: 30 | Q8: 0 | R8: 100 | S8: 0 | T8: 0 | U8: 18862.7 | V8: 2240 | W8: 10216.4 | X8: 6135.9 | Y8: 11262.7 | Z8: 1284 | AA8: 822.7 | AB8: 1836.2 | AC8: 291.3 | AD8: 15301.1 | AE8: 0 | AF8: 0 | AG8: 0 | AH8: 0 | AI8: 47.9 | AJ8: 0.314441 | AK8: 0.527733 | AL8: 0.879554 | AM8: 1 | AN8: 2500 | AO8: 0 | AP8: 34185 | AQ8: 38889770 | AR8: =$AP8/($AQ8/100000) -> 87.902294 | AS8: 923291590000000 | AT8: 0 | AU8: 187227182553239 | AV8: 743523232912676 | AW8: 234216731265149 | AX8: 0 | AY8: 738063389239436 | AZ8: 1.7890784e+15 | BA8: 978420092120629 | BB8: 0 | BC8: 182392553336683 | BD8: 660411632774181 | BE8: 148935435371110 | BF8: 206666891944876 | BG8: 864961552577066 | BH8: 2.0435819e+15 | BI8: =IFERROR($AS8/$BA8,0)*100 -> 94.365559 | BJ8: =IFERROR($AT8/$BB8,0)*100 -> 0 | BK8: =IFERROR($AU8/$BC8,0)*100 -> 102.65067 | BL8: =IFERROR($AV8/$BD8,0)*100 -> 112.58482 | BM8: =IFERROR($AW8/$BE8,0)*100 -> 157.26058 | BN8: =IFERROR($AX8/$BF8,0)*100 -> 0 | BO8: =IFERROR($AY8/$BG8,0)*100 -> 85.32904 | BP8: =IFERROR($AZ8/$BH8,0)*100 -> 87.546206 | BQ8: 0.094714495 | BR8: 0.10006029 | BS8: 0.3919081 | BT8: 0.37080992 | BU8: 0.57072796 | BV8: 0.68511781 | BW8: 0.13396842 | BX8: 0.22272941 | BY8: 0.30757767 | BZ8: 0.32534459 | CA8: 1 | CB8: 1 | CC8: 0.13165796 | CD8: 0.21690919 | CE8: 0.30332175 | CF8: 0.31731581 | CG8: 1 | CH8: 1 | CI8: 1 | CJ8: 1 | CK8: 1 | CL8: =IF(CM8=0,"FALSE","TRUE") -> FALSE | CM8: 0
A9: Colorado | B9: 219494.69 | C9: =B9/1000 -> 219.49469 | D9: 2807326 | E9: 2791384 | F9: =IFERROR(($E9/$D9) - 1, 0) -> -0.0056787135 | G9: 3200 | H9: 0 | I9: =IFERROR(($H9/$G9)-1,0) -> -1 | J9: 2693.1729 | K9: 980.07093 | L9: 1288.1545 | M9: 3300 | N9: 300 | O9: 0 | P9: 0 | Q9: 0 | R9: 150 | S9: 0 | T9: 4337 | U9: 3218.5 | V9: 0 | W9: 680.3 | X9: 3750.3 | Y9: 591 | Z9: 0 | AA9: 28.7 | AB9: 0 | AC9: 164 | AD9: 3171.8 | AE9: 0 | AF9: 0 | AG9: 0 | AH9: 0 | AI9: 0 | AJ9: 0.272718 | AK9: 0.359345 | AL9: 0.551847 | AM9: 1 | AN9: 2400 | AO9: 4000 | AP9: 3355 | AQ9: 5914181 | AR9: =$AP9/($AQ9/100000) -> 56.728058 | AS9: 1.0862254e+15 | AT9: 95209854964974 | AU9: 0 | AV9: 0 | AW9: 142219417683423 | AX9: 1.252779e+15 | AY9: 0 | AZ9: 0 | BA9: 1.1510825e+15 | BB9: 265058383448991 | BC9: 4.538325e+12 | BD9: 1.1064715e+13 | BE9: 151828806635462 | BF9: 2.0281277e+15 | BG9: 7.1994376e+13 | BH9: 91827852515001 | BI9: =IFERROR($AS9/$BA9,0)*100 -> 94.365559 | BJ9: =IFERROR($AT9/$BB9,0)*100 -> 35.920333 | BK9: =IFERROR($AU9/$BC9,0)*100 -> 0 | BL9: =IFERROR($AV9/$BD9,0)*100 -> 0 | BM9: =IFERROR($AW9/$BE9,0)*100 -> 93.670905 | BN9: =IFERROR($AX9/$BF9,0)*100 -> 61.770222 | BO9: =IFERROR($AY9/$BG9,0)*100 -> 0 | BP9: =IFERROR($AZ9/$BH9,0)*100 -> 0 | BQ9: 0.0474998 | BR9: 0.052728436 | BS9: 0.42961482 | BT9: 0.40757345 | BU9: 0.63551482 | BV9: 0.74097401 | BW9: 0.091777266 | BX9: 0.12816516 | BY9: 0.33922669 | BZ9: 0.34832921 | CA9: 1 | CB9: 1 | CC9: 0.091731581 | CD9: 0.12795608 | CE9: 0.33910381 | CF9: 0.34790879 | CG9: 1 | CH9: 1 | CI9: 1 | CJ9: 0.82 | CK9: 1 | CL9: =IF(CM9=0,"FALSE","TRUE") -> FALSE | CM9: 0
A10: Connecticut | B10: 3467.3276 | C10: =B10/1000 -> 3.4673276 | D10: 3587296 | E10: 73555 | F10: =IFERROR(($E10/$D10) - 1, 0) -> -0.9794957 | G10: 171332 | H10: 13974993 | I10: =IFERROR(($H10/$G10)-1,0) -> 80.566742 | J10: 1855.0622 | K10: 675.07456 | L10: 887.28302 | M10: 0 | N10: 0 | O10: 0 | P10: 0 | Q10: 0 | R10: 50 | S10: 0 | T10: 383.4 | U10: 3918.4 | V10: 2073.1 | W10: 119.4 | X10: 1 | Y10: 132.3 | Z10: 0 | AA10: 39.9 | AB10: 0 | AC10: 1051.6 | AD10: 1287.7 | AE10: 0 | AF10: 0 | AG10: 0 | AH10: 0 | AI10: 160 | AJ10: 0.706409 | AK10: 0.881409 | AL10: 0.691409 | AM10: 0 | AN10: 2250 | AO10: 0 | AP10: 1216 | AQ10: 3625646 | AR10: =$AP10/($AQ10/100000) -> 33.538851 | AS10: 0 | AT10: 0 | AU10: 0 | AV10: 0 | AW10: 0 | AX10: 0 | AY10: 0 | AZ10: 0 | BA10: 0 | BB10: 0 | BC10: 0 | BD10: 0 | BE10: 0 | BF10: 0 | BG10: 0 | BH10: 0 | BI10: =IFERROR($AS10/$BA10,0)*100 -> 0 | BJ10: =IFERROR($AT10/$BB10,0)*100 -> 0 | BK10: =IFERROR($AU10/$BC10,0)*100 -> 0 | BL10: =IFERROR($AV10/$BD10,0)*100 -> 0 | BM10: =IFERROR($AW10/$BE10,0)*100 -> 0 | BN10: =IFERROR($AX10/$BF10,0)*100 -> 0 | BO10: =IFERROR($AY10/$BG10,0)*100 -> 0 | BP10: =IFERROR($AZ10/$BH10,0)*100 -> 0 | BQ10: 0.018606316 | BR10: 0.018449311 | BS10: 0.44621209 | BT10: 0.40396345 | BU10: 0.504728 | BV10: 0.62794653 | BW10: 0.063885483 | BX10: 0.12517229 | BY10: 0.42339738 | BZ10: 0.42646896 | CA10: 1 | CB10: 1 | CC10: 0.063509105 | CD10: 0.12403025 | CE10: 0.42185745 | CF10: 0.42271742 | CG10: 1 | CH10: 1 | CI10: 1 | CJ10: 0 | CK10: 0 | CL10: =IF(CM10=0,"FALSE","TRUE") -> TRUE | CM10: 55.15
A11: DC | B11: 0 | C11: =B11/1000 -> 0 | T11: 0 | U11: 0 | V11: 0 | W11: 0 | X11: 0 | Y11: 6.9 | Z11: 0 | AA11: 0 | AB11: 0 | AC11: 0 | AD11: 0 | AE11: 0 | AF11: 0 | AG11: 0 | AH11: 0 | AI11: 0 | AJ11: 0 | AK11: 0 | AL11: 0 | AP11: 671 | AQ11: 686995 | AR11: =$AP11/($AQ11/100000) -> 97.671744 | AS11: 0 | AT11: 0 | AU11: 0 | AV11: 0 | AW11: 0 | AX11: 0 | AY11: 0 | AZ11: 0 | BA11: 0 | BB11: 0 | BC11: 0 | BD11: 0 | BE11: 0 | BF11: 0 | BG11: 0 | BH11: 0 | BI11: =IFERROR($AS11/$BA11,0)*100 -> 0 | BJ11: =IFERROR($AT11/$BB11,0)*100 -> 0 | BK11: =IFERROR($AU11/$BC11,0)*100 -> 0 | BL11: =IFERROR($AV11/$BD11,0)*100 -> 0 | BM11: =IFERROR($AW11/$BE11,0)*100 -> 0 | BN11: =IFERROR($AX11/$BF11,0)*100 -> 0 | BO11: =IFERROR($AY11/$BG11,0)*100 -> 0 | BP11: =IFERROR($AZ11/$BH11,0)*100 -> 0 | CI11: 0 | CJ11: 0.82 | CK11: 0 | CL11: =IF(CM11=0,"FALSE","TRUE") -> TRUE | CM11: -
A12: Delaware | B12: 3008.4827 | C12: =B12/1000 -> 3.0084827 | D12: 5877137 | E12: 8705706 | F12: =IFERROR(($E12/$D12) - 1, 0) -> 0.48128349 | G12: 0 | H12: 0 | I12: =IFERROR(($H12/$G12)-1,0) -> 0 | J12: 932.6865 | K12: 339.41338 | L12: 446.10737 | M12: 400 | N12: 0 | O12: 0 | P12: 3 | Q12: 0 | R12: 0 | S12: 0 | T12: 410 | U12: 1504 | V12: 0 | W12: 0 | X12: 0 | Y12: 36.2 | Z12: 0 | AA12: 10 | AB12: 0 | AC12: 158.5 | AD12: 955.1 | AE12: 0 | AF12: 0 | AG12: 0 | AH12: 0 | AI12: 0 | AJ12: 0.21 | AK12: 0.25 | AL12: 0.25 | AM12: 0 | AN12: 2500 | AO12: 0 | AP12: 271 | AQ12: 1044321 | AR12: =$AP12/($AQ12/100000) -> 25.949876 | AS12: 0 | AT12: 0 | AU12: 2.5133446e+13 | AV12: 1.531958e+13 | AW12: 183018339214898 | AX12: 0 | AY12: 4.5438136e+13 | AZ12: 750891694849213 | BA12: 0 | BB12: 0 | BC12: 1.1994643e+13 | BD12: 3.2343627e+13 | BE12: 184631397161521 | BF12: 0 | BG12: 9.2424026e+13 | BH12: 943745297152327 | BI12: =IFERROR($AS12/$BA12,0)*100 -> 0 | BJ12: =IFERROR($AT12/$BB12,0)*100 -> 0 | BK12: =IFERROR($AU12/$BC12,0)*100 -> 209.53893 | BL12: =IFERROR($AV12/$BD12,0)*100 -> 47.365066 | BM12: =IFERROR($AW12/$BE12,0)*100 -> 99.126336 | BN12: =IFERROR($AX12/$BF12,0)*100 -> 0 | BO12: =IFERROR($AY12/$BG12,0)*100 -> 49.162688 | BP12: =IFERROR($AZ12/$BH12,0)*100 -> 79.565079 | BQ12: 0.044924605 | BR12: 0.050296835 | BS12: 0.34603107 | BT12: 0.31305396 | BU12: 0.52940701 | BV12: 0.64967905 | BW12: 0.1967287 | BX12: 0.27794117 | BY12: 0.57780218 | BZ12: 0.57720661 | CA12: 1 | CB12: 1 | CC12: 0.19652808 | CD12: 0.2769098 | CE12: 0.57749233 | CF12: 0.57608393 | CG12: 1 | CH12: 1 | CI12: 0 | CJ12: 1 | CK12: 0 | CL12: =IF(CM12=0,"FALSE","TRUE") -> TRUE | CM12: 25
A13: Florida | B13: 99253.471 | C13: =B13/1000 -> 99.253471 | D13: 28820791 | E13: 13186727 | F13: =IFERROR(($E13/$D13) - 1, 0) -> -0.54245784 | G13: 0 | H13: 0 | I13: =IFERROR(($H13/$G13)-1,0) -> 0 | J13: 9413.5042 | K13: 3425.6626 | L13: 4502.5135 | M13: 2100 | N13: 0 | O13: 0 | P13: 21 | Q13: 0 | R13: 500 | S13: 0 | T13: 7782 | U13: 31717.2 | V13: 3626 | W13: 43.5 | X13: 0 | Y13: 2134.6 | Z13: 0 | AA13: 291.8 | AB13: 0 | AC13: 3296.6 | AD13: 10128.2 | AE13: 0 | AF13: 0 | AG13: 0 | AH13: 0 | AI13: 482.2 | AJ13: 0.127695 | AK13: 0.127695 | AL13: 0.127695 | AM13: 0 | AN13: 0 | AO13: 0 | AP13: 5644 | AQ13: 22975931 | AR13: =$AP13/($AQ13/100000) -> 24.564837 | AS13: 10444475000000 | AT13: 0 | AU13: 0 | AV13: 0 | AW13: 0 | AX13: 0 | AY13: 0 | AZ13: 0 | BA13: 1.1068101e+13 | BB13: 0 | BC13: 0 | BD13: 0 | BE13: 0 | BF13: 5.1209573e+11 | BG13: 0 | BH13: 0 | BI13: =IFERROR($AS13/$BA13,0)*100 -> 94.365559 | BJ13: =IFERROR($AT13/$BB13,0)*100 -> 0 | BK13: =IFERROR($AU13/$BC13,0)*100 -> 0 | BL13: =IFERROR($AV13/$BD13,0)*100 -> 0 | BM13: =IFERROR($AW13/$BE13,0)*100 -> 0 | BN13: =IFERROR($AX13/$BF13,0)*100 -> 0 | BO13: =IFERROR($AY13/$BG13,0)*100 -> 0 | BP13: =IFERROR($AZ13/$BH13,0)*100 -> 0 | BQ13: 0.047655825 | BR13: 0.050352665 | BS13: 0.62784484 | BT13: 0.59516608 | BU13: 0.67586842 | BV13: 0.77121589 | BW13: 0.66470591 | BX13: 0.76887318 | BY13: 0.88980166 | BZ13: 0.89265522 | CA13: 1 | CB13: 1 | CC13: 0.66481587 | CD13: 0.76973149 | CE13: 0.88985004 | CF13: 0.89311245 | CG13: 1 | CH13: 1 | CI13: 0 | CJ13: 0 | CK13: 0 | CL13: =IF(CM13=0,"FALSE","TRUE") -> FALSE | CM13: 0
A14: Georgia | B14: 122035.67 | C14: =B14/1000 -> 122.03567 | D14: 14025574 | E14: 25641906 | F14: =IFERROR(($E14/$D14) - 1, 0) -> 0.82822507 | G14: 0 | H14: 0 | I14: =IFERROR(($H14/$G14)-1,0) -> 0 | J14: 5597.116 | K14: 2036.8431 | L14: 2677.1211 | M14: 2650 | N14: 0 | O14: 0 | P14: 0 | Q14: 0 | R14: 0 | S14: 0 | T14: 8416 | U14: 8009.5 | V14: 4061 | W14: 2025.9 | X14: 0 | Y14: 1510.2 | Z14: 0 | AA14: 288.7 | AB14: 0 | AC14: 852.2 | AD14: 8439.3 | AE14: 0 | AF14: 0 | AG14: 0 | AH14: 0 | AI14: 0 | AJ14: 0.302841 | AK14: 0.302841 | AL14: 0.302841 | AM14: 0 | AN14: 0 | AO14: 0 | AP14: 3754 | AQ14: 11145304 | AR14: =$AP14/($AQ14/100000) -> 33.682347 | AS14: 0 | AT14: 0 | AU14: 0 | AV14: 0 | AW14: 0 | AX14: 0 | AY14: 0 | AZ14: 0 | BA14: 0 | BB14: 0 | BC14: 0 | BD14: 0 | BE14: 0 | BF14: 0 | BG14: 0 | BH14: 0 | BI14: =IFERROR($AS14/$BA14,0)*100 -> 0 | BJ14: =IFERROR($AT14/$BB14,0)*100 -> 0 | BK14: =IFERROR($AU14/$BC14,0)*100 -> 0 | BL14: =IFERROR($AV14/$BD14,0)*100 -> 0 | BM14: =IFERROR($AW14/$BE14,0)*100 -> 0 | BN14: =IFERROR($AX14/$BF14,0)*100 -> 0 | BO14: =IFERROR($AY14/$BG14,0)*100 -> 0 | BP14: =IFERROR($AZ14/$BH14,0)*100 -> 0 | BQ14: 0.084643674 | BR14: 0.089127144 | BS14: 0.58201812 | BT14: 0.54521744 | BU14: 0.6890723 | BV14: 0.78281016 | BW14: 0.21972716 | BX14: 0.28262391 | BY14: 0.54077375 | BZ14: 0.52821562 | CA14: 1 | CB14: 1 | CC14: 0.21971476 | CD14: 0.28221683 | CE14: 0.54075578 | CF14: 0.52776245 | CG14: 1 | CH14: 1 | CI14: 0 | CJ14: 0 | CK14: 0 | CL14: =IF(CM14=0,"FALSE","TRUE") -> FALSE | CM14: 0
A15: Hawaii | B15: 0 | C15: =B15/1000 -> 0 | D15: 0 | E15: 0 | F15: =IFERROR(($E15/$D15) - 1, 0) -> 0 | G15: 0 | H15: 0 | I15: =IFERROR(($H15/$G15)-1,0) -> 0 | J15: 450.27921 | K15: 163.86084 | L15: 215.3702 | M15: 0 | N15: 0 | O15: 0 | P15: 0 | Q15: 0 | R15: 0 | S15: 0 | T15: 180 | U15: 0 | V15: 0 | W15: 13.9 | X15: 205.6 | Y15: 267.7 | Z15: 0 | AA15: 67.9 | AB15: 43 | AC15: 1957.5 | AD15: 0 | AE15: 0 | AF15: 0 | AG15: 0 | AH15: 0 | AI15: 0 | AJ15: 0.322521 | AK15: 0.412521 | AL15: 1 | AM15: 1 | AN15: 0 | AO15: 0 | AP15: 751 | AQ15: 1430877 | AR15: =$AP15/($AQ15/100000) -> 52.485294 | AS15: 0 | AT15: 0 | AU15: 1.4053321e+13 | AV15: 5.544062e+13 | AW15: 0 | AX15: 0 | AY15: 0 | AZ15: 9.7878226e+13 | BA15: 0 | BB15: 0 | BC15: 1.317481e+13 | BD15: 47703688074261 | BE15: 1.0758093e+13 | BF15: 0 | BG15: 6.2478997e+13 | BH15: 147614590883634 | BI15: =IFERROR($AS15/$BA15,0)*100 -> 0 | BJ15: =IFERROR($AT15/$BB15,0)*100 -> 0 | BK15: =IFERROR($AU15/$BC15,0)*100 -> 106.66811 | BL15: =IFERROR($AV15/$BD15,0)*100 -> 116.21873 | BM15: =IFERROR($AW15/$BE15,0)*100 -> 0 | BN15: =IFERROR($AX15/$BF15,0)*100 -> 0 | BO15: =IFERROR($AY15/$BG15,0)*100 -> 0 | BP15: =IFERROR($AZ15/$BH15,0)*100 -> 66.306606 | BQ15: 0.00029999707 | BR15: 0.00040906166 | BS15: 0.56046022 | BT15: 0.52769477 | BU15: 0.50598866 | BV15: 0.61934886 | BW15: 0.62782514 | BX15: 0.74531223 | BY15: 0.72788754 | BZ15: 0.72518806 | CA15: 1 | CB15: 1 | CC15: 0.62782514 | CD15: 0.74531223 | CE15: 0.72788754 | CF15: 0.72518806 | CG15: 1 | CH15: 1 | CI15: 0 | CJ15: 0 | CK15: 0 | CL15: =IF(CM15=0,"FALSE","TRUE") -> FALSE | CM15: 0
A16: Iowa | B16: 64827.356 | C16: =B16/1000 -> 64.827356 | D16: 0 | E16: 24480 | F16: =IFERROR(($E16/$D16) - 1, 0) -> 0 | G16: 2933106 | H16: 9314891 | I16: =IFERROR(($H16/$G16)-1,0) -> 2.1757771 | J16: 7193.6429 | K16: 2617.8342 | L16: 3440.7457 | M16: 50 | N16: 0 | O16: 0 | P16: 0 | Q16: 0 | R16: 50 | S16: 0 | T16: 4849.7 | U16: 1781 | V16: 601.4 | W16: 146.4 | X16: 9783 | Y16: 13.4 | Z16: 0 | AA16: 16.2 | AB16: 0 | AC16: 779.6 | AD16: 1683.7 | AE16: 0 | AF16: 0 | AG16: 0 | AH16: 0 | AI16: 0 | AJ16: 0.014583 | AK16: 0.014583 | AL16: 0.014583 | AM16: 0 | AN16: 0 | AO16: 0 | AP16: 523 | AQ16: 3214315 | AR16: =$AP16/($AQ16/100000) -> 16.270963 | AS16: 0 | AT16: 0 | AU16: 0 | AV16: 0 | AW16: 0 | AX16: 0 | AY16: 0 | AZ16: 0 | BA16: 0 | BB16: 0 | BC16: 0 | BD16: 0 | BE16: 0 | BF16: 0 | BG16: 0 | BH16: 0 | BI16: =IFERROR($AS16/$BA16,0)*100 -> 0 | BJ16: =IFERROR($AT16/$BB16,0)*100 -> 0 | BK16: =IFERROR($AU16/$BC16,0)*100 -> 0 | BL16: =IFERROR($AV16/$BD16,0)*100 -> 0 | BM16: =IFERROR($AW16/$BE16,0)*100 -> 0 | BN16: =IFERROR($AX16/$BF16,0)*100 -> 0 | BO16: =IFERROR($AY16/$BG16,0)*100 -> 0 | BP16: =IFERROR($AZ16/$BH16,0)*100 -> 0 | BQ16: 0.034373216 | BR16: 0.038052461 | BS16: 0.39824131 | BT16: 0.3784332 | BU16: 0.55306069 | BV16: 0.67777046 | BW16: 0.099086115 | BX16: 0.136848 | BY16: 0.39964564 | BZ16: 0.39779268 | CA16: 1 | CB16: 1 | CC16: 0.099073291 | CD16: 0.13664637 | CE16: 0.39961117 | CF16: 0.39731573 | CG16: 1 | CH16: 1 | CI16: 0 | CJ16: 0 | CK16: 0 | CL16: =IF(CM16=0,"FALSE","TRUE") -> FALSE | CM16: 0
A17: Idaho | B17: 199705.75 | C17: =B17/1000 -> 199.70575 | D17: 14467241 | E17: 10428327 | F17: =IFERROR(($E17/$D17) - 1, 0) -> -0.27917652 | G17: 88678 | H17: 0 | I17: =IFERROR(($H17/$G17)-1,0) -> -1 | J17: 1449.6371 | K17: 527.53656 | L17: 693.36673 | M17: 0 | N17: 0 | O17: 0 | P17: 0 | Q17: 0 | R17: 0 | S17: 0 | T17: 0 | U17: 547.7 | V17: 0 | W17: 2764.2 | X17: 970.4 | Y17: 240 | Z17: 0 | AA17: 26.4 | AB17: 10 | AC17: 5.4 | AD17: 547.4 | AE17: 0 | AF17: 0 | AG17: 0 | AH17: 0 | AI17: 0 | AJ17: 0.474875 | AK17: 0.474875 | AL17: 0.474875 | AM17: 0 | AN17: 0 | AO17: 0 | AP17: 260 | AQ17: 1990456 | AR17: =$AP17/($AQ17/100000) -> 13.062333 | AS17: 0 | AT17: 0 | AU17: 0 | AV17: 0 | AW17: 0 | AX17: 0 | AY17: 0 | AZ17: 0 | BA17: 0 | BB17: 0 | BC17: 0 | BD17: 0 | BE17: 0 | BF17: 1.083533e+12 | BG17: 0 | BH17: 0 | BI17: =IFERROR($AS17/$BA17,0)*100 -> 0 | BJ17: =IFERROR($AT17/$BB17,0)*100 -> 0 | BK17: =IFERROR($AU17/$BC17,0)*100 -> 0 | BL17: =IFERROR($AV17/$BD17,0)*100 -> 0 | BM17: =IFERROR($AW17/$BE17,0)*100 -> 0 | BN17: =IFERROR($AX17/$BF17,0)*100 -> 0 | BO17: =IFERROR($AY17/$BG17,0)*100 -> 0 | BP17: =IFERROR($AZ17/$BH17,0)*100 -> 0 | BQ17: 0.039382038 | BR17: 0.042626526 | BS17: 0.4131226 | BT17: 0.3863852 | BU17: 0.62733718 | BV17: 0.73139706 | BW17: 0.11809843 | BX17: 0.14990162 | BY17: 0.49445256 | BZ17: 0.50242416 | CA17: 1 | CB17: 1 | CC17: 0.11800171 | CD17: 0.14912561 | CE17: 0.49422033 | CF17: 0.50092122 | CG17: 1 | CH17: 1 | CI17: 0 | CJ17: 0 | CK17: 0 | CL17: =IF(CM17=0,"FALSE","TRUE") -> FALSE | CM17: 0
A18: Illinois | B18: 68672.635 | C18: =B18/1000 -> 68.672635 | D18: 52802 | E18: 0 | F18: =IFERROR(($E18/$D18) - 1, 0) -> -1 | G18: 40457236 | H18: 34602295 | I18: =IFERROR(($H18/$G18)-1,0) -> -0.14471925 | J18: 9458.5315 | K18: 3442.0485 | L18: 4524.0503 | M18: 6400 | N18: 3550 | O18: 0 | P18: 0 | Q18: 0 | R18: 10700 | S18: 0 | T18: 10173.5 | U18: 3574 | V18: 11582.4 | W18: 32.9 | X18: 5229.3 | Y18: 41.8 | Z18: 0 | AA18: 88.2 | AB18: 0 | AC18: 658.9 | AD18: 11891.5 | AE18: 0 | AF18: 0 | AG18: 0 | AH18: 0 | AI18: 0 | AJ18: 0.709708 | AK18: 0.934708 | AL18: 1 | AM18: 1 | AN18: 0 | AO18: 0 | AP18: 2251 | AQ18: 12516863 | AR18: =$AP18/($AQ18/100000) -> 17.983739 | AS18: 48044585000000 | AT18: 462623653961154 | AU18: 1.659928e+13 | AV18: 111072071198079 | AW18: 624173403723381 | AX18: 0 | AY18: 511714473125996 | AZ18: 1.0363863e+15 | BA18: 5.0913263e+13 | BB18: 944481216942459 | BC18: 2.6993932e+13 | BD18: 151701502758254 | BE18: 613024925192508 | BF18: 2.3868496e+12 | BG18: 639364826547338 | BH18: 1.2676881e+15 | BI18: =IFERROR($AS18/$BA18,0)*100 -> 94.365559 | BJ18: =IFERROR($AT18/$BB18,0)*100 -> 48.981774 | BK18: =IFERROR($AU18/$BC18,0)*100 -> 61.492634 | BL18: =IFERROR($AV18/$BD18,0)*100 -> 73.217515 | BM18: =IFERROR($AW18/$BE18,0)*100 -> 101.8186 | BN18: =IFERROR($AX18/$BF18,0)*100 -> 0 | BO18: =IFERROR($AY18/$BG18,0)*100 -> 80.034818 | BP18: =IFERROR($AZ18/$BH18,0)*100 -> 81.754039 | BQ18: 0.025383592 | BR18: 0.02931316 | BS18: 0.32912647 | BT18: 0.30062602 | BU18: 0.6012365 | BV18: 0.7148189 | BW18: 0.075302592 | BX18: 0.11178244 | BY18: 0.2959006 | BZ18: 0.29281164 | CA18: 1 | CB18: 1 | CC18: 0.075282061 | CD18: 0.11114284 | CE18: 0.29583917 | CF18: 0.2912788 | CG18: 1 | CH18: 1 | CI18: 0 | CJ18: 0 | CK18: 0 | CL18: =IF(CM18=0,"FALSE","TRUE") -> FALSE | CM18: 0
A19: Indiana | B19: 87980.974 | C19: =B19/1000 -> 87.980974 | D19: 22719 | E19: 18310966 | F19: =IFERROR(($E19/$D19) - 1, 0) -> 804.97588 | G19: 6444160 | H19: 0 | I19: =IFERROR(($H19/$G19)-1,0) -> -1 | J19: 8251.2962 | K19: 3002.7242 | L19: 3946.6252 | M19: 8500 | N19: 0 | O19: 0 | P19: 0 | Q19: 0 | R19: 250 | S19: 0 | T19: 15229.3 | U19: 3866 | V19: 0 | W19: 66.2 | X19: 2308.8 | Y19: 243.5 | Z19: 0 | AA19: 55.4 | AB19: 0 | AC19: 71.7 | AD19: 3867.2 | AE19: 0 | AF19: 0 | AG19: 0 | AH19: 0 | AI19: 0 | AJ19: 0.08411 | AK19: 0.10411 | AL19: 0.10411 | AM19: 0 | AN19: 0 | AO19: 0 | AP19: 830 | AQ19: 6892124 | AR19: =$AP19/($AQ19/100000) -> 12.042732 | AS19: 8355580000000 | AT19: 141831090611445 | AU19: 1.1670545e+12 | AV19: 2.9795523e+13 | AW19: 266052687154763 | AX19: 0 | AY19: 166717292717333 | AZ19: 357201001547554 | BA19: 8.8544805e+12 | BB19: 650047091793914 | BC19: 1.1667961e+13 | BD19: 65572041405239 | BE19: 264976253011965 | BF19: 5.5429418e+12 | BG19: 276361513347857 | BH19: 547950399312461 | BI19: =IFERROR($AS19/$BA19,0)*100 -> 94.365559 | BJ19: =IFERROR($AT19/$BB19,0)*100 -> 21.818587 | BK19: =IFERROR($AU19/$BC19,0)*100 -> 10.002214 | BL19: =IFERROR($AV19/$BD19,0)*100 -> 45.439371 | BM19: =IFERROR($AW19/$BE19,0)*100 -> 100.40624 | BN19: =IFERROR($AX19/$BF19,0)*100 -> 0 | BO19: =IFERROR($AY19/$BG19,0)*100 -> 60.3258 | BP19: =IFERROR($AZ19/$BH19,0)*100 -> 65.188565 | BQ19: 0.026354643 | BR19: 0.033307416 | BS19: 0.35992151 | BT19: 0.34616493 | BU19: 0.60958835 | BV19: 0.73096953 | BW19: 0.12944088 | BX19: 0.18336619 | BY19: 0.44888059 | BZ19: 0.44714468 | CA19: 1 | CB19: 1 | CC19: 0.12941922 | CD19: 0.18288614 | CE19: 0.44883303 | CF19: 0.4462422 | CG19: 1 | CH19: 1 | CI19: 0 | CJ19: 0 | CK19: 0 | CL19: =IF(CM19=0,"FALSE","TRUE") -> FALSE | CM19: 0
A20: Kansas | B20: 53004.202 | C20: =B20/1000 -> 53.004202 | D20: 0 | E20: 0 | F20: =IFERROR(($E20/$D20) - 1, 0) -> 0 | G20: 3597275 | H20: 13717698 | I20: =IFERROR(($H20/$G20)-1,0) -> 2.8133582 | J20: 2519.0892 | K20: 916.72022 | L20: 1204.8896 | M20: 3600 | N20: 150 | O20: 0 | P20: 0 | Q20: 0 | R20: 0 | S20: 0 | T20: 4678.5 | U20: 266 | V20: 1225 | W20: 7 | X20: 6129.4 | Y20: 10.2 | Z20: 0 | AA20: 9 | AB20: 0 | AC20: 557.9 | AD20: 3279 | AE20: 0 | AF20: 0 | AG20: 0 | AH20: 0 | AI20: 0 | AJ20: 0.151944 | AK20: 0.151944 | AL20: 0.151944 | AM20: 0 | AN20: 0 | AO20: 0 | AP20: 937 | AQ20: 2944376 | AR20: =$AP20/($AQ20/100000) -> 31.823381 | AS20: 190089445000000 | AT20: 0 | AU20: 0 | AV20: 2.1199977e+13 | AW20: 228178989121794 | AX20: 0 | AY20: 130231497764670 | AZ20: 285372548061551 | BA20: 201439430730717 | BB20: 0 | BC20: 1.0047136e+13 | BD20: 5.6463266e+13 | BE20: 228167742079547 | BF20: 184196219160670 | BG20: 237971447559943 | BH20: 471833245287323 | BI20: =IFERROR($AS20/$BA20,0)*100 -> 94.365559 | BJ20: =IFERROR($AT20/$BB20,0)*100 -> 0 | BK20: =IFERROR($AU20/$BC20,0)*100 -> 0 | BL20: =IFERROR($AV20/$BD20,0)*100 -> 37.546494 | BM20: =IFERROR($AW20/$BE20,0)*100 -> 100.00493 | BN20: =IFERROR($AX20/$BF20,0)*100 -> 0 | BO20: =IFERROR($AY20/$BG20,0)*100 -> 54.725682 | BP20: =IFERROR($AZ20/$BH20,0)*100 -> 60.481653 | BQ20: 0.049619555 | BR20: 0.058474483 | BS20: 0.46009995 | BT20: 0.42909386 | BU20: 0.63027476 | BV20: 0.73838938 | BW20: 0.10797167 | BX20: 0.16465647 | BY20: 0.36095743 | BZ20: 0.37126915 | CA20: 1 | CB20: 1 | CC20: 0.10792 | CD20: 0.16343278 | CE20: 0.36083366 | CF20: 0.36887116 | CG20: 1 | CH20: 1 | CI20: 0 | CJ20: 0 | CK20: 0 | CL20: =IF(CM20=0,"FALSE","TRUE") -> FALSE | CM20: 0
A21: Kentucky | B21: 0 | C21: =B21/1000 -> 0 | D21: 3102595 | E21: 9143236 | F21: =IFERROR(($E21/$D21) - 1, 0) -> 1.9469641 | G21: 0 | H21: 0 | I21: =IFERROR(($H21/$G21)-1,0) -> 0 | J21: 3169.2896 | K21: 1153.3343 | L21: 1515.8828 | M21: 6100 | N21: 0 | O21: 0 | P21: 0 | Q21: 0 | R21: 0 | S21: 0 | T21: 11281.8 | U21: 1763 | V21: 0 | W21: 1146.9 | X21: 0 | Y21: 26.1 | Z21: 0 | AA21: 22.3 | AB21: 0 | AC21: 11.9 | AD21: 5168.2 | AE21: 0 | AF21: 0 | AG21: 0 | AH21: 0 | AI21: 0 | AJ21: 0.069755 | AK21: 0.069755 | AL21: 0.069755 | AM21: 0 | AN21: 0 | AO21: 0 | AP21: 399 | AQ21: 4540745 | AR21: =$AP21/($AQ21/100000) -> 8.7871043 | AS21: 14622265000000 | AT21: 323564250382524 | AU21: 0 | AV21: 7.1237827e+12 | AW21: 166156465278814 | AX21: 0 | AY21: 7.0481824e+13 | AZ21: 167745218270253 | BA21: 1.5495341e+13 | BB21: 741647685808990 | BC21: 7.3928479e+12 | BD21: 4.1546601e+13 | BE21: 167889584268201 | BF21: 7.9985837e+13 | BG21: 175103312301754 | BH21: 347182676539735 | BI21: =IFERROR($AS21/$BA21,0)*100 -> 94.365559 | BJ21: =IFERROR($AT21/$BB21,0)*100 -> 43.627757 | BK21: =IFERROR($AU21/$BC21,0)*100 -> 0 | BL21: =IFERROR($AV21/$BD21,0)*100 -> 17.146487 | BM21: =IFERROR($AW21/$BE21,0)*100 -> 98.967703 | BN21: =IFERROR($AX21/$BF21,0)*100 -> 0 | BO21: =IFERROR($AY21/$BG21,0)*100 -> 40.251565 | BP21: =IFERROR($AZ21/$BH21,0)*100 -> 48.316126 | BQ21: 0.0779703 | BR21: 0.09322195 | BS21: 0.52150137 | BT21: 0.4876177 | BU21: 0.65922724 | BV21: 0.76005646 | BW21: 0.22413671 | BX21: 0.30629535 | BY21: 0.62391055 | BZ21: 0.62721264 | CA21: 1 | CB21: 1 | CC21: 0.22413833 | CD21: 0.30651882 | CE21: 0.62391273 | CF21: 0.62745771 | CG21: 1 | CH21: 1 | CI21: 0 | CJ21: 0 | CK21: 0 | CL21: =IF(CM21=0,"FALSE","TRUE") -> FALSE | CM21: 0
A22: Louisiana | B22: 73514.235 | C22: =B22/1000 -> 73.514235 | D22: 11978785 | E22: 24913874 | F22: =IFERROR(($E22/$D22) - 1, 0) -> 1.0798331 | G22: 0 | H22: 0 | I22: =IFERROR(($H22/$G22)-1,0) -> 0 | J22: 9282.5548 | K22: 3378.0089 | L22: 4439.88 | M22: 550 | N22: 1500 | O22: 0 | P22: 0 | Q22: 0 | R22: 0 | S22: 0 | T22: 2191.8 | U22: 6052.9 | V22: 2132.9 | W22: 192 | X22: 0 | Y22: 1.1 | Z22: 0 | AA22: 11.1 | AB22: 0 | AC22: 854.7 | AD22: 7230.8 | AE22: 645.3 | AF22: 0 | AG22: 0 | AH22: 0 | AI22: 0 | AJ22: 0.185968 | AK22: 0.185968 | AL22: 0.185968 | AM22: 0 | AN22: 1500 | AO22: 0 | AP22: 339 | AQ22: 4559475 | AR22: =$AP22/($AQ22/100000) -> 7.4350665 | AS22: 263200770000000 | AT22: 0 | AU22: 154656103049267 | AV22: 622685613631238 | AW22: 1.9490838e+15 | AX22: 1.114466e+15 | AY22: 1.9975472e+15 | AZ22: 1.289778e+15 | BA22: 278916134857916 | BB22: 0 | BC22: 128984261203424 | BD22: 693802324119365 | BE22: 2.0724052e+15 | BF22: 3.4852257e+15 | BG22: 2.2147271e+15 | BH22: 1.5346485e+15 | BI22: =IFERROR($AS22/$BA22,0)*100 -> 94.365559 | BJ22: =IFERROR($AT22/$BB22,0)*100 -> 0 | BK22: =IFERROR($AU22/$BC22,0)*100 -> 119.90308 | BL22: =IFERROR($AV22/$BD22,0)*100 -> 89.749716 | BM22: =IFERROR($AW22/$BE22,0)*100 -> 94.049358 | BN22: =IFERROR($AX22/$BF22,0)*100 -> 31.976866 | BO22: =IFERROR($AY22/$BG22,0)*100 -> 90.193827 | BP22: =IFERROR($AZ22/$BH22,0)*100 -> 84.043869 | BQ22: 0.079603037 | BR22: 0.090441014 | BS22: 0.4797053 | BT22: 0.44303782 | BU22: 0.66226106 | BV22: 0.76078054 | BW22: 0.32739706 | BX22: 0.53754771 | BY22: 0.5304329 | BZ22: 0.55043532 | CA22: 1 | CB22: 1 | CC22: 0.32728774 | CD22: 0.53494658 | CE22: 0.53030924 | CF22: 0.54771246 | CG22: 1 | CH22: 1 | CI22: 0 | CJ22: 0 | CK22: 0 | CL22: =IF(CM22=0,"FALSE","TRUE") -> FALSE | CM22: 0
A23: Massachusetts | B23: 5379.7904 | C23: =B23/1000 -> 5.3797904 | D23: 18950009 | E23: 34836185 | F23: =IFERROR(($E23/$D23) - 1, 0) -> 0.83832024 | G23: 328490 | H23: 0 | I23: =IFERROR(($H23/$G23)-1,0) -> -1 | J23: 2423.8159 | K23: 882.0494 | L23: 1159.32 | M23: 0 | N23: 1450 | O23: 0 | P23: 0 | Q23: 0 | R23: 50 | S23: 0 | T23: 0 | U23: 5960.6 | V23: 0 | W23: 264.3 | X23: 90.8 | Y23: 846.2 | Z23: 0 | AA23: 43.6 | AB23: 0 | AC23: 2385.8 | AD23: 884.5 | AE23: 0 | AF23: 0 | AG23: 0 | AH23: 0 | AI23: 232.3 | AJ23: 0.237375 | AK23: 0.457375 | AL23: 0.657375 | AM23: 1 | AN23: 2500 | AO23: 0 | AP23: 4110 | AQ23: 7020058 | AR23: =$AP23/($AQ23/100000) -> 58.546525 | AS23: 0 | AT23: 0 | AU23: 0 | AV23: 0 | AW23: 0 | AX23: 0 | AY23: 0 | AZ23: 0 | BA23: 0 | BB23: 0 | BC23: 0 | BD23: 0 | BE23: 0 | BF23: 0 | BG23: 0 | BH23: 0 | BI23: =IFERROR($AS23/$BA23,0)*100 -> 0 | BJ23: =IFERROR($AT23/$BB23,0)*100 -> 0 | BK23: =IFERROR($AU23/$BC23,0)*100 -> 0 | BL23: =IFERROR($AV23/$BD23,0)*100 -> 0 | BM23: =IFERROR($AW23/$BE23,0)*100 -> 0 | BN23: =IFERROR($AX23/$BF23,0)*100 -> 0 | BO23: =IFERROR($AY23/$BG23,0)*100 -> 0 | BP23: =IFERROR($AZ23/$BH23,0)*100 -> 0 | BQ23: 0.024066738 | BR23: 0.024358536 | BS23: 0.48570254 | BT23: 0.44540855 | BU23: 0.5487651 | BV23: 0.66623414 | BW23: 0.059710733 | BX23: 0.099824285 | BY23: 0.35864112 | BZ23: 0.35164844 | CA23: 1 | CB23: 1 | CC23: 0.05938685 | CD23: 0.09927592 | CE23: 0.35731193 | CF23: 0.34959321 | CG23: 1 | CH23: 1 | CI23: 1 | CJ23: 1 | CK23: 1 | CL23: =IF(CM23=0,"FALSE","TRUE") -> TRUE | CM23: 35
... A54: Wyoming | B54: 138513.36 | C54: =B54/1000 -> 138.51336 | D54: 22734 | E54: 0 | F54: =IFERROR(($E54/$D54) - 1, 0) -> -1 | G54: 27550707 | H54: 25354948 | I54: =IFERROR(($H54/$G54)-1,0) -> -0.079698826 | J54: 1487.9992 | K54: 541.49688 | L54: 711.71544 | M54: 3950 | N54: 0 | O54: 0 | P54: 0 | Q54: 0 | R54: 0 | S54: 0 | T54: 6332 | U54: 94 | V54: 0 | W54: 307.1 | X54: 1485.9 | Y54: 92 | Z54: 0 | AA54: 0 | AB54: 0 | AC54: 4.7 | AD54: 150 | AE54: 0 | AF54: 0 | AG54: 0 | AH54: 0 | AI54: 0 | AJ54: 0.018188 | AK54: 0.018188 | AL54: 0.018188 | AM54: 0 | AN54: 0 | AO54: 0 | AP54: 169 | AQ54: 586485 | AR54: =$AP54/($AQ54/100000) -> 28.815741 | AS54: 584890600000000 | AT54: 4.8804873e+15 | AU54: 0 | AV54: 0 | AW54: 248398817024236 | AX54: 1.1683039e+15 | AY54: 2.2593272e+13 | AZ54: 0 | BA54: 619813633017593 | BB54: 5.7038488e+15 | BC54: 7.7765031e+12 | BD54: 1.8959593e+13 | BE54: 260161446643039 | BF54: 1.5444511e+15 | BG54: 123363685147293 | BH54: 157348710576286 | BI54: =IFERROR($AS54/$BA54,0)*100 -> 94.365559 | BJ54: =IFERROR($AT54/$BB54,0)*100 -> 85.564808 | BK54: =IFERROR($AU54/$BC54,0)*100 -> 0 | BL54: =IFERROR($AV54/$BD54,0)*100 -> 0 | BM54: =IFERROR($AW54/$BE54,0)*100 -> 95.478719 | BN54: =IFERROR($AX54/$BF54,0)*100 -> 75.645253 | BO54: =IFERROR($AY54/$BG54,0)*100 -> 18.314362 | BP54: =IFERROR($AZ54/$BH54,0)*100 -> 0 | BQ54: 0.043807047 | BR54: 0.044915653 | BS54: 0.39160038 | BT54: 0.36467501 | BU54: 0.61345479 | BV54: 0.71961257 | BW54: 0.096155864 | BX54: 0.12039135 | BY54: 0.40887863 | BZ54: 0.41446199 | CA54: 1 | CB54: 1 | CC54: 0.096126217 | CD54: 0.11946722 | CE54: 0.40879617 | CF54: 0.41238763 | CG54: 1 | CH54: 1 | CI54: 0 | CJ54: 0 | CK54: 0 | CL54: =IF(CM54=0,"FALSE","TRUE") -> FALSE | CM54: 0

Sheet PolicyLevers
A1: Sector | B1: Short Name | C1: Vensim Variable Name | D1: Subscript 1 Value | E1: Subscript 2 Value | F1: Subscript 1 Display Name | G1: Subscript 2 Display Name | H1: Policy ID Number | I1: Include in Web App | J1: Policy Group | K1: Policy Schedule Subscript | L1: Min Slider Value | M1: Max Slider Value | N1: Slider Step Size | O1: Units | P1: Text for Pop-Over Panel Description | Q1: URL for "How the model handles this policy" links | R1: URL for "How to design this policy well" links
A2: =IF(ISBLANK(INDEX('Policy Characteristics'!A:A,MATCH($C2,'Policy Characteristics'!$C:$C,0))),"",INDEX('Policy Characteristics'!A:A,MATCH($C2,'Policy Characteristics'!$C:$C,0))) -> Transportation | B2: =IF(ISBLANK(INDEX('Policy Characteristics'!B:B,MATCH($C2,'Policy Characteristics'!$C:$C,0))),"",INDEX('Policy Characteristics'!B:B,MATCH($C2,'Policy Characteristics'!$C:$C,0))) -> Conventional Pollutant Standards | C2: Percentage Reduction of Separately Regulated Pollutants | D2: LDVs | E2: VOC | F2: Passenger cars, SUVs, Light and Medium Commercial Trucks | G2: VOCs | H2: 300 | I2: Yes | J2: =IF(ISBLANK(INDEX('Policy Characteristics'!D:D,MATCH($C2,'Policy Characteristics'!$C:$C,0))),"",INDEX('Policy Characteristics'!D:D,MATCH($C2,'Policy Characteristics'!$C:$C,0))) -> Conventional Pollutant Standard | K2: =IF(ISBLANK(INDEX('Policy Characteristics'!E:E,MATCH($C2,'Policy Characteristics'!$C:$C,0))),"",INDEX('Policy Characteristics'!E:E,MATCH($C2,'Policy Characteristics'!$C:$C,0))) -> trans reduce regulated pollutants | L2: =IF(ISBLANK(INDEX('Policy Characteristics'!F:F,MATCH($C2,'Policy Characteristics'!$C:$C,0))),"",INDEX('Policy Characteristics'!F:F,MATCH($C2,'Policy Characteristics'!$C:$C,0))) -> 0 | M2: =IF(ISBLANK(INDEX('Policy Characteristics'!G:G,MATCH($C2,'Policy Characteristics'!$C:$C,0))),"",INDEX('Policy Characteristics'!G:G,MATCH($C2,'Policy Characteristics'!$C:$C,0))) -> 1 | N2: =IF(ISBLANK(INDEX('Policy Characteristics'!H:H,MATCH($C2,'Policy Characteristics'!$C:$C,0))),"",INDEX('Policy Characteristics'!H:H,MATCH($C2,'Policy Characteristics'!$C:$C,0))) -> 0.02 | O2: =IF(ISBLANK(INDEX('Policy Characteristics'!I:I,MATCH($C2,'Policy Characteristics'!$C:$C,0))),"",INDEX('Policy Characteristics'!I:I,MATCH($C2,'Policy Characteristics'!$C:$C,0))) -> % reduction in emissions | P2: =IF(ISBLANK(INDEX('Policy Characteristics'!J:J,MATCH($C2,'Policy Characteristics'!$C:$C,0))),"",INDEX('Policy Characteristics'!J:J,MATCH($C2,'Policy Characteristics'!$C:$C,0))) -> **Description:** This policy represents strengthening standards for the selected pollutant(s) emitted by the selected vehicle type(s). Conventional pollutants' most important, harmful impacts are on human health rather than on climate change. The following descriptions detail the different vehicle types: // **Passenger cars and SUVs:** most light-duty road vehicles // **Light and Medium Commercial Trucks:** commercial trucks carrying freight, not passengers // **Buses:** including school, transit, and intercity buses // **Heavy Duty Trucks:** all other heavy road vehicles (mostly freight trucks) // **Commercial passenger flights:** this is not general aviation // **Commercial freight flights:** this includes all other commercial flights, and is not general aviation // **Passenger rail:** intercity, transit, and commuter rail // **Freight rail:** all other rail // **Recreational boats:** not commercial passenger ferries // **Cargo ships:** commercial ships carrying freight // **Passenger motorbikes:** registered motorcycles // **Guidance for setting values:** In the United States, since 1997, the 24-hour national ambient air quality standard (NAAQS) for PM2.5, the most harmful type of particulate for human health, declined from 65 µg/m^3 to 35 µg/m^3, a reduction of 46%. | Q2: =IF(ISBLANK(INDEX('Policy Characteristics'!K:K,MATCH($C2,'Policy Characteristics'!$C:$C,0))),"",INDEX('Policy Characteristics'!K:K,MATCH($C2,'Policy Characteristics'!$C:$C,0))) -> transportation-sector-main.html#conv-pol-stds | R2: =IF(ISBLANK(INDEX('Policy Characteristics'!L:L,MATCH($C2,'Policy Characteristics'!$C:$C,0))),"",INDEX('Policy Characteristics'!L:L,MATCH($C2,'Policy Characteristics'!$C:$C,0))) -> conventional-pollutant-standards.html
